Workbook

Sheet 饼图
D1: 1月
F2: 自动 | I2: 自动 | J2: 自动 | K2: 自动
C3: 项 目 | D3: 2026年 | E3: 占 比 % | F3: 奉贤 | G3: 占 比 % | H3: 2025年 | I3: 占 比 % | J3: 增减额 | K3: 增减率
C4: 人员经费 | D4: 24327 | E4: 0.34595694 | F4: 6393 | G4: 0.36775196 | H4: 21579 | I4: 0.37453138 | J4: 2748 | K4: 0.12734603 | M4: =E4-I4 -> -0.028574442
C5: 药品费 | D5: 16495 | E5: 0.23457721 | F5: 2771 | G5: 0.15939945 | H5: 13387 | I5: 0.23234865 | J5: 3108 | K5: 0.23216553 | M5: =E5-I5 -> 0.0022285533
C6: 耗材费 | D6: 22400 | E6: 0.31855286 | F6: 6605 | G6: 0.37994708 | H6: 16986 | I6: 0.29481394 | J6: 5414 | K6: 0.31873307 | M6: =E6-I6 -> 0.023738919
C7: 折旧/摊销 | D7: 1120 | E7: 0.015927643 | F7: 178 | G7: 0.010239301 | H7: 1078 | I7: 0.018710081 | J7: 42 | K7: 0.038961039 | M7: =E7-I7 -> -0.0027824375
C8: 风险基金 | D8: 103 | E8: 0.0014647743 | F8: 22 | G8: 0.0012655315 | H8: 77 | I8: 0.0013364343 | J8: 26 | K8: 0.33766234 | L8: 自动 | M8: =E9-I9 -> 0.0052610667
C9: 其他费用 | D9: 5873 | E9: 0.083520578 | F9: 1415 | G9: 0.081396687 | H9: 4509 | I9: 0.078259511 | J9: 1364 | K9: 0.3025061
C10: 医疗成本合计 | D10: 70318 | E10: 1 | F10: 17384 | G10: 1 | H10: 57616 | I10: 1 | J10: 12702 | K10: 0.22045959 | L10: 自动 | M10: =E9-I9 -> 0.0052610667
L13: 自动 | P13: 2025年 | R13: 2024年
K14: 人员经费 | L14: =E4 -> 0.34595694 | O14: 医疗风险基金 | P14: 78 | R14: 78
K15: 药品费 | L15: =E5 -> 0.23457721 | O15: 能源费 | P15: 516 | R15: 472
K16: 耗材费 | L16: =E6 -> 0.31855286 | O16: 物业管理费 | R16: 624
K17: 折旧/摊销 | L17: =E7 -> 0.015927643 | O17: 维修护费 | R17: 1353
K18: 其他费用 | L18: =E9 -> 0.083520578 | O18: 劳务费 | R18: 354
O24: 其他 | P24: =P25-P14-P15-P16-P17-P18-P19-P20-P21-P22-P23 -> 3992 | R24: =R25-R14-R15-R16-R17-R18-R19-R20-R21-R22-R23 -> 1243
C25: 2024年 | D25: 2023年 | F25: 增减额 | H25: 增减率 | O25: 总计 | P25: 4586 | R25: 4124
B26: 项 目 | C26: 1-9月 | D26: 1-9月
C27: 498726 | D27: 451737 | F27: =C27-D27 -> 46989 | H27: =C27/D27-1 -> 0.10401849
B28: 医疗成本 | C28: 143587 | D28: 127531 | F28: =C28-D28 -> 16056 | H28: =C28/D28-1 -> 0.1258988
B29: 其中：工资总额 | C29: 3802 | D29: 3829 | F29: =C29-D29 -> -27 | H29: =C29/D29-1 -> -0.0070514495
B30: 其他费用 | C30: =C27+C29 -> 502528 | D30: =D27+D29 -> 455566 | F30: =C30-D30 -> 46962 | H30: =C30/D30-1 -> 0.10308495
B31: 小 计

Sheet 医疗成本
B3: 项 目 | C3: 2026年 | D3: 占 比% | E3: 奉贤院区 | F3: 占 比% | G3: 2025年 | H3: 占 比% | I3: 增减额 | J3: 增减率 | K3: 46082
C4: 4月 | G4: 4月
B5: 人员经费 | C5: =ROUND(当月附表3!B7/10000,0) -> 24327 | D5: =C5/C$11 -> 0.34595694 | E5: =ROUND(当月奉贤附表3!B7/10000,0) -> 6393 | F5: =E5/E$11 -> 0.36775196 | G5: =ROUND(上年同期附表3!B7/10000,0) -> 21579 | H5: =G5/G$11 -> 0.37453138 | I5: =C5-G5 -> 2748 | J5: =I5/G5 -> 0.12734603 | K5: =ROUND(当月附表3!B7/10000,0) -> 24327
B6: 药品费 | C6: =ROUND(当月附表3!B47/10000,0) -> 16495 | D6: =C6/C$11 -> 0.23457721 | E6: =ROUND(当月奉贤附表3!B47/10000,0) -> 2771 | F6: =E6/E$11 -> 0.15939945 | G6: =ROUND(上年同期附表3!B47/10000,0) -> 13387 | H6: =G6/G$11 -> 0.23234865 | I6: =C6-G6 -> 3108 | J6: =I6/G6 -> 0.23216553 | K6: =ROUND(当月附表3!B47/10000,0) -> 16495
B7: 卫生材料费 | C7: =ROUND(当月附表3!B33/10000,0) -> 22400 | D7: =C7/C$11 -> 0.31855286 | E7: =ROUND(当月奉贤附表3!B33/10000,0) -> 6605 | F7: =E7/E$11 -> 0.37994708 | G7: =ROUND(上年同期附表3!B33/10000,0) -> 16986 | H7: =G7/G$11 -> 0.29481394 | I7: =C7-G7 -> 5414 | J7: =I7/G7 -> 0.31873307 | K7: =ROUND(当月附表3!B33/10000,0) -> 22400
B8: 折旧/摊销 | C8: =C11-C10-C7-C6-C5-C9 -> 1120 | D8: =C8/C$11 -> 0.015927643 | E8: =E11-E10-E7-E6-E5-E9 -> 178 | F8: =E8/E$11 -> 0.010239301 | G8: =G11-G10-G7-G6-G5-G9 -> 1078 | H8: =G8/G$11 -> 0.018710081 | I8: =C8-G8 -> 42 | J8: =I8/G8 -> 0.038961039 | K8: =K11-K10-K7-K6-K5-K9 -> 1120
B9: 医疗风险基金 | C9: =ROUND(当月附表3!B53/10000,0) -> 103 | D9: =C9/C$11 -> 0.0014647743 | E9: =ROUND(当月奉贤附表3!B53/10000,0) -> 22 | F9: =E9/E$11 -> 0.0012655315 | G9: =ROUND(上年同期附表3!B53/10000,0) -> 77 | H9: =G9/G$11 -> 0.0013364343 | I9: =C9-G9 -> 26 | J9: =I9/G9 -> 0.33766234 | K9: =ROUND(当月附表3!B53/10000,0) -> 103
B10: 商品和服务费 | C10: =ROUND(当月附表3!B54/10000,0) -> 5873 | D10: =C10/C$11 -> 0.083520578 | E10: =ROUND(当月奉贤附表3!B54/10000,0) -> 1415 | F10: =E10/E$11 -> 0.081396687 | G10: =ROUND(上年同期附表3!B54/10000,0) -> 4509 | H10: =G10/G$11 -> 0.078259511 | I10: =C10-G10 -> 1364 | J10: =I10/G10 -> 0.3025061 | K10: =ROUND(当月附表3!B54/10000,0) -> 5873
B11: 医疗成本合计 | C11: =ROUND(当月附表3!B6/10000,0) -> 70318 | D11: 1 | E11: =ROUND(当月奉贤附表3!B6/10000,0) -> 17384 | F11: 1 | G11: =ROUND(上年同期附表3!B6/10000,0) -> 57616 | H11: 1 | I11: =C11-G11 -> 12702 | J11: =I11/G11 -> 0.22045959 | K11: =ROUND(当月附表3!B6/10000,0) -> 70318

Sheet 人员经费
B3: 项 目 | C3: 46113 | D3: 其中 | E3: 45748 | F3: 增减额 | G3: 增减率
D4: 奉贤院区
B5: 医疗服务收入 | C5: =ROUND((当年累计数据表!AQ3+当年累计数据表!AX3+当年累计数据表!BZ3+当年累计数据表!CG3)/10000,0) -> 31689 | D5: =ROUND((当年累计数据表奉贤!AQ3+当年累计数据表奉贤!AX3+当年累计数据表奉贤!BZ3+当年累计数据表奉贤!CG3)/10000,0) -> 6304 | E5: =ROUND((去年累计数据表!AQ3+去年累计数据表!AX3+去年累计数据表!BZ3+去年累计数据表!CG3)/10000,0) -> 24331 | F5: =C5-E5 -> 7358 | G5: =F5/E5 -> 0.30241256
B6: 人员经费 | C6: =医疗成本!C5 -> 24327 | D6: =医疗成本!E5 -> 6393 | E6: =医疗成本!G5 -> 21579 | F6: =医疗成本!I5 -> 2748 | G6: =医疗成本!J5 -> 0.12734603
B7: 其中：工资总额 | C7: =ROUND((当月附表3!B9+当月附表3!B10+当月附表3!B11+当月附表3!B12+当月附表3!B13+当月附表3!B20)/10000,0) -> 19440 | D7: =ROUND((当月奉贤附表3!B9+当月奉贤附表3!B10+当月奉贤附表3!B11+当月奉贤附表3!B12+当月奉贤附表3!B13+当月奉贤附表3!B20)/10000,0) -> 5701 | E7: =ROUND((上年同期附表3!B9+上年同期附表3!B10+上年同期附表3!B11+上年同期附表3!B12+上年同期附表3!B13+上年同期附表3!B20)/10000,0) -> 17018 | F7: =C7-E7 -> 2422 | G7: =F7/E7 -> 0.1423199
B8: 其中：基本工资等 | C8: =ROUND((当月附表3!B9+当月附表3!B10+当月附表3!B11+当月附表3!B12+当月附表3!B20)/10000,0) -> 3697 | D8: =ROUND((当月奉贤附表3!B9+当月奉贤附表3!B10+当月奉贤附表3!B11+当月奉贤附表3!B12+当月奉贤附表3!B20)/10000,0) -> 520 | E8: =ROUND((上年同期附表3!B9+上年同期附表3!B10+上年同期附表3!B11+上年同期附表3!B12+上年同期附表3!B20)/10000,0) -> 3848 | F8: =C8-E8 -> -151 | G8: =F8/E8 -> -0.039241164
B9: 绩效工资 | C9: =C7-C8 -> 15743 | D9: =D7-D8 -> 5181 | E9: =E7-E8 -> 13170 | F9: =C9-E9 -> 2573 | G9: =F9/E9 -> 0.19536826
B10: 社保公积金 | C10: =ROUND((当月附表3!B14+当月附表3!B15+当月附表3!B16+当月附表3!B17+当月附表3!B18)/10000,0) -> 4601 | D10: =ROUND((当月奉贤附表3!B14+当月奉贤附表3!B15+当月奉贤附表3!B16+当月奉贤附表3!B17+当月奉贤附表3!B18)/10000,0) -> 692 | E10: =ROUND((上年同期附表3!B14+上年同期附表3!B15+上年同期附表3!B16+上年同期附表3!B17+上年同期附表3!B18)/10000,0) -> 4270 | F10: =C10-E10 -> 331 | G10: =F10/E10 -> 0.077517564

Sheet 水电煤
B2: 项 目 | C2: 46113 | D2: 其中 | E2: 45748 | F2: 增减额 | G2: 增减率
D3: 奉贤院区
B4: 能耗成本 | C4: =C5+C6+C7 -> 461 | D4: =D5+D6+D7 -> 134 | E4: =E5+E6+E7 -> 515 | F4: =C4-E4 -> -54 | G4: =F4/E4 -> -0.10485437
B5: 其中：水费 | C5: =ROUND(当月附表3!B59/10000,0) -> 61 | D5: =ROUND(当月奉贤附表3!B59/10000,0) -> 8 | E5: =ROUND(上年同期附表3!B59/10000,0) -> 58 | F5: =C5-E5 -> 3 | G5: =F5/E5 -> 0.051724138
B6: 电费 | C6: =ROUND(当月附表3!B60/10000,0) -> 338 | D6: =ROUND(当月奉贤附表3!B60/10000,0) -> 95 | E6: =ROUND(上年同期附表3!B60/10000,0) -> 326 | F6: =C6-E6 -> 12 | G6: =F6/E6 -> 0.036809816
B7: 燃气费 | C7: =ROUND(当月附表3!B72/10000,0) -> 62 | D7: =ROUND(当月奉贤附表3!B72/10000,0) -> 31 | E7: =ROUND(上年同期附表3!B72/10000,0) -> 131 | F7: =C7-E7 -> -69 | G7: =F7/E7 -> -0.52671756

Sheet 预算完成情况
B2: 项 目 | C2: 执行率指标 | J2: 年终
C3: 核定数 | D3: 执行数 | E3: 执行率 | F3: 与时间节点比较 | H3: 0.333 | J3: 17532 | K3: =J3*(1-H3) -> 11693.844
B4: 医疗收入 | C4: 750000 | D4: =收支结余!C4 -> 67338 | E4: =D4/C4 -> 0.089784 | F4: =E4-$H$3 -> -0.243216 | K4: =D6-K3 -> 7746.156 | L4: =K4/C6 -> 0.03442736
B5: 医疗成本 | C5: 768743 | D5: =收支结余!C6 -> 70318 | E5: =D5/C5 -> 0.091471402 | F5: =E5-$H$3 -> -0.2415286
B6: 工资总额 | C6: 225000 | D6: =人员经费!C7 -> 19440 | E6: =D6/C6 -> 0.0864 | F6: =E6-$H$3 -> -0.2466

Sheet 收支结余
B2: 项 目 | C2: 46113 | D2: 其中 | E2: 45748 | F2: 增减额 | G2: 增减率
D3: 奉贤院区
B4: 医疗收入 | C4: =ROUND(当年累计数据表!O3/10000,0) -> 67338 | D4: =ROUND(当年累计数据表奉贤!O3/10000,0) -> 14595 | E4: =ROUND(去年累计数据表!O3/10000,0) -> 51336 | F4: =C4-E4 -> 16002 | G4: =F4/E4 -> 0.31171108
B5: 加：财政基本拨款收入 | C5: 2502 | D5: 0 | E5: 2411 | F5: =C5-E5 -> 91 | G5: =F5/E5 -> 0.037743675
B6: 减：医疗成本 | C6: =医疗成本!C11 -> 70318 | D6: =医疗成本!E11 -> 17384 | E6: =医疗成本!G11 -> 57616 | F6: =C6-E6 -> 12702 | G6: =F6/E6 -> 0.22045959
B7: 医疗服务盈余 | C7: =C4+C5-C6 -> -478 | D7: =D4+D5-D6 -> -2789 | E7: =E4+E5-E6 -> -3869 | F7: =C7-E7 -> 3391 | G7: =F7/E7 -> -0.87645386
B8: 其他盈余 | C8: =C9-C7 -> 277 | D8: =D9-D7 -> 116 | E8: =E9-E7 -> 1854 | F8: =C8-E8 -> -1577 | G8: -
B9: 收支结余 | C9: =ROUND(当月附表1!B5/10000,0) -> -201 | D9: =ROUND(当月奉贤附表1!B5/10000,0) -> -2673 | E9: =ROUND(上年同期附表1!B5/10000,0) -> -2015 | F9: =C9-E9 -> 1814 | G9: -
B16: 项 目 | C16: 46113 | D16: 45748 | E16: 增减额 | F16: 增减率
B17: 新华医疗开发公司 | E17: =C17-D17 -> 0 | F17: =E17/D17 -> #DIV/0!

Sheet 商品服务
B2: 项 目 | C2: 46113 | D2: 其中 | E2: 45748 | F2: 增减额 | G2: 增减率
D3: 奉贤院区
B4: 商品服务 | C4: =ROUND(当月附表3!B54/10000,0) -> 5873 | D4: =ROUND(当月奉贤附表3!B54/10000,0) -> 1415 | E4: =ROUND(上年同期附表3!B54/10000,0) -> 4509 | F4: =C4-E4 -> 1364 | G4: =F4/E4 -> 0.3025061
B5: 其中：能源成本 | C5: =水电煤!C4 -> 461 | D5: =水电煤!D4 -> 134 | E5: =水电煤!E4 -> 515 | F5: =C5-E5 -> -54 | G5: =F5/E5 -> -0.10485437
B6: 维修护费 | C6: =ROUND(当月附表3!B66/10000,0) -> 723 | D6: =ROUND(当月奉贤附表3!B66/10000,0) -> 219 | E6: =ROUND(上年同期附表3!B66/10000,0) -> 731 | F6: =C6-E6 -> -8 | G6: =F6/E6 -> -0.010943912
B7: 物业管理费 | C7: =ROUND(当月附表3!B63/10000,0) -> 1046 | D7: =ROUND(当月奉贤附表3!B63/10000,0) -> 367 | E7: =ROUND(上年同期附表3!B63/10000,0) -> 854 | F7: =C7-E7 -> 192 | G7: =F7/E7 -> 0.22482436
B8: 委托业务费 | C8: =ROUND(当月附表3!B74/10000,0) -> 1094 | D8: =ROUND(当月奉贤附表3!B74/10000,0) -> 93 | E8: =ROUND(上年同期附表3!B74/10000,0) -> 840 | F8: =C8-E8 -> 254 | G8: =F8/E8 -> 0.30238095
B9: 劳务费 | C9: =ROUND(当月附表3!B73/10000,0) -> 584 | D9: =ROUND(当月奉贤附表3!B73/10000,0) -> 185 | E9: =ROUND(上年同期附表3!B73/10000,0) -> 358 | F9: =C9-E9 -> 226 | G9: =F9/E9 -> 0.63128492
B10: 专用材料费 | C10: =ROUND(当月附表3!B71/10000,0) -> 149 | D10: =ROUND(当月奉贤附表3!B71/10000,0) -> 30 | E10: =ROUND(上年同期附表3!B71/10000,0) -> 106 | F10: =C10-E10 -> 43 | G10: =F10/E10 -> 0.40566038
B11: 供应室外包成本 | C11: 470 | D11: 104 | E11: 575 | F11: =C11-E11 -> -105 | G11: =F11/E11 -> -0.1826087
B12: 租赁费 | C12: =ROUND(当月附表3!B67/10000,0) -> 372 | D12: =ROUND(当月奉贤附表3!B67/10000,0) -> 95 | E12: =ROUND(上年同期附表3!B67/10000,0) -> 328 | F12: =C12-E12 -> 44 | G12: =F12/E12 -> 0.13414634
B13: 其他 | C13: =C4-C5-C6-C7-C8-C9-C10-C11-C12 -> 974 | D13: =D4-D5-D6-D7-D8-D9-D10-D11-D12 -> 188 | E13: =E4-E5-E6-E7-E8-E9-E10-E11-E12 -> 202 | F13: =C13-E13 -> 772 | G13: =F13/E13 -> 3.8217822
C24: =C11+C13 -> 1444 | D24: =D11+D13 -> 292 | E24: =E11+E13 -> 777 | F24: =F11+F13 -> 667 | G24: =F24/E24 -> 0.85842986

Sheet 物业管理
B3: 项 目 | C3: 46113 | D3: 其中 | E3: 45748 | F3: 增减额 | G3: 增减率 | I3: 项 目 | J3: 46113 | K3: 其中 | L3: 45748 | M3: 增减额 | N3: 增减率
D4: 奉贤院区 | K4: 奉贤院区
B5: 物业管理费 | C5: =商品服务!C7 -> 1046 | D5: =商品服务!D7 -> 367 | E5: =商品服务!E7 -> 854 | F5: =C5-E5 -> 192 | G5: =F5/E5 -> 0.22482436 | I5: 物业管理费 | J5: =商品服务!C7 -> 1046 | K5: =商品服务!D7 -> 367 | L5: =商品服务!E7 -> 854 | M5: =J5-L5 -> 192 | N5: =M5/L5 -> 0.22482436
B6: 其中： 电梯驾驶服务 | C6: -51 | D6: 15 | E6: 0 | F6: =C6-E6 -> -51 | G6: =F6/E6 -> #DIV/0! | I6: 其中： 电梯驾驶服务 | M6: =J6-L6 -> 0 | N6: =M6/L6 -> #DIV/0!
B7: 保安管理 | C7: 180 | D7: 58 | E7: 157 | F7: =C7-E7 -> 23 | G7: =F7/E7 -> 0.14649682 | I7: 保安管理 | J7: 180 | K7: 58 | L7: 157 | M7: =J7-L7 -> 23 | N7: =M7/L7 -> 0.14649682
B8: 运送服务费 | C8: 137 | D8: 74 | E8: 122 | F8: =C8-E8 -> 15 | G8: =F8/E8 -> 0.12295082 | I8: 运送服务费 | J8: 137 | K8: 74 | L8: 122 | M8: =J8-L8 -> 15 | N8: =M8/L8 -> 0.12295082
B9: 保洁服务 | C9: 595 | D9: 123 | E9: 272 | F9: =C9-E9 -> 323 | G9: =F9/E9 -> 1.1875 | I9: 保洁服务 | J9: 595 | K9: 123 | L9: 272 | M9: =J9-L9 -> 323 | N9: =M9/L9 -> 1.1875
B10: 被服洗涤 | C10: 73 | D10: 29 | E10: 58 | F10: =C10-E10 -> 15 | G10: =F10/E10 -> 0.25862069 | I10: 被服洗涤 | J10: 73 | K10: 29 | L10: 58 | M10: =J10-L10 -> 15 | N10: =M10/L10 -> 0.25862069
B11: 会务 | C11: 30 | D11: 20 | E11: 0 | F11: =C11-E11 -> 30 | G11: =F11/E11 -> #DIV/0! | I11: 物业其他 | J11: =J5-J6-J7-J8-J9-J10 -> 61 | K11: =K5-K6-K7-K8-K9-K10 -> 83 | L11: =L5-L6-L7-L8-L9-L10 -> 245 | M11: =J11-L11 -> -184 | N11: =M11/L11 -> -0.75102041
B12: 绿化 | C12: 3 | D12: 0 | E12: 2 | F12: =C12-E12 -> 1 | G12: =F12/E12 -> 0.5
B13: 垃圾清运 | C13: 17 | D13: 2 | E13: 7 | F13: =C13-E13 -> 10 | G13: =F13/E13 -> 1.4285714
B14: 危险废弃物 | C14: 3 | D14: 1 | E14: 124 | F14: =C14-E14 -> -121 | G14: =F14/E14 -> -0.97580645
B15: 医废处置 | C15: 19 | D15: 14 | E15: 0 | F15: =C15-E15 -> 19 | G15: =F15/E15 -> #DIV/0!
B16: 医废收运 | C16: 14 | D16: 7 | E16: 10 | F16: =C16-E16 -> 4 | G16: =F16/E16 -> 0.4
B17: 交通管理服务费 | C17: 6 | D17: 1
B18: 物业管理其他 | C18: =C5-C6-C7-C8-C9-C10-C11-C12-C13-C14-C15-C16-C17 -> 20 | D18: =D5-D6-D7-D8-D9-D10-D11-D12-D13-D14-D15-D16-D17 -> 23 | E18: =E5-E6-E7-E8-E9-E10-E11-E12-E13-E14-E15-E16-E17 -> 102 | F18: =C18-E18 -> -82 | G18: =F18/E18 -> -0.80392157

Sheet 维修护费
B1: 项 目 | C1: 46113 | D1: 其中 | E1: 45748 | F1: 增减额 | G1: 增减率
D2: 奉贤院区 | I2: 柯渡
B3: 维修费 | C3: =商品服务!C6 -> 723 | D3: =商品服务!D6 -> 219 | E3: =商品服务!E6 -> 731 | F3: =C3-E3 -> -8 | G3: =F3/E3 -> -0.010943912
B4: 其中：网络维修 | C4: 6 | D4: 1 | E4: 5 | F4: =C4-E4 -> 1 | G4: =F4/E4 -> 0.2
B5: 设备维修 | C5: 371 | D5: 86 | E5: 228 | F5: =C5-E5 -> 143 | G5: =F5/E5 -> 0.62719298 | H5: 1114 | I5: 100 | J5: 1146
B6: 后勤维修 | C6: 343 | D6: 132 | E6: 492 | F6: =C6-E6 -> -149 | G6: =F6/E6 -> -0.30284553
B7: 房屋维修 | C7: 3 | D7: 0 | E7: 6 | F7: =C7-E7 -> -3 | G7: =F7/E7 -> -0.5

Sheet 后勤维修
C3: 项 目 | D3: 46113 | E3: 其中 | F3: 45748 | G3: 增减额 | H3: 增减率 | K3: 项 目 | L3: 46113 | M3: 其中 | N3: 45748 | O3: 增减额 | P3: 增减率
E4: 奉贤院区 | M4: 奉贤院区
C5: 后勤维修费 | D5: =维修护费!C6 -> 343 | E5: =维修护费!D6 -> 132 | F5: =维修护费!E6 -> 492 | G5: =D5-F5 -> -149 | H5: =G5/F5 -> -0.30284553 | K5: 后勤维修费 | L5: =维修护费!C6 -> 343 | M5: =维修护费!D6 -> 132 | N5: =维修护费!E6 -> 492 | O5: =L5-N5 -> -149 | P5: =O5/N5 -> -0.30284553
C6: 其中：物业维修 | D6: 68 | E6: 32 | F6: 64 | G6: =D6-F6 -> 4 | H6: =G6/F6 -> 0.0625 | K6: 其中：物业维修 | L6: 68 | M6: 32 | N6: 64 | O6: =L6-N6 -> 4 | P6: =O6/N6 -> 0.0625
C7: 电梯运行 | D7: 12 | E7: 2 | F7: 0 | G7: =D7-F7 -> 12 | H7: =G7/F7 -> #DIV/0! | K7: 通用设施设备管理 | L7: 46 | M7: 9 | N7: 244 | O7: =L7-N7 -> -198 | P7: =O7/N7 -> -0.81147541
C8: 通用设施 | D8: 46 | E8: 9 | F8: 244 | G8: =D8-F8 -> -198 | H8: =G8/F8 -> -0.81147541 | K8: 空调运行管理费 | L8: 128 | M8: 30 | N8: 33 | O8: =L8-N8 -> 95 | P8: =O8/N8 -> 2.8787879
C9: 空调运行管理费 | D9: 128 | E9: 30 | F9: 33 | G9: =D9-F9 -> 95 | H9: =G9/F9 -> 2.8787879 | K9: 其他 | L9: =L5-L6-L7-L8 -> 101 | M9: =M5-M6-M7-M8 -> 61 | N9: =N5-N6-N7-N8 -> 151 | O9: =L9-N9 -> -50 | P9: =O9/N9 -> -0.33112583
C10: 电站运行 | D10: 1 | E10: 12 | F10: 9 | G10: =D10-F10 -> -8 | H10: =G10/F10 -> -0.88888889
C11: 给排水锅炉 | D11: 18 | E11: 12 | F11: 0 | G11: =D11-F11 -> 18 | H11: =G11/F11 -> #DIV/0!
C12: 后勤智能化 | D12: 8 | E12: 5 | F12: 0 | G12: =D12-F12 -> 8 | H12: =G12/F12 -> #DIV/0!
C13: 污水处理站 | D13: 27 | E13: 20 | F13: 11 | G13: =D13-F13 -> 16 | H13: =G13/F13 -> 1.4545455
C14: 污水管线 | D14: 2 | E14: 1 | F14: 1 | G14: =D14-F14 -> 1 | H14: =G14/F14 -> 1
C15: 医用气体 | D15: 9 | E15: 5 | F15: 12 | G15: =D15-F15 -> -3 | H15: =G15/F15 -> -0.25
C16: 其他 | D16: =D5-D6-D7-D8-D9-D10-D11-D12-D13-D14-D15 -> 24 | E16: =E5-E6-E7-E8-E9-E10-E11-E12-E13-E14-E15 -> 4 | F16: =F5-F6-F7-F8-F9-F10-F11-F12-F13-F14-F15 -> 118 | G16: =D16-F16 -> -94 | H16: =G16/F16 -> -0.79661017

Sheet 卫生材料
B2: 项 目 | C2: 46113 | D2: 其中 | E2: 45748 | F2: 增减额 | G2: 增减率
D3: 奉贤院区
B4: 卫生材料收入 | C4: =ROUND((当年累计数据表!AJ3+当年累计数据表!BS3)/10000,0) -> 19200 | D4: =ROUND((当年累计数据表奉贤!AJ3+当年累计数据表奉贤!BS3)/10000,0) -> 5553 | E4: =ROUND((去年累计数据表!AJ3+去年累计数据表!BS3)/10000,0) -> 13661 | F4: =C4-E4 -> 5539 | G4: =F4/E4 -> 0.4054608
B5: 卫生材料费 | C5: =医疗成本!C7 -> 22400 | D5: =医疗成本!E7 -> 6605 | E5: =医疗成本!G7 -> 16986 | F5: =C5-E5 -> 5414 | G5: =F5/E5 -> 0.31873307
B6: 其中：可收费 | C6: =C5-C7 -> 18910 | D6: =D5-D7 -> 5891 | E6: =E5-E7 -> 14222 | F6: =C6-E6 -> 4688 | G6: =F6/E6 -> 0.32963015 | I6: 调整
B7: 不可收费 | C7: 3490 | D7: 714 | E7: 2764 | F7: =C7-E7 -> 726 | G7: =F7/E7 -> 0.26266281 | I7: 101
B8: 其中：检验试剂 | C8: 2558 | D8: 567 | E8: 1729 | F8: =C8-E8 -> 829 | G8: =F8/E8 -> 0.4794679
B9: 其他不可收费卫生材料 | C9: =C7-C8 -> 932 | D9: =D7-D8 -> 147 | E9: =E7-E8 -> 1035 | F9: =F7-F8 -> -103 | G9: =F9/E9 -> -0.099516908
B11: 项 目 | C11: 46113 | D11: 其中：奉贤院区 | E11: 45748 | F11: 增减额 | G11: 增减率
B12: 检验试剂成本 | C12: =C8 -> 2558 | D12: =D8 -> 567 | E12: =E8 -> 1729 | F12: =F8 -> 829 | G12: =G8 -> 0.4794679
B13: 其中：医学检验科 | C13: 2059 | D13: 395 | E13: 1373 | F13: =C13-E13 -> 686 | G13: =F13/E13 -> 0.49963583
B14: 化验收入 | C14: =ROUND((当月附表2!B10+当月附表2!B23)/10000,0) -> 8020 | D14: =ROUND((当月奉贤附表2!B10+当月奉贤附表2!B23)/10000,0) -> 1512 | E14: =ROUND((上年同期附表2!B10+上年同期附表2!B23)/10000,0) -> 6132 | F14: =C14-E14 -> 1888 | G14: =F14/E14 -> 0.30789302
B15: 成本收入比重 | C15: =C12/C14 -> 0.31895262 | D15: =D12/D14 -> 0.375 | E15: =E12/E14 -> 0.28196347 | F15: =C15-E15 -> 0.036989148 | G15: -
B16: 门急诊人次 | C16: =ROUND(当年累计数据表!G3/10000,2) -> 46.53 | D16: =ROUND(当年累计数据表奉贤!G3/10000,2) -> 9.69 | E16: =ROUND(去年累计数据表!G3/10000,2) -> 36.18 | F16: =C16-E16 -> 10.35 | G16: =F16/E16 -> 0.28606965
B17: 住院人次 | C17: =ROUND(当年累计数据表!H3/10000,2) -> 1.63 | D17: =ROUND(当年累计数据表奉贤!H3/10000,2) -> 0.36 | E17: =ROUND(去年累计数据表!H3/10000,2) -> 1.35 | F17: =C17-E17 -> 0.28 | G17: =F17/E17 -> 0.20740741

Sheet 当年累计数据表
A1: 日期范围：20260401-20260430 | D1: 25 | O1: 1=2+5=8+43 | P1: 2=3+4 | Q1: 3 | R1: 4 | S1: 5=6+7 | T1: 6 | U1: 7 | V1: 8=9+12=15+22+29+36 | W1: 9=10+11 | X1: 10 | Y1: 11 | Z1: 12=13+14 | AA1: 13 | AB1: 14 | AC1: 15=16+19 | AD1: 16=17+18 | AE1: 17 | AF1: 18 | AG1: 19=20+21 | AH1: 20 | AI1: 21 | AJ1: 22=23+26 | AK1: 23=24+25 | AL1: 24 | AM1: 25 | AN1: 26=27+28 | AO1: 27 | AP1: 28 | AQ1: 29=30+33 | AR1: 30=31+32 | AS1: 31 | AT1: 32 | AU1: 33=34+35 | AV1: 34 | AW1: 35 | AX1: 36=37+40 | AY1: 37=38+39 | AZ1: 38 | BA1: 39 | BB1: 40=41+42 | BC1: 41 | BD1: 42 | BE1: 43=50+57+64+71=44+47 | BF1: 44=45+46 | BG1: 45 | BH1: 46 | BI1: 47=48+49 | BJ1: 48 | BK1: 49 | BL1: 50=51+54 | BM1: 51=52+53 | BN1: 52 | BO1: 53 | BP1: 54=55+56 | BQ1: 55 | BR1: 56 | BS1: 57=58+61 | BT1: 58=59+60 | BU1: 59 | BV1: 60 | BW1: 61=62+63 | BX1: 62 | BY1: 63 | BZ1: 64=65+68 | CA1: 65=66+67 | CB1: 66 | CC1: 67 | CD1: 68=69+70 | CE1: 69 | CF1: 70 | CG1: 71=72+75 | CH1: 72=73+74 | CI1: 73 | CJ1: 74 | CK1: 75=76+77 | CL1: 76 | CM1: 77 | CV1: 78=85+93+100+108+86+101=79+82 | CW1: 79=80+81 | CX1: 80 | CY1: 81 | CZ1: 82=83+84 | DA1: 83 | DB1: 84 | DC1: 85=87+90=78-93-100-108-86-101 | DD1: 86 | DE1: 87=88+89 | DF1: 88 | DG1: 89 | DH1: 90=91+92 | DI1: 91 | DJ1: 92 | DK1: 93=94+97 | DL1: 94=95+96 | DM1: 95 | DN1: 96 | DO1: 97=98+99 | DP1: 98 | DQ1: 99 | DR1: 100=102+105 | DS1: 101 | DT1: 102=103+104 | DU1: 103 | DV1: 104 | DW1: 105=106+107 | DX1: 106 | DY1: 107 | DZ1: 108=109+112 | EA1: 109=110+111 | EB1: 110 | EC1: 111 | ED1: 112=113+114 | EE1: 113 | EF1: 114 | EG1: 115=116+119 | EH1: 116=117+118 | EI1: 117 | EJ1: 118 | EK1: 119=120+121 | EL1: 120 | EM1: 121 | EN1: 122=123+124+125 | EO1: 123 | EP1: 124 | EQ1: 125 | EU1: 126=127+128+129 | EV1: 127 | EW1: 128 | EX1: 129 | EY1: 130=131+132 | EZ1: 131 | FA1: 132 | FB1: 133
A2: 序号 | B2: 科室类别 | C2: 科室名称 | D2: 医疗收入不含药耗 | E2: 门急诊收入不含药耗 | F2: 住院收入不含药耗 | G2: 门急诊人次 | H2: 住院人次 | I2: 门急诊治疗收入 | J2: 门急诊手术收入 | K2: 门诊中药饮片收入 | L2: 住院治疗收入 | M2: 住院手术收入 | N2: 住院中药饮片收入 | O2: 医疗收入 | P2: 其中本地病人医疗收入 | Q2: 其中本地病人医保医疗收入 | R2: 其中本地病人自费医疗收入 | S2: 其中异地病人医疗收入 | T2: 其中异地病人医保医疗收入 | U2: 其中异地病人自费医疗收入 | V2: 门急诊收入 | W2: 其中本地病人医疗收入 | X2: 其中本地病人医保医疗收入 | Y2: 其中本地病人自费医疗收入 | Z2: 其中异地病人医疗收入 | AA2: 其中异地病人医保医疗收入 | AB2: 其中异地病人自费医疗收入 | AC2: 门急诊药品收入 | AD2: 其中本地病人医疗收入 | AE2: 其中本地病人医保医疗收入 | AF2: 其中本地病人自费医疗收入 | AG2: 其中异地病人医疗收入 | AH2: 其中异地病人医保医疗收入 | AI2: 其中异地病人自费医疗收入 | AJ2: 门急诊耗材收入 | AK2: 其中本地病人医疗收入 | AL2: 其中本地病人医保医疗收入 | AM2: 其中本地病人自费医疗收入 | AN2: 其中异地病人医疗收入 | AO2: 其中异地病人医保医疗收入 | AP2: 其中异地病人自费医疗收入 | AQ2: 门急诊检查化验收入 | AR2: 其中本地病人医疗收入 | AS2: 其中本地病人医保医疗收入 | AT2: 其中本地病人自费医疗收入 | AU2: 其中异地病人医疗收入 | AV2: 其中异地病人医保医疗收入 | AW2: 其中异地病人自费医疗收入 | AX2: 门急诊劳务收入 | AY2: 其中本地病人医疗收入 | AZ2: 其中本地病人医保医疗收入 | BA2: 其中本地病人自费医疗收入 | BB2: 其中异地病人医疗收入 | BC2: 其中异地病人医保医疗收入 | BD2: 其中异地病人自费医疗收入 | BE2: 住院收入 | BF2: 其中本地病人医疗收入 | BG2: 其中本地病人医保医疗收入 | BH2: 其中本地病人自费医疗收入 | BI2: 其中异地病人医疗收入 | BJ2: 其中异地病人医保医疗收入 | BK2: 其中异地病人自费医疗收入 | BL2: 住院药品收入 | BM2: 其中本地病人医疗收入 | BN2: 其中本地病人医保医疗收入 | BO2: 其中本地病人自费医疗收入 | BP2: 其中异地病人医疗收入 | BQ2: 其中异地病人医保医疗收入 | BR2: 其中异地病人自费医疗收入 | BS2: 住院耗材收入 | BT2: 其中本地病人医疗收入 | BU2: 其中本地病人医保医疗收入 | BV2: 其中本地病人自费医疗收入 | BW2: 其中异地病人医疗收入 | BX2: 其中异地病人医保医疗收入 | BY2: 其中异地病人自费医疗收入 | BZ2: 住院检查化验收入 | CA2: 其中本地病人医疗收入 | CB2: 其中本地病人医保医疗收入 | CC2: 其中本地病人自费医疗收入 | CD2: 其中异地病人医疗收入 | CE2: 其中异地病人医保医疗收入 | CF2: 其中异地病人自费医疗收入 | CG2: 住院劳务收入 | CH2: 其中本地病人医疗收入 | CI2: 其中本地病人医保医疗收入 | CJ2: 其中本地病人自费医疗收入 | CK2: 其中异地病人医疗收入 | CL2: 其中异地病人医保医疗收入 | CM2: 其中异地病人自费医疗收入 | CN2: 急诊收入 | CO2: 普通门诊收入 | CP2: 专家门诊收入 | CQ2: 专病门诊收入 | CR2: 特需门诊收入 | CS2: MDT门诊收入 | CT2: 镜朗诊疗部收入 | CU2: 特需病房收入 | CV2: 门急诊人次 | CW2: 其中本地病人人次 | CX2: 其中本地病人医保人次 | CY2: 其中本地病人自费人次 | CZ2: 其中异地病人人次 | DA2: 其中异地病人医保人次 | DB2: 其中异地病人自费人次 | DC2: 普通门诊 (普通+专病) | DD2: 互联网普通门诊人次 | DE2: 其中本地病人人次 | DF2: 其中本地病人医保人次 | DG2: 其中本地病人自费人次 | DH2: 其中异地病人人次 | DI2: 其中异地病人医保人次 | DJ2: 其中异地病人自费人次 | DK2: 专家门诊 | DL2: 其中本地病人人次 | DM2: 其中本地病人医保人次 | DN2: 其中本地病人自费人次 | DO2: 其中异地病人人次 | DP2: 其中异地病人医保人次 | DQ2: 其中异地病人自费人次 | DR2: 特需门诊 (特需+MDT) | DS2: 互联网特需门诊人次 | DT2: 其中本地病人人次 | DU2: 其中本地病人医保人次 | DV2: 其中本地病人自费人次 | DW2: 其中异地病人人次 | DX2: 其中异地病人医保人次 | DY2: 其中异地病人自费人次 | DZ2: 急诊人次 | EA2: 其中本地病人人次 | EB2: 其中本地病人医保人次 | EC2: 其中本地病人自费人次 | ED2: 其中异地病人人次 | EE2: 其中异地病人医保人次 | EF2: 其中异地病人自费人次 | EG2: 住院人次 | EH2: 其中本地病人人次 | EI2: 其中本地病人医保人次 | EJ2: 其中本地病人自费人次 | EK2: 其中异地病人人次 | EL2: 其中异地病人医保人次 | EM2: 其中异地病人自费人次 | EN2: 手术人次与操作人次 | EO2: 手术人次 | EP2: 介入人次 | EQ2: 操作人次(治疗+诊断) | ER2: 微创手术人次（手术） | ES2: 微创手术人次（介入） | ET2: 微创手术人次（操作） | EU2: 三级手术 | EV2: 三级手术(手术) | EW2: 三级手术(介入) | EX2: 三级手术(操作) | EY2: 四级手术 | EZ2: 四级手术(手术) | FA2: 四级手术(介入) | FB2: 重点病种人次
A3: 小计： | D3: 3.1689143e+08 | E3: 1.4034284e+08 | F3: 1.7654859e+08 | G3: 465346 | H3: 16313 | I3: 24748353 | J3: 6537395.3 | K3: 2649428.8 | L3: 17414725 | M3: 46022880 | N3: 30481.97 | O3: 6.7337873e+08 | P3: 4.5465716e+08 | Q3: 4.2016861e+08 | R3: 34488555 | S3: 2.1872157e+08 | T3: 1.8332464e+08 | U3: 35396927 | V3: 2.4815185e+08 | W3: 2.0291608e+08 | X3: 1.8635817e+08 | Y3: 16557903 | Z3: 45235777 | AA3: 24023951 | AB3: 21211826 | AC3: 99357344 | AD3: 86868261 | AE3: 83908655 | AF3: 2959606.5 | AG3: 12489082 | AH3: 9125418.1 | AI3: 3363664.3 | AJ3: 8451670.7 | AK3: 7386333.1 | AL3: 6548799.3 | AM3: 837533.73 | AN3: 1065337.6 | AO3: 643343.93 | AP3: 421993.66 | AQ3: 79576300 | AR3: 64896578 | AS3: 59049566 | AT3: 5847011.8 | AU3: 14679722 | AV3: 7721562 | AW3: 6958159.8 | AX3: 60766540 | AY3: 43764904 | AZ3: 36851153 | BA3: 6913750.5 | BB3: 17001636 | BC3: 6533627 | BD3: 10468009 | BE3: 4.2522687e+08 | BF3: 2.5174108e+08 | BG3: 2.3381043e+08 | BH3: 17930653 | BI3: 1.7348579e+08 | BJ3: 1.5930069e+08 | BK3: 14185100 | BL3: 65126079 | BM3: 35808649 | BN3: 34236417 | BO3: 1572232.2 | BP3: 29317430 | BQ3: 27074032 | BR3: 2243398.6 | BS3: 1.8355221e+08 | BT3: 1.1280396e+08 | BU3: 1.0626868e+08 | BV3: 6535286.7 | BW3: 70748244 | BX3: 66595536 | BY3: 4152708.1 | BZ3: 72619444 | CA3: 44602626 | CB3: 41788514 | CC3: 2814112.5 | CD3: 28016817 | CE3: 26268769 | CF3: 1748048 | CG3: 1.0392914e+08 | CH3: 58525846 | CI3: 51516825 | CJ3: 7009021.2 | CK3: 45403297 | CL3: 39362351 | CM3: 6040945.8 | CN3: 29773959 | CO3: 89007270 | CP3: 65220304 | CQ3: 32373823 | CR3: 31494861 | CS3: 279820.57 | CT3: 10791056 | CU3: 0 | CV3: 465346 | CW3: 395943 | CX3: 362249 | CY3: 33694 | CZ3: 69403 | DA3: 36636 | DB3: 32767 | DC3: 255385 | DD3: 5407 | DE3: 224825 | DF3: 209134 | DG3: 15691 | DH3: 30560 | DI3: 17462 | DJ3: 13098 | DK3: 108889 | DL3: 87969 | DM3: 80744 | DN3: 7225 | DO3: 20920 | DP3: 11751 | DQ3: 9169 | DR3: 37467 | DS3: 136 | DT3: 26808 | DU3: 22411 | DV3: 4397 | DW3: 10659 | DX3: 4049 | DY3: 6610 | DZ3: 58062 | EA3: 51845 | EB3: 46370 | EC3: 5475 | ED3: 6217 | EE3: 3342 | EF3: 2875 | EG3: 16313 | EH3: 10149 | EI3: 9379 | EJ3: 770 | EK3: 6164 | EL3: 5572 | EM3: 592 | EN3: 13222 | EO3: 7087 | EP3: 962 | EQ3: 5173 | ER3: 1793 | ES3: 0 | ET3: 122 | EU3: 3463 | EV3: 2798 | EW3: 484 | EX3: 181 | EY3: 2380 | EZ3: 2130 | FA3: 250 | FB3: 5188
A4: 1 | B4: 成人非手术 | C4: 内科 | D4: 210990 | E4: 210990 | F4: 0 | G4: 1084 | H4: 0 | I4: 18 | J4: 0 | K4: 0 | L4: 0 | M4: 0 | N4: 0 | O4: 530057.92 | P4: 491380.33 | Q4: 472210.09 | R4: 19170.24 | S4: 38677.59 | T4: 31098.94 | U4: 7578.65 | V4: 530057.92 | W4: 491380.33 | X4: 472210.09 | Y4: 19170.24 | Z4: 38677.59 | AA4: 31098.94 | AB4: 7578.65 | AC4: 318013.92 | AD4: 303723.33 | AE4: 300395.09 | AF4: 3328.24 | AG4: 14290.59 | AH4: 13595.94 | AI4: 694.65 | AJ4: 1054 | AK4: 882 | AL4: 882 | AM4: 0 | AN4: 172 | AO4: 172 | AP4: 0 | AQ4: 178887 | AR4: 157880 | AS4: 143791 | AT4: 14089 | AU4: 21007 | AV4: 15851 | AW4: 5156 | AX4: 32103 | AY4: 28895 | AZ4: 27142 | BA4: 1753 | BB4: 3208 | BC4: 1480 | BD4: 1728 | BE4: 0 | BF4: 0 | BG4: 0 | BH4: 0 | BI4: 0 | BJ4: 0 | BK4: 0 | BL4: 0 | BM4: 0 | BN4: 0 | BO4: 0 | BP4: 0 | BQ4: 0 | BR4: 0 | BS4: 0 | BT4: 0 | BU4: 0 | BV4: 0 | BW4: 0 | BX4: 0 | BY4: 0 | BZ4: 0 | CA4: 0 | CB4: 0 | CC4: 0 | CD4: 0 | CE4: 0 | CF4: 0 | CG4: 0 | CH4: 0 | CI4: 0 | CJ4: 0 | CK4: 0 | CL4: 0 | CM4: 0 | CN4: 0 | CO4: 295279.04 | CP4: 155014.39 | CQ4: 68454.13 | CR4: 11310.36 | CS4: 0 | CT4: 0 | CU4: 0 | CV4: 1084 | CW4: 1004 | CX4: 970 | CY4: 34 | CZ4: 80 | DA4: 57 | DB4: 23 | DC4: 820 | DD4: 47 | DE4: 773 | DF4: 755 | DG4: 18 | DH4: 47 | DI4: 41 | DJ4: 6 | DK4: 207 | DL4: 190 | DM4: 184 | DN4: 6 | DO4: 17 | DP4: 15 | DQ4: 2 | DR4: 10 | DS4: 0 | DT4: 7 | DU4: 4 | DV4: 3 | DW4: 3 | DX4: 0 | DY4: 3 | DZ4: 0 | EA4: 0 | EB4: 0 | EC4: 0 | ED4: 0 | EE4: 0 | EF4: 0 | EG4: 0 | EH4: 0 | EI4: 0 | EJ4: 0 | EK4: 0 | EL4: 0 | EM4: 0 | EN4: 0 | EO4: 0 | EP4: 0 | EQ4: 0 | ER4: 0 | ES4: 0 | ET4: 0 | EU4: 0 | EV4: 0 | EW4: 0 | EX4: 0 | EY4: 0 | EZ4: 0 | FA4: 0 | FB4: 0
A5: 2 | B5: 成人非手术 | C5: 呼吸内科 | D5: 5743610 | E5: 2473467 | F5: 3270143 | G5: 10858 | H5: 340 | I5: 11502 | J5: 0 | K5: 0 | L5: 201558.5 | M5: 3928 | N5: 0 | O5: 10923919 | P5: 8259203.3 | Q5: 8089892.5 | R5: 169310.85 | S5: 2664715.5 | T5: 2476119.2 | U5: 188596.31 | V5: 5052053 | W5: 4417989.1 | X5: 4280274.5 | Y5: 137714.54 | Z5: 634063.99 | AA5: 460326.47 | AB5: 173737.52 | AC5: 2507130.3 | AD5: 2173417 | AE5: 2129423.4 | AF5: 43993.54 | AG5: 333713.35 | AH5: 255796.83 | AI5: 77916.52 | AJ5: 71455.72 | AK5: 62491.08 | AL5: 60164.08 | AM5: 2327 | AN5: 8964.64 | AO5: 6029.64 | AP5: 2935 | AQ5: 2076910 | AR5: 1837741 | AS5: 1762625 | AT5: 75116 | AU5: 239169 | AV5: 164325 | AW5: 74844 | AX5: 396557 | AY5: 344340 | AZ5: 328062 | BA5: 16278 | BB5: 52217 | BC5: 34175 | BD5: 18042 | BE5: 5871865.8 | BF5: 3841214.2 | BG5: 3809617.9 | BH5: 31596.31 | BI5: 2030651.5 | BJ5: 2015792.7 | BK5: 14858.79 | BL5: 2420489.4 | BM5: 1566584.5 | BN5: 1548759.9 | BO5: 17824.62 | BP5: 853904.9 | BQ5: 853761.81 | BR5: 143.09 | BS5: 181233.37 | BT5: 118209.25 | BU5: 117998.56 | BV5: 210.69 | BW5: 63024.12 | BX5: 61750.42 | BY5: 1273.7 | BZ5: 2557112 | CA5: 1660445 | CB5: 1649058 | CC5: 11387 | CD5: 896667 | CE5: 884599 | CF5: 12068 | CG5: 713031 | CH5: 495975.5 | CI5: 493801.5 | CJ5: 2174 | CK5: 217055.5 | CL5: 215681.5 | CM5: 1374 | CN5: 25 | CO5: 3106612.2 | CP5: 1604478.9 | CQ5: 91788.1 | CR5: 249173.8 | CS5: 0 | CT5: 0 | CU5: 0 | CV5: 10858 | CW5: 9614 | CX5: 9269 | CY5: 345 | CZ5: 1244 | DA5: 854 | DB5: 390 | DC5: 8091 | DD5: 59 | DE5: 7212 | DF5: 6974 | DG5: 238 | DH5: 879 | DI5: 603 | DJ5: 276 | DK5: 2400 | DL5: 2096 | DM5: 2010 | DN5: 86 | DO5: 304 | DP5: 218 | DQ5: 86 | DR5: 307 | DS5: 1 | DT5: 248 | DU5: 229 | DV5: 19 | DW5: 59 | DX5: 33 | DY5: 26 | DZ5: 0 | EA5: 0 | EB5: 0 | EC5: 0 | ED5: 0 | EE5: 0 | EF5: 0 | EG5: 340 | EH5: 225 | EI5: 223 | EJ5: 2 | EK5: 115 | EL5: 114 | EM5: 1 | EN5: 208 | EO5: 3 | EP5: 0 | EQ5: 205 | ER5: 1 | ES5: 0 | ET5: 1 | EU5: 1 | EV5: 1 | EW5: 0 | EX5: 0 | EY5: 0 | EZ5: 0 | FA5: 0 | FB5: 99
A6: 3 | B6: 成人非手术 | C6: 消化内科（内窥镜诊治部） | D6: 11432853 | E6: 6981108 | F6: 4451745 | G6: 23158 | H6: 737 | I6: 472266 | J6: 30900 | K6: 0 | L6: 385759 | M6: 495540 | N6: 1397 | O6: 20840483 | P6: 17231788 | Q6: 16550936 | R6: 680852.02 | S6: 3608694.5 | T6: 2986734.8 | U6: 621959.68 | V6: 12923344 | W6: 11282768 | X6: 10674431 | Y6: 608336.49 | Z6: 1640576.7 | AA6: 1087990.7 | AB6: 552585.93 | AC6: 5239104.2 | AD6: 4637267.5 | AE6: 4506613 | AF6: 130654.49 | AG6: 601836.66 | AH6: 420962.73 | AI6: 180873.93 | AJ6: 703132.29 | AK6: 612125.29 | AL6: 584896.29 | AM6: 27229 | AN6: 91007 | AO6: 69451 | AP6: 21556 | AQ6: 4965555 | AR6: 4322568 | AS6: 4147890 | AT6: 174678 | AU6: 642987 | AV6: 452893 | AW6: 190094 | AX6: 2015553 | AY6: 1710807 | AZ6: 1435032 | BA6: 275775 | BB6: 304746 | BC6: 144684 | BD6: 160062 | BE6: 7917138.3 | BF6: 5949020.4 | BG6: 5876504.9 | BH6: 72515.53 | BI6: 1968117.8 | BJ6: 1898744.1 | BK6: 69373.75 | BL6: 1423513.2 | BM6: 1053361.7 | BN6: 1044954 | BO6: 8407.65 | BP6: 370151.53 | BQ6: 360460.12 | BR6: 9691.41 | BS6: 2041880.1 | BT6: 1595162.3 | BU6: 1575099.4 | BV6: 20062.88 | BW6: 446717.81 | BX6: 418325.47 | BY6: 28392.34 | BZ6: 2879927 | CA6: 2082617 | CB6: 2058262 | CC6: 24355 | CD6: 797310 | CE6: 775874 | CF6: 21436 | CG6: 1571818 | CH6: 1217879.5 | CI6: 1198189.5 | CJ6: 19690 | CK6: 353938.5 | CL6: 344084.5 | CM6: 9854 | CN6: -981 | CO6: 6424854 | CP6: 3097263.5 | CQ6: 1826549.8 | CR6: 1574677.2 | CS6: 0 | CT6: 96162.56 | CU6: 0 | CV6: 23158 | CW6: 20250 | CX6: 19321 | CY6: 929 | CZ6: 2908 | DA6: 1894 | DB6: 1014 | DC6: 16127 | DD6: 251 | DE6: 14217 | DF6: 13703 | DG6: 514 | DH6: 1910 | DI6: 1272 | DJ6: 638 | DK6: 5607 | DL6: 4839 | DM6: 4665 | DN6: 174 | DO6: 768 | DP6: 540 | DQ6: 228 | DR6: 1173 | DS6: 0 | DT6: 957 | DU6: 722 | DV6: 235 | DW6: 216 | DX6: 78 | DY6: 138 | DZ6: 0 | EA6: 0 | EB6: 0 | EC6: 0 | ED6: 0 | EE6: 0 | EF6: 0 | EG6: 737 | EH6: 550 | EI6: 545 | EJ6: 5 | EK6: 187 | EL6: 181 | EM6: 6 | EN6: 860 | EO6: 0 | EP6: 0 | EQ6: 860 | ER6: 0 | ES6: 0 | ET6: 98 | EU6: 73 | EV6: 0 | EW6: 0 | EX6: 73 | EY6: 0 | EZ6: 0 | FA6: 0 | FB6: 54
A7: 4 | B7: 成人非手术 | C7: 神经内科 | D7: 6972544.5 | E7: 3626581.5 | F7: 3345963 | G7: 15467 | H7: 306 | I7: 826 | J7: 0 | K7: 93509.65 | L7: 156244.5 | M7: 59201 | N7: 399.07 | O7: 15524657 | P7: 12939918 | Q7: 12664442 | R7: 275476.47 | S7: 2584739.1 | T7: 2257222.1 | U7: 327516.94 | V7: 7964990.2 | W7: 7011810.4 | X7: 6783101 | Y7: 228709.37 | Z7: 953179.89 | AA7: 713075.13 | AB7: 240104.76 | AC7: 4327761.5 | AD7: 3908922.6 | AE7: 3820626.2 | AF7: 88296.37 | AG7: 418838.89 | AH7: 317814.13 | AI7: 101024.76 | AJ7: 10647.28 | AK7: 8239.28 | AL7: 7594.28 | AM7: 645 | AN7: 2408 | AO7: 1763 | AP7: 645 | AQ7: 3007835 | AR7: 2564902 | AS7: 2451381 | AT7: 113521 | AU7: 442933 | AV7: 332149 | AW7: 110784 | AX7: 618746.5 | AY7: 529746.5 | AZ7: 503499.5 | BA7: 26247 | BB7: 89000 | BC7: 61349 | BD7: 27651 | BE7: 7559667.2 | BF7: 5928108 | BG7: 5881340.9 | BH7: 46767.1 | BI7: 1631559.2 | BJ7: 1544147 | BK7: 87412.18 | BL7: 1399756.3 | BM7: 1085758.6 | BN7: 1077473 | BO7: 8285.65 | BP7: 313997.68 | BQ7: 297799.76 | BR7: 16197.92 | BS7: 2813947.9 | BT7: 2299958.4 | BU7: 2296061.5 | BV7: 3896.95 | BW7: 513989.52 | BX7: 507281.26 | BY7: 6708.26 | BZ7: 2507090 | CA7: 1852666 | CB7: 1827609 | CC7: 25057 | CD7: 654424 | CE7: 599601 | CF7: 54823 | CG7: 838873 | CH7: 689725 | CI7: 680197.5 | CJ7: 9527.5 | CK7: 149148 | CL7: 139465 | CM7: 9683 | CN7: -60 | CO7: 3960365 | CP7: 1616226.9 | CQ7: 1430226.6 | CR7: 958171.78 | CS7: 0 | CT7: 0 | CU7: 0 | CV7: 15467 | CW7: 13804 | CX7: 13267 | CY7: 537 | CZ7: 1663 | DA7: 1173 | DB7: 490 | DC7: 11687 | DD7: 271 | DE7: 10604 | DF7: 10240 | DG7: 364 | DH7: 1083 | DI7: 766 | DJ7: 317 | DK7: 2591 | DL7: 2219 | DM7: 2112 | DN7: 107 | DO7: 372 | DP7: 276 | DQ7: 96 | DR7: 918 | DS7: 0 | DT7: 726 | DU7: 674 | DV7: 52 | DW7: 192 | DX7: 131 | DY7: 61 | DZ7: 0 | EA7: 0 | EB7: 0 | EC7: 0 | ED7: 0 | EE7: 0 | EF7: 0 | EG7: 306 | EH7: 235 | EI7: 231 | EJ7: 4 | EK7: 71 | EL7: 66 | EM7: 5 | EN7: 126 | EO7: 0 | EP7: 27 | EQ7: 99 | ER7: 0 | ES7: 0 | ET7: 0 | EU7: 4 | EV7: 0 | EW7: 4 | EX7: 0 | EY7: 23 | EZ7: 0 | FA7: 23 | FB7: 86
A8: 5 | B8: 成人非手术 | C8: 心血管内科 | D8: 18452422 | E8: 4874729 | F8: 13577693 | G8: 36241 | H8: 1191 | I8: 5742 | J8: 0 | K8: 0 | L8: 238314.5 | M8: 2970828 | N8: 456.83 | O8: 73227690 | P8: 56427676 | Q8: 55729351 | R8: 698324.99 | S8: 16800013 | T8: 16420941 | U8: 379072.27 | V8: 16650715 | W8: 15304543 | X8: 15079078 | Y8: 225465.25 | Z8: 1346171.7 | AA8: 1122950.7 | AB8: 223220.95 | AC8: 11715680 | AD8: 10878793 | AE8: 10774702 | AF8: 104091.25 | AG8: 836886.69 | AH8: 735685.74 | AI8: 101200.95 | AJ8: 60306 | AK8: 53269 | AL8: 51779 | AM8: 1490 | AN8: 7037 | AO8: 4887 | AP8: 2150 | AQ8: 3631631 | AR8: 3265794 | AS8: 3177688 | AT8: 88106 | AU8: 365837 | AV8: 280305 | AW8: 85532 | AX8: 1243098 | AY8: 1106687 | AZ8: 1074909 | BA8: 31778 | BB8: 136411 | BC8: 102073 | BD8: 34338 | BE8: 56576975 | BF8: 41123133 | BG8: 40650273 | BH8: 472859.74 | BI8: 15453842 | BJ8: 15297990 | BK8: 155851.32 | BL8: 2914392.3 | BM8: 2272102 | BN8: 2248265.6 | BO8: 23836.36 | BP8: 642290.26 | BQ8: 636215.9 | BR8: 6074.36 | BS8: 40084890 | BT8: 28689193 | BU8: 28353638 | BV8: 335555.13 | BW8: 11395697 | BX8: 11292577 | BY8: 103119.96 | BZ8: 8590941 | CA8: 6458582 | CB8: 6393427 | CC8: 65155 | CD8: 2132359 | CE8: 2106561 | CF8: 25798 | CG8: 4986752 | CH8: 3703256.2 | CI8: 3654943 | CJ8: 48313.25 | CK8: 1283495.8 | CL8: 1262636.8 | CM8: 20859 | CN8: 0 | CO8: 7696489 | CP8: 6051406.9 | CQ8: 2468449.1 | CR8: 434369.72 | CS8: 0 | CT8: 0 | CU8: 0 | CV8: 36241 | CW8: 33096 | CX8: 32455 | CY8: 641 | CZ8: 3145 | DA8: 2470 | DB8: 675 | DC8: 24540 | DD8: 507 | DE8: 22707 | DF8: 22330 | DG8: 377 | DH8: 1833 | DI8: 1441 | DJ8: 392 | DK8: 10662 | DL8: 9489 | DM8: 9257 | DN8: 232 | DO8: 1173 | DP8: 944 | DQ8: 229 | DR8: 532 | DS8: 0 | DT8: 406 | DU8: 382 | DV8: 24 | DW8: 126 | DX8: 81 | DY8: 45 | DZ8: 0 | EA8: 0 | EB8: 0 | EC8: 0 | ED8: 0 | EE8: 0 | EF8: 0 | EG8: 1191 | EH8: 893 | EI8: 886 | EJ8: 7 | EK8: 298 | EL8: 296 | EM8: 2 | EN8: 1156 | EO8: 171 | EP8: 570 | EQ8: 415 | ER8: 0 | ES8: 0 | ET8: 0 | EU8: 518 | EV8: 165 | EW8: 353 | EX8: 0 | EY8: 43 | EZ8: 2 | FA8: 41 | FB8: 290
A9: 6 | B9: 成人非手术 | C9: 血液内科 | D9: 2099214 | E9: 263441 | F9: 1835773 | G9: 1416 | H9: 386 | I9: 986 | J9: 0 | K9: 0 | L9: 101490 | M9: 5289 | N9: 519.12 | O9: 8213142.6 | P9: 4135836.6 | Q9: 4125777.5 | R9: 10059.11 | S9: 4077305.9 | T9: 4030383 | U9: 46922.87 | V9: 1127742.8 | W9: 980816.06 | X9: 971400.45 | Y9: 9415.61 | Z9: 146926.77 | AA9: 128171.57 | AB9: 18755.2 | AC9: 851849.53 | AD9: 756557.76 | AE9: 754348.15 | AF9: 2209.61 | AG9: 95291.77 | AH9: 88191.57 | AI9: 7100.2 | AJ9: 12452.3 | AK9: 12194.3 | AL9: 12194.3 | AM9: 0 | AN9: 258 | AO9: 258 | AP9: 0 | AQ9: 209898 | AR9: 168826 | AS9: 163410 | AT9: 5416 | AU9: 41072 | AV9: 31356 | AW9: 9716 | AX9: 53543 | AY9: 43238 | AZ9: 41448 | BA9: 1790 | BB9: 10305 | BC9: 8366 | BD9: 1939 | BE9: 7085399.7 | BF9: 3155020.6 | BG9: 3154377.1 | BH9: 643.5 | BI9: 3930379.1 | BJ9: 3902211.5 | BK9: 28167.67 | BL9: 5022957.5 | BM9: 2246441.6 | BN9: 2246441.6 | BO9: 0 | BP9: 2776516 | BQ9: 2760374.6 | BR9: 16141.35 | BS9: 226669.18 | BT9: 83771.03 | BU9: 83771.03 | BV9: 0 | BW9: 142898.15 | BX9: 141183.33 | BY9: 1714.82 | BZ9: 1304941 | CA9: 615656 | CB9: 615089 | CC9: 567 | CD9: 689285 | CE9: 682633 | CF9: 6652 | CG9: 530832 | CH9: 209152 | CI9: 209075.5 | CJ9: 76.5 | CK9: 321680 | CL9: 318020.5 | CM9: 3659.5 | CN9: 0 | CO9: 285085.98 | CP9: 699225.37 | CQ9: 130565.12 | CR9: 12866.36 | CS9: 0 | CT9: 0 | CU9: 0 | CV9: 1416 | CW9: 1125 | CX9: 1076 | CY9: 49 | CZ9: 291 | DA9: 238 | DB9: 53 | DC9: 851 | DD9: 0 | DE9: 654 | DF9: 628 | DG9: 26 | DH9: 197 | DI9: 160 | DJ9: 37 | DK9: 548 | DL9: 457 | DM9: 434 | DN9: 23 | DO9: 91 | DP9: 76 | DQ9: 15 | DR9: 17 | DS9: 0 | DT9: 14 | DU9: 14 | DV9: 0 | DW9: 3 | DX9: 2 | DY9: 1 | DZ9: 0 | EA9: 0 | EB9: 0 | EC9: 0 | ED9: 0 | EE9: 0 | EF9: 0 | EG9: 386 | EH9: 176 | EI9: 175 | EJ9: 1 | EK9: 210 | EL9: 209 | EM9: 1 | EN9: 268 | EO9: 0 | EP9: 0 | EQ9: 268 | ER9: 0 | ES9: 0 | ET9: 0 | EU9: 0 | EV9: 0 | EW9: 0 | EX9: 0 | EY9: 0 | EZ9: 0 | FA9: 0 | FB9: 39
A10: 7 | B10: 成人非手术 | C10: 肾脏风湿免疫科 | D10: 7367993.5 | E10: 5188718 | F10: 2179275.5 | G10: 8314 | H10: 250 | I10: 3630905 | J10: 0 | K10: 0 | L10: 141301.5 | M10: 45729 | N10: 0 | O10: 13471348 | P10: 11874330 | Q10: 11740331 | R10: 133999.08 | S10: 1597018.1 | T10: 1439276.5 | U10: 157741.53 | V10: 10113520 | W10: 9321683.6 | X10: 9215928.1 | Y10: 105755.5 | Z10: 791836.85 | AA10: 653816.03 | AB10: 138020.82 | AC10: 3995686.3 | AD10: 3666715.5 | AE10: 3626135.5 | AF10: 40579.96 | AG10: 328970.81 | AH10: 260195.17 | AI10: 68775.64 | AJ10: 929116.17 | AK10: 887282.13 | AL10: 881691.59 | AM10: 5590.54 | AN10: 41834.04 | AO10: 34666.86 | AP10: 7167.18 | AQ10: 1261705 | AR10: 1105671 | AS10: 1069571 | AT10: 36100 | AU10: 156034 | AV10: 119885 | AW10: 36149 | AX10: 3927013 | AY10: 3662015 | AZ10: 3638530 | BA10: 23485 | BB10: 264998 | BC10: 239069 | BD10: 25929 | BE10: 3357827.4 | BF10: 2552646.2 | BG10: 2524402.6 | BH10: 28243.58 | BI10: 805181.22 | BJ10: 785460.51 | BK10: 19720.71 | BL10: 995537.89 | BM10: 797627.04 | BN10: 793281.16 | BO10: 4345.88 | BP10: 197910.85 | BQ10: 196431.03 | BR10: 1479.82 | BS10: 183014.04 | BT10: 139315.67 | BU10: 139089.47 | BV10: 226.2 | BW10: 43698.37 | BX10: 43424.98 | BY10: 273.39 | BZ10: 1631340 | CA10: 1210610 | CB10: 1189086 | CC10: 21524 | CD10: 420730 | CE10: 404968 | CF10: 15762 | CG10: 547935.5 | CH10: 405093.5 | CI10: 402946 | CJ10: 2147.5 | CK10: 142842 | CL10: 140636.5 | CM10: 2205.5 | CN10: 0 | CO10: 1474700.8 | CP10: 1616938.7 | CQ10: 6852330 | CR10: 169550.97 | CS10: 0 | CT10: 0 | CU10: 0 | CV10: 8314 | CW10: 7420 | CX10: 7214 | CY10: 206 | CZ10: 894 | DA10: 653 | DB10: 241 | DC10: 6026 | DD10: 108 | DE10: 5416 | DF10: 5261 | DG10: 155 | DH10: 610 | DI10: 452 | DJ10: 158 | DK10: 2030 | DL10: 1795 | DM10: 1752 | DN10: 43 | DO10: 235 | DP10: 175 | DQ10: 60 | DR10: 150 | DS10: 0 | DT10: 114 | DU10: 108 | DV10: 6 | DW10: 36 | DX10: 25 | DY10: 11 | DZ10: 0 | EA10: 0 | EB10: 0 | EC10: 0 | ED10: 0 | EE10: 0 | EF10: 0 | EG10: 250 | EH10: 185 | EI10: 183 | EJ10: 2 | EK10: 65 | EL10: 63 | EM10: 2 | EN10: 71 | EO10: 18 | EP10: 0 | EQ10: 53 | ER10: 0 | ES10: 0 | ET10: 0 | EU10: 0 | EV10: 0 | EW10: 0 | EX10: 0 | EY10: 0 | EZ10: 0 | FA10: 0 | FB10: 149
A11: 8 | B11: 成人非手术 | C11: 内分泌科 | D11: 6248309 | E11: 4211805 | F11: 2036504 | G11: 18604 | H11: 214 | I11: 7038 | J11: 1148 | K11: 0 | L11: 205970.5 | M11: 8960 | N11: 0 | O11: 11514934 | P11: 10237945 | Q11: 10059900 | R11: 178045.52 | S11: 1276988.4 | T11: 1071549.2 | U11: 205439.26 | V11: 8897351.9 | W11: 8146723.3 | X11: 7968677.8 | Y11: 178045.52 | Z11: 750628.63 | AA11: 592793.65 | AB11: 157834.98 | AC11: 4596625.7 | AD11: 4256485.3 | AE11: 4196368.6 | AF11: 60116.72 | AG11: 340140.43 | AH11: 290620.65 | AI11: 49519.78 | AJ11: 88921.2 | AK11: 81103 | AL11: 79615.2 | AM11: 1487.8 | AN11: 7818.2 | AO11: 6592 | AP11: 1226.2 | AQ11: 3543082 | AR11: 3207566 | AS11: 3114547 | AT11: 93019 | AU11: 335516 | AV11: 245449 | AW11: 90067 | AX11: 668723 | AY11: 601569 | AZ11: 578147 | BA11: 23422 | BB11: 67154 | BC11: 50132 | BD11: 17022 | BE11: 2617581.6 | BF11: 2091221.8 | BG11: 2091221.8 | BH11: 0 | BI11: 526359.82 | BJ11: 478755.54 | BK11: 47604.28 | BL11: 534509.3 | BM11: 429732.53 | BN11: 429732.53 | BO11: 0 | BP11: 104776.77 | BQ11: 94013.87 | BR11: 10762.9 | BS11: 46568.32 | BT11: 38837.27 | BU11: 38837.27 | BV11: 0 | BW11: 7731.05 | BX11: 6800.67 | BY11: 930.38 | BZ11: 1580809 | CA11: 1260897 | CB11: 1260897 | CC11: 0 | CD11: 319912 | CE11: 291584 | CF11: 28328 | CG11: 455695 | CH11: 361755 | CI11: 361755 | CJ11: 0 | CK11: 93940 | CL11: 86357 | CM11: 7583 | CN11: -90 | CO11: 4815032.5 | CP11: 2871145.7 | CQ11: 839638.59 | CR11: 371535.07 | CS11: 0 | CT11: 0 | CU11: 0 | CV11: 18604 | CW11: 16899 | CX11: 16433 | CY11: 466 | CZ11: 1705 | DA11: 1292 | DB11: 413 | DC11: 12632 | DD11: 208 | DE11: 11526 | DF11: 11230 | DG11: 296 | DH11: 1106 | DI11: 841 | DJ11: 265 | DK11: 5295 | DL11: 4775 | DM11: 4629 | DN11: 146 | DO11: 520 | DP11: 406 | DQ11: 114 | DR11: 462 | DS11: 7 | DT11: 395 | DU11: 374 | DV11: 21 | DW11: 67 | DX11: 45 | DY11: 22 | DZ11: 0 | EA11: 0 | EB11: 0 | EC11: 0 | ED11: 0 | EE11: 0 | EF11: 0 | EG11: 214 | EH11: 172 | EI11: 167 | EJ11: 5 | EK11: 42 | EL11: 36 | EM11: 6 | EN11: 1 | EO11: 0 | EP11: 0 | EQ11: 1 | ER11: 0 | ES11: 0 | ET11: 0 | EU11: 0 | EV11: 0 | EW11: 0 | EX11: 0 | EY11: 0 | EZ11: 0 | FA11: 0 | FB11: 197
A12: 9 | B12: 成人非手术 | C12: 老年医学科 | D12: 4062487.5 | E12: 257381.5 | F12: 3805106 | G12: 2336 | H12: 67 | I12: 8342 | J12: 0 | K12: 56510.61 | L12: 754731.5 | M12: 23002 | N12: 761.79 | O12: 7445922.8 | P12: 7414010.7 | Q12: 7404248.1 | R12: 9762.59 | S12: 31912.16 | T12: 18441.51 | U12: 13470.65 | V12: 1631098.5 | W12: 1599186.3 | X12: 1589423.8 | Y12: 9762.59 | Z12: 31912.16 | AA12: 18441.51 | AB12: 13470.65 | AC12: 1364326.6 | AD12: 1337916.4 | AE12: 1330875.8 | AF12: 7040.59 | AG12: 26410.16 | AH12: 15133.51 | AI12: 11276.65 | AJ12: 9390.45 | AK12: 9302.45 | AL12: 9302.45 | AM12: 0 | AN12: 88 | AO12: 43 | AP12: 45 | AQ12: 186999 | AR12: 183867 | AS12: 181776 | AT12: 2091 | AU12: 3132 | AV12: 2268 | AW12: 864 | AX12: 70382.5 | AY12: 68100.5 | AZ12: 67469.5 | BA12: 631 | BB12: 2282 | BC12: 997 | BD12: 1285 | BE12: 5814824.3 | BF12: 5814824.3 | BG12: 5814824.3 | BH12: 0 | BI12: 0 | BJ12: 0 | BK12: 0 | BL12: 1860077.9 | BM12: 1860077.9 | BN12: 1860077.9 | BO12: 0 | BP12: 0 | BQ12: 0 | BR12: 0 | BS12: 149640.37 | BT12: 149640.37 | BU12: 149640.37 | BV12: 0 | BW12: 0 | BX12: 0 | BY12: 0 | BZ12: 1717023 | CA12: 1717023 | CB12: 1717023 | CC12: 0 | CD12: 0 | CE12: 0 | CF12: 0 | CG12: 2088083 | CH12: 2088083 | CI12: 2088083 | CJ12: 0 | CK12: 0 | CL12: 0 | CM12: 0 | CN12: 0 | CO12: 1611616 | CP12: 0 | CQ12: 75 | CR12: 19407.5 | CS12: 0 | CT12: 0 | CU12: 0 | CV12: 2336 | CW12: 2289 | CX12: 2282 | CY12: 7 | CZ12: 47 | DA12: 37 | DB12: 10 | DC12: 2323 | DD12: 0 | DE12: 2285 | DF12: 2282 | DG12: 3 | DH12: 38 | DI12: 37 | DJ12: 1 | DK12: 0 | DL12: 0 | DM12: 0 | DN12: 0 | DO12: 0 | DP12: 0 | DQ12: 0 | DR12: 13 | DS12: 0 | DT12: 4 | DU12: 0 | DV12: 4 | DW12: 9 | DX12: 0 | DY12: 9 | DZ12: 0 | EA12: 0 | EB12: 0 | EC12: 0 | ED12: 0 | EE12: 0 | EF12: 0 | EG12: 67 | EH12: 67 | EI12: 67 | EJ12: 0 | EK12: 0 | EL12: 0 | EM12: 0 | EN12: 35 | EO12: 0 | EP12: 0 | EQ12: 35 | ER12: 0 | ES12: 0 | ET12: 0 | EU12: 0 | EV12: 0 | EW12: 0 | EX12: 0 | EY12: 0 | EZ12: 0 | FA12: 0 | FB12: 0
A13: 10 | B13: 成人非手术 | C13: 全科医学科 | D13: 1779935.8 | E13: 604848 | F13: 1175087.8 | G13: 3411 | H13: 75 | I13: 132 | J13: 0 | K13: 0 | L13: 37921.5 | M13: 48467.8 | N13: 0 | O13: 2908503.5 | P13: 2265453.7 | Q13: 2201044.4 | R13: 64409.34 | S13: 643049.78 | T13: 614396.95 | U13: 28652.83 | V13: 1412393.7 | W13: 1279667.4 | X13: 1258071.7 | Y13: 21595.68 | Z13: 132726.37 | AA13: 104073.54 | AB13: 28652.83 | AC13: 805793.73 | AD13: 750893.36 | AE13: 746243.68 | AF13: 4649.68 | AG13: 54900.37 | AH13: 48444.54 | AI13: 6455.83 | AJ13: 1752 | AK13: 1583 | AL13: 1583 | AM13: 0 | AN13: 169 | AO13: 126 | AP13: 43 | AQ13: 513570 | AR13: 443982 | AS13: 428671 | AT13: 15311 | AU13: 69588 | AV13: 48854 | AW13: 20734 | AX13: 91278 | AY13: 83209 | AZ13: 81574 | BA13: 1635 | BB13: 8069 | BC13: 6649 | BD13: 1420 | BE13: 1496109.7 | BF13: 985786.33 | BG13: 942972.67 | BH13: 42813.66 | BI13: 510323.41 | BJ13: 510323.41 | BK13: 0 | BL13: 225899.78 | BM13: 156775.99 | BN13: 154261.61 | BO13: 2514.38 | BP13: 69123.79 | BQ13: 69123.79 | BR13: 0 | BS13: 95122.16 | BT13: 55594.64 | BU13: 54839.36 | BV13: 755.28 | BW13: 39527.52 | BX13: 39527.52 | BY13: 0 | BZ13: 565618 | CA13: 369167 | CB13: 357918 | CC13: 11249 | CD13: 196451 | CE13: 196451 | CF13: 0 | CG13: 609469.8 | CH13: 404248.7 | CI13: 375953.7 | CJ13: 28295 | CK13: 205221.1 | CL13: 205221.1 | CM13: 0 | CN13: 0 | CO13: 1222825.7 | CP13: 162239.61 | CQ13: 2660.54 | CR13: 24667.92 | CS13: 0 | CT13: 0 | CU13: 0 | CV13: 3411 | CW13: 3123 | CX13: 3059 | CY13: 64 | CZ13: 288 | DA13: 236 | DB13: 52 | DC13: 3086 | DD13: 61 | DE13: 2832 | DF13: 2783 | DG13: 49 | DH13: 254 | DI13: 212 | DJ13: 42 | DK13: 238 | DL13: 211 | DM13: 202 | DN13: 9 | DO13: 27 | DP13: 19 | DQ13: 8 | DR13: 26 | DS13: 0 | DT13: 22 | DU13: 22 | DV13: 0 | DW13: 4 | DX13: 4 | DY13: 0 | DZ13: 0 | EA13: 0 | EB13: 0 | EC13: 0 | ED13: 0 | EE13: 0 | EF13: 0 | EG13: 75 | EH13: 50 | EI13: 47 | EJ13: 3 | EK13: 25 | EL13: 25 | EM13: 0 | EN13: 6 | EO13: 0 | EP13: 0 | EQ13: 6 | ER13: 0 | ES13: 0 | ET13: 0 | EU13: 0 | EV13: 0 | EW13: 0 | EX13: 0 | EY13: 0 | EZ13: 0 | FA13: 0 | FB13: 0
A14: 11 | B14: 成人手术 | C14: 普外科 | D14: 14792687 | E14: 2553220.5 | F14: 12239466 | G14: 11197 | H14: 1151 | I14: 175110.5 | J14: 123470 | K14: 0 | L14: 916504.75 | M14: 3773027.9 | N14: 3003 | O14: 31673731 | P14: 21547094 | Q14: 21055002 | R14: 492091.72 | S14: 10126637 | T14: 9717516.8 | U14: 409120.38 | V14: 4275525.2 | W14: 3580090.5 | X14: 3427570.6 | Y14: 152519.86 | Z14: 695434.78 | AA14: 549725.23 | AB14: 145709.55 | AC14: 1186994.3 | AD14: 973392.89 | AE14: 943987.05 | AF14: 29405.84 | AG14: 213601.4 | AH14: 189484.86 | AI14: 24116.54 | AJ14: 535310.46 | AK14: 490578.08 | AL14: 477013.06 | AM14: 13565.02 | AN14: 44732.38 | AO14: 35721.37 | AP14: 9011.01 | AQ14: 1822088 | AR14: 1501330 | AS14: 1431913 | AT14: 69417 | AU14: 320758 | AV14: 240327 | AW14: 80431 | AX14: 731132.5 | AY14: 614789.5 | AZ14: 574657.5 | BA14: 40132 | BB14: 116343 | BC14: 84192 | BD14: 32151 | BE14: 27398206 | BF14: 17967003 | BG14: 17627431 | BH14: 339571.86 | BI14: 9431202.4 | BJ14: 9167791.6 | BK14: 263410.83 | BL14: 4990311.1 | BM14: 3191183.1 | BN14: 3144610.8 | BO14: 46572.33 | BP14: 1799128 | BQ14: 1744128.6 | BR14: 54999.36 | BS14: 10168429 | BT14: 6773311.9 | BU14: 6667769.2 | BV14: 105542.78 | BW14: 3395116.6 | BX14: 3318879.9 | BY14: 76236.72 | BZ14: 4572319 | CA14: 2773131 | CB14: 2718023 | CC14: 55108 | CD14: 1799188 | CE14: 1740299 | CF14: 58889 | CG14: 7667147.1 | CH14: 5229377.2 | CI14: 5097028.5 | CJ14: 132348.75 | CK14: 2437769.9 | CL14: 2364484.1 | CM14: 73285.75 | CN14: 1140711.6 | CO14: 1346056.6 | CP14: 1075406.1 | CQ14: 576037.93 | CR14: 137273 | CS14: 0 | CT14: 129945.5 | CU14: 0 | CV14: 11197 | CW14: 9428 | CX14: 8983 | CY14: 445 | CZ14: 1769 | DA14: 1305 | DB14: 464 | DC14: 5569 | DD14: 21 | DE14: 4809 | DF14: 4576 | DG14: 233 | DH14: 760 | DI14: 532 | DJ14: 228 | DK14: 2937 | DL14: 2406 | DM14: 2302 | DN14: 104 | DO14: 531 | DP14: 409 | DQ14: 122 | DR14: 194 | DS14: 0 | DT14: 126 | DU14: 113 | DV14: 13 | DW14: 68 | DX14: 48 | DY14: 20 | DZ14: 2476 | EA14: 2068 | EB14: 1974 | EC14: 94 | ED14: 408 | EE14: 316 | EF14: 92 | EG14: 1151 | EH14: 813 | EI14: 803 | EJ14: 10 | EK14: 338 | EL14: 328 | EM14: 10 | EN14: 1010 | EO14: 762 | EP14: 0 | EQ14: 248 | ER14: 376 | ES14: 0 | ET14: 3 | EU14: 266 | EV14: 202 | EW14: 0 | EX14: 64 | EY14: 194 | EZ14: 194 | FA14: 0 | FB14: 379
A15: 12 | B15: 成人手术 | C15: 神经外科 | D15: 10008305 | E15: 689654 | F15: 9318651 | G15: 3295 | H15: 632 | I15: 537 | J15: 0 | K15: 0 | L15: 635143.25 | M15: 2756204 | N15: 0 | O15: 36684250 | P15: 20216003 | Q15: 19690013 | R15: 525989.89 | S15: 16468248 | T15: 15867837 | U15: 600410.93 | V15: 1045625.5 | W15: 808909.05 | X15: 757974.51 | Y15: 50934.54 | Z15: 236716.46 | AA15: 149251.52 | AB15: 87464.94 | AC15: 345565.51 | AD15: 285819.05 | AE15: 276771.51 | AF15: 9047.54 | AG15: 59746.46 | AH15: 43986.52 | AI15: 15759.94 | AJ15: 10406 | AK15: 8471 | AL15: 8084 | AM15: 387 | AN15: 1935 | AO15: 1204 | AP15: 731 | AQ15: 556861 | AR15: 430826 | AS15: 397012 | AT15: 33814 | AU15: 126035 | AV15: 76335 | AW15: 49700 | AX15: 132793 | AY15: 83793 | AZ15: 76107 | BA15: 7686 | BB15: 49000 | BC15: 27726 | BD15: 21274 | BE15: 35638625 | BF15: 19407094 | BG15: 18932038 | BH15: 475055.35 | BI15: 16231531 | BJ15: 15718585 | BK15: 512945.99 | BL15: 3639828.9 | BM15: 1943397.4 | BN15: 1874619.3 | BO15: 68778.1 | BP15: 1696431.5 | BQ15: 1638530 | BR15: 57901.57 | BS15: 22680145 | BT15: 12822802 | BU15: 12635459 | BV15: 187343 | BW15: 9857342.9 | BX15: 9635128 | BY15: 222214.92 | BZ15: 3615948 | CA15: 1865240 | CB15: 1800781 | CC15: 64459 | CD15: 1750708 | CE15: 1690209 | CF15: 60499 | CG15: 5702703 | CH15: 2775654.3 | CI15: 2621179 | CJ15: 154475.25 | CK15: 2927048.7 | CL15: 2754718.2 | CM15: 172330.5 | CN15: -50 | CO15: 537335.11 | CP15: 406826.83 | CQ15: 69212.97 | CR15: 32250.6 | CS15: 0 | CT15: 519104.78 | CU15: 0 | CV15: 3295 | CW15: 2423 | CX15: 2224 | CY15: 199 | CZ15: 872 | DA15: 524 | DB15: 348 | DC15: 1807 | DD15: 24 | DE15: 1485 | DF15: 1363 | DG15: 122 | DH15: 322 | DI15: 203 | DJ15: 119 | DK15: 1388 | DL15: 902 | DM15: 829 | DN15: 73 | DO15: 486 | DP15: 287 | DQ15: 199 | DR15: 76 | DS15: 0 | DT15: 14 | DU15: 11 | DV15: 3 | DW15: 62 | DX15: 34 | DY15: 28 | DZ15: 0 | EA15: 0 | EB15: 0 | EC15: 0 | ED15: 0 | EE15: 0 | EF15: 0 | EG15: 632 | EH15: 346 | EI15: 329 | EJ15: 17 | EK15: 286 | EL15: 270 | EM15: 16 | EN15: 548 | EO15: 247 | EP15: 157 | EQ15: 144 | ER15: 112 | ES15: 0 | ET15: 0 | EU15: 118 | EV15: 82 | EW15: 11 | EX15: 25 | EY15: 273 | EZ15: 127 | FA15: 146 | FB15: 254
... A66: 63 | B66: 其他 | C66: 临床药物试验办公室GCP | D66: 55044 | E66: 55044 | F66: 0 | G66: 194 | H66: 0 | I66: 0 | J66: 0 | K66: 0 | L66: 0 | M66: 0 | N66: 0 | O66: 57314.82 | P66: 33600.79 | Q66: 0 | R66: 33600.79 | S66: 23714.03 | T66: 0 | U66: 23714.03 | V66: 57314.82 | W66: 33600.79 | X66: 0 | Y66: 33600.79 | Z66: 23714.03 | AA66: 0 | AB66: 23714.03 | AC66: 2232.82 | AD66: 434.79 | AE66: 0 | AF66: 434.79 | AG66: 1798.03 | AH66: 0 | AI66: 1798.03 | AJ66: 38 | AK66: 38 | AL66: 0 | AM66: 38 | AN66: 0 | AO66: 0 | AP66: 0 | AQ66: 50194 | AR66: 30253 | AS66: 0 | AT66: 30253 | AU66: 19941 | AV66: 0 | AW66: 19941 | AX66: 4850 | AY66: 2875 | AZ66: 0 | BA66: 2875 | BB66: 1975 | BC66: 0 | BD66: 1975 | BE66: 0 | BF66: 0 | BG66: 0 | BH66: 0 | BI66: 0 | BJ66: 0 | BK66: 0 | BL66: 0 | BM66: 0 | BN66: 0 | BO66: 0 | BP66: 0 | BQ66: 0 | BR66: 0 | BS66: 0 | BT66: 0 | BU66: 0 | BV66: 0 | BW66: 0 | BX66: 0 | BY66: 0 | BZ66: 0 | CA66: 0 | CB66: 0 | CC66: 0 | CD66: 0 | CE66: 0 | CF66: 0 | CG66: 0 | CH66: 0 | CI66: 0 | CJ66: 0 | CK66: 0 | CL66: 0 | CM66: 0 | CN66: 0 | CO66: 0 | CP66: 0 | CQ66: 57314.82 | CR66: 0 | CS66: 0 | CT66: 0 | CU66: 0 | CV66: 194 | CW66: 115 | CX66: 0 | CY66: 115 | CZ66: 79 | DA66: 0 | DB66: 79 | DC66: 194 | DD66: 0 | DE66: 115 | DF66: 0 | DG66: 115 | DH66: 79 | DI66: 0 | DJ66: 79 | DK66: 0 | DL66: 0 | DM66: 0 | DN66: 0 | DO66: 0 | DP66: 0 | DQ66: 0 | DR66: 0 | DS66: 0 | DT66: 0 | DU66: 0 | DV66: 0 | DW66: 0 | DX66: 0 | DY66: 0 | DZ66: 0 | EA66: 0 | EB66: 0 | EC66: 0 | ED66: 0 | EE66: 0 | EF66: 0 | EG66: 0 | EH66: 0 | EI66: 0 | EJ66: 0 | EK66: 0 | EL66: 0 | EM66: 0 | EN66: 0 | EO66: 0 | EP66: 0 | EQ66: 0 | ER66: 0 | ES66: 0 | ET66: 0 | EU66: 0 | EV66: 0 | EW66: 0 | EX66: 0 | EY66: 0 | EZ66: 0 | FA66: 0 | FB66: 0
A67: 64 | C67: 其它 | D67: 67.5 | E67: 0 | F67: 67.5 | G67: 188 | H67: 74 | I67: 0 | J67: 0 | K67: 0 | L67: 0 | M67: 0 | N67: 0 | O67: 67.5 | P67: 0 | Q67: 0 | R67: 0 | S67: 67.5 | T67: 0 | U67: 67.5 | V67: 0 | W67: 0 | X67: 0 | Y67: 0 | Z67: 0 | AA67: 0 | AB67: 0 | AC67: 0 | AD67: 0 | AE67: 0 | AF67: 0 | AG67: 0 | AH67: 0 | AI67: 0 | AJ67: 0 | AK67: 0 | AL67: 0 | AM67: 0 | AN67: 0 | AO67: 0 | AP67: 0 | AQ67: 0 | AR67: 0 | AS67: 0 | AT67: 0 | AU67: 0 | AV67: 0 | AW67: 0 | AX67: 0 | AY67: 0 | AZ67: 0 | BA67: 0 | BB67: 0 | BC67: 0 | BD67: 0 | BE67: 67.5 | BF67: 0 | BG67: 0 | BH67: 0 | BI67: 67.5 | BJ67: 0 | BK67: 67.5 | BL67: 0 | BM67: 0 | BN67: 0 | BO67: 0 | BP67: 0 | BQ67: 0 | BR67: 0 | BS67: 0 | BT67: 0 | BU67: 0 | BV67: 0 | BW67: 0 | BX67: 0 | BY67: 0 | BZ67: 0 | CA67: 0 | CB67: 0 | CC67: 0 | CD67: 0 | CE67: 0 | CF67: 0 | CG67: 67.5 | CH67: 0 | CI67: 0 | CJ67: 0 | CK67: 67.5 | CL67: 0 | CM67: 67.5 | CN67: 0 | CO67: 0 | CP67: 0 | CQ67: 250 | CR67: 0 | CS67: 0 | CT67: 0 | CU67: 0 | CV67: 188 | CW67: 60 | CX67: 9 | CY67: 51 | CZ67: 128 | DA67: 0 | DB67: 128 | DC67: 188 | DD67: 0 | DE67: 60 | DF67: 9 | DG67: 51 | DH67: 128 | DI67: 0 | DJ67: 128 | DK67: 0 | DL67: 0 | DM67: 0 | DN67: 0 | DO67: 0 | DP67: 0 | DQ67: 0 | DR67: 0 | DS67: 0 | DT67: 0 | DU67: 0 | DV67: 0 | DW67: 0 | DX67: 0 | DY67: 0 | DZ67: 0 | EA67: 0 | EB67: 0 | EC67: 0 | ED67: 0 | EE67: 0 | EF67: 0 | EG67: 74 | EH67: 50 | EI67: 48 | EJ67: 2 | EK67: 24 | EL67: 23 | EM67: 1 | EN67: 0 | EO67: 0 | EP67: 0 | EQ67: 0 | ER67: 0 | ES67: 0 | ET67: 0 | EU67: 0 | EV67: 0 | EW67: 0 | EX67: 0 | EY67: 0 | EZ67: 0 | FA67: 0 | FB67: 0

Sheet 当年累计数据表奉贤
A1: 日期范围：20260401-20260430 | D1: 25 | O1: 1=2+5=8+43 | P1: 2=3+4 | Q1: 3 | R1: 4 | S1: 5=6+7 | T1: 6 | U1: 7 | V1: 8=9+12=15+22+29+36 | W1: 9=10+11 | X1: 10 | Y1: 11 | Z1: 12=13+14 | AA1: 13 | AB1: 14 | AC1: 15=16+19 | AD1: 16=17+18 | AE1: 17 | AF1: 18 | AG1: 19=20+21 | AH1: 20 | AI1: 21 | AJ1: 22=23+26 | AK1: 23=24+25 | AL1: 24 | AM1: 25 | AN1: 26=27+28 | AO1: 27 | AP1: 28 | AQ1: 29=30+33 | AR1: 30=31+32 | AS1: 31 | AT1: 32 | AU1: 33=34+35 | AV1: 34 | AW1: 35 | AX1: 36=37+40 | AY1: 37=38+39 | AZ1: 38 | BA1: 39 | BB1: 40=41+42 | BC1: 41 | BD1: 42 | BE1: 43=50+57+64+71=44+47 | BF1: 44=45+46 | BG1: 45 | BH1: 46 | BI1: 47=48+49 | BJ1: 48 | BK1: 49 | BL1: 50=51+54 | BM1: 51=52+53 | BN1: 52 | BO1: 53 | BP1: 54=55+56 | BQ1: 55 | BR1: 56 | BS1: 57=58+61 | BT1: 58=59+60 | BU1: 59 | BV1: 60 | BW1: 61=62+63 | BX1: 62 | BY1: 63 | BZ1: 64=65+68 | CA1: 65=66+67 | CB1: 66 | CC1: 67 | CD1: 68=69+70 | CE1: 69 | CF1: 70 | CG1: 71=72+75 | CH1: 72=73+74 | CI1: 73 | CJ1: 74 | CK1: 75=76+77 | CL1: 76 | CM1: 77 | CV1: 78=85+93+100+108+86+101=79+82 | CW1: 79=80+81 | CX1: 80 | CY1: 81 | CZ1: 82=83+84 | DA1: 83 | DB1: 84 | DC1: 85=87+90=78-93-100-108-86-101 | DD1: 86 | DE1: 87=88+89 | DF1: 88 | DG1: 89 | DH1: 90=91+92 | DI1: 91 | DJ1: 92 | DK1: 93=94+97 | DL1: 94=95+96 | DM1: 95 | DN1: 96 | DO1: 97=98+99 | DP1: 98 | DQ1: 99 | DR1: 100=102+105 | DS1: 101 | DT1: 102=103+104 | DU1: 103 | DV1: 104 | DW1: 105=106+107 | DX1: 106 | DY1: 107 | DZ1: 108=109+112 | EA1: 109=110+111 | EB1: 110 | EC1: 111 | ED1: 112=113+114 | EE1: 113 | EF1: 114 | EG1: 115=116+119 | EH1: 116=117+118 | EI1: 117 | EJ1: 118 | EK1: 119=120+121 | EL1: 120 | EM1: 121 | EN1: 122=123+124+125 | EO1: 123 | EP1: 124 | EQ1: 125 | EU1: 126=127+128+129 | EV1: 127 | EW1: 128 | EX1: 129 | EY1: 130=131+132 | EZ1: 131 | FA1: 132 | FB1: 133
A2: 序号 | B2: 科室类别 | C2: 科室名称 | D2: 医疗收入不含药耗 | E2: 门急诊收入不含药耗 | F2: 住院收入不含药耗 | G2: 门急诊人次 | H2: 住院人次 | I2: 门急诊治疗收入 | J2: 门急诊手术收入 | K2: 门诊中药饮片收入 | L2: 住院治疗收入 | M2: 住院手术收入 | N2: 住院中药饮片收入 | O2: 医疗收入 | P2: 其中本地病人医疗收入 | Q2: 其中本地病人医保医疗收入 | R2: 其中本地病人自费医疗收入 | S2: 其中异地病人医疗收入 | T2: 其中异地病人医保医疗收入 | U2: 其中异地病人自费医疗收入 | V2: 门急诊收入 | W2: 其中本地病人医疗收入 | X2: 其中本地病人医保医疗收入 | Y2: 其中本地病人自费医疗收入 | Z2: 其中异地病人医疗收入 | AA2: 其中异地病人医保医疗收入 | AB2: 其中异地病人自费医疗收入 | AC2: 门急诊药品收入 | AD2: 其中本地病人医疗收入 | AE2: 其中本地病人医保医疗收入 | AF2: 其中本地病人自费医疗收入 | AG2: 其中异地病人医疗收入 | AH2: 其中异地病人医保医疗收入 | AI2: 其中异地病人自费医疗收入 | AJ2: 门急诊耗材收入 | AK2: 其中本地病人医疗收入 | AL2: 其中本地病人医保医疗收入 | AM2: 其中本地病人自费医疗收入 | AN2: 其中异地病人医疗收入 | AO2: 其中异地病人医保医疗收入 | AP2: 其中异地病人自费医疗收入 | AQ2: 门急诊检查化验收入 | AR2: 其中本地病人医疗收入 | AS2: 其中本地病人医保医疗收入 | AT2: 其中本地病人自费医疗收入 | AU2: 其中异地病人医疗收入 | AV2: 其中异地病人医保医疗收入 | AW2: 其中异地病人自费医疗收入 | AX2: 门急诊劳务收入 | AY2: 其中本地病人医疗收入 | AZ2: 其中本地病人医保医疗收入 | BA2: 其中本地病人自费医疗收入 | BB2: 其中异地病人医疗收入 | BC2: 其中异地病人医保医疗收入 | BD2: 其中异地病人自费医疗收入 | BE2: 住院收入 | BF2: 其中本地病人医疗收入 | BG2: 其中本地病人医保医疗收入 | BH2: 其中本地病人自费医疗收入 | BI2: 其中异地病人医疗收入 | BJ2: 其中异地病人医保医疗收入 | BK2: 其中异地病人自费医疗收入 | BL2: 住院药品收入 | BM2: 其中本地病人医疗收入 | BN2: 其中本地病人医保医疗收入 | BO2: 其中本地病人自费医疗收入 | BP2: 其中异地病人医疗收入 | BQ2: 其中异地病人医保医疗收入 | BR2: 其中异地病人自费医疗收入 | BS2: 住院耗材收入 | BT2: 其中本地病人医疗收入 | BU2: 其中本地病人医保医疗收入 | BV2: 其中本地病人自费医疗收入 | BW2: 其中异地病人医疗收入 | BX2: 其中异地病人医保医疗收入 | BY2: 其中异地病人自费医疗收入 | BZ2: 住院检查化验收入 | CA2: 其中本地病人医疗收入 | CB2: 其中本地病人医保医疗收入 | CC2: 其中本地病人自费医疗收入 | CD2: 其中异地病人医疗收入 | CE2: 其中异地病人医保医疗收入 | CF2: 其中异地病人自费医疗收入 | CG2: 住院劳务收入 | CH2: 其中本地病人医疗收入 | CI2: 其中本地病人医保医疗收入 | CJ2: 其中本地病人自费医疗收入 | CK2: 其中异地病人医疗收入 | CL2: 其中异地病人医保医疗收入 | CM2: 其中异地病人自费医疗收入 | CN2: 急诊收入 | CO2: 普通门诊收入 | CP2: 专家门诊收入 | CQ2: 专病门诊收入 | CR2: 特需门诊收入 | CS2: MDT门诊收入 | CT2: 镜朗诊疗部收入 | CU2: 特需病房收入 | CV2: 门急诊人次 | CW2: 其中本地病人人次 | CX2: 其中本地病人医保人次 | CY2: 其中本地病人自费人次 | CZ2: 其中异地病人人次 | DA2: 其中异地病人医保人次 | DB2: 其中异地病人自费人次 | DC2: 普通门诊 (普通+专病) | DD2: 互联网普通门诊人次 | DE2: 其中本地病人人次 | DF2: 其中本地病人医保人次 | DG2: 其中本地病人自费人次 | DH2: 其中异地病人人次 | DI2: 其中异地病人医保人次 | DJ2: 其中异地病人自费人次 | DK2: 专家门诊 | DL2: 其中本地病人人次 | DM2: 其中本地病人医保人次 | DN2: 其中本地病人自费人次 | DO2: 其中异地病人人次 | DP2: 其中异地病人医保人次 | DQ2: 其中异地病人自费人次 | DR2: 特需门诊 (特需+MDT) | DS2: 互联网特需门诊人次 | DT2: 其中本地病人人次 | DU2: 其中本地病人医保人次 | DV2: 其中本地病人自费人次 | DW2: 其中异地病人人次 | DX2: 其中异地病人医保人次 | DY2: 其中异地病人自费人次 | DZ2: 急诊人次 | EA2: 其中本地病人人次 | EB2: 其中本地病人医保人次 | EC2: 其中本地病人自费人次 | ED2: 其中异地病人人次 | EE2: 其中异地病人医保人次 | EF2: 其中异地病人自费人次 | EG2: 住院人次 | EH2: 其中本地病人人次 | EI2: 其中本地病人医保人次 | EJ2: 其中本地病人自费人次 | EK2: 其中异地病人人次 | EL2: 其中异地病人医保人次 | EM2: 其中异地病人自费人次 | EN2: 手术人次与操作人次 | EO2: 手术人次 | EP2: 介入人次 | EQ2: 操作人次(治疗+诊断) | ER2: 微创手术人次（手术） | ES2: 微创手术人次（介入） | ET2: 微创手术人次（操作） | EU2: 三级手术 | EV2: 三级手术(手术) | EW2: 三级手术(介入) | EX2: 三级手术(操作) | EY2: 四级手术 | EZ2: 四级手术(手术) | FA2: 四级手术(介入) | FB2: 重点病种人次
A3: 小计： | D3: 63035641 | E3: 26460446 | F3: 36575196 | G3: 96874 | H3: 3626 | I3: 3975904.1 | J3: 1220362.2 | K3: 449634.74 | L3: 2637791.4 | M3: 11101801 | N3: 3234.33 | O3: 1.4595393e+08 | P3: 1.0799713e+08 | Q3: 99873532 | R3: 8123601.5 | S3: 37956801 | T3: 33982810 | U3: 3973990.4 | V3: 44517237 | W3: 38292509 | X3: 34983354 | Y3: 3309155.6 | Z3: 6224727.8 | AA3: 3987539.8 | AB3: 2237188.1 | AC3: 16038423 | AD3: 14065901 | AE3: 13302765 | AF3: 763135.7 | AG3: 1972522.2 | AH3: 1430608.1 | AI3: 541914.15 | AJ3: 2018368.7 | AK3: 1794913.1 | AL3: 1466583.2 | AM3: 328329.87 | AN3: 223455.64 | AO3: 140656.47 | AP3: 82799.17 | AQ3: 17326586 | AR3: 14770406 | AS3: 13462756 | AT3: 1307650 | AU3: 2556180 | AV3: 1577459 | AW3: 978721 | AX3: 9133859.2 | AY3: 7661289.2 | AZ3: 6751249.2 | BA3: 910039.99 | BB3: 1472570 | BC3: 838816.25 | BD3: 633753.76 | BE3: 1.014367e+08 | BF3: 69704624 | BG3: 64890178 | BH3: 4814445.9 | BI3: 31732073 | BJ3: 29995271 | BK3: 1736802.4 | BL3: 11351020 | BM3: 6961777.4 | BN3: 6515567.6 | BO3: 446209.81 | BP3: 4389242.5 | BQ3: 4155953.8 | BR3: 233288.72 | BS3: 53510482 | BT3: 37626985 | BU3: 34846189 | BV3: 2780796.4 | BW3: 15883496 | BX3: 14961163 | BY3: 922333.53 | BZ3: 14330608 | CA3: 9832429 | CB3: 9381494 | CC3: 450935 | CD3: 4498179.5 | CE3: 4285196.5 | CF3: 212983 | CG3: 22244587 | CH3: 15283432 | CI3: 14146928 | CJ3: 1136504.6 | CK3: 6961154.8 | CL3: 6592957.7 | CM3: 368197.1 | CN3: 8821136.2 | CO3: 15814905 | CP3: 13122985 | CQ3: 4866573.9 | CR3: 1891036.1 | CS3: 516 | CT3: 384522.6 | CU3: 0 | CV3: 96874 | CW3: 83352 | CX3: 74886 | CY3: 8466 | CZ3: 13522 | DA3: 7980 | DB3: 5542 | DC3: 49568 | DD3: 0 | DE3: 43086 | DF3: 39214 | DG3: 3872 | DH3: 6482 | DI3: 3708 | DJ3: 2774 | DK3: 27179 | DL3: 22567 | DM3: 20273 | DN3: 2294 | DO3: 4612 | DP3: 2842 | DQ3: 1770 | DR3: 2458 | DS3: 0 | DT3: 1894 | DU3: 1679 | DV3: 215 | DW3: 564 | DX3: 272 | DY3: 292 | DZ3: 17669 | EA3: 15805 | EB3: 13720 | EC3: 2085 | ED3: 1864 | EE3: 1158 | EF3: 706 | EG3: 3626 | EH3: 2561 | EI3: 2408 | EJ3: 153 | EK3: 1065 | EL3: 1013 | EM3: 52 | EN3: 3022 | EO3: 1849 | EP3: 283 | EQ3: 890 | ER3: 578 | ES3: 0 | ET3: 56 | EU3: 945 | EV3: 759 | EW3: 132 | EX3: 54 | EY3: 675 | EZ3: 581 | FA3: 94 | FB3: 1237
A4: 1 | B4: 成人非手术 | C4: 内科 | D4: 0 | E4: 0 | F4: 0 | G4: 48 | H4: 0 | I4: 0 | J4: 0 | K4: 0 | L4: 0 | M4: 0 | N4: 0 | O4: 0 | P4: 0 | Q4: 0 | R4: 0 | S4: 0 | T4: 0 | U4: 0 | V4: 0 | W4: 0 | X4: 0 | Y4: 0 | Z4: 0 | AA4: 0 | AB4: 0 | AC4: 0 | AD4: 0 | AE4: 0 | AF4: 0 | AG4: 0 | AH4: 0 | AI4: 0 | AJ4: 0 | AK4: 0 | AL4: 0 | AM4: 0 | AN4: 0 | AO4: 0 | AP4: 0 | AQ4: 0 | AR4: 0 | AS4: 0 | AT4: 0 | AU4: 0 | AV4: 0 | AW4: 0 | AX4: 0 | AY4: 0 | AZ4: 0 | BA4: 0 | BB4: 0 | BC4: 0 | BD4: 0 | BE4: 0 | BF4: 0 | BG4: 0 | BH4: 0 | BI4: 0 | BJ4: 0 | BK4: 0 | BL4: 0 | BM4: 0 | BN4: 0 | BO4: 0 | BP4: 0 | BQ4: 0 | BR4: 0 | BS4: 0 | BT4: 0 | BU4: 0 | BV4: 0 | BW4: 0 | BX4: 0 | BY4: 0 | BZ4: 0 | CA4: 0 | CB4: 0 | CC4: 0 | CD4: 0 | CE4: 0 | CF4: 0 | CG4: 0 | CH4: 0 | CI4: 0 | CJ4: 0 | CK4: 0 | CL4: 0 | CM4: 0 | CN4: 0 | CO4: 0 | CP4: 0 | CQ4: 0 | CR4: 0 | CS4: 0 | CT4: 0 | CU4: 0 | CV4: 48 | CW4: 40 | CX4: 36 | CY4: 4 | CZ4: 8 | DA4: 7 | DB4: 1 | DC4: 48 | DD4: 0 | DE4: 40 | DF4: 36 | DG4: 4 | DH4: 8 | DI4: 7 | DJ4: 1 | DK4: 0 | DL4: 0 | DM4: 0 | DN4: 0 | DO4: 0 | DP4: 0 | DQ4: 0 | DR4: 0 | DS4: 0 | DT4: 0 | DU4: 0 | DV4: 0 | DW4: 0 | DX4: 0 | DY4: 0 | DZ4: 0 | EA4: 0 | EB4: 0 | EC4: 0 | ED4: 0 | EE4: 0 | EF4: 0 | EG4: 0 | EH4: 0 | EI4: 0 | EJ4: 0 | EK4: 0 | EL4: 0 | EM4: 0 | EN4: 0 | EO4: 0 | EP4: 0 | EQ4: 0 | ER4: 0 | ES4: 0 | ET4: 0 | EU4: 0 | EV4: 0 | EW4: 0 | EX4: 0 | EY4: 0 | EZ4: 0 | FA4: 0 | FB4: 0
A5: 2 | B5: 成人非手术 | C5: 呼吸内科 | D5: 1609046.5 | E5: 845153 | F5: 763893.5 | G5: 3260 | H5: 72 | I5: 114 | J5: 0 | K5: 0 | L5: 34479.5 | M5: 324 | N5: 0 | O5: 2697115.5 | P5: 2201713.6 | Q5: 2130532.4 | R5: 71181.23 | S5: 495401.92 | T5: 421775.21 | U5: 73626.71 | V5: 1516628 | W5: 1338243.6 | X5: 1277637.1 | Y5: 60606.54 | Z5: 178384.36 | AA5: 121163.32 | AB5: 57221.04 | AC5: 649678.97 | AD5: 580867.61 | AE5: 561373.07 | AF5: 19494.54 | AG5: 68811.36 | AH5: 48778.32 | AI5: 20033.04 | AJ5: 21796 | AK5: 18599 | AL5: 17915 | AM5: 684 | AN5: 3197 | AO5: 1981 | AP5: 1216 | AQ5: 743087 | AR5: 650008 | AS5: 614453 | AT5: 35555 | AU5: 93079 | AV5: 61637 | AW5: 31442 | AX5: 102066 | AY5: 88769 | AZ5: 83896 | BA5: 4873 | BB5: 13297 | BC5: 8767 | BD5: 4530 | BE5: 1180487.6 | BF5: 863470.02 | BG5: 852895.33 | BH5: 10574.69 | BI5: 317017.56 | BJ5: 300611.89 | BK5: 16405.67 | BL5: 377462.85 | BM5: 282954.13 | BN5: 281529.13 | BO5: 1425 | BP5: 94508.72 | BQ5: 93913.75 | BR5: 594.97 | BS5: 39131.23 | BT5: 26438.89 | BU5: 26228.2 | BV5: 210.69 | BW5: 12692.34 | BX5: 11418.64 | BY5: 1273.7 | BZ5: 549007 | CA5: 384092 | CB5: 376715 | CC5: 7377 | CD5: 164915 | CE5: 151762 | CF5: 13153 | CG5: 214886.5 | CH5: 169985 | CI5: 168423 | CJ5: 1562 | CK5: 44901.5 | CL5: 43517.5 | CM5: 1384 | CN5: 50 | CO5: 1155937 | CP5: 335952.15 | CQ5: 0 | CR5: 24738.8 | CS5: 0 | CT5: 0 | CU5: 0 | CV5: 3260 | CW5: 2840 | CX5: 2691 | CY5: 149 | CZ5: 420 | DA5: 277 | DB5: 143 | DC5: 2537 | DD5: 0 | DE5: 2218 | DF5: 2109 | DG5: 109 | DH5: 319 | DI5: 207 | DJ5: 112 | DK5: 676 | DL5: 580 | DM5: 543 | DN5: 37 | DO5: 96 | DP5: 68 | DQ5: 28 | DR5: 47 | DS5: 0 | DT5: 42 | DU5: 39 | DV5: 3 | DW5: 5 | DX5: 2 | DY5: 3 | DZ5: 0 | EA5: 0 | EB5: 0 | EC5: 0 | ED5: 0 | EE5: 0 | EF5: 0 | EG5: 72 | EH5: 53 | EI5: 52 | EJ5: 1 | EK5: 19 | EL5: 18 | EM5: 1 | EN5: 43 | EO5: 0 | EP5: 0 | EQ5: 43 | ER5: 0 | ES5: 0 | ET5: 0 | EU5: 0 | EV5: 0 | EW5: 0 | EX5: 0 | EY5: 0 | EZ5: 0 | FA5: 0 | FB5: 33
A6: 3 | B6: 成人非手术 | C6: 消化内科（内窥镜诊治部） | D6: 3786873 | E6: 2296995 | F6: 1489878 | G6: 7264 | H6: 242 | I6: 165668 | J6: 8400 | K6: 0 | L6: 158184 | M6: 179651 | N6: 693 | O6: 6721784.5 | P6: 5734804.8 | Q6: 5551091.2 | R6: 183713.55 | S6: 986979.69 | T6: 813870.73 | U6: 173108.96 | V6: 3869968.7 | W6: 3383876.5 | X6: 3209098.6 | Y6: 174777.93 | Z6: 486092.23 | AA6: 332607.77 | AB6: 153484.46 | AC6: 1343633.7 | AD6: 1198305.5 | AE6: 1144632.6 | AF6: 53672.93 | AG6: 145328.23 | AH6: 98055.77 | AI6: 47272.46 | AJ6: 229340 | AK6: 196832 | AL6: 184080 | AM6: 12752 | AN6: 32508 | AO6: 25951 | AP6: 6557 | AQ6: 1891258 | AR6: 1636069 | AS6: 1547657 | AT6: 88412 | AU6: 255189 | AV6: 170559 | AW6: 84630 | AX6: 405737 | AY6: 352670 | AZ6: 332729 | BA6: 19941 | BB6: 53067 | BC6: 38042 | BD6: 15025 | BE6: 2851815.8 | BF6: 2350928.3 | BG6: 2341992.7 | BH6: 8935.62 | BI6: 500887.46 | BJ6: 481262.96 | BK6: 19624.5 | BL6: 397804.6 | BM6: 326410.05 | BN6: 325217.42 | BO6: 1192.63 | BP6: 71394.55 | BQ6: 68969.55 | BR6: 2425 | BS6: 964133.16 | BT6: 809389.25 | BU6: 807536.26 | BV6: 1852.99 | BW6: 154743.91 | BX6: 146673.41 | BY6: 8070.5 | BZ6: 777726 | CA6: 625760 | CB6: 621384 | CC6: 4376 | CD6: 151966 | CE6: 146771 | CF6: 5195 | CG6: 712152 | CH6: 589369 | CI6: 587855 | CJ6: 1514 | CK6: 122783 | CL6: 118849 | CM6: 3934 | CN6: -50 | CO6: 2463388.7 | CP6: 642607.71 | CQ6: 641381.61 | CR6: 122590.71 | CS6: 0 | CT6: 68170.35 | CU6: 0 | CV6: 7264 | CW6: 6332 | CX6: 5987 | CY6: 345 | CZ6: 932 | DA6: 602 | DB6: 330 | DC6: 5907 | DD6: 0 | DE6: 5112 | DF6: 4848 | DG6: 264 | DH6: 795 | DI6: 498 | DJ6: 297 | DK6: 1198 | DL6: 1082 | DM6: 1012 | DN6: 70 | DO6: 116 | DP6: 92 | DQ6: 24 | DR6: 159 | DS6: 0 | DT6: 138 | DU6: 127 | DV6: 11 | DW6: 21 | DX6: 12 | DY6: 9 | DZ6: 0 | EA6: 0 | EB6: 0 | EC6: 0 | ED6: 0 | EE6: 0 | EF6: 0 | EG6: 242 | EH6: 196 | EI6: 195 | EJ6: 1 | EK6: 46 | EL6: 44 | EM6: 2 | EN6: 237 | EO6: 0 | EP6: 0 | EQ6: 237 | ER6: 0 | ES6: 0 | ET6: 55 | EU6: 39 | EV6: 0 | EW6: 0 | EX6: 39 | EY6: 0 | EZ6: 0 | FA6: 0 | FB6: 7
A7: 4 | B7: 成人非手术 | C7: 神经内科 | D7: 2184103 | E7: 1089818 | F7: 1094285 | G7: 3050 | H7: 100 | I7: 84 | J7: 0 | K7: 1911.63 | L7: 37990.5 | M7: 13398 | N7: 0 | O7: 4249541.8 | P7: 3617359.6 | Q7: 3482214.8 | R7: 135144.84 | S7: 632182.16 | T7: 522272.36 | U7: 109909.8 | V7: 1972862.9 | W7: 1663756.2 | X7: 1565804.4 | Y7: 97951.78 | Z7: 309106.66 | AA7: 213095.81 | AB7: 96010.85 | AC7: 877841.86 | AD7: 766925.2 | AE7: 726402.42 | AF7: 40522.78 | AG7: 110916.66 | AH7: 80184.81 | AI7: 30731.85 | AJ7: 5203 | AK7: 3999 | AL7: 3440 | AM7: 559 | AN7: 1204 | AO7: 817 | AP7: 387 | AQ7: 922475 | AR7: 752934 | AS7: 705575 | AT7: 47359 | AU7: 169541 | AV7: 113994 | AW7: 55547 | AX7: 167343 | AY7: 139898 | AZ7: 130387 | BA7: 9511 | BB7: 27445 | BC7: 18100 | BD7: 9345 | BE7: 2276678.9 | BF7: 1953603.4 | BG7: 1916410.3 | BH7: 37193.06 | BI7: 323075.5 | BJ7: 309176.55 | BK7: 13898.95 | BL7: 410668.61 | BM7: 345223.11 | BN7: 338051.5 | BO7: 7171.61 | BP7: 65445.5 | BQ7: 63453.73 | BR7: 1991.77 | BS7: 771725.28 | BT7: 736029.28 | BU7: 732175.33 | BV7: 3853.95 | BW7: 35696 | BX7: 33446.82 | BY7: 2249.18 | BZ7: 791411 | CA7: 616991 | CB7: 599337 | CC7: 17654 | CD7: 174420 | CE7: 166314 | CF7: 8106 | CG7: 302874 | CH7: 255360 | CI7: 246846.5 | CJ7: 8513.5 | CK7: 47514 | CL7: 45962 | CM7: 1552 | CN7: 40 | CO7: 799274.67 | CP7: 500683.78 | CQ7: 313700.13 | CR7: 359204.28 | CS7: 0 | CT7: 0 | CU7: 0 | CV7: 3050 | CW7: 2599 | CX7: 2430 | CY7: 169 | CZ7: 451 | DA7: 304 | DB7: 147 | DC7: 1867 | DD7: 0 | DE7: 1620 | DF7: 1517 | DG7: 103 | DH7: 247 | DI7: 166 | DJ7: 81 | DK7: 814 | DL7: 674 | DM7: 629 | DN7: 45 | DO7: 140 | DP7: 94 | DQ7: 46 | DR7: 369 | DS7: 0 | DT7: 305 | DU7: 284 | DV7: 21 | DW7: 64 | DX7: 44 | DY7: 20 | DZ7: 0 | EA7: 0 | EB7: 0 | EC7: 0 | ED7: 0 | EE7: 0 | EF7: 0 | EG7: 100 | EH7: 77 | EI7: 74 | EJ7: 3 | EK7: 23 | EL7: 22 | EM7: 1 | EN7: 46 | EO7: 0 | EP7: 7 | EQ7: 39 | ER7: 0 | ES7: 0 | ET7: 0 | EU7: 2 | EV7: 0 | EW7: 2 | EX7: 0 | EY7: 5 | EZ7: 0 | FA7: 5 | FB7: 30
A8: 5 | B8: 成人非手术 | C8: 心血管内科 | D8: 4850815.5 | E8: 1172058 | F8: 3678757.5 | G8: 6934 | H8: 289 | I8: 992 | J8: 0 | K8: 0 | L8: 34579 | M8: 747076.5 | N8: 37.5 | O8: 16956629 | P8: 12358020 | Q8: 12202150 | R8: 155870.05 | S8: 4598608.3 | T8: 4421296.7 | U8: 177311.66 | V8: 3116542.8 | W8: 2786885.5 | X8: 2704974.1 | Y8: 81911.33 | Z8: 329657.34 | AA8: 253833.95 | AB8: 75823.39 | AC8: 1924812.8 | AD8: 1743694.4 | AE8: 1708786.1 | AF8: 34908.33 | AG8: 181118.34 | AH8: 149688.95 | AI8: 31429.39 | AJ8: 19672 | AK8: 16973 | AL8: 16290 | AM8: 683 | AN8: 2699 | AO8: 1710 | AP8: 989 | AQ8: 934816 | AR8: 818174 | AS8: 780777 | AT8: 37397 | AU8: 116642 | AV8: 80955 | AW8: 35687 | AX8: 237242 | AY8: 208044 | AZ8: 199121 | BA8: 8923 | BB8: 29198 | BC8: 21480 | BD8: 7718 | BE8: 13840086 | BF8: 9571134.8 | BG8: 9497176.1 | BH8: 73958.72 | BI8: 4268951 | BJ8: 4167462.7 | BK8: 101488.27 | BL8: 854353.33 | BM8: 603734.2 | BN8: 595538.33 | BO8: 8195.87 | BP8: 250619.13 | BQ8: 244673.1 | BR8: 5946.03 | BS8: 9306974.9 | BT8: 6405604.8 | BU8: 6369171.5 | BV8: 36433.35 | BW8: 2901370.1 | BX8: 2844255.9 | BY8: 57114.24 | BZ8: 2192369 | CA8: 1551787 | CB8: 1536960 | CC8: 14827 | CD8: 640582 | CE8: 618900 | CF8: 21682 | CG8: 1486388.5 | CH8: 1010008.8 | CI8: 995506.25 | CJ8: 14502.5 | CK8: 476379.75 | CL8: 459633.75 | CM8: 16746 | CN8: 0 | CO8: 1648009.8 | CP8: 1349781.6 | CQ8: 70660 | CR8: 48091.39 | CS8: 0 | CT8: 0 | CU8: 0 | CV8: 6934 | CW8: 6138 | CX8: 5888 | CY8: 250 | CZ8: 796 | DA8: 579 | DB8: 217 | DC8: 4233 | DD8: 0 | DE8: 3801 | DF8: 3657 | DG8: 144 | DH8: 432 | DI8: 300 | DJ8: 132 | DK8: 2646 | DL8: 2292 | DM8: 2189 | DN8: 103 | DO8: 354 | DP8: 272 | DQ8: 82 | DR8: 55 | DS8: 0 | DT8: 45 | DU8: 42 | DV8: 3 | DW8: 10 | DX8: 7 | DY8: 3 | DZ8: 0 | EA8: 0 | EB8: 0 | EC8: 0 | ED8: 0 | EE8: 0 | EF8: 0 | EG8: 289 | EH8: 213 | EI8: 213 | EJ8: 0 | EK8: 76 | EL8: 75 | EM8: 1 | EN8: 314 | EO8: 36 | EP8: 162 | EQ8: 116 | ER8: 0 | ES8: 0 | ET8: 0 | EU8: 143 | EV8: 36 | EW8: 107 | EX8: 0 | EY8: 7 | EZ8: 0 | FA8: 7 | FB8: 33
A9: 6 | B9: 成人非手术 | C9: 血液内科 | D9: 40850 | E9: 40850 | F9: 0 | G9: 192 | H9: 0 | I9: 66 | J9: 0 | K9: 0 | L9: 0 | M9: 0 | N9: 0 | O9: 119309.91 | P9: 113825.53 | Q9: 110624.96 | R9: 3200.57 | S9: 5484.38 | T9: 4133.38 | U9: 1351 | V9: 119309.91 | W9: 113825.53 | X9: 110624.96 | Y9: 3200.57 | Z9: 5484.38 | AA9: 4133.38 | AB9: 1351 | AC9: 78459.91 | AD9: 75974.53 | AE9: 75568.96 | AF9: 405.57 | AG9: 2485.38 | AH9: 2485.38 | AI9: 0 | AJ9: 0 | AK9: 0 | AL9: 0 | AM9: 0 | AN9: 0 | AO9: 0 | AP9: 0 | AQ9: 33559 | AR9: 31153 | AS9: 28908 | AT9: 2245 | AU9: 2406 | AV9: 1205 | AW9: 1201 | AX9: 7291 | AY9: 6698 | AZ9: 6148 | BA9: 550 | BB9: 593 | BC9: 443 | BD9: 150 | BE9: 0 | BF9: 0 | BG9: 0 | BH9: 0 | BI9: 0 | BJ9: 0 | BK9: 0 | BL9: 0 | BM9: 0 | BN9: 0 | BO9: 0 | BP9: 0 | BQ9: 0 | BR9: 0 | BS9: 0 | BT9: 0 | BU9: 0 | BV9: 0 | BW9: 0 | BX9: 0 | BY9: 0 | BZ9: 0 | CA9: 0 | CB9: 0 | CC9: 0 | CD9: 0 | CE9: 0 | CF9: 0 | CG9: 0 | CH9: 0 | CI9: 0 | CJ9: 0 | CK9: 0 | CL9: 0 | CM9: 0 | CN9: 0 | CO9: 27975.63 | CP9: 91334.28 | CQ9: 0 | CR9: 0 | CS9: 0 | CT9: 0 | CU9: 0 | CV9: 192 | CW9: 178 | CX9: 164 | CY9: 14 | CZ9: 14 | DA9: 10 | DB9: 4 | DC9: 95 | DD9: 0 | DE9: 90 | DF9: 84 | DG9: 6 | DH9: 5 | DI9: 3 | DJ9: 2 | DK9: 97 | DL9: 88 | DM9: 80 | DN9: 8 | DO9: 9 | DP9: 7 | DQ9: 2 | DR9: 0 | DS9: 0 | DT9: 0 | DU9: 0 | DV9: 0 | DW9: 0 | DX9: 0 | DY9: 0 | DZ9: 0 | EA9: 0 | EB9: 0 | EC9: 0 | ED9: 0 | EE9: 0 | EF9: 0 | EG9: 0 | EH9: 0 | EI9: 0 | EJ9: 0 | EK9: 0 | EL9: 0 | EM9: 0 | EN9: 0 | EO9: 0 | EP9: 0 | EQ9: 0 | ER9: 0 | ES9: 0 | ET9: 0 | EU9: 0 | EV9: 0 | EW9: 0 | EX9: 0 | EY9: 0 | EZ9: 0 | FA9: 0 | FB9: 0
A10: 7 | B10: 成人非手术 | C10: 肾脏风湿免疫科 | D10: 1448921 | E10: 1091491 | F10: 357430 | G10: 1972 | H10: 45 | I10: 587069 | J10: 0 | K10: 0 | L10: 16669 | M10: 14556 | N10: 0 | O10: 2330696 | P10: 1968697.9 | Q10: 1937822.8 | R10: 30875.02 | S10: 361998.16 | T10: 323627.01 | U10: 38371.15 | V10: 1862990.5 | W10: 1673561.8 | X10: 1642686.8 | Y10: 30875.02 | Z10: 189428.69 | AA10: 161197.56 | AB10: 28231.13 | AC10: 687721.47 | AD10: 625272.78 | AE10: 615376.76 | AF10: 9896.02 | AG10: 62448.69 | AH10: 52595.56 | AI10: 9853.13 | AJ10: 83778 | AK10: 81549 | AL10: 81549 | AM10: 0 | AN10: 2229 | AO10: 2229 | AP10: 0 | AQ10: 436927 | AR10: 377076 | AS10: 358575 | AT10: 18501 | AU10: 59851 | AV10: 44210 | AW10: 15641 | AX10: 654564 | AY10: 589664 | AZ10: 587186 | BA10: 2478 | BB10: 64900 | BC10: 62163 | BD10: 2737 | BE10: 467705.54 | BF10: 295136.07 | BG10: 295136.07 | BH10: 0 | BI10: 172569.47 | BJ10: 162429.45 | BK10: 10140.02 | BL10: 97103.41 | BM10: 59107.89 | BN10: 59107.89 | BO10: 0 | BP10: 37995.52 | BQ10: 36598.89 | BR10: 1396.63 | BS10: 13172.13 | BT10: 7331.18 | BU10: 7331.18 | BV10: 0 | BW10: 5840.95 | BX10: 5567.56 | BY10: 273.39 | BZ10: 266476 | CA10: 176337 | CB10: 176337 | CC10: 0 | CD10: 90139 | CE10: 83162 | CF10: 6977 | CG10: 90954 | CH10: 52360 | CI10: 52360 | CJ10: 0 | CK10: 38594 | CL10: 37101 | CM10: 1493 | CN10: 0 | CO10: 508718.1 | CP10: 347728.78 | CQ10: 953451.1 | CR10: 53092.49 | CS10: 0 | CT10: 0 | CU10: 0 | CV10: 1972 | CW10: 1710 | CX10: 1634 | CY10: 76 | CZ10: 262 | DA10: 181 | DB10: 81 | DC10: 1467 | DD10: 0 | DE10: 1274 | DF10: 1214 | DG10: 60 | DH10: 193 | DI10: 134 | DJ10: 59 | DK10: 458 | DL10: 396 | DM10: 382 | DN10: 14 | DO10: 62 | DP10: 42 | DQ10: 20 | DR10: 47 | DS10: 0 | DT10: 40 | DU10: 38 | DV10: 2 | DW10: 7 | DX10: 5 | DY10: 2 | DZ10: 0 | EA10: 0 | EB10: 0 | EC10: 0 | ED10: 0 | EE10: 0 | EF10: 0 | EG10: 45 | EH10: 31 | EI10: 31 | EJ10: 0 | EK10: 14 | EL10: 13 | EM10: 1 | EN10: 16 | EO10: 7 | EP10: 0 | EQ10: 9 | ER10: 0 | ES10: 0 | ET10: 0 | EU10: 0 | EV10: 0 | EW10: 0 | EX10: 0 | EY10: 0 | EZ10: 0 | FA10: 0 | FB10: 37
A11: 8 | B11: 成人非手术 | C11: 内分泌科 | D11: 1038748 | E11: 1038748 | F11: 0 | G11: 3391 | H11: 0 | I11: 84 | J11: 1148 | K11: 0 | L11: 0 | M11: 0 | N11: 0 | O11: 1778621.8 | P11: 1590060.8 | Q11: 1526237.9 | R11: 63822.83 | S11: 188561.03 | T11: 148973.41 | U11: 39587.62 | V11: 1778621.8 | W11: 1590060.8 | X11: 1526237.9 | Y11: 63822.83 | Z11: 188561.03 | AA11: 148973.41 | AB11: 39587.62 | AC11: 727098.8 | AD11: 653391.97 | AE11: 629854.14 | AF11: 23537.83 | AG11: 73706.83 | AH11: 60930.21 | AI11: 12776.62 | AJ11: 12775 | AK11: 10506.8 | AL11: 10079.8 | AM11: 427 | AN11: 2268.2 | AO11: 1878.2 | AP11: 390 | AQ11: 914491 | AR11: 816534 | AS11: 782077 | AT11: 34457 | AU11: 97957 | AV11: 74924 | AW11: 23033 | AX11: 124257 | AY11: 109628 | AZ11: 104227 | BA11: 5401 | BB11: 14629 | BC11: 11241 | BD11: 3388 | BE11: 0 | BF11: 0 | BG11: 0 | BH11: 0 | BI11: 0 | BJ11: 0 | BK11: 0 | BL11: 0 | BM11: 0 | BN11: 0 | BO11: 0 | BP11: 0 | BQ11: 0 | BR11: 0 | BS11: 0 | BT11: 0 | BU11: 0 | BV11: 0 | BW11: 0 | BX11: 0 | BY11: 0 | BZ11: 0 | CA11: 0 | CB11: 0 | CC11: 0 | CD11: 0 | CE11: 0 | CF11: 0 | CG11: 0 | CH11: 0 | CI11: 0 | CJ11: 0 | CK11: 0 | CL11: 0 | CM11: 0 | CN11: 0 | CO11: 849688.14 | CP11: 898135.62 | CQ11: 0 | CR11: 30798.04 | CS11: 0 | CT11: 0 | CU11: 0 | CV11: 3391 | CW11: 3000 | CX11: 2848 | CY11: 152 | CZ11: 391 | DA11: 299 | DB11: 92 | DC11: 1650 | DD11: 0 | DE11: 1448 | DF11: 1379 | DG11: 69 | DH11: 202 | DI11: 150 | DJ11: 52 | DK11: 1701 | DL11: 1517 | DM11: 1434 | DN11: 83 | DO11: 184 | DP11: 147 | DQ11: 37 | DR11: 40 | DS11: 0 | DT11: 35 | DU11: 35 | DV11: 0 | DW11: 5 | DX11: 2 | DY11: 3 | DZ11: 0 | EA11: 0 | EB11: 0 | EC11: 0 | ED11: 0 | EE11: 0 | EF11: 0 | EG11: 0 | EH11: 0 | EI11: 0 | EJ11: 0 | EK11: 0 | EL11: 0 | EM11: 0 | EN11: 0 | EO11: 0 | EP11: 0 | EQ11: 0 | ER11: 0 | ES11: 0 | ET11: 0 | EU11: 0 | EV11: 0 | EW11: 0 | EX11: 0 | EY11: 0 | EZ11: 0 | FA11: 0 | FB11: 0
A12: 9 | B12: 成人手术 | C12: 普外科 | D12: 3744259.2 | E12: 823869.5 | F12: 2920389.8 | G12: 3249 | H12: 305 | I12: 33274.5 | J12: 23324 | K12: 0 | L12: 235637.25 | M12: 953861.5 | N12: 787.5 | O12: 7521416 | P12: 5612862.9 | Q12: 5561287.6 | R12: 51575.29 | S12: 1908553.1 | T12: 1834176.4 | U12: 74376.71 | V12: 1113523 | W12: 964776.82 | X12: 913201.53 | Y12: 51575.29 | Z12: 148746.18 | AA12: 107601.48 | AB12: 41144.7 | AC12: 217812.53 | AD12: 192572.1 | AE12: 187019.33 | AF12: 5552.77 | AG12: 25240.43 | AH12: 19824.52 | AI12: 5415.91 | AJ12: 71840.97 | AK12: 65503.22 | AL12: 63871.7 | AM12: 1631.52 | AN12: 6337.75 | AO12: 4436.96 | AP12: 1900.79 | AQ12: 657992 | AR12: 562783 | AS12: 529592 | AT12: 33191 | AU12: 95209 | AV12: 67456 | AW12: 27753 | AX12: 165877.5 | AY12: 143918.5 | AZ12: 132718.5 | BA12: 11200 | BB12: 21959 | BC12: 15884 | BD12: 6075 | BE12: 6407893 | BF12: 4648086.1 | BG12: 4648086.1 | BH12: 0 | BI12: 1759806.9 | BJ12: 1726574.9 | BK12: 33232.01 | BL12: 1002076.9 | BM12: 715989.54 | BN12: 715989.54 | BO12: 0 | BP12: 286087.35 | BQ12: 279981.21 | BR12: 6106.14 | BS12: 2485426.4 | BT12: 1761401.8 | BU12: 1761401.8 | BV12: 0 | BW12: 724024.55 | BX12: 714205.68 | BY12: 9818.87 | BZ12: 953667 | CA12: 697268 | CB12: 697268 | CC12: 0 | CD12: 256399 | CE12: 249640 | CF12: 6759 | CG12: 1966722.8 | CH12: 1473426.8 | CI12: 1473426.8 | CJ12: 0 | CK12: 493296 | CL12: 482748 | CM12: 10548 | CN12: 479016.15 | CO12: 248461.54 | CP12: 285717.35 | CQ12: 94373.67 | CR12: 5914.29 | CS12: 0 | CT12: 0 | CU12: 0 | CV12: 3249 | CW12: 2766 | CX12: 2570 | CY12: 196 | CZ12: 483 | DA12: 338 | DB12: 145 | DC12: 1331 | DD12: 0 | DE12: 1124 | DF12: 1038 | DG12: 86 | DH12: 207 | DI12: 140 | DJ12: 67 | DK12: 991 | DL12: 849 | DM12: 793 | DN12: 56 | DO12: 142 | DP12: 96 | DQ12: 46 | DR12: 17 | DS12: 0 | DT12: 13 | DU12: 13 | DV12: 0 | DW12: 4 | DX12: 3 | DY12: 1 | DZ12: 910 | EA12: 780 | EB12: 726 | EC12: 54 | ED12: 130 | EE12: 99 | EF12: 31 | EG12: 305 | EH12: 241 | EI12: 241 | EJ12: 0 | EK12: 64 | EL12: 62 | EM12: 2 | EN12: 252 | EO12: 194 | EP12: 0 | EQ12: 58 | ER12: 127 | ES12: 0 | ET12: 0 | EU12: 83 | EV12: 69 | EW12: 0 | EX12: 14 | EY12: 35 | EZ12: 35 | FA12: 0 | FB12: 113
A13: 10 | B13: 成人手术 | C13: 神经外科 | D13: 3315823.2 | E13: 306679 | F13: 3009144.2 | G13: 1466 | H13: 231 | I13: 333 | J13: 0 | K13: 0 | L13: 186796.25 | M13: 950743.5 | N13: 0 | O13: 15521799 | P13: 9691912.2 | Q13: 9579381.4 | R13: 112530.74 | S13: 5829886.6 | T13: 5721711.5 | U13: 108175.13 | V13: 491626.85 | W13: 401884.16 | X13: 371287.56 | Y13: 30596.6 | Z13: 89742.69 | AA13: 61043.06 | AB13: 28699.63 | AC13: 179013.85 | AD13: 150866.16 | AE13: 146563.56 | AF13: 4302.6 | AG13: 28147.69 | AH13: 20839.06 | AI13: 7308.63 | AJ13: 5934 | AK13: 4859 | AL13: 4558 | AM13: 301 | AN13: 1075 | AO13: 688 | AP13: 387 | AQ13: 259511 | AR13: 209621 | AS13: 187451 | AT13: 22170 | AU13: 49890 | AV13: 32976 | AW13: 16914 | AX13: 47168 | AY13: 36538 | AZ13: 32715 | BA13: 3823 | BB13: 10630 | BC13: 6540 | BD13: 4090 | BE13: 15030172 | BF13: 9290028 | BG13: 9208093.9 | BH13: 81934.14 | BI13: 5740143.9 | BJ13: 5660668.4 | BK13: 79475.5 | BL13: 1135116.6 | BM13: 735135.51 | BN13: 714218.71 | BO13: 20916.8 | BP13: 399981.04 | BQ13: 393191.66 | BR13: 6789.38 | BS13: 10885911 | BT13: 6809134 | BU13: 6789175.2 | BV13: 19958.84 | BW13: 4076777.1 | BX13: 4037866 | BY13: 38911.12 | BZ13: 1158446 | CA13: 684634 | CB13: 665569 | CC13: 19065 | CD13: 473812 | CE13: 458748 | CF13: 15064 | CG13: 1850698.2 | CH13: 1061124.5 | CI13: 1039131 | CJ13: 21993.5 | CK13: 789573.75 | CL13: 770862.75 | CM13: 18711 | CN13: -50 | CO13: 314358.88 | CP13: 152801.25 | CQ13: 24466.72 | CR13: 0 | CS13: 0 | CT13: 77447.78 | CU13: 0 | CV13: 1466 | CW13: 1161 | CX13: 1045 | CY13: 116 | CZ13: 305 | DA13: 185 | DB13: 120 | DC13: 1001 | DD13: 0 | DE13: 828 | DF13: 747 | DG13: 81 | DH13: 173 | DI13: 102 | DJ13: 71 | DK13: 465 | DL13: 333 | DM13: 298 | DN13: 35 | DO13: 132 | DP13: 83 | DQ13: 49 | DR13: 0 | DS13: 0 | DT13: 0 | DU13: 0 | DV13: 0 | DW13: 0 | DX13: 0 | DY13: 0 | DZ13: 0 | EA13: 0 | EB13: 0 | EC13: 0 | ED13: 0 | EE13: 0 | EF13: 0 | EG13: 231 | EH13: 150 | EI13: 141 | EJ13: 9 | EK13: 81 | EL13: 79 | EM13: 2 | EN13: 200 | EO13: 81 | EP13: 75 | EQ13: 44 | ER13: 38 | ES13: 0 | ET13: 0 | EU13: 32 | EV13: 28 | EW13: 4 | EX13: 0 | EY13: 107 | EZ13: 36 | FA13: 71 | FB13: 94
A14: 11 | B14: 成人手术 | C14: 骨科 | D14: 6639662.2 | E14: 1454944 | F14: 5184718.2 | G14: 7324 | H14: 433 | I14: 44349 | J14: 21078 | K14: 0 | L14: 398391.75 | M14: 2561946 | N14: 0 | O14: 20597728 | P14: 16475874 | Q14: 11919864 | R14: 4556010.5 | S14: 4121853.3 | T14: 3027103.9 | U14: 1094749.5 | V14: 2737284.7 | W14: 2382048.8 | X14: 1669652.5 | Y14: 712396.27 | Z14: 355235.97 | AA14: 159444.3 | AB14: 195791.67 | AC14: 705067.41 | AD14: 611873.24 | AE14: 478969.17 | AF14: 132904.07 | AG14: 93194.17 | AH14: 45980.97 | AI14: 47213.2 | AJ14: 577273.31 | AK14: 523013.51 | AL14: 289450.81 | AM14: 233562.7 | AN14: 54259.8 | AO14: 19806.33 | AP14: 34453.47 | AQ14: 1136513 | AR14: 977214 | AS14: 699941 | AT14: 277273 | AU14: 159299 | AV14: 68551 | AW14: 90748 | AX14: 318431 | AY14: 269948 | AZ14: 201291.5 | BA14: 68656.5 | BB14: 48483 | BC14: 25106 | BD14: 23377 | BE14: 17860443 | BF14: 14093826 | BG14: 10250211 | BH14: 3843614.3 | BI14: 3766617.4 | BJ14: 2867659.6 | BK14: 898957.81 | BL14: 1416648.4 | BM14: 1120132.2 | BN14: 810421.57 | BO14: 309710.63 | BP14: 296516.25 | BQ14: 227742.92 | BR14: 68773.33 | BS14: 11259076 | BT14: 8817847.3 | BU14: 6289627.7 | BV14: 2528219.6 | BW14: 2441228.9 | BX14: 1809954.9 | BY14: 631273.98 | BZ14: 941721 | CA14: 740007 | CB14: 560507 | CC14: 179500 | CD14: 201714 | CE14: 166983 | CF14: 34731 | CG14: 4242997.2 | CH14: 3415839 | CI14: 2589655 | CJ14: 826184 | CK14: 827158.25 | CL14: 662978.75 | CM14: 164179.5 | CN14: 1130682.5 | CO14: 805741.93 | CP14: 773152.46 | CQ14: 0 | CR14: 27677.83 | CS14: 0 | CT14: 78908.8 | CU14: 0 | CV14: 7324 | CW14: 6216 | CX14: 4830 | CY14: 1386 | CZ14: 1108 | DA14: 533 | DB14: 575 | DC14: 2814 | DD14: 0 | DE14: 2410 | DF14: 1971 | DG14: 439 | DH14: 404 | DI14: 175 | DJ14: 229 | DK14: 2893 | DL14: 2436 | DM14: 2087 | DN14: 349 | DO14: 457 | DP14: 266 | DQ14: 191 | DR14: 70 | DS14: 0 | DT14: 60 | DU14: 46 | DV14: 14 | DW14: 10 | DX14: 8 | DY14: 2 | DZ14: 1547 | EA14: 1310 | EB14: 726 | EC14: 584 | ED14: 237 | EE14: 84 | EF14: 153 | EG14: 433 | EH14: 349 | EI14: 264 | EJ14: 85 | EK14: 84 | EL14: 67 | EM14: 17 | EN14: 400 | EO14: 387 | EP14: 0 | EQ14: 13 | ER14: 162 | ES14: 0 | ET14: 0 | EU14: 156 | EV14: 156 | EW14: 0 | EX14: 0 | EY14: 96 | EZ14: 96 | FA14: 0 | FB14: 193
A15: 12 | B15: 成人手术 | C15: 泌尿外科 | D15: 3460769.4 | E15: 571053 | F15: 2889716.4 | G15: 3382 | H15: 296 | I15: 55539 | J15: 3105 | K15: 0 | L15: 603662.4 | M15: 742647.5 | N15: 0 | O15: 7243229.8 | P15: 5503262.4 | Q15: 5420321.6 | R15: 82940.82 | S15: 1739967.4 | T15: 1672563.9 | U15: 67403.43 | V15: 1442083.3 | W15: 1230392 | X15: 1174692.1 | Y15: 55699.95 | Z15: 211691.28 | AA15: 162645.51 | AB15: 49045.77 | AC15: 745013.44 | AD15: 631963.14 | AE15: 610611.71 | AF15: 21351.43 | AG15: 113050.3 | AH15: 96180.91 | AI15: 16869.39 | AJ15: 126016.86 | AK15: 109859.88 | AL15: 103426.36 | AM15: 6433.52 | AN15: 16156.98 | AO15: 11545.6 | AP15: 4611.38 | AQ15: 393724 | AR15: 335957 | AS15: 317746 | AT15: 18211 | AU15: 57767 | AV15: 37742 | AW15: 20025 | AX15: 177329 | AY15: 152612 | AZ15: 142908 | BA15: 9704 | BB15: 24717 | BC15: 17177 | BD15: 7540 | BE15: 5801146.5 | BF15: 4272870.4 | BG15: 4245629.5 | BH15: 27240.87 | BI15: 1528276.1 | BJ15: 1509918.4 | BK15: 18357.66 | BL15: 673819.6 | BM15: 487995.91 | BN15: 485137.72 | BO15: 2858.19 | BP15: 185823.69 | BQ15: 183634.52 | BR15: 2189.17 | BS15: 2237610.5 | BT15: 1693862.8 | BU15: 1679520.1 | BV15: 14342.68 | BW15: 543747.76 | BX15: 536000.27 | BY15: 7747.49 | BZ15: 952918 | CA15: 694070 | CB15: 692724 | CC15: 1346 | CD15: 258848 | CE15: 257317 | CF15: 1531 | CG15: 1936798.4 | CH15: 1396941.8 | CI15: 1388247.8 | CJ15: 8694 | CK15: 539856.65 | CL15: 532966.65 | CM15: 6890 | CN15: 203824.37 | CO15: 534402.48 | CP15: 694039.56 | CQ15: 0 | CR15: 9816.89 | CS15: 0 | CT15: 84655.13 | CU15: 0 | CV15: 3382 | CW15: 2901 | CX15: 2709 | CY15: 192 | CZ15: 481 | DA15: 298 | DB15: 183 | DC15: 1543 | DD15: 0 | DE15: 1312 | DF15: 1235 | DG15: 77 | DH15: 231 | DI15: 139 | DJ15: 92 | DK15: 1248 | DL15: 1090 | DM15: 1031 | DN15: 59 | DO15: 158 | DP15: 108 | DQ15: 50 | DR15: 20 | DS15: 0 | DT15: 12 | DU15: 10 | DV15: 2 | DW15: 8 | DX15: 7 | DY15: 1 | DZ15: 571 | EA15: 487 | EB15: 433 | EC15: 54 | ED15: 84 | EE15: 44 | EF15: 40 | EG15: 296 | EH15: 227 | EI15: 225 | EJ15: 2 | EK15: 69 | EL15: 67 | EM15: 2 | EN15: 273 | EO15: 213 | EP15: 0 | EQ15: 60 | ER15: 34 | ES15: 0 | ET15: 0 | EU15: 130 | EV15: 130 | EW15: 0 | EX15: 0 | EY15: 50 | EZ15: 50 | FA15: 0 | FB15: 83
... A58: 55 | B58: 医技平台 | C58: 超声诊断科 | D58: 20011 | E58: 20011 | F58: 0 | G58: 51 | H58: 0 | I58: 0 | J58: 3076 | K58: 0 | L58: 0 | M58: 0 | N58: 0 | O58: 26363.77 | P58: 23582.24 | Q58: 23582.24 | R58: 0 | S58: 2781.53 | T58: 2651.53 | U58: 130 | V58: 26363.77 | W58: 23582.24 | X58: 23582.24 | Y58: 0 | Z58: 2781.53 | AA58: 2651.53 | AB58: 130 | AC58: 4612.77 | AD58: 4100.24 | AE58: 4100.24 | AF58: 0 | AG58: 512.53 | AH58: 512.53 | AI58: 0 | AJ58: 1740 | AK58: 1550 | AL58: 1550 | AM58: 0 | AN58: 190 | AO58: 190 | AP58: 0 | AQ58: 14985 | AR58: 13560 | AS58: 13560 | AT58: 0 | AU58: 1425 | AV58: 1335 | AW58: 90 | AX58: 5026 | AY58: 4372 | AZ58: 4372 | BA58: 0 | BB58: 654 | BC58: 614 | BD58: 40 | BE58: 0 | BF58: 0 | BG58: 0 | BH58: 0 | BI58: 0 | BJ58: 0 | BK58: 0 | BL58: 0 | BM58: 0 | BN58: 0 | BO58: 0 | BP58: 0 | BQ58: 0 | BR58: 0 | BS58: 0 | BT58: 0 | BU58: 0 | BV58: 0 | BW58: 0 | BX58: 0 | BY58: 0 | BZ58: 0 | CA58: 0 | CB58: 0 | CC58: 0 | CD58: 0 | CE58: 0 | CF58: 0 | CG58: 0 | CH58: 0 | CI58: 0 | CJ58: 0 | CK58: 0 | CL58: 0 | CM58: 0 | CN58: 0 | CO58: 0 | CP58: 19863.18 | CQ58: 6500.59 | CR58: 0 | CS58: 0 | CT58: 0 | CU58: 0 | CV58: 51 | CW58: 49 | CX58: 49 | CY58: 0 | CZ58: 2 | DA58: 1 | DB58: 1 | DC58: 6 | DD58: 0 | DE58: 6 | DF58: 6 | DG58: 0 | DH58: 0 | DI58: 0 | DJ58: 0 | DK58: 45 | DL58: 43 | DM58: 43 | DN58: 0 | DO58: 2 | DP58: 1 | DQ58: 1 | DR58: 0 | DS58: 0 | DT58: 0 | DU58: 0 | DV58: 0 | DW58: 0 | DX58: 0 | DY58: 0 | DZ58: 0 | EA58: 0 | EB58: 0 | EC58: 0 | ED58: 0 | EE58: 0 | EF58: 0 | EG58: 0 | EH58: 0 | EI58: 0 | EJ58: 0 | EK58: 0 | EL58: 0 | EM58: 0 | EN58: 15 | EO58: 0 | EP58: 0 | EQ58: 15 | ER58: 0 | ES58: 0 | ET58: 0 | EU58: 0 | EV58: 0 | EW58: 0 | EX58: 0 | EY58: 0 | EZ58: 0 | FA58: 0 | FB58: 0
A59: 56 | C59: 其它 | D59: 0 | E59: 0 | F59: 0 | G59: 178 | H59: 74 | I59: 0 | J59: 0 | K59: 0 | L59: 0 | M59: 0 | N59: 0 | O59: 0 | P59: 0 | Q59: 0 | R59: 0 | S59: 0 | T59: 0 | U59: 0 | V59: 0 | W59: 0 | X59: 0 | Y59: 0 | Z59: 0 | AA59: 0 | AB59: 0 | AC59: 0 | AD59: 0 | AE59: 0 | AF59: 0 | AG59: 0 | AH59: 0 | AI59: 0 | AJ59: 0 | AK59: 0 | AL59: 0 | AM59: 0 | AN59: 0 | AO59: 0 | AP59: 0 | AQ59: 0 | AR59: 0 | AS59: 0 | AT59: 0 | AU59: 0 | AV59: 0 | AW59: 0 | AX59: 0 | AY59: 0 | AZ59: 0 | BA59: 0 | BB59: 0 | BC59: 0 | BD59: 0 | BE59: 0 | BF59: 0 | BG59: 0 | BH59: 0 | BI59: 0 | BJ59: 0 | BK59: 0 | BL59: 0 | BM59: 0 | BN59: 0 | BO59: 0 | BP59: 0 | BQ59: 0 | BR59: 0 | BS59: 0 | BT59: 0 | BU59: 0 | BV59: 0 | BW59: 0 | BX59: 0 | BY59: 0 | BZ59: 0 | CA59: 0 | CB59: 0 | CC59: 0 | CD59: 0 | CE59: 0 | CF59: 0 | CG59: 0 | CH59: 0 | CI59: 0 | CJ59: 0 | CK59: 0 | CL59: 0 | CM59: 0 | CN59: 0 | CO59: 0 | CP59: 0 | CQ59: 0 | CR59: 0 | CS59: 0 | CT59: 0 | CU59: 0 | CV59: 178 | CW59: 51 | CX59: 0 | CY59: 51 | CZ59: 127 | DA59: 0 | DB59: 127 | DC59: 178 | DD59: 0 | DE59: 51 | DF59: 0 | DG59: 51 | DH59: 127 | DI59: 0 | DJ59: 127 | DK59: 0 | DL59: 0 | DM59: 0 | DN59: 0 | DO59: 0 | DP59: 0 | DQ59: 0 | DR59: 0 | DS59: 0 | DT59: 0 | DU59: 0 | DV59: 0 | DW59: 0 | DX59: 0 | DY59: 0 | DZ59: 0 | EA59: 0 | EB59: 0 | EC59: 0 | ED59: 0 | EE59: 0 | EF59: 0 | EG59: 74 | EH59: 50 | EI59: 48 | EJ59: 2 | EK59: 24 | EL59: 23 | EM59: 1 | EN59: 0 | EO59: 0 | EP59: 0 | EQ59: 0 | ER59: 0 | ES59: 0 | ET59: 0 | EU59: 0 | EV59: 0 | EW59: 0 | EX59: 0 | EY59: 0 | EZ59: 0 | FA59: 0 | FB59: 0

Sheet 去年累计数据表
A1: 日期范围：20250401-20250430 | D1: 25 | O1: 1=2+5=8+43 | P1: 2=3+4 | Q1: 3 | R1: 4 | S1: 5=6+7 | T1: 6 | U1: 7 | V1: 8=9+12=15+22+29+36 | W1: 9=10+11 | X1: 10 | Y1: 11 | Z1: 12=13+14 | AA1: 13 | AB1: 14 | AC1: 15=16+19 | AD1: 16=17+18 | AE1: 17 | AF1: 18 | AG1: 19=20+21 | AH1: 20 | AI1: 21 | AJ1: 22=23+26 | AK1: 23=24+25 | AL1: 24 | AM1: 25 | AN1: 26=27+28 | AO1: 27 | AP1: 28 | AQ1: 29=30+33 | AR1: 30=31+32 | AS1: 31 | AT1: 32 | AU1: 33=34+35 | AV1: 34 | AW1: 35 | AX1: 36=37+40 | AY1: 37=38+39 | AZ1: 38 | BA1: 39 | BB1: 40=41+42 | BC1: 41 | BD1: 42 | BE1: 43=50+57+64+71=44+47 | BF1: 44=45+46 | BG1: 45 | BH1: 46 | BI1: 47=48+49 | BJ1: 48 | BK1: 49 | BL1: 50=51+54 | BM1: 51=52+53 | BN1: 52 | BO1: 53 | BP1: 54=55+56 | BQ1: 55 | BR1: 56 | BS1: 57=58+61 | BT1: 58=59+60 | BU1: 59 | BV1: 60 | BW1: 61=62+63 | BX1: 62 | BY1: 63 | BZ1: 64=65+68 | CA1: 65=66+67 | CB1: 66 | CC1: 67 | CD1: 68=69+70 | CE1: 69 | CF1: 70 | CG1: 71=72+75 | CH1: 72=73+74 | CI1: 73 | CJ1: 74 | CK1: 75=76+77 | CL1: 76 | CM1: 77 | CV1: 78=85+93+100+108+86+101=79+82 | CW1: 79=80+81 | CX1: 80 | CY1: 81 | CZ1: 82=83+84 | DA1: 83 | DB1: 84 | DC1: 85=87+90=78-93-100-108-86-101 | DD1: 86 | DE1: 87=88+89 | DF1: 88 | DG1: 89 | DH1: 90=91+92 | DI1: 91 | DJ1: 92 | DK1: 93=94+97 | DL1: 94=95+96 | DM1: 95 | DN1: 96 | DO1: 97=98+99 | DP1: 98 | DQ1: 99 | DR1: 100=102+105 | DS1: 101 | DT1: 102=103+104 | DU1: 103 | DV1: 104 | DW1: 105=106+107 | DX1: 106 | DY1: 107 | DZ1: 108=109+112 | EA1: 109=110+111 | EB1: 110 | EC1: 111 | ED1: 112=113+114 | EE1: 113 | EF1: 114 | EG1: 115=116+119 | EH1: 116=117+118 | EI1: 117 | EJ1: 118 | EK1: 119=120+121 | EL1: 120 | EM1: 121 | EN1: 122=123+124+125 | EO1: 123 | EP1: 124 | EQ1: 125 | EU1: 126=127+128+129 | EV1: 127 | EW1: 128 | EX1: 129 | EY1: 130=131+132 | EZ1: 131 | FA1: 132 | FB1: 133
A2: 序号 | B2: 科室类别 | C2: 科室名称 | D2: 医疗收入不含药耗 | E2: 门急诊收入不含药耗 | F2: 住院收入不含药耗 | G2: 门急诊人次 | H2: 住院人次 | I2: 门急诊治疗收入 | J2: 门急诊手术收入 | K2: 门诊中药饮片收入 | L2: 住院治疗收入 | M2: 住院手术收入 | N2: 住院中药饮片收入 | O2: 医疗收入 | P2: 其中本地病人医疗收入 | Q2: 其中本地病人医保医疗收入 | R2: 其中本地病人自费医疗收入 | S2: 其中异地病人医疗收入 | T2: 其中异地病人医保医疗收入 | U2: 其中异地病人自费医疗收入 | V2: 门急诊收入 | W2: 其中本地病人医疗收入 | X2: 其中本地病人医保医疗收入 | Y2: 其中本地病人自费医疗收入 | Z2: 其中异地病人医疗收入 | AA2: 其中异地病人医保医疗收入 | AB2: 其中异地病人自费医疗收入 | AC2: 门急诊药品收入 | AD2: 其中本地病人医疗收入 | AE2: 其中本地病人医保医疗收入 | AF2: 其中本地病人自费医疗收入 | AG2: 其中异地病人医疗收入 | AH2: 其中异地病人医保医疗收入 | AI2: 其中异地病人自费医疗收入 | AJ2: 门急诊耗材收入 | AK2: 其中本地病人医疗收入 | AL2: 其中本地病人医保医疗收入 | AM2: 其中本地病人自费医疗收入 | AN2: 其中异地病人医疗收入 | AO2: 其中异地病人医保医疗收入 | AP2: 其中异地病人自费医疗收入 | AQ2: 门急诊检查化验收入 | AR2: 其中本地病人医疗收入 | AS2: 其中本地病人医保医疗收入 | AT2: 其中本地病人自费医疗收入 | AU2: 其中异地病人医疗收入 | AV2: 其中异地病人医保医疗收入 | AW2: 其中异地病人自费医疗收入 | AX2: 门急诊劳务收入 | AY2: 其中本地病人医疗收入 | AZ2: 其中本地病人医保医疗收入 | BA2: 其中本地病人自费医疗收入 | BB2: 其中异地病人医疗收入 | BC2: 其中异地病人医保医疗收入 | BD2: 其中异地病人自费医疗收入 | BE2: 住院收入 | BF2: 其中本地病人医疗收入 | BG2: 其中本地病人医保医疗收入 | BH2: 其中本地病人自费医疗收入 | BI2: 其中异地病人医疗收入 | BJ2: 其中异地病人医保医疗收入 | BK2: 其中异地病人自费医疗收入 | BL2: 住院药品收入 | BM2: 其中本地病人医疗收入 | BN2: 其中本地病人医保医疗收入 | BO2: 其中本地病人自费医疗收入 | BP2: 其中异地病人医疗收入 | BQ2: 其中异地病人医保医疗收入 | BR2: 其中异地病人自费医疗收入 | BS2: 住院耗材收入 | BT2: 其中本地病人医疗收入 | BU2: 其中本地病人医保医疗收入 | BV2: 其中本地病人自费医疗收入 | BW2: 其中异地病人医疗收入 | BX2: 其中异地病人医保医疗收入 | BY2: 其中异地病人自费医疗收入 | BZ2: 住院检查化验收入 | CA2: 其中本地病人医疗收入 | CB2: 其中本地病人医保医疗收入 | CC2: 其中本地病人自费医疗收入 | CD2: 其中异地病人医疗收入 | CE2: 其中异地病人医保医疗收入 | CF2: 其中异地病人自费医疗收入 | CG2: 住院劳务收入 | CH2: 其中本地病人医疗收入 | CI2: 其中本地病人医保医疗收入 | CJ2: 其中本地病人自费医疗收入 | CK2: 其中异地病人医疗收入 | CL2: 其中异地病人医保医疗收入 | CM2: 其中异地病人自费医疗收入 | CN2: 急诊收入 | CO2: 普通门诊收入 | CP2: 专家门诊收入 | CQ2: 专病门诊收入 | CR2: 特需门诊收入 | CS2: MDT门诊收入 | CT2: 镜朗诊疗部收入 | CU2: 特需病房收入 | CV2: 门急诊人次 | CW2: 其中本地病人人次 | CX2: 其中本地病人医保人次 | CY2: 其中本地病人自费人次 | CZ2: 其中异地病人人次 | DA2: 其中异地病人医保人次 | DB2: 其中异地病人自费人次 | DC2: 普通门诊 (普通+专病) | DD2: 互联网普通门诊人次 | DE2: 其中本地病人人次 | DF2: 其中本地病人医保人次 | DG2: 其中本地病人自费人次 | DH2: 其中异地病人人次 | DI2: 其中异地病人医保人次 | DJ2: 其中异地病人自费人次 | DK2: 专家门诊 | DL2: 其中本地病人人次 | DM2: 其中本地病人医保人次 | DN2: 其中本地病人自费人次 | DO2: 其中异地病人人次 | DP2: 其中异地病人医保人次 | DQ2: 其中异地病人自费人次 | DR2: 特需门诊 (特需+MDT) | DS2: 互联网特需门诊人次 | DT2: 其中本地病人人次 | DU2: 其中本地病人医保人次 | DV2: 其中本地病人自费人次 | DW2: 其中异地病人人次 | DX2: 其中异地病人医保人次 | DY2: 其中异地病人自费人次 | DZ2: 急诊人次 | EA2: 其中本地病人人次 | EB2: 其中本地病人医保人次 | EC2: 其中本地病人自费人次 | ED2: 其中异地病人人次 | EE2: 其中异地病人医保人次 | EF2: 其中异地病人自费人次 | EG2: 住院人次 | EH2: 其中本地病人人次 | EI2: 其中本地病人医保人次 | EJ2: 其中本地病人自费人次 | EK2: 其中异地病人人次 | EL2: 其中异地病人医保人次 | EM2: 其中异地病人自费人次 | EN2: 手术人次与操作人次 | EO2: 手术人次 | EP2: 介入人次 | EQ2: 操作人次(治疗+诊断) | ER2: 微创手术人次（手术） | ES2: 微创手术人次（介入） | ET2: 微创手术人次（操作） | EU2: 三级手术 | EV2: 三级手术(手术) | EW2: 三级手术(介入) | EX2: 三级手术(操作) | EY2: 四级手术 | EZ2: 四级手术(手术) | FA2: 四级手术(介入) | FB2: 重点病种人次
A3: 小计： | D3: 2.4331278e+08 | E3: 1.0669272e+08 | F3: 1.3662006e+08 | G3: 361768 | H3: 13475 | I3: 17394874 | J3: 3713883.8 | K3: 2592608.4 | L3: 17670574 | M3: 27554888 | N3: 100898.36 | O3: 5.1335709e+08 | P3: 3.3876525e+08 | Q3: 3.1077734e+08 | R3: 27987913 | S3: 1.7459184e+08 | T3: 1.3917634e+08 | U3: 35415504 | V3: 1.8599363e+08 | W3: 1.5382038e+08 | X3: 1.3947165e+08 | Y3: 14348729 | Z3: 32173249 | AA3: 12868851 | AB3: 19304398 | AC3: 72719452 | AD3: 65082715 | AE3: 62383363 | AF3: 2699351.6 | AG3: 7636737 | AH3: 4486983.1 | AI3: 3149753.9 | AJ3: 6581453.1 | AK3: 5835041.8 | AL3: 5305154.5 | AM3: 529887.33 | AN3: 746411.3 | AO3: 429667.09 | AP3: 316744.21 | AQ3: 59668926 | AR3: 48490728 | AS3: 43432453 | AT3: 5058275.5 | AU3: 11178198 | AV3: 4706470.5 | AW3: 6471727.5 | AX3: 47023794 | AY3: 34411892 | AZ3: 28350677 | BA3: 6061214.6 | BB3: 12611902 | BC3: 3245730.2 | BD3: 9366172.2 | BE3: 3.2736347e+08 | BF3: 1.8494487e+08 | BG3: 1.7130569e+08 | BH3: 13639184 | BI3: 1.4241859e+08 | BJ3: 1.2630749e+08 | BK3: 16111106 | BL3: 60713933 | BM3: 32949221 | BN3: 30774664 | BO3: 2174557 | BP3: 27764711 | BQ3: 25160377 | BR3: 2604334.6 | BS3: 1.3002947e+08 | BT3: 76757528 | BU3: 72964304 | BV3: 3793223.7 | BW3: 53271945 | BX3: 48559385 | BY3: 4712560.2 | BZ3: 55371083 | CA3: 32424594 | CB3: 30505548 | CC3: 1919046.7 | CD3: 22946489 | CE3: 20794485 | CF3: 2152004.1 | CG3: 81248978 | CH3: 42813529 | CI3: 37061172 | CJ3: 5752356.8 | CK3: 38435449 | CL3: 31793242 | CM3: 6642207.3 | CN3: 21526916 | CO3: 67573028 | CP3: 44415688 | CQ3: 25979112 | CR3: 25773602 | CS3: 724358.89 | CT3: 9723238.1 | CU3: 0 | CV3: 361768 | CW3: 307964 | CX3: 279417 | CY3: 28547 | CZ3: 53804 | DA3: 23233 | DB3: 30571 | DC3: 199349 | DD3: 3753 | DE3: 176311 | DF3: 163016 | DG3: 13295 | DH3: 23038 | DI3: 10957 | DJ3: 12081 | DK3: 79683 | DL3: 64282 | DM3: 58109 | DN3: 6173 | DO3: 15401 | DP3: 7175 | DQ3: 8226 | DR3: 34581 | DS3: 93 | DT3: 24800 | DU3: 20279 | DV3: 4521 | DW3: 9781 | DX3: 3005 | DY3: 6776 | DZ3: 44309 | EA3: 39286 | EB3: 35371 | EC3: 3915 | ED3: 5023 | EE3: 2075 | EF3: 2948 | EG3: 13475 | EH3: 7991 | EI3: 7325 | EJ3: 666 | EK3: 5484 | EL3: 4761 | EM3: 723 | EN3: 10930 | EO3: 5232 | EP3: 627 | EQ3: 5071 | ER3: 1383 | ES3: 0 | ET3: 98 | EU3: 2108 | EV3: 1658 | EW3: 308 | EX3: 142 | EY3: 1873 | EZ3: 1681 | FA3: 192 | FB3: 3816
A4: 1 | B4: 成人非手术 | C4: 内科 | D4: 174447 | E4: 174447 | F4: 0 | G4: 833 | H4: 0 | I4: 972 | J4: 0 | K4: 0 | L4: 0 | M4: 0 | N4: 0 | O4: 422549.63 | P4: 396592.89 | Q4: 382899.69 | R4: 13693.2 | S4: 25956.74 | T4: 17721.38 | U4: 8235.36 | V4: 422549.63 | W4: 396592.89 | X4: 382899.69 | Y4: 13693.2 | Z4: 25956.74 | AA4: 17721.38 | AB4: 8235.36 | AC4: 247477.63 | AD4: 239538.89 | AE4: 238284.69 | AF4: 1254.2 | AG4: 7938.74 | AH4: 5722.38 | AI4: 2216.36 | AJ4: 625 | AK4: 441 | AL4: 368 | AM4: 73 | AN4: 184 | AO4: 146 | AP4: 38 | AQ4: 145051 | AR4: 129143 | AS4: 119661 | AT4: 9482 | AU4: 15908 | AV4: 10893 | AW4: 5015 | AX4: 29396 | AY4: 27470 | AZ4: 24586 | BA4: 2884 | BB4: 1926 | BC4: 960 | BD4: 966 | BE4: 0 | BF4: 0 | BG4: 0 | BH4: 0 | BI4: 0 | BJ4: 0 | BK4: 0 | BL4: 0 | BM4: 0 | BN4: 0 | BO4: 0 | BP4: 0 | BQ4: 0 | BR4: 0 | BS4: 0 | BT4: 0 | BU4: 0 | BV4: 0 | BW4: 0 | BX4: 0 | BY4: 0 | BZ4: 0 | CA4: 0 | CB4: 0 | CC4: 0 | CD4: 0 | CE4: 0 | CF4: 0 | CG4: 0 | CH4: 0 | CI4: 0 | CJ4: 0 | CK4: 0 | CL4: 0 | CM4: 0 | CN4: 0 | CO4: 243349.78 | CP4: 130926.69 | CQ4: 38998.52 | CR4: 9274.64 | CS4: 0 | CT4: 0 | CU4: 0 | CV4: 833 | CW4: 786 | CX4: 757 | CY4: 29 | CZ4: 47 | DA4: 31 | DB4: 16 | DC4: 626 | DD4: 0 | DE4: 597 | DF4: 582 | DG4: 15 | DH4: 29 | DI4: 20 | DJ4: 9 | DK4: 198 | DL4: 181 | DM4: 171 | DN4: 10 | DO4: 17 | DP4: 11 | DQ4: 6 | DR4: 9 | DS4: 0 | DT4: 8 | DU4: 4 | DV4: 4 | DW4: 1 | DX4: 0 | DY4: 1 | DZ4: 0 | EA4: 0 | EB4: 0 | EC4: 0 | ED4: 0 | EE4: 0 | EF4: 0 | EG4: 0 | EH4: 0 | EI4: 0 | EJ4: 0 | EK4: 0 | EL4: 0 | EM4: 0 | EN4: 0 | EO4: 0 | EP4: 0 | EQ4: 0 | ER4: 0 | ES4: 0 | ET4: 0 | EU4: 0 | EV4: 0 | EW4: 0 | EX4: 0 | EY4: 0 | EZ4: 0 | FA4: 0 | FB4: 0
A5: 2 | B5: 成人非手术 | C5: 呼吸内科 | D5: 4333596.5 | E5: 1720748 | F5: 2612848.5 | G5: 8145 | H5: 256 | I5: 13110 | J5: 0 | K5: 0 | L5: 144153.5 | M5: 504 | N5: 0 | O5: 8471634 | P5: 6514925 | Q5: 6428815.8 | R5: 86109.25 | S5: 1956709 | T5: 1794020.9 | U5: 162688.06 | V5: 3520226.1 | W5: 3121541.7 | X5: 3035432.5 | Y5: 86109.25 | Z5: 398684.41 | AA5: 264399.06 | AB5: 134285.35 | AC5: 1749803.9 | AD5: 1543951.1 | AE5: 1510885.3 | AF5: 33065.85 | AG5: 205852.81 | AH5: 141570.46 | AI5: 64282.35 | AJ5: 49674.2 | AK5: 44658.6 | AL5: 43316.2 | AM5: 1342.4 | AN5: 5015.6 | AO5: 3373.6 | AP5: 1642 | AQ5: 1408900 | AR5: 1262714 | AS5: 1222782 | AT5: 39932 | AU5: 146186 | AV5: 95321 | AW5: 50865 | AX5: 311848 | AY5: 270218 | AZ5: 258449 | BA5: 11769 | BB5: 41630 | BC5: 24134 | BD5: 17496 | BE5: 4951407.8 | BF5: 3393383.3 | BG5: 3393383.3 | BH5: 0 | BI5: 1558024.6 | BJ5: 1529621.9 | BK5: 28402.71 | BL5: 2154247.1 | BM5: 1421957 | BN5: 1421957 | BO5: 0 | BP5: 732290.09 | BQ5: 720424.58 | BR5: 11865.51 | BS5: 184312.27 | BT5: 130797.3 | BU5: 130797.3 | BV5: 0 | BW5: 53514.97 | BX5: 52921.77 | BY5: 593.2 | BZ5: 2124504 | CA5: 1482879 | CB5: 1482879 | CC5: 0 | CD5: 641625 | CE5: 627971 | CF5: 13654 | CG5: 488344.5 | CH5: 357750 | CI5: 357750 | CJ5: 0 | CK5: 130594.5 | CL5: 128304.5 | CM5: 2290 | CN5: 25 | CO5: 2249402.7 | CP5: 955675.77 | CQ5: 91482.57 | CR5: 223665.07 | CS5: 0 | CT5: 0 | CU5: 0 | CV5: 8145 | CW5: 7237 | CX5: 6977 | CY5: 260 | CZ5: 908 | DA5: 532 | DB5: 376 | DC5: 6311 | DD5: 23 | DE5: 5669 | DF5: 5471 | DG5: 198 | DH5: 642 | DI5: 364 | DJ5: 278 | DK5: 1523 | DL5: 1314 | DM5: 1268 | DN5: 46 | DO5: 209 | DP5: 136 | DQ5: 73 | DR5: 287 | DS5: 1 | DT5: 232 | DU5: 216 | DV5: 16 | DW5: 55 | DX5: 32 | DY5: 23 | DZ5: 0 | EA5: 0 | EB5: 0 | EC5: 0 | ED5: 0 | EE5: 0 | EF5: 0 | EG5: 256 | EH5: 174 | EI5: 174 | EJ5: 0 | EK5: 82 | EL5: 80 | EM5: 2 | EN5: 175 | EO5: 1 | EP5: 0 | EQ5: 174 | ER5: 0 | ES5: 0 | ET5: 0 | EU5: 0 | EV5: 0 | EW5: 0 | EX5: 0 | EY5: 0 | EZ5: 0 | FA5: 0 | FB5: 63
A6: 3 | B6: 成人非手术 | C6: 消化内科（内窥镜诊治部） | D6: 7816691.5 | E6: 4729971.5 | F6: 3086720 | G6: 14896 | H6: 484 | I6: 320172 | J6: 28700 | K6: 0 | L6: 248966 | M6: 66567 | N6: 450.8 | O6: 13841529 | P6: 11109727 | Q6: 10680421 | R6: 429305.93 | S6: 2731801.8 | T6: 2313504.9 | U6: 418296.88 | V6: 8552536.2 | W6: 7455013.1 | X6: 7042577.7 | Y6: 412435.38 | Z6: 1097523.1 | AA6: 716824.99 | AB6: 380698.13 | AC6: 3225691.7 | AD6: 2855361.6 | AE6: 2767400.2 | AF6: 87961.38 | AG6: 370330.12 | AH6: 232392.99 | AI6: 137937.13 | AJ6: 596873 | AK6: 501129 | AL6: 481591 | AM6: 19538 | AN6: 95744 | AO6: 77374 | AP6: 18370 | AQ6: 3199071.5 | AR6: 2807895.5 | AS6: 2713884.5 | AT6: 94011 | AU6: 391176 | AV6: 275786 | AW6: 115390 | AX6: 1530900 | AY6: 1290627 | AZ6: 1079702 | BA6: 210925 | BB6: 240273 | BC6: 131272 | BD6: 109001 | BE6: 5288992.6 | BF6: 3654713.9 | BG6: 3637843.4 | BH6: 16870.55 | BI6: 1634278.6 | BJ6: 1596679.9 | BK6: 37598.75 | BL6: 879169.58 | BM6: 613835.13 | BN6: 612042.53 | BO6: 1792.6 | BP6: 265334.45 | BQ6: 257739.9 | BR6: 7594.55 | BS6: 1323103 | BT6: 938703.3 | BU6: 934667.85 | BV6: 4035.45 | BW6: 384399.7 | BX6: 380359.5 | BY6: 4040.2 | BZ6: 2244800.5 | CA6: 1509057 | CB6: 1500804 | CC6: 8253 | CD6: 735743.5 | CE6: 713624.5 | CF6: 22119 | CG6: 841919.5 | CH6: 593118.5 | CI6: 590329 | CJ6: 2789.5 | CK6: 248801 | CL6: 244956 | CM6: 3845 | CN6: 50 | CO6: 3681360.4 | CP6: 2084134 | CQ6: 1284974.4 | CR6: 1502067.5 | CS6: 0 | CT6: 2193 | CU6: 0 | CV6: 14896 | CW6: 13237 | CX6: 12652 | CY6: 585 | CZ6: 1659 | DA6: 1026 | DB6: 633 | DC6: 9887 | DD6: 181 | DE6: 8943 | DF6: 8687 | DG6: 256 | DH6: 944 | DI6: 626 | DJ6: 318 | DK6: 3835 | DL6: 3308 | DM6: 3168 | DN6: 140 | DO6: 527 | DP6: 321 | DQ6: 206 | DR6: 993 | DS6: 0 | DT6: 813 | DU6: 630 | DV6: 183 | DW6: 180 | DX6: 78 | DY6: 102 | DZ6: 0 | EA6: 0 | EB6: 0 | EC6: 0 | ED6: 0 | EE6: 0 | EF6: 0 | EG6: 484 | EH6: 340 | EI6: 337 | EJ6: 3 | EK6: 144 | EL6: 140 | EM6: 4 | EN6: 631 | EO6: 0 | EP6: 0 | EQ6: 631 | ER6: 0 | ES6: 0 | ET6: 66 | EU6: 50 | EV6: 0 | EW6: 0 | EX6: 50 | EY6: 0 | EZ6: 0 | FA6: 0 | FB6: 45
A7: 4 | B7: 成人非手术 | C7: 神经内科 | D7: 4397080.5 | E7: 2002290 | F7: 2394790.5 | G7: 11393 | H7: 206 | I7: 1738 | J7: 0 | K7: 88931.36 | L7: 282332 | M7: 0 | N7: 973.11 | O7: 9014299.2 | P7: 7676932.5 | Q7: 7468193.9 | R7: 208738.62 | S7: 1337366.6 | T7: 1148415.4 | U7: 188951.24 | V7: 5025074.9 | W7: 4504411.5 | X7: 4373027.1 | Y7: 131384.44 | Z7: 520663.44 | AA7: 340335.49 | AB7: 180327.95 | AC7: 3022528.2 | AD7: 2765880 | AE7: 2697940.6 | AF7: 67939.44 | AG7: 256648.16 | AH7: 177124.21 | AI7: 79523.95 | AJ7: 256.78 | AK7: 192 | AL7: 192 | AM7: 0 | AN7: 64.78 | AO7: 64.78 | AP7: 0 | AQ7: 1633383 | AR7: 1417642 | AS7: 1367435 | AT7: 50207 | AU7: 215741 | AV7: 134858 | AW7: 80883 | AX7: 368907 | AY7: 320697.5 | AZ7: 307459.5 | BA7: 13238 | BB7: 48209.5 | BC7: 28288.5 | BD7: 19921 | BE7: 3989224.2 | BF7: 3172521 | BG7: 3095166.9 | BH7: 77354.18 | BI7: 816703.18 | BJ7: 808079.89 | BK7: 8623.29 | BL7: 782506.2 | BM7: 650285.67 | BN7: 610333.75 | BO7: 39951.92 | BP7: 132220.53 | BQ7: 131602.39 | BR7: 618.14 | BS7: 811927.52 | BT7: 682339.87 | BU7: 680833.61 | BV7: 1506.26 | BW7: 129587.65 | BX7: 129352 | BY7: 235.65 | BZ7: 1766339 | CA7: 1326802 | CB7: 1306456 | CC7: 20346 | CD7: 439537 | CE7: 432745 | CF7: 6792 | CG7: 628451.5 | CH7: 513093.5 | CI7: 497543.5 | CJ7: 15550 | CK7: 115358 | CL7: 114380.5 | CM7: 977.5 | CN7: 0 | CO7: 2541914.5 | CP7: 1381057.9 | CQ7: 893549.39 | CR7: 208553.12 | CS7: 0 | CT7: 4016.59 | CU7: 0 | CV7: 11393 | CW7: 10308 | CX7: 9948 | CY7: 360 | CZ7: 1085 | DA7: 663 | DB7: 422 | DC7: 8720 | DD7: 175 | DE7: 8015 | DF7: 7777 | DG7: 238 | DH7: 705 | DI7: 449 | DJ7: 256 | DK7: 2334 | DL7: 2023 | DM7: 1917 | DN7: 106 | DO7: 311 | DP7: 191 | DQ7: 120 | DR7: 164 | DS7: 0 | DT7: 110 | DU7: 100 | DV7: 10 | DW7: 54 | DX7: 23 | DY7: 31 | DZ7: 0 | EA7: 0 | EB7: 0 | EC7: 0 | ED7: 0 | EE7: 0 | EF7: 0 | EG7: 206 | EH7: 158 | EI7: 155 | EJ7: 3 | EK7: 48 | EL7: 47 | EM7: 1 | EN7: 42 | EO7: 0 | EP7: 9 | EQ7: 33 | ER7: 0 | ES7: 0 | ET7: 0 | EU7: 4 | EV7: 0 | EW7: 4 | EX7: 0 | EY7: 5 | EZ7: 0 | FA7: 5 | FB7: 57
A8: 5 | B8: 成人非手术 | C8: 心血管一科 | D8: 4450190.5 | E8: 1334508 | F8: 3115682.5 | G8: 9695 | H8: 354 | I8: 480 | J8: 0 | K8: 0 | L8: 832978 | M8: 0 | N8: 823.45 | O8: 24749727 | P8: 19111409 | Q8: 18989457 | R8: 121952.69 | S8: 5638317.6 | T8: 5353813.9 | U8: 284503.75 | V8: 4208051.3 | W8: 3867026.4 | X8: 3821737.2 | Y8: 45289.17 | Z8: 341024.86 | AA8: 264336.36 | AB8: 76688.5 | AC8: 2872912.5 | AD8: 2690192.6 | AE8: 2667407.4 | AF8: 22785.17 | AG8: 182719.86 | AH8: 153628.36 | AI8: 29091.5 | AJ8: 630.8 | AK8: 510.8 | AL8: 510.8 | AM8: 0 | AN8: 120 | AO8: 120 | AP8: 0 | AQ8: 974860 | AR8: 859616 | AS8: 842751 | AT8: 16865 | AU8: 115244 | AV8: 79918 | AW8: 35326 | AX8: 359648 | AY8: 316707 | AZ8: 311068 | BA8: 5639 | BB8: 42941 | BC8: 30670 | BD8: 12271 | BE8: 20541676 | BF8: 15244383 | BG8: 15167719 | BH8: 76663.52 | BI8: 5297292.8 | BJ8: 5089477.5 | BK8: 207815.25 | BL8: 608620.26 | BM8: 444674.04 | BN8: 442711.32 | BO8: 1962.72 | BP8: 163946.22 | BQ8: 154483.25 | BR8: 9462.97 | BS8: 16817373 | BT8: 12514166 | BU8: 12457935 | BV8: 56230.8 | BW8: 4303207 | BX8: 4134681.2 | BY8: 168525.78 | BZ8: 1929983 | CA8: 1424808 | CB8: 1414897 | CC8: 9911 | CD8: 505175 | CE8: 485509 | CF8: 19666 | CG8: 1185699.5 | CH8: 860735 | CI8: 852176 | CJ8: 8559 | CK8: 324964.5 | CL8: 314804 | CM8: 10160.5 | CN8: 0 | CO8: 1918996.9 | CP8: 1401979.9 | CQ8: 718518.39 | CR8: 168556.03 | CS8: 0 | CT8: 0 | CU8: 0 | CV8: 9695 | CW8: 8868 | CX8: 8714 | CY8: 154 | CZ8: 827 | DA8: 603 | DB8: 224 | DC8: 6601 | DD8: 198 | DE8: 6171 | DF8: 6079 | DG8: 92 | DH8: 430 | DI8: 326 | DJ8: 104 | DK8: 2693 | DL8: 2341 | DM8: 2284 | DN8: 57 | DO8: 352 | DP8: 247 | DQ8: 105 | DR8: 203 | DS8: 0 | DT8: 159 | DU8: 157 | DV8: 2 | DW8: 44 | DX8: 30 | DY8: 14 | DZ8: 0 | EA8: 0 | EB8: 0 | EC8: 0 | ED8: 0 | EE8: 0 | EF8: 0 | EG8: 354 | EH8: 263 | EI8: 261 | EJ8: 2 | EK8: 91 | EL8: 88 | EM8: 3 | EN8: 274 | EO8: 89 | EP8: 80 | EQ8: 105 | ER8: 1 | ES8: 0 | ET8: 0 | EU8: 114 | EV8: 86 | EW8: 28 | EX8: 0 | EY8: 42 | EZ8: 1 | FA8: 41 | FB8: 156
A9: 6 | B9: 成人非手术 | C9: 血液内科 | D9: 1726205 | E9: 319543 | F9: 1406662 | G9: 1255 | H9: 384 | I9: 1202 | J9: 0 | K9: 0 | L9: 98303 | M9: 2367 | N9: 0 | O9: 9363559.2 | P9: 4513060.5 | Q9: 3816788.9 | R9: 696271.64 | S9: 4850498.7 | T9: 4376344.5 | U9: 474154.25 | V9: 976304.92 | W9: 824339.22 | X9: 809971.95 | Y9: 14367.27 | Z9: 151965.7 | AA9: 129618.44 | AB9: 22347.26 | AC9: 636456.72 | AD9: 562977.02 | AE9: 552907.75 | AF9: 10069.27 | AG9: 73479.7 | AH9: 61318.44 | AI9: 12161.26 | AJ9: 20305.2 | AK9: 18405.2 | AL9: 18405.2 | AM9: 0 | AN9: 1900 | AO9: 1900 | AP9: 0 | AQ9: 273399 | AR9: 205835 | AS9: 203824 | AT9: 2011 | AU9: 67564 | AV9: 59671 | AW9: 7893 | AX9: 46144 | AY9: 37122 | AZ9: 34835 | BA9: 2287 | BB9: 9022 | BC9: 6729 | BD9: 2293 | BE9: 8387254.3 | BF9: 3688721.3 | BG9: 3006816.9 | BH9: 681904.37 | BI9: 4698533 | BJ9: 4246726 | BK9: 451806.99 | BL9: 6765528.2 | BM9: 3010344.3 | BN9: 2331206.6 | BO9: 679137.75 | BP9: 3755183.9 | BQ9: 3315885.4 | BR9: 439298.51 | BS9: 215064.05 | BT9: 84968.95 | BU9: 84727.83 | BV9: 241.12 | BW9: 130095.1 | BX9: 127314.62 | BY9: 2780.48 | BZ9: 1015149 | CA9: 434615 | CB9: 433370 | CC9: 1245 | CD9: 580534 | CE9: 574693 | CF9: 5841 | CG9: 391513 | CH9: 158793 | CI9: 157512.5 | CJ9: 1280.5 | CK9: 232720 | CL9: 228833 | CM9: 3887 | CN9: 0 | CO9: 250193.82 | CP9: 524451.38 | CQ9: 193600.78 | CR9: 8058.94 | CS9: 0 | CT9: 0 | CU9: 0 | CV9: 1255 | CW9: 973 | CX9: 933 | CY9: 40 | CZ9: 282 | DA9: 219 | DB9: 63 | DC9: 726 | DD9: 0 | DE9: 526 | DF9: 509 | DG9: 17 | DH9: 200 | DI9: 161 | DJ9: 39 | DK9: 512 | DL9: 431 | DM9: 412 | DN9: 19 | DO9: 81 | DP9: 58 | DQ9: 23 | DR9: 17 | DS9: 0 | DT9: 16 | DU9: 12 | DV9: 4 | DW9: 1 | DX9: 0 | DY9: 1 | DZ9: 0 | EA9: 0 | EB9: 0 | EC9: 0 | ED9: 0 | EE9: 0 | EF9: 0 | EG9: 384 | EH9: 165 | EI9: 155 | EJ9: 10 | EK9: 219 | EL9: 212 | EM9: 7 | EN9: 292 | EO9: 0 | EP9: 0 | EQ9: 292 | ER9: 0 | ES9: 0 | ET9: 0 | EU9: 0 | EV9: 0 | EW9: 0 | EX9: 0 | EY9: 0 | EZ9: 0 | FA9: 0 | FB9: 34
A10: 7 | B10: 成人非手术 | C10: 肾脏风湿免疫科 | D10: 6106297.5 | E10: 4557301 | F10: 1548996.5 | G10: 6191 | H10: 185 | I10: 3006689 | J10: 0 | K10: 0 | L10: 108706 | M10: 33251.5 | N10: 398.77 | O10: 11353909 | P10: 10232224 | Q10: 10133476 | R10: 98748.27 | S10: 1121684.9 | T10: 971825.95 | U10: 149859 | V10: 9055480.5 | W10: 8491824 | X10: 8422140 | Y10: 69683.97 | Z10: 563656.5 | AA10: 450469.79 | AB10: 113186.71 | AC10: 3278815.3 | AD10: 3072508.3 | AE10: 3034113.8 | AF10: 38394.51 | AG10: 206307.02 | AH10: 152618.69 | AI10: 53688.33 | AJ10: 1219364.2 | AK10: 1160436.7 | AL10: 1157741.2 | AM10: 2695.46 | AN10: 58927.48 | AO10: 49407.1 | AP10: 9520.38 | AQ10: 1331640 | AR10: 1228924 | AS10: 1212715 | AT10: 16209 | AU10: 102716 | AV10: 80083 | AW10: 22633 | AX10: 3225661 | AY10: 3029955 | AZ10: 3017570 | BA10: 12385 | BB10: 195706 | BC10: 168361 | BD10: 27345 | BE10: 2298428.4 | BF10: 1740399.9 | BG10: 1711335.6 | BH10: 29064.3 | BI10: 558028.45 | BJ10: 521356.16 | BK10: 36672.29 | BL10: 575107.28 | BM10: 413795.33 | BN10: 411321.92 | BO10: 2473.41 | BP10: 161311.95 | BQ10: 153414.96 | BR10: 7896.99 | BS10: 174324.57 | BT10: 135839.57 | BU10: 130729.68 | BV10: 5109.89 | BW10: 38485 | BX10: 38331.2 | BY10: 153.8 | BZ10: 1180480 | CA10: 891969 | CB10: 879943 | CC10: 12026 | CD10: 288511 | CE10: 262275 | CF10: 26236 | CG10: 368516.5 | CH10: 298796 | CI10: 289341 | CJ10: 9455 | CK10: 69720.5 | CL10: 67335 | CM10: 2385.5 | CN10: 56 | CO10: 1088155.7 | CP10: 1126090.2 | CQ10: 6790894 | CR10: 50334.63 | CS10: 0 | CT10: 0 | CU10: 0 | CV10: 6191 | CW10: 5638 | CX10: 5522 | CY10: 116 | CZ10: 553 | DA10: 377 | DB10: 176 | DC10: 4600 | DD10: 89 | DE10: 4231 | DF10: 4155 | DG10: 76 | DH10: 369 | DI10: 248 | DJ10: 121 | DK10: 1422 | DL10: 1262 | DM10: 1232 | DN10: 30 | DO10: 160 | DP10: 119 | DQ10: 41 | DR10: 80 | DS10: 0 | DT10: 60 | DU10: 53 | DV10: 7 | DW10: 20 | DX10: 10 | DY10: 10 | DZ10: 0 | EA10: 0 | EB10: 0 | EC10: 0 | ED10: 0 | EE10: 0 | EF10: 0 | EG10: 185 | EH10: 139 | EI10: 137 | EJ10: 2 | EK10: 46 | EL10: 41 | EM10: 5 | EN10: 48 | EO10: 13 | EP10: 0 | EQ10: 35 | ER10: 0 | ES10: 0 | ET10: 0 | EU10: 0 | EV10: 0 | EW10: 0 | EX10: 0 | EY10: 0 | EZ10: 0 | FA10: 0 | FB10: 28
A11: 8 | B11: 成人非手术 | C11: 内分泌科 | D11: 4960555.5 | E11: 2992161 | F11: 1968394.5 | G11: 13392 | H11: 218 | I11: 10412 | J11: 1771 | K11: 0 | L11: 216771 | M11: 0 | N11: 0 | O11: 9461242.2 | P11: 8381659.2 | Q11: 8236842.3 | R11: 144816.93 | S11: 1079583 | T11: 944750.03 | U11: 134833 | V11: 6744077.9 | W11: 6239196 | X11: 6115004.5 | Y11: 124191.45 | Z11: 504881.94 | AA11: 382415.89 | AB11: 122466.05 | AC11: 3662166.3 | AD11: 3392406.8 | AE11: 3336455.3 | AF11: 55951.45 | AG11: 269759.54 | AH11: 219492.49 | AI11: 50267.05 | AJ11: 89750.6 | AK11: 84059.2 | AL11: 83223.2 | AM11: 836 | AN11: 5691.4 | AO11: 4855.4 | AP11: 836 | AQ11: 2525631 | AR11: 2334823 | AS11: 2279164 | AT11: 55659 | AU11: 190808 | AV11: 131483 | AW11: 59325 | AX11: 466530 | AY11: 427907 | AZ11: 416162 | BA11: 11745 | BB11: 38623 | BC11: 26585 | BD11: 12038 | BE11: 2717164.3 | BF11: 2142463.2 | BG11: 2121837.8 | BH11: 20625.48 | BI11: 574701.09 | BJ11: 562334.14 | BK11: 12366.95 | BL11: 684996.17 | BM11: 536930.08 | BN11: 533160.4 | BO11: 3769.68 | BP11: 148066.09 | BQ11: 144569.14 | BR11: 3496.95 | BS11: 63773.65 | BT11: 51505.65 | BU11: 51290.85 | BV11: 214.8 | BW11: 12268 | BX11: 12027 | BY11: 241 | BZ11: 1513853 | CA11: 1190966 | CB11: 1177850 | CC11: 13116 | CD11: 322887 | CE11: 316235 | CF11: 6652 | CG11: 454541.5 | CH11: 363061.5 | CI11: 359536.5 | CJ11: 3525 | CK11: 91480 | CL11: 89503 | CM11: 1977 | CN11: 25 | CO11: 3716436.5 | CP11: 1778215.6 | CQ11: 1002773.9 | CR11: 243922.99 | CS11: 2728.9 | CT11: 0 | CU11: 0 | CV11: 13392 | CW11: 12342 | CX11: 12053 | CY11: 289 | CZ11: 1050 | DA11: 745 | DB11: 305 | DC11: 9909 | DD11: 127 | DE11: 9148 | DF11: 8943 | DG11: 205 | DH11: 761 | DI11: 547 | DJ11: 214 | DK11: 3079 | DL11: 2823 | DM11: 2750 | DN11: 73 | DO11: 256 | DP11: 178 | DQ11: 78 | DR11: 277 | DS11: 0 | DT11: 244 | DU11: 234 | DV11: 10 | DW11: 33 | DX11: 20 | DY11: 13 | DZ11: 0 | EA11: 0 | EB11: 0 | EC11: 0 | ED11: 0 | EE11: 0 | EF11: 0 | EG11: 218 | EH11: 173 | EI11: 171 | EJ11: 2 | EK11: 45 | EL11: 44 | EM11: 1 | EN11: 0 | EO11: 0 | EP11: 0 | EQ11: 0 | ER11: 0 | ES11: 0 | ET11: 0 | EU11: 0 | EV11: 0 | EW11: 0 | EX11: 0 | EY11: 0 | EZ11: 0 | FA11: 0 | FB11: 201
A12: 9 | B12: 成人非手术 | C12: 老年医学科 | D12: 4557811.8 | E12: 245363 | F12: 4312448.8 | G12: 2283 | H12: 78 | I12: 7915 | J12: 0 | K12: 69964.84 | L12: 1403523 | M12: 30885.25 | N12: 38348.17 | O12: 7617244.8 | P12: 7596368.9 | Q12: 7585914.9 | R12: 10454.02 | S12: 20875.86 | T12: 15690.39 | U12: 5185.47 | V12: 1484883.8 | W12: 1464008 | X12: 1453553.9 | Y12: 10454.02 | Z12: 20875.86 | AA12: 15690.39 | AB12: 5185.47 | AC12: 1237115.4 | AD12: 1225058.6 | AE12: 1218083.5 | AF12: 6975.02 | AG12: 12056.86 | AH12: 10932.39 | AI12: 1124.47 | AJ12: 2405.4 | AK12: 2332.4 | AL12: 2332.4 | AM12: 0 | AN12: 73 | AO12: 0 | AP12: 73 | AQ12: 178438 | AR12: 170591 | AS12: 167487 | AT12: 3104 | AU12: 7847 | AV12: 4034 | AW12: 3813 | AX12: 66925 | AY12: 66026 | AZ12: 65651 | BA12: 375 | BB12: 899 | BC12: 724 | BD12: 175 | BE12: 6132361 | BF12: 6132361 | BG12: 6132361 | BH12: 0 | BI12: 0 | BJ12: 0 | BK12: 0 | BL12: 1651385.5 | BM12: 1651385.5 | BN12: 1651385.5 | BO12: 0 | BP12: 0 | BQ12: 0 | BR12: 0 | BS12: 168526.73 | BT12: 168526.73 | BU12: 168526.73 | BV12: 0 | BW12: 0 | BX12: 0 | BY12: 0 | BZ12: 1637110.5 | CA12: 1637110.5 | CB12: 1637110.5 | CC12: 0 | CD12: 0 | CE12: 0 | CF12: 0 | CG12: 2675338.2 | CH12: 2675338.2 | CI12: 2675338.2 | CJ12: 0 | CK12: 0 | CL12: 0 | CM12: 0 | CN12: 0 | CO12: 1483914.6 | CP12: 724.19 | CQ12: 245 | CR12: 0 | CS12: 0 | CT12: 0 | CU12: 0 | CV12: 2283 | CW12: 2250 | CX12: 2235 | CY12: 15 | CZ12: 33 | DA12: 26 | DB12: 7 | DC12: 2282 | DD12: 0 | DE12: 2249 | DF12: 2234 | DG12: 15 | DH12: 33 | DI12: 26 | DJ12: 7 | DK12: 1 | DL12: 1 | DM12: 1 | DN12: 0 | DO12: 0 | DP12: 0 | DQ12: 0 | DR12: 0 | DS12: 0 | DT12: 0 | DU12: 0 | DV12: 0 | DW12: 0 | DX12: 0 | DY12: 0 | DZ12: 0 | EA12: 0 | EB12: 0 | EC12: 0 | ED12: 0 | EE12: 0 | EF12: 0 | EG12: 78 | EH12: 78 | EI12: 78 | EJ12: 0 | EK12: 0 | EL12: 0 | EM12: 0 | EN12: 37 | EO12: 0 | EP12: 0 | EQ12: 37 | ER12: 0 | ES12: 0 | ET12: 0 | EU12: 0 | EV12: 0 | EW12: 0 | EX12: 0 | EY12: 0 | EZ12: 0 | FA12: 0 | FB12: 0
A13: 10 | B13: 成人非手术 | C13: 全科医学科 | D13: 1455771 | E13: 468316 | F13: 987455 | G13: 2719 | H13: 66 | I13: 36 | J13: 0 | K13: 0 | L13: 49688 | M13: 750 | N13: 120.4 | O13: 2343094.3 | P13: 1670102.8 | Q13: 1632178.9 | R13: 37923.88 | S13: 672991.49 | T13: 639207.62 | U13: 33783.87 | V13: 1094619.7 | W13: 997831.11 | X13: 984348.9 | Y13: 13482.21 | Z13: 96788.61 | AA13: 72001.75 | AB13: 24786.86 | AC13: 625124.72 | AD13: 579636.11 | AE13: 575420.9 | AF13: 4215.21 | AG13: 45488.61 | AH13: 39946.75 | AI13: 5541.86 | AJ13: 1179 | AK13: 960 | AL13: 887 | AM13: 73 | AN13: 219 | AO13: 73 | AP13: 146 | AQ13: 394995 | AR13: 350885 | AS13: 342756 | AT13: 8129 | AU13: 44110 | AV13: 26907 | AW13: 17203 | AX13: 73321 | AY13: 66350 | AZ13: 65285 | BA13: 1065 | BB13: 6971 | BC13: 5075 | BD13: 1896 | BE13: 1248474.6 | BF13: 672271.7 | BG13: 647830.03 | BH13: 24441.67 | BI13: 576202.88 | BJ13: 567205.87 | BK13: 8997.01 | BL13: 189065.24 | BM13: 113331.38 | BN13: 110859.31 | BO13: 2472.07 | BP13: 75733.86 | BQ13: 75053.21 | BR13: 680.65 | BS13: 71954.34 | BT13: 39321.32 | BU13: 38436.72 | BV13: 884.6 | BW13: 32633.02 | BX13: 29910.16 | BY13: 2722.86 | BZ13: 478370.5 | CA13: 239796.5 | CB13: 233125.5 | CC13: 6671 | CD13: 238574 | CE13: 236734 | CF13: 1840 | CG13: 509084.5 | CH13: 279822.5 | CI13: 265408.5 | CJ13: 14414 | CK13: 229262 | CL13: 225508.5 | CM13: 3753.5 | CN13: 0 | CO13: 953361.62 | CP13: 125905.97 | CQ13: 898.47 | CR13: 14453.66 | CS13: 0 | CT13: 0 | CU13: 0 | CV13: 2719 | CW13: 2463 | CX13: 2421 | CY13: 42 | CZ13: 256 | DA13: 190 | DB13: 66 | DC13: 2476 | DD13: 21 | DE13: 2249 | DF13: 2214 | DG13: 35 | DH13: 227 | DI13: 171 | DJ13: 56 | DK13: 207 | DL13: 181 | DM13: 177 | DN13: 4 | DO13: 26 | DP13: 18 | DQ13: 8 | DR13: 15 | DS13: 0 | DT13: 14 | DU13: 14 | DV13: 0 | DW13: 1 | DX13: 0 | DY13: 1 | DZ13: 0 | EA13: 0 | EB13: 0 | EC13: 0 | ED13: 0 | EE13: 0 | EF13: 0 | EG13: 66 | EH13: 36 | EI13: 34 | EJ13: 2 | EK13: 30 | EL13: 29 | EM13: 1 | EN13: 6 | EO13: 0 | EP13: 0 | EQ13: 6 | ER13: 0 | ES13: 0 | ET13: 0 | EU13: 0 | EV13: 0 | EW13: 0 | EX13: 0 | EY13: 0 | EZ13: 0 | FA13: 0 | FB13: 0
A14: 11 | B14: 成人非手术 | C14: 心血管二科 | D14: 6949087.9 | E14: 1443144 | F14: 5505943.9 | G14: 13430 | H14: 496 | I14: 876 | J14: 0 | K14: 0 | L14: 1268118.5 | M14: 10400 | N14: 1796.48 | O14: 22745124 | P14: 17672498 | Q14: 17565045 | R14: 107453.57 | S14: 5072625.1 | T14: 4914266 | U14: 158359.03 | V14: 6240302.6 | W14: 5862403.7 | X14: 5783682.2 | Y14: 78721.49 | Z14: 377898.86 | AA14: 290357.26 | AB14: 87541.6 | AC14: 4796928.4 | AD14: 4545028.5 | AE14: 4505557 | AF14: 39471.49 | AG14: 251899.86 | AH14: 207252.26 | AI14: 44647.6 | AJ14: 230.2 | AK14: 154.2 | AL14: 116.2 | AM14: 38 | AN14: 76 | AO14: 76 | AP14: 0 | AQ14: 1017769 | AR14: 926245 | AS14: 898312 | AT14: 27933 | AU14: 91524 | AV14: 59427 | AW14: 32097 | AX14: 425375 | AY14: 390976 | AZ14: 379697 | BA14: 11279 | BB14: 34399 | BC14: 23602 | BD14: 10797 | BE14: 16504821 | BF14: 11810095 | BG14: 11781363 | BH14: 28732.08 | BI14: 4694726.2 | BJ14: 4623908.8 | BK14: 70817.43 | BL14: 1035442.9 | BM14: 783508.88 | BN14: 779041.5 | BO14: 4467.38 | BP14: 251934.06 | BQ14: 246626.68 | BR14: 5307.38 | BS14: 9963434.1 | BT14: 7020218 | BU14: 7012532.3 | BV14: 7685.7 | BW14: 2943216.1 | BX14: 2911079.6 | BY14: 32136.55 | BZ14: 3690779.4 | CA14: 2679918.4 | CB14: 2666046.4 | CC14: 13872 | CD14: 1010861 | CE14: 985044 | CF14: 25817 | CG14: 1815164.5 | CH14: 1326449.5 | CI14: 1323742.5 | CJ14: 2707 | CK14: 488715 | CL14: 481158.5 | CM14: 7556.5 | CN14: 0 | CO14: 2529722.6 | CP14: 2160915.2 | CQ14: 1491531.1 | CR14: 58133.74 | CS14: 0 | CT14: 0 | CU14: 0 | CV14: 13430 | CW14: 12523 | CX14: 12315 | CY14: 208 | CZ14: 907 | DA14: 674 | DB14: 233 | DC14: 9298 | DD14: 148 | DE14: 8757 | DF14: 8652 | DG14: 105 | DH14: 541 | DI14: 412 | DJ14: 129 | DK14: 3915 | DL14: 3571 | DM14: 3480 | DN14: 91 | DO14: 344 | DP14: 253 | DQ14: 91 | DR14: 69 | DS14: 0 | DT14: 54 | DU14: 44 | DV14: 10 | DW14: 15 | DX14: 6 | DY14: 9 | DZ14: 0 | EA14: 0 | EB14: 0 | EC14: 0 | ED14: 0 | EE14: 0 | EF14: 0 | EG14: 496 | EH14: 359 | EI14: 357 | EJ14: 2 | EK14: 137 | EL14: 133 | EM14: 4 | EN14: 465 | EO14: 4 | EP14: 265 | EQ14: 196 | ER14: 0 | ES14: 0 | ET14: 0 | EU14: 181 | EV14: 0 | EW14: 181 | EX14: 0 | EY14: 4 | EZ14: 3 | FA14: 1 | FB14: 181
A15: 12 | B15: 成人手术 | C15: 普外科 | D15: 10451172 | E15: 1710377.5 | F15: 8740794.2 | G15: 7932 | H15: 845 | I15: 136204 | J15: 103809 | K15: 0 | L15: 449359.5 | M15: 2328318.8 | N15: 1188.58 | O15: 23449655 | P15: 14279339 | Q15: 13958908 | R15: 320430.93 | S15: 9170315.4 | T15: 8370535.2 | U15: 799780.21 | V15: 3329520.7 | W15: 2755406.7 | X15: 2633891.8 | Y15: 121514.87 | Z15: 574114.03 | AA15: 414268.82 | AB15: 159845.21 | AC15: 1229897.2 | AD15: 1012031.1 | AE15: 991668.84 | AF15: 20362.3 | AG15: 217866.1 | AH15: 179928.81 | AI15: 37937.29 | AJ15: 389245.99 | AK15: 365128.06 | AL15: 359215.49 | AM15: 5912.57 | AN15: 24117.93 | AO15: 12519.01 | AP15: 11598.92 | AQ15: 1125660.5 | AR15: 886911.5 | AS15: 851251.5 | AT15: 35660 | AU15: 238749 | AV15: 172981 | AW15: 65768 | AX15: 584717 | AY15: 491336 | AZ15: 431756 | BA15: 59580 | BB15: 93381 | BC15: 48840 | BD15: 44541 | BE15: 20120134 | BF15: 11523933 | BG15: 11325017 | BH15: 198916.06 | BI15: 8596201.4 | BJ15: 7956266.4 | BK15: 639935 | BL15: 4147710 | BM15: 2241950.5 | BN15: 2216497.1 | BO15: 25453.39 | BP15: 1905759.4 | BQ15: 1779032.4 | BR15: 126726.99 | BS15: 7231629.8 | BT15: 4313594.3 | BU15: 4267937.2 | BV15: 45657.17 | BW15: 2918035.5 | BX15: 2715500.7 | BY15: 202534.76 | BZ15: 3569330.5 | CA15: 1830135 | CB15: 1815331 | CC15: 14804 | CD15: 1739195.5 | CE15: 1613993 | CF15: 125202.5 | CG15: 5171463.8 | CH15: 3138252.8 | CI15: 3025251.2 | CJ15: 113001.5 | CK15: 2033211 | CL15: 1847740.2 | CM15: 185470.75 | CN15: 692302.32 | CO15: 1261887.2 | CP15: 853580.42 | CQ15: 401644.6 | CR15: 115918.37 | CS15: 4187.84 | CT15: 298402.9 | CU15: 0 | CV15: 7932 | CW15: 6615 | CX15: 6356 | CY15: 259 | CZ15: 1317 | DA15: 873 | DB15: 444 | DC15: 4371 | DD15: 21 | DE15: 3809 | DF15: 3672 | DG15: 137 | DH15: 562 | DI15: 356 | DJ15: 206 | DK15: 1952 | DL15: 1544 | DM15: 1496 | DN15: 48 | DO15: 408 | DP15: 278 | DQ15: 130 | DR15: 157 | DS15: 0 | DT15: 110 | DU15: 72 | DV15: 38 | DW15: 47 | DX15: 22 | DY15: 25 | DZ15: 1431 | EA15: 1137 | EB15: 1101 | EC15: 36 | ED15: 294 | EE15: 214 | EF15: 80 | EG15: 845 | EH15: 530 | EI15: 519 | EJ15: 11 | EK15: 315 | EL15: 292 | EM15: 23 | EN15: 793 | EO15: 582 | EP15: 0 | EQ15: 211 | ER15: 283 | ES15: 0 | ET15: 1 | EU15: 210 | EV15: 152 | EW15: 0 | EX15: 58 | EY15: 172 | EZ15: 172 | FA15: 0 | FB15: 325
... A68: 65 | B68: 医技平台 | C68: 超声诊断科 | D68: 210777 | E68: 210777 | F68: 0 | G68: 1374 | H68: 0 | I68: 1620 | J68: 15564 | K68: 0 | L68: 0 | M68: 0 | N68: 0 | O68: 281639.2 | P68: 218865.3 | Q68: 205776.65 | R68: 13088.65 | S68: 62773.9 | T68: 35283.6 | U68: 27490.3 | V68: 281639.2 | W68: 218865.3 | X68: 205776.65 | Y68: 13088.65 | Z68: 62773.9 | AA68: 35283.6 | AB68: 27490.3 | AC68: 57078 | AD68: 42650.1 | AE68: 40561.45 | AF68: 2088.65 | AG68: 14427.9 | AH68: 9302.6 | AI68: 5125.3 | AJ68: 13784.2 | AK68: 11884.2 | AL68: 11284.2 | AM68: 600 | AN68: 1900 | AO68: 1330 | AP68: 570 | AQ68: 108474 | AR68: 87471 | AS68: 83076 | AT68: 4395 | AU68: 21003 | AV68: 12743 | AW68: 8260 | AX68: 102303 | AY68: 76860 | AZ68: 70855 | BA68: 6005 | BB68: 25443 | BC68: 11908 | BD68: 13535 | BE68: 0 | BF68: 0 | BG68: 0 | BH68: 0 | BI68: 0 | BJ68: 0 | BK68: 0 | BL68: 0 | BM68: 0 | BN68: 0 | BO68: 0 | BP68: 0 | BQ68: 0 | BR68: 0 | BS68: 0 | BT68: 0 | BU68: 0 | BV68: 0 | BW68: 0 | BX68: 0 | BY68: 0 | BZ68: 0 | CA68: 0 | CB68: 0 | CC68: 0 | CD68: 0 | CE68: 0 | CF68: 0 | CG68: 0 | CH68: 0 | CI68: 0 | CJ68: 0 | CK68: 0 | CL68: 0 | CM68: 0 | CN68: -25 | CO68: -25 | CP68: 18212.12 | CQ68: 59555.08 | CR68: 203897 | CS68: 0 | CT68: 0 | CU68: 0 | CV68: 1374 | CW68: 1119 | CX68: 1065 | CY68: 54 | CZ68: 255 | DA68: 138 | DB68: 117 | DC68: 1113 | DD68: 0 | DE68: 920 | DF68: 877 | DG68: 43 | DH68: 193 | DI68: 111 | DJ68: 82 | DK68: 57 | DL68: 49 | DM68: 49 | DN68: 0 | DO68: 8 | DP68: 4 | DQ68: 4 | DR68: 204 | DS68: 0 | DT68: 150 | DU68: 139 | DV68: 11 | DW68: 54 | DX68: 23 | DY68: 31 | DZ68: 0 | EA68: 0 | EB68: 0 | EC68: 0 | ED68: 0 | EE68: 0 | EF68: 0 | EG68: 0 | EH68: 0 | EI68: 0 | EJ68: 0 | EK68: 0 | EL68: 0 | EM68: 0 | EN68: 79 | EO68: 3 | EP68: 0 | EQ68: 76 | ER68: 0 | ES68: 0 | ET68: 0 | EU68: 0 | EV68: 0 | EW68: 0 | EX68: 0 | EY68: 0 | EZ68: 0 | FA68: 0 | FB68: 0
A69: 66 | C69: 其它 | D69: 0 | E69: 0 | F69: 0 | G69: 0 | H69: 0 | I69: 0 | J69: 0 | K69: 0 | L69: 0 | M69: 0 | N69: 0 | O69: 97.38 | P69: 65.68 | Q69: 13.68 | R69: 52 | S69: 31.7 | T69: 31.7 | U69: 0 | V69: 0 | W69: 0 | X69: 0 | Y69: 0 | Z69: 0 | AA69: 0 | AB69: 0 | AC69: 0 | AD69: 0 | AE69: 0 | AF69: 0 | AG69: 0 | AH69: 0 | AI69: 0 | AJ69: 0 | AK69: 0 | AL69: 0 | AM69: 0 | AN69: 0 | AO69: 0 | AP69: 0 | AQ69: 0 | AR69: 0 | AS69: 0 | AT69: 0 | AU69: 0 | AV69: 0 | AW69: 0 | AX69: 0 | AY69: 0 | AZ69: 0 | BA69: 0 | BB69: 0 | BC69: 0 | BD69: 0 | BE69: 97.38 | BF69: 65.68 | BG69: 13.68 | BH69: 52 | BI69: 31.7 | BJ69: 31.7 | BK69: 0 | BL69: 0 | BM69: 0 | BN69: 0 | BO69: 0 | BP69: 0 | BQ69: 0 | BR69: 0 | BS69: 97.38 | BT69: 65.68 | BU69: 13.68 | BV69: 52 | BW69: 31.7 | BX69: 31.7 | BY69: 0 | BZ69: 0 | CA69: 0 | CB69: 0 | CC69: 0 | CD69: 0 | CE69: 0 | CF69: 0 | CG69: 0 | CH69: 0 | CI69: 0 | CJ69: 0 | CK69: 0 | CL69: 0 | CM69: 0 | CN69: 0 | CO69: 0 | CP69: 0 | CQ69: 0 | CR69: 0 | CS69: 0 | CT69: 0 | CU69: 0 | CV69: 0 | CW69: 0 | CX69: 0 | CY69: 0 | CZ69: 0 | DA69: 0 | DB69: 0 | DC69: 0 | DD69: 0 | DE69: 0 | DF69: 0 | DG69: 0 | DH69: 0 | DI69: 0 | DJ69: 0 | DK69: 0 | DL69: 0 | DM69: 0 | DN69: 0 | DO69: 0 | DP69: 0 | DQ69: 0 | DR69: 0 | DS69: 0 | DT69: 0 | DU69: 0 | DV69: 0 | DW69: 0 | DX69: 0 | DY69: 0 | DZ69: 0 | EA69: 0 | EB69: 0 | EC69: 0 | ED69: 0 | EE69: 0 | EF69: 0 | EG69: 0 | EH69: 0 | EI69: 0 | EJ69: 0 | EK69: 0 | EL69: 0 | EM69: 0 | EN69: 0 | EO69: 0 | EP69: 0 | EQ69: 0 | ER69: 0 | ES69: 0 | ET69: 0 | EU69: 0 | EV69: 0 | EW69: 0 | EX69: 0 | EY69: 0 | EZ69: 0 | FA69: 0 | FB69: 0

Sheet 当年连续累计数据表
A1: 日期范围：20260101-20260430 | D1: 25 | O1: 1=2+5=8+43 | P1: 2=3+4 | Q1: 3 | R1: 4 | S1: 5=6+7 | T1: 6 | U1: 7 | V1: 8=9+12=15+22+29+36 | W1: 9=10+11 | X1: 10 | Y1: 11 | Z1: 12=13+14 | AA1: 13 | AB1: 14 | AC1: 15=16+19 | AD1: 16=17+18 | AE1: 17 | AF1: 18 | AG1: 19=20+21 | AH1: 20 | AI1: 21 | AJ1: 22=23+26 | AK1: 23=24+25 | AL1: 24 | AM1: 25 | AN1: 26=27+28 | AO1: 27 | AP1: 28 | AQ1: 29=30+33 | AR1: 30=31+32 | AS1: 31 | AT1: 32 | AU1: 33=34+35 | AV1: 34 | AW1: 35 | AX1: 36=37+40 | AY1: 37=38+39 | AZ1: 38 | BA1: 39 | BB1: 40=41+42 | BC1: 41 | BD1: 42 | BE1: 43=50+57+64+71=44+47 | BF1: 44=45+46 | BG1: 45 | BH1: 46 | BI1: 47=48+49 | BJ1: 48 | BK1: 49 | BL1: 50=51+54 | BM1: 51=52+53 | BN1: 52 | BO1: 53 | BP1: 54=55+56 | BQ1: 55 | BR1: 56 | BS1: 57=58+61 | BT1: 58=59+60 | BU1: 59 | BV1: 60 | BW1: 61=62+63 | BX1: 62 | BY1: 63 | BZ1: 64=65+68 | CA1: 65=66+67 | CB1: 66 | CC1: 67 | CD1: 68=69+70 | CE1: 69 | CF1: 70 | CG1: 71=72+75 | CH1: 72=73+74 | CI1: 73 | CJ1: 74 | CK1: 75=76+77 | CL1: 76 | CM1: 77 | CV1: 78=85+93+100+108+86+101=79+82 | CW1: 79=80+81 | CX1: 80 | CY1: 81 | CZ1: 82=83+84 | DA1: 83 | DB1: 84 | DC1: 85=87+90=78-93-100-108-86-101 | DD1: 86 | DE1: 87=88+89 | DF1: 88 | DG1: 89 | DH1: 90=91+92 | DI1: 91 | DJ1: 92 | DK1: 93=94+97 | DL1: 94=95+96 | DM1: 95 | DN1: 96 | DO1: 97=98+99 | DP1: 98 | DQ1: 99 | DR1: 100=102+105 | DS1: 101 | DT1: 102=103+104 | DU1: 103 | DV1: 104 | DW1: 105=106+107 | DX1: 106 | DY1: 107 | DZ1: 108=109+112 | EA1: 109=110+111 | EB1: 110 | EC1: 111 | ED1: 112=113+114 | EE1: 113 | EF1: 114 | EG1: 115=116+119 | EH1: 116=117+118 | EI1: 117 | EJ1: 118 | EK1: 119=120+121 | EL1: 120 | EM1: 121 | EN1: 122=123+124+125 | EO1: 123 | EP1: 124 | EQ1: 125 | EU1: 126=127+128+129 | EV1: 127 | EW1: 128 | EX1: 129 | EY1: 130=131+132 | EZ1: 131 | FA1: 132 | FB1: 133
A2: 序号 | B2: 科室类别 | C2: 科室名称 | D2: 医疗收入不含药耗 | E2: 门急诊收入不含药耗 | F2: 住院收入不含药耗 | G2: 门急诊人次 | H2: 住院人次 | I2: 门急诊治疗收入 | J2: 门急诊手术收入 | K2: 门诊中药饮片收入 | L2: 住院治疗收入 | M2: 住院手术收入 | N2: 住院中药饮片收入 | O2: 医疗收入 | P2: 其中本地病人医疗收入 | Q2: 其中本地病人医保医疗收入 | R2: 其中本地病人自费医疗收入 | S2: 其中异地病人医疗收入 | T2: 其中异地病人医保医疗收入 | U2: 其中异地病人自费医疗收入 | V2: 门急诊收入 | W2: 其中本地病人医疗收入 | X2: 其中本地病人医保医疗收入 | Y2: 其中本地病人自费医疗收入 | Z2: 其中异地病人医疗收入 | AA2: 其中异地病人医保医疗收入 | AB2: 其中异地病人自费医疗收入 | AC2: 门急诊药品收入 | AD2: 其中本地病人医疗收入 | AE2: 其中本地病人医保医疗收入 | AF2: 其中本地病人自费医疗收入 | AG2: 其中异地病人医疗收入 | AH2: 其中异地病人医保医疗收入 | AI2: 其中异地病人自费医疗收入 | AJ2: 门急诊耗材收入 | AK2: 其中本地病人医疗收入 | AL2: 其中本地病人医保医疗收入 | AM2: 其中本地病人自费医疗收入 | AN2: 其中异地病人医疗收入 | AO2: 其中异地病人医保医疗收入 | AP2: 其中异地病人自费医疗收入 | AQ2: 门急诊检查化验收入 | AR2: 其中本地病人医疗收入 | AS2: 其中本地病人医保医疗收入 | AT2: 其中本地病人自费医疗收入 | AU2: 其中异地病人医疗收入 | AV2: 其中异地病人医保医疗收入 | AW2: 其中异地病人自费医疗收入 | AX2: 门急诊劳务收入 | AY2: 其中本地病人医疗收入 | AZ2: 其中本地病人医保医疗收入 | BA2: 其中本地病人自费医疗收入 | BB2: 其中异地病人医疗收入 | BC2: 其中异地病人医保医疗收入 | BD2: 其中异地病人自费医疗收入 | BE2: 住院收入 | BF2: 其中本地病人医疗收入 | BG2: 其中本地病人医保医疗收入 | BH2: 其中本地病人自费医疗收入 | BI2: 其中异地病人医疗收入 | BJ2: 其中异地病人医保医疗收入 | BK2: 其中异地病人自费医疗收入 | BL2: 住院药品收入 | BM2: 其中本地病人医疗收入 | BN2: 其中本地病人医保医疗收入 | BO2: 其中本地病人自费医疗收入 | BP2: 其中异地病人医疗收入 | BQ2: 其中异地病人医保医疗收入 | BR2: 其中异地病人自费医疗收入 | BS2: 住院耗材收入 | BT2: 其中本地病人医疗收入 | BU2: 其中本地病人医保医疗收入 | BV2: 其中本地病人自费医疗收入 | BW2: 其中异地病人医疗收入 | BX2: 其中异地病人医保医疗收入 | BY2: 其中异地病人自费医疗收入 | BZ2: 住院检查化验收入 | CA2: 其中本地病人医疗收入 | CB2: 其中本地病人医保医疗收入 | CC2: 其中本地病人自费医疗收入 | CD2: 其中异地病人医疗收入 | CE2: 其中异地病人医保医疗收入 | CF2: 其中异地病人自费医疗收入 | CG2: 住院劳务收入 | CH2: 其中本地病人医疗收入 | CI2: 其中本地病人医保医疗收入 | CJ2: 其中本地病人自费医疗收入 | CK2: 其中异地病人医疗收入 | CL2: 其中异地病人医保医疗收入 | CM2: 其中异地病人自费医疗收入 | CN2: 急诊收入 | CO2: 普通门诊收入 | CP2: 专家门诊收入 | CQ2: 专病门诊收入 | CR2: 特需门诊收入 | CS2: MDT门诊收入 | CT2: 镜朗诊疗部收入 | CU2: 特需病房收入 | CV2: 门急诊人次 | CW2: 其中本地病人人次 | CX2: 其中本地病人医保人次 | CY2: 其中本地病人自费人次 | CZ2: 其中异地病人人次 | DA2: 其中异地病人医保人次 | DB2: 其中异地病人自费人次 | DC2: 普通门诊 (普通+专病) | DD2: 互联网普通门诊人次 | DE2: 其中本地病人人次 | DF2: 其中本地病人医保人次 | DG2: 其中本地病人自费人次 | DH2: 其中异地病人人次 | DI2: 其中异地病人医保人次 | DJ2: 其中异地病人自费人次 | DK2: 专家门诊 | DL2: 其中本地病人人次 | DM2: 其中本地病人医保人次 | DN2: 其中本地病人自费人次 | DO2: 其中异地病人人次 | DP2: 其中异地病人医保人次 | DQ2: 其中异地病人自费人次 | DR2: 特需门诊 (特需+MDT) | DS2: 互联网特需门诊人次 | DT2: 其中本地病人人次 | DU2: 其中本地病人医保人次 | DV2: 其中本地病人自费人次 | DW2: 其中异地病人人次 | DX2: 其中异地病人医保人次 | DY2: 其中异地病人自费人次 | DZ2: 急诊人次 | EA2: 其中本地病人人次 | EB2: 其中本地病人医保人次 | EC2: 其中本地病人自费人次 | ED2: 其中异地病人人次 | EE2: 其中异地病人医保人次 | EF2: 其中异地病人自费人次 | EG2: 住院人次 | EH2: 其中本地病人人次 | EI2: 其中本地病人医保人次 | EJ2: 其中本地病人自费人次 | EK2: 其中异地病人人次 | EL2: 其中异地病人医保人次 | EM2: 其中异地病人自费人次 | EN2: 手术人次与操作人次 | EO2: 手术人次 | EP2: 介入人次 | EQ2: 操作人次(治疗+诊断) | ER2: 微创手术人次（手术） | ES2: 微创手术人次（介入） | ET2: 微创手术人次（操作） | EU2: 三级手术 | EV2: 三级手术(手术) | EW2: 三级手术(介入) | EX2: 三级手术(操作) | EY2: 四级手术 | EZ2: 四级手术(手术) | FA2: 四级手术(介入) | FB2: 重点病种人次
A3: 小计： | D3: 1.1193735e+09 | E3: 5.0244567e+08 | F3: 6.1692788e+08 | G3: 1653273 | H3: 57468 | I3: 90328915 | J3: 19368115 | K3: 9827744.6 | L3: 57011726 | M3: 1.4049941e+08 | N3: 171011.05 | O3: 2.4112149e+09 | P3: 1.6301332e+09 | Q3: 1.5042772e+09 | R3: 1.2585602e+08 | S3: 7.810817e+08 | T3: 6.4772431e+08 | U3: 1.3335738e+08 | V3: 8.9663713e+08 | W3: 7.3785717e+08 | X3: 6.7421846e+08 | Y3: 63638708 | Z3: 1.5877996e+08 | AA3: 81119276 | AB3: 77660680 | AC3: 3.6190004e+08 | AD3: 3.1784172e+08 | AE3: 3.0620327e+08 | AF3: 11638456 | AG3: 44058320 | AH3: 31526706 | AI3: 12531614 | AJ3: 32291414 | AK3: 28349746 | AL3: 24925637 | AM3: 3424108.7 | AN3: 3941668.1 | AO3: 2324290.6 | AP3: 1617377.5 | AQ3: 2.8306524e+08 | AR3: 2.3124006e+08 | AS3: 2.1013601e+08 | AT3: 21104044 | AU3: 51825180 | AV3: 25839242 | AW3: 25985938 | AX3: 2.1938043e+08 | AY3: 1.6042564e+08 | AZ3: 1.3295354e+08 | BA3: 27472099 | BB3: 58954787 | BC3: 21429037 | BD3: 37525750 | BE3: 1.5145778e+09 | BF3: 8.9227605e+08 | BG3: 8.3005873e+08 | BH3: 62217316 | BI3: 6.2230174e+08 | BJ3: 5.6660504e+08 | BK3: 55696703 | BL3: 2.4632105e+08 | BM3: 1.348373e+08 | BN3: 1.2901145e+08 | BO3: 5825848.2 | BP3: 1.1148375e+08 | BQ3: 1.0397118e+08 | BR3: 7512567.4 | BS3: 6.5132886e+08 | BT3: 3.9841782e+08 | BU3: 3.7616446e+08 | BV3: 22253353 | BW3: 2.5291104e+08 | BX3: 2.3646843e+08 | BY3: 16442610 | BZ3: 2.5758419e+08 | CA3: 1.5731885e+08 | CB3: 1.4788019e+08 | CC3: 9438665.5 | CD3: 1.0026534e+08 | CE3: 92501185 | CF3: 7764154 | CG3: 3.5934369e+08 | CH3: 2.0170208e+08 | CI3: 1.7700263e+08 | CJ3: 24699450 | CK3: 1.5764161e+08 | CL3: 1.3366424e+08 | CM3: 23977372 | CN3: 1.157464e+08 | CO3: 3.215656e+08 | CP3: 2.253908e+08 | CQ3: 1.2070977e+08 | CR3: 1.121167e+08 | CS3: 1104290.9 | CT3: 38484383 | CU3: 0 | CV3: 1653273 | CW3: 1408768 | CX3: 1283947 | CY3: 124821 | CZ3: 244505 | DA3: 124607 | DB3: 119898 | DC3: 907710 | DD3: 20270 | DE3: 799358 | DF3: 740921 | DG3: 58437 | DH3: 108352 | DI3: 60139 | DJ3: 48213 | DK3: 373919 | DL3: 304155 | DM3: 278694 | DN3: 25461 | DO3: 69764 | DP3: 37959 | DQ3: 31805 | DR3: 137096 | DS3: 536 | DT3: 98333 | DU3: 81380 | DV3: 16953 | DW3: 38763 | DX3: 14168 | DY3: 24595 | DZ3: 213742 | EA3: 190029 | EB3: 169703 | EC3: 20326 | ED3: 23713 | EE3: 12217 | EF3: 11496 | EG3: 57468 | EH3: 35736 | EI3: 32900 | EJ3: 2836 | EK3: 21732 | EL3: 19257 | EM3: 2475 | EN3: 46779 | EO3: 24644 | EP3: 3215 | EQ3: 18920 | ER3: 6227 | ES3: 0 | ET3: 368 | EU3: 11828 | EV3: 9612 | EW3: 1628 | EX3: 588 | EY3: 8337 | EZ3: 7529 | FA3: 808 | FB3: 18722
A4: 1 | B4: 成人非手术 | C4: 内科 | D4: 682594 | E4: 682594 | F4: 0 | G4: 3810 | H4: 0 | I4: 2034 | J4: 0 | K4: 0 | L4: 0 | M4: 0 | N4: 0 | O4: 1831053.3 | P4: 1703349.5 | Q4: 1670217.3 | R4: 33132.21 | S4: 127703.83 | T4: 101887.83 | U4: 25816 | V4: 1831053.3 | W4: 1703349.5 | X4: 1670217.3 | Y4: 33132.21 | Z4: 127703.83 | AA4: 101887.83 | AB4: 25816 | AC4: 1143479.1 | AD4: 1094001.3 | AE4: 1089682.1 | AF4: 4319.21 | AG4: 49477.83 | AH4: 44220.83 | AI4: 5257 | AJ4: 4980.16 | AK4: 4011.16 | AL4: 4011.16 | AM4: 0 | AN4: 969 | AO4: 879 | AP4: 90 | AQ4: 570515 | AR4: 502237 | AS4: 478257 | AT4: 23980 | AU4: 68278 | AV4: 51038 | AW4: 17240 | AX4: 112079 | AY4: 103100 | AZ4: 98267 | BA4: 4833 | BB4: 8979 | BC4: 5750 | BD4: 3229 | BE4: 0 | BF4: 0 | BG4: 0 | BH4: 0 | BI4: 0 | BJ4: 0 | BK4: 0 | BL4: 0 | BM4: 0 | BN4: 0 | BO4: 0 | BP4: 0 | BQ4: 0 | BR4: 0 | BS4: 0 | BT4: 0 | BU4: 0 | BV4: 0 | BW4: 0 | BX4: 0 | BY4: 0 | BZ4: 0 | CA4: 0 | CB4: 0 | CC4: 0 | CD4: 0 | CE4: 0 | CF4: 0 | CG4: 0 | CH4: 0 | CI4: 0 | CJ4: 0 | CK4: 0 | CL4: 0 | CM4: 0 | CN4: 0 | CO4: 1064049.8 | CP4: 531246.91 | CQ4: 207330.92 | CR4: 28425.7 | CS4: 0 | CT4: 0 | CU4: 0 | CV4: 3810 | CW4: 3537 | CX4: 3442 | CY4: 95 | CZ4: 273 | DA4: 186 | DB4: 87 | DC4: 2922 | DD4: 122 | DE4: 2756 | DF4: 2704 | DG4: 52 | DH4: 166 | DI4: 132 | DJ4: 34 | DK4: 741 | DL4: 679 | DM4: 669 | DN4: 10 | DO4: 62 | DP4: 50 | DQ4: 12 | DR4: 25 | DS4: 0 | DT4: 19 | DU4: 11 | DV4: 8 | DW4: 6 | DX4: 2 | DY4: 4 | DZ4: 0 | EA4: 0 | EB4: 0 | EC4: 0 | ED4: 0 | EE4: 0 | EF4: 0 | EG4: 0 | EH4: 0 | EI4: 0 | EJ4: 0 | EK4: 0 | EL4: 0 | EM4: 0 | EN4: 0 | EO4: 0 | EP4: 0 | EQ4: 0 | ER4: 0 | ES4: 0 | ET4: 0 | EU4: 0 | EV4: 0 | EW4: 0 | EX4: 0 | EY4: 0 | EZ4: 0 | FA4: 0 | FB4: 0
A5: 2 | B5: 成人非手术 | C5: 呼吸内科 | D5: 20973862 | E5: 8822892 | F5: 12150970 | G5: 39509 | H5: 1243 | I5: 48978 | J5: 0 | K5: 0 | L5: 749424.5 | M5: 6101 | N5: 1513.45 | O5: 40158826 | P5: 30258811 | Q5: 29686749 | R5: 572061.57 | S5: 9900015.1 | T5: 9145922.2 | U5: 754092.9 | V5: 18295346 | W5: 16074650 | X5: 15587546 | Y5: 487103.9 | Z5: 2220696.8 | AA5: 1572333.6 | AB5: 648363.21 | AC5: 9209823.5 | AD5: 8034764.3 | AE5: 7866867.8 | AF5: 167896.5 | AG5: 1175059.1 | AH5: 874799.92 | AI5: 300259.21 | AJ5: 262630.91 | AK5: 232714.27 | AL5: 224424.87 | AM5: 8289.4 | AN5: 29916.64 | AO5: 19928.64 | AP5: 9988 | AQ5: 7382852 | AR5: 6555777 | AS5: 6303009 | AT5: 252768 | AU5: 827075 | AV5: 557305 | AW5: 269770 | AX5: 1440040 | AY5: 1251394 | AZ5: 1193244 | BA5: 58150 | BB5: 188646 | BC5: 120300 | BD5: 68346 | BE5: 21863479 | BF5: 14184161 | BG5: 14099203 | BH5: 84957.67 | BI5: 7679318.3 | BJ5: 7573588.6 | BK5: 105729.69 | BL5: 8987466.5 | BM5: 5643755 | BN5: 5602597.6 | BO5: 41157.41 | BP5: 3343711.5 | BQ5: 3315987.2 | BR5: 27724.34 | BS5: 725042.32 | BT5: 473854.51 | BU5: 471441.75 | BV5: 2412.76 | BW5: 251187.81 | BX5: 245688.96 | BY5: 5498.85 | BZ5: 9500444 | CA5: 6310132 | CB5: 6274354 | CC5: 35778 | CD5: 3190312 | CE5: 3128791 | CF5: 61521 | CG5: 2650526.5 | CH5: 1756419.5 | CI5: 1750810 | CJ5: 5609.5 | CK5: 894107 | CL5: 883121.5 | CM5: 10985.5 | CN5: 75 | CO5: 11481604 | CP5: 5451354.2 | CQ5: 373985.17 | CR5: 988403.2 | CS5: 0 | CT5: 13098.03 | CU5: 0 | CV5: 39509 | CW5: 35181 | CX5: 33880 | CY5: 1301 | CZ5: 4328 | DA5: 2916 | DB5: 1412 | DC5: 29609 | DD5: 232 | DE5: 26578 | DF5: 25668 | DG5: 910 | DH5: 3031 | DI5: 2021 | DJ5: 1010 | DK5: 8546 | DL5: 7490 | DM5: 7174 | DN5: 316 | DO5: 1056 | DP5: 761 | DQ5: 295 | DR5: 1115 | DS5: 7 | DT5: 882 | DU5: 814 | DV5: 68 | DW5: 233 | DX5: 133 | DY5: 100 | DZ5: 0 | EA5: 0 | EB5: 0 | EC5: 0 | ED5: 0 | EE5: 0 | EF5: 0 | EG5: 1243 | EH5: 820 | EI5: 814 | EJ5: 6 | EK5: 423 | EL5: 417 | EM5: 6 | EN5: 840 | EO5: 6 | EP5: 0 | EQ5: 834 | ER5: 1 | ES5: 0 | ET5: 1 | EU5: 1 | EV5: 1 | EW5: 0 | EX5: 0 | EY5: 0 | EZ5: 0 | FA5: 0 | FB5: 335
A6: 3 | B6: 成人非手术 | C6: 消化内科（内窥镜诊治部） | D6: 39986115 | E6: 25223304 | F6: 14762811 | G6: 84273 | H6: 2465 | I6: 1720801 | J6: 67850 | K6: 0 | L6: 1297367 | M6: 805287 | N6: 7121.4 | O6: 72497388 | P6: 60090607 | Q6: 57636775 | R6: 2453831.6 | S6: 12406781 | T6: 10121318 | U6: 2285462.8 | V6: 46461001 | W6: 40803240 | X6: 38578236 | Y6: 2225004.7 | Z6: 5657760.6 | AA6: 3710238.4 | AB6: 1947522.2 | AC6: 18956207 | AD6: 16861285 | AE6: 16367630 | AF6: 493654.73 | AG6: 2094921.6 | AH6: 1457132.4 | AI6: 637789.16 | AJ6: 2281490.2 | AK6: 1998991.2 | AL6: 1923931.2 | AM6: 75060 | AN6: 282499 | AO6: 210547 | AP6: 71952 | AQ6: 18059476 | AR6: 15837597 | AS6: 15194147 | AT6: 643450 | AU6: 2221879 | AV6: 1529224 | AW6: 692655 | AX6: 7163828 | AY6: 6105367 | AZ6: 5092527 | BA6: 1012840 | BB6: 1058461 | BC6: 513335 | BD6: 545126 | BE6: 26036387 | BF6: 19287367 | BG6: 19058540 | BH6: 228826.86 | BI6: 6749020.4 | BJ6: 6411079.8 | BK6: 337940.62 | BL6: 4736820 | BM6: 3433554.9 | BN6: 3403816.6 | BO6: 29738.23 | BP6: 1303265.1 | BQ6: 1238694.9 | BR6: 64570.28 | BS6: 6536756.6 | BT6: 4948167.8 | BU6: 4899708.7 | BV6: 48459.13 | BW6: 1588588.8 | BX6: 1503861.9 | BY6: 84726.84 | BZ6: 9679602 | CA6: 6997608 | CB6: 6928320 | CC6: 69288 | CD6: 2681994 | CE6: 2546519 | CF6: 135475 | CG6: 5083208.6 | CH6: 3908036.1 | CI6: 3826694.6 | CJ6: 81341.5 | CK6: 1175172.5 | CL6: 1122004 | CM6: 53168.5 | CN6: -40 | CO6: 23360318 | CP6: 11151711 | CQ6: 6448472.7 | CR6: 5500499.1 | CS6: 0 | CT6: 174438.21 | CU6: 0 | CV6: 84273 | CW6: 74406 | CX6: 70955 | CY6: 3451 | CZ6: 9867 | DA6: 6372 | DB6: 3495 | DC6: 58526 | DD6: 986 | DE6: 52115 | DF6: 50236 | DG6: 1879 | DH6: 6411 | DI6: 4193 | DJ6: 2218 | DK6: 20424 | DL6: 17831 | DM6: 17149 | DN6: 682 | DO6: 2593 | DP6: 1830 | DQ6: 763 | DR6: 4337 | DS6: 0 | DT6: 3540 | DU6: 2674 | DV6: 866 | DW6: 797 | DX6: 324 | DY6: 473 | DZ6: 0 | EA6: 0 | EB6: 0 | EC6: 0 | ED6: 0 | EE6: 0 | EF6: 0 | EG6: 2465 | EH6: 1855 | EI6: 1832 | EJ6: 23 | EK6: 610 | EL6: 576 | EM6: 34 | EN6: 2841 | EO6: 4 | EP6: 0 | EQ6: 2837 | ER6: 0 | ES6: 0 | ET6: 297 | EU6: 220 | EV6: 4 | EW6: 0 | EX6: 216 | EY6: 0 | EZ6: 0 | FA6: 0 | FB6: 215
A7: 4 | B7: 成人非手术 | C7: 神经内科 | D7: 24902334 | E7: 12111534 | F7: 12790799 | G7: 54829 | H7: 1090 | I7: 3398 | J7: 0 | K7: 327327.34 | L7: 752420.5 | M7: 141004 | N7: 9202.33 | O7: 58747219 | P7: 47122788 | Q7: 46140658 | R7: 982130.03 | S7: 11624431 | T7: 10533564 | U7: 1090867.9 | V7: 27574310 | W7: 24502670 | X7: 23662640 | Y7: 840029.72 | Z7: 3071640.6 | AA7: 2250712.8 | AB7: 820927.79 | AC7: 15431000 | AD7: 14030883 | AE7: 13677253 | AF7: 353630.54 | AG7: 1400116.9 | AH7: 1056101.3 | AI7: 344015.61 | AJ7: 31775.58 | AK7: 25775.4 | AL7: 24165.22 | AM7: 1610.18 | AN7: 6000.18 | AO7: 4386 | AP7: 1614.18 | AQ7: 9992675 | AR7: 8614609 | AS7: 8222314 | AT7: 392295 | AU7: 1378066 | AV7: 999391 | AW7: 378675 | AX7: 2118859.5 | AY7: 1831402 | AZ7: 1738908 | BA7: 92494 | BB7: 287457.5 | BC7: 190834.5 | BD7: 96623 | BE7: 31172909 | BF7: 22620118 | BG7: 22478018 | BH7: 142100.31 | BI7: 8552790.8 | BJ7: 8282850.8 | BK7: 269940.07 | BL7: 5154045.1 | BM7: 3881705.4 | BN7: 3841948.6 | BO7: 39756.73 | BP7: 1272339.7 | BQ7: 1219485.8 | BR7: 52853.88 | BS7: 13228065 | BT7: 9259730.6 | BU7: 9253252.1 | BV7: 6478.58 | BW7: 3968334.1 | BX7: 3896824.9 | BY7: 71509.19 | BZ7: 9325320 | CA7: 6850368 | CB7: 6789436 | CC7: 60932 | CD7: 2474952 | CE7: 2361144 | CF7: 113808 | CG7: 3465479 | CH7: 2628314 | CI7: 2593381 | CJ7: 34933 | CK7: 837165 | CL7: 805396 | CM7: 31769 | CN7: 40 | CO7: 13762879 | CP7: 6073359.1 | CQ7: 4738702 | CR7: 2999370 | CS7: 0 | CT7: 0 | CU7: 0 | CV7: 54829 | CW7: 49179 | CX7: 47275 | CY7: 1904 | CZ7: 5650 | DA7: 3867 | DB7: 1783 | DC7: 40963 | DD7: 1038 | DE7: 37304 | DF7: 36042 | DG7: 1262 | DH7: 3659 | DI7: 2545 | DJ7: 1114 | DK7: 10000 | DL7: 8624 | DM7: 8213 | DN7: 411 | DO7: 1376 | DP7: 970 | DQ7: 406 | DR7: 2828 | DS7: 0 | DT7: 2275 | DU7: 2099 | DV7: 176 | DW7: 553 | DX7: 351 | DY7: 202 | DZ7: 0 | EA7: 0 | EB7: 0 | EC7: 0 | ED7: 0 | EE7: 0 | EF7: 0 | EG7: 1090 | EH7: 810 | EI7: 801 | EJ7: 9 | EK7: 280 | EL7: 268 | EM7: 12 | EN7: 403 | EO7: 3 | EP7: 112 | EQ7: 288 | ER7: 0 | ES7: 0 | ET7: 0 | EU7: 21 | EV7: 1 | EW7: 20 | EX7: 0 | EY7: 94 | EZ7: 2 | FA7: 92 | FB7: 327
A8: 5 | B8: 成人非手术 | C8: 心血管内科 | D8: 61539984 | E8: 15950978 | F8: 45589006 | G8: 126050 | H8: 4218 | I8: 17604 | J8: 0 | K8: 0 | L8: 764105.5 | M8: 9492367.8 | N8: 2053.43 | O8: 2.4445755e+08 | P8: 1.8999453e+08 | Q8: 1.881543e+08 | R8: 1840224.8 | S8: 54463025 | T8: 52865565 | U8: 1597459.3 | V8: 59124233 | W8: 54565113 | X8: 53756707 | Y8: 808406.24 | Z8: 4559120.4 | AA8: 3740074.6 | AB8: 819045.77 | AC8: 42989019 | AD8: 40104933 | AE8: 39724481 | AF8: 380451.24 | AG8: 2884086.4 | AH8: 2489810.6 | AI8: 394275.77 | AJ8: 184236.4 | AK8: 161056.4 | AL8: 155362.4 | AM8: 5694 | AN8: 23180 | AO8: 16750 | AP8: 6430 | AQ8: 11636940 | AR8: 10449431 | AS8: 10139462 | AT8: 309969 | AU8: 1187509 | AV8: 894437 | AW8: 293072 | AX8: 4314038 | AY8: 3849693 | AZ8: 3737401 | BA8: 112292 | BB8: 464345 | BC8: 339077 | BD8: 125268 | BE8: 1.8533332e+08 | BF8: 1.3542941e+08 | BG8: 1.3439759e+08 | BH8: 1031818.5 | BI8: 49903904 | BJ8: 49125491 | BK8: 778413.55 | BL8: 10238397 | BM8: 7935960.9 | BN8: 7883157.4 | BO8: 52803.57 | BP8: 2302436.2 | BQ8: 2258572.7 | BR8: 43863.49 | BS8: 1.2950591e+08 | BT8: 93222237 | BU8: 92494912 | BV8: 727324.44 | BW8: 36283678 | BX8: 35823677 | BY8: 460000.81 | BZ8: 29148031 | CA8: 22022499 | CB8: 21892072 | CC8: 130427 | CD8: 7125532 | CE8: 6940554 | CF8: 184978 | CG8: 16440975 | CH8: 12248717 | CI8: 12127453 | CJ8: 121263.5 | CK8: 4192258.5 | CL8: 4102687.2 | CM8: 89571.25 | CN8: 0 | CO8: 27113698 | CP8: 20985440 | CQ8: 9446442.4 | CR8: 1578653 | CS8: 0 | CT8: 33797.47 | CU8: 0 | CV8: 126050 | CW8: 115393 | CX8: 113123 | CY8: 2270 | CZ8: 10657 | DA8: 8252 | DB8: 2405 | DC8: 85256 | DD8: 1831 | DE8: 78948 | DF8: 77645 | DG8: 1303 | DH8: 6308 | DI8: 4920 | DJ8: 1388 | DK8: 37123 | DL8: 33257 | DM8: 32412 | DN8: 845 | DO8: 3866 | DP8: 3043 | DQ8: 823 | DR8: 1840 | DS8: 0 | DT8: 1410 | DU8: 1317 | DV8: 93 | DW8: 430 | DX8: 271 | DY8: 159 | DZ8: 0 | EA8: 0 | EB8: 0 | EC8: 0 | ED8: 0 | EE8: 0 | EF8: 0 | EG8: 4218 | EH8: 3172 | EI8: 3150 | EJ8: 22 | EK8: 1046 | EL8: 1019 | EM8: 27 | EN8: 3874 | EO8: 565 | EP8: 1811 | EQ8: 1498 | ER8: 0 | ES8: 0 | ET8: 0 | EU8: 1644 | EV8: 542 | EW8: 1102 | EX8: 0 | EY8: 117 | EZ8: 16 | FA8: 101 | FB8: 1465
A9: 6 | B9: 成人非手术 | C9: 血液内科 | D9: 8163579.5 | E9: 1021827 | F9: 7141752.5 | G9: 5232 | H9: 1510 | I9: 4854 | J9: 0 | K9: 0 | L9: 504941.5 | M9: 16679 | N9: 519.12 | O9: 32814894 | P9: 17176537 | Q9: 17051530 | R9: 125006.49 | S9: 15638357 | T9: 15423386 | U9: 214970.55 | V9: 4403328.8 | W9: 3738697 | X9: 3649773.2 | Y9: 88923.74 | Z9: 664631.79 | AA9: 537555.75 | AB9: 127076.04 | AC9: 3344118.6 | AD9: 2889817.7 | AE9: 2827674.9 | AF9: 62142.74 | AG9: 454300.89 | AH9: 369070.85 | AI9: 85230.04 | AJ9: 37383.2 | AK9: 33611.3 | AL9: 32191.3 | AM9: 1420 | AN9: 3771.9 | AO9: 2265.9 | AP9: 1506 | AQ9: 827095 | AR9: 658030 | AS9: 639795 | AT9: 18235 | AU9: 169065 | AV9: 137293 | AW9: 31772 | AX9: 194732 | AY9: 157238 | AZ9: 150112 | BA9: 7126 | BB9: 37494 | BC9: 28926 | BD9: 8568 | BE9: 28411565 | BF9: 13437840 | BG9: 13401757 | BH9: 36082.75 | BI9: 14973725 | BJ9: 14885830 | BK9: 87894.51 | BL9: 20277890 | BM9: 9616661.5 | BN9: 9594037.7 | BO9: 22623.81 | BP9: 10661229 | BQ9: 10612726 | BR9: 48502.99 | BS9: 991922.11 | BT9: 427532.38 | BU9: 424350.94 | BV9: 3181.44 | BW9: 564389.73 | BX9: 560309.21 | BY9: 4080.52 | BZ9: 4970472 | CA9: 2437537 | CB9: 2430934 | CC9: 6603 | CD9: 2532935 | CE9: 2504893 | CF9: 28042 | CG9: 2171280.5 | CH9: 956109 | CI9: 952434.5 | CJ9: 3674.5 | CK9: 1215171.5 | CL9: 1207902.5 | CM9: 7269 | CN9: -25 | CO9: 1328189 | CP9: 2412736.3 | CQ9: 570153.86 | CR9: 92249.57 | CS9: 0 | CT9: 0 | CU9: 0 | CV9: 5232 | CW9: 4168 | CX9: 4010 | CY9: 158 | CZ9: 1064 | DA9: 842 | DB9: 222 | DC9: 3279 | DD9: 0 | DE9: 2533 | DF9: 2453 | DG9: 80 | DH9: 746 | DI9: 596 | DJ9: 150 | DK9: 1870 | DL9: 1569 | DM9: 1498 | DN9: 71 | DO9: 301 | DP9: 235 | DQ9: 66 | DR9: 83 | DS9: 0 | DT9: 66 | DU9: 59 | DV9: 7 | DW9: 17 | DX9: 11 | DY9: 6 | DZ9: 0 | EA9: 0 | EB9: 0 | EC9: 0 | ED9: 0 | EE9: 0 | EF9: 0 | EG9: 1510 | EH9: 718 | EI9: 712 | EJ9: 6 | EK9: 792 | EL9: 786 | EM9: 6 | EN9: 1121 | EO9: 0 | EP9: 0 | EQ9: 1121 | ER9: 0 | ES9: 0 | ET9: 0 | EU9: 0 | EV9: 0 | EW9: 0 | EX9: 0 | EY9: 0 | EZ9: 0 | FA9: 0 | FB9: 135
A10: 7 | B10: 成人非手术 | C10: 肾脏风湿免疫科 | D10: 28820828 | E10: 21047852 | F10: 7772976.5 | G10: 30477 | H10: 883 | I10: 14232370 | J10: 0 | K10: 0 | L10: 569499 | M10: 130189 | N10: 0 | O10: 51713591 | P10: 45494905 | Q10: 44989059 | R10: 505846.34 | S10: 6218685.5 | T10: 5674489.4 | U10: 544196.14 | V10: 39573724 | W10: 36613734 | X10: 36209571 | Y10: 404163.57 | Z10: 2959989.4 | AA10: 2470678.4 | AB10: 489311.06 | AC10: 14854266 | AD10: 13644754 | AE10: 13477385 | AF10: 167369.18 | AG10: 1209511.5 | AH10: 966414.76 | AI10: 243096.7 | AJ10: 3671606 | AK10: 3503431 | AL10: 3483098.6 | AM10: 20332.39 | AN10: 168174.97 | AO10: 141207.61 | AP10: 26967.36 | AQ10: 5742410 | AR10: 5180313 | AS10: 5059192 | AT10: 121121 | AU10: 562097 | AV10: 438947 | AW10: 123150 | AX10: 15305442 | AY10: 14285236 | AZ10: 14189895 | BA10: 95341 | BB10: 1020206 | BC10: 924109 | BD10: 96097 | BE10: 12139867 | BF10: 8881170.8 | BG10: 8779488 | BH10: 101682.77 | BI10: 3258696.1 | BJ10: 3203811 | BK10: 54885.08 | BL10: 3514062.7 | BM10: 2525899.6 | BN10: 2512629.6 | BO10: 13270.02 | BP10: 988163.06 | BQ10: 973986.51 | BR10: 14176.55 | BS10: 852827.69 | BT10: 655676.65 | BU10: 650638.9 | BV10: 5037.75 | BW10: 197151.04 | BX10: 196679.01 | BY10: 472.03 | BZ10: 5711181 | CA10: 4158695 | CB10: 4095645 | CC10: 63050 | CD10: 1552486 | CE10: 1517280 | CF10: 35206 | CG10: 2061795.5 | CH10: 1540899.5 | CI10: 1520574.5 | CJ10: 20325 | CK10: 520896 | CL10: 515865.5 | CM10: 5030.5 | CN10: -19 | CO10: 5504999.3 | CP10: 5896184.6 | CQ10: 27598811 | CR10: 573722.82 | CS10: 0 | CT10: 0 | CU10: 0 | CV10: 30477 | CW10: 27278 | CX10: 26547 | CY10: 731 | CZ10: 3199 | DA10: 2320 | DB10: 879 | DC10: 22356 | DD10: 416 | DE10: 20175 | DF10: 19640 | DG10: 535 | DH10: 2181 | DI10: 1587 | DJ10: 594 | DK10: 7178 | DL10: 6324 | DM10: 6159 | DN10: 165 | DO10: 854 | DP10: 646 | DQ10: 208 | DR10: 527 | DS10: 0 | DT10: 397 | DU10: 376 | DV10: 21 | DW10: 130 | DX10: 84 | DY10: 46 | DZ10: 0 | EA10: 0 | EB10: 0 | EC10: 0 | ED10: 0 | EE10: 0 | EF10: 0 | EG10: 883 | EH10: 650 | EI10: 642 | EJ10: 8 | EK10: 233 | EL10: 227 | EM10: 6 | EN10: 251 | EO10: 53 | EP10: 0 | EQ10: 198 | ER10: 0 | ES10: 0 | ET10: 0 | EU10: 1 | EV10: 1 | EW10: 0 | EX10: 0 | EY10: 0 | EZ10: 0 | FA10: 0 | FB10: 550
A11: 8 | B11: 成人非手术 | C11: 内分泌科 | D11: 20541900 | E11: 13545395 | F11: 6996505 | G11: 64483 | H11: 739 | I11: 18760 | J11: 1826 | K11: 0 | L11: 715875.5 | M11: 14676 | N11: 0 | O11: 40546466 | P11: 36423905 | Q11: 35735915 | R11: 687989.62 | S11: 4122561.5 | T11: 3482123.6 | U11: 640437.82 | V11: 31657484 | W11: 29137979 | X11: 28494526 | Y11: 643453.02 | Z11: 2519505.2 | AA11: 1961170.9 | AB11: 558334.27 | AC11: 17786409 | AD11: 16496922 | AE11: 16237034 | AF11: 259887.82 | AG11: 1289487 | AH11: 1069211.9 | AI11: 220275.07 | AJ11: 325679.8 | AK11: 301369.6 | AL11: 296262.4 | AM11: 5107.2 | AN11: 24310.2 | AO11: 20099 | AP11: 4211.2 | AQ11: 11281881 | AR11: 10297399 | AS11: 9994582 | AT11: 302817 | AU11: 984482 | AV11: 716346 | AW11: 268136 | AX11: 2263514 | AY11: 2042288 | AZ11: 1966647 | BA11: 75641 | BB11: 221226 | BC11: 155514 | BD11: 65712 | BE11: 8888982.5 | BF11: 7285926.2 | BG11: 7241389.6 | BH11: 44536.6 | BI11: 1603056.3 | BJ11: 1520952.7 | BK11: 82103.55 | BL11: 1719534.1 | BM11: 1407482.8 | BN11: 1400146.7 | BO11: 7336.06 | BP11: 312051.34 | BQ11: 294087.28 | BR11: 17964.06 | BS11: 172943.4 | BT11: 140758.95 | BU11: 140083.91 | BV11: 675.04 | BW11: 32184.45 | BX11: 30903.96 | BY11: 1280.49 | BZ11: 5390280 | CA11: 4416042 | CB11: 4387273 | CC11: 28769 | CD11: 974238 | CE11: 924511 | CF11: 49727 | CG11: 1606225 | CH11: 1321642.5 | CI11: 1313886 | CJ11: 7756.5 | CK11: 284582.5 | CL11: 271450.5 | CM11: 13132 | CN11: 0 | CO11: 17233607 | CP11: 10367754 | CQ11: 2888791.7 | CR11: 1164829.1 | CS11: 2501.64 | CT11: 0 | CU11: 0 | CV11: 64483 | CW11: 58691 | CX11: 57054 | CY11: 1637 | CZ11: 5792 | DA11: 4277 | DB11: 1515 | DC11: 44073 | DD11: 716 | DE11: 40198 | DF11: 39179 | DG11: 1019 | DH11: 3875 | DI11: 2920 | DJ11: 955 | DK11: 18179 | DL11: 16505 | DM11: 15977 | DN11: 528 | DO11: 1674 | DP11: 1227 | DQ11: 447 | DR11: 1508 | DS11: 7 | DT11: 1293 | DU11: 1217 | DV11: 76 | DW11: 215 | DX11: 128 | DY11: 87 | DZ11: 0 | EA11: 0 | EB11: 0 | EC11: 0 | ED11: 0 | EE11: 0 | EF11: 0 | EG11: 739 | EH11: 611 | EI11: 600 | EJ11: 11 | EK11: 128 | EL11: 117 | EM11: 11 | EN11: 4 | EO11: 0 | EP11: 0 | EQ11: 4 | ER11: 0 | ES11: 0 | ET11: 0 | EU11: 0 | EV11: 0 | EW11: 0 | EX11: 0 | EY11: 0 | EZ11: 0 | FA11: 0 | FB11: 691
A12: 9 | B12: 成人非手术 | C12: 老年医学科 | D12: 16586560 | E12: 876068.5 | F12: 15710492 | G12: 8416 | H12: 255 | I12: 31245 | J12: 0 | K12: 219497.17 | L12: 3131099.5 | M12: 86749.5 | N12: 30719.06 | O12: 30266245 | P12: 30172401 | Q12: 30150084 | R12: 22316.97 | S12: 93844.41 | T12: 58390.27 | U12: 35454.14 | V12: 5847525.3 | W12: 5753680.8 | X12: 5731363.9 | Y12: 22316.97 | Z12: 93844.41 | AA12: 58390.27 | AB12: 35454.14 | AC12: 4952486 | AD12: 4879423.6 | AE12: 4864413.6 | AF12: 15009.97 | AG12: 73062.41 | AH12: 45545.27 | AI12: 27517.14 | AJ12: 18970.75 | AK12: 18661.75 | AL12: 18661.75 | AM12: 0 | AN12: 309 | AO12: 264 | AP12: 45 | AQ12: 623555 | AR12: 608873 | AS12: 602672 | AT12: 6201 | AU12: 14682 | AV12: 9649 | AW12: 5033 | AX12: 252513.5 | AY12: 246722.5 | AZ12: 245616.5 | BA12: 1106 | BB12: 5791 | BC12: 2932 | BD12: 2859 | BE12: 24418720 | BF12: 24418720 | BG12: 24418720 | BH12: 0 | BI12: 0 | BJ12: 0 | BK12: 0 | BL12: 7960294.8 | BM12: 7960294.8 | BN12: 7960294.8 | BO12: 0 | BP12: 0 | BQ12: 0 | BR12: 0 | BS12: 747933.39 | BT12: 747933.39 | BU12: 747933.39 | BV12: 0 | BW12: 0 | BX12: 0 | BY12: 0 | BZ12: 7031039.5 | CA12: 7031039.5 | CB12: 7031039.5 | CC12: 0 | CD12: 0 | CE12: 0 | CF12: 0 | CG12: 8679452.5 | CH12: 8679452.5 | CI12: 8679452.5 | CJ12: 0 | CK12: 0 | CL12: 0 | CM12: 0 | CN12: 0 | CO12: 5815726.3 | CP12: 0 | CQ12: 250 | CR12: 31549 | CS12: 0 | CT12: 0 | CU12: 0 | CV12: 8416 | CW12: 8278 | CX12: 8252 | CY12: 26 | CZ12: 138 | DA12: 107 | DB12: 31 | DC12: 8394 | DD12: 0 | DE12: 8274 | DF12: 8252 | DG12: 22 | DH12: 120 | DI12: 107 | DJ12: 13 | DK12: 0 | DL12: 0 | DM12: 0 | DN12: 0 | DO12: 0 | DP12: 0 | DQ12: 0 | DR12: 22 | DS12: 0 | DT12: 4 | DU12: 0 | DV12: 4 | DW12: 18 | DX12: 0 | DY12: 18 | DZ12: 0 | EA12: 0 | EB12: 0 | EC12: 0 | ED12: 0 | EE12: 0 | EF12: 0 | EG12: 255 | EH12: 255 | EI12: 255 | EJ12: 0 | EK12: 0 | EL12: 0 | EM12: 0 | EN12: 137 | EO12: 0 | EP12: 0 | EQ12: 137 | ER12: 0 | ES12: 0 | ET12: 0 | EU12: 0 | EV12: 0 | EW12: 0 | EX12: 0 | EY12: 0 | EZ12: 0 | FA12: 0 | FB12: 0
A13: 10 | B13: 成人非手术 | C13: 全科医学科 | D13: 6843466.5 | E13: 2021566 | F13: 4821900.5 | G13: 12030 | H13: 250 | I13: 448 | J13: 0 | K13: 0 | L13: 221414 | M13: 114471.05 | N13: 0 | O13: 10986827 | P13: 8795271.7 | Q13: 8538226 | R13: 257045.71 | S13: 2191555.5 | T13: 1934649.7 | U13: 256905.79 | V13: 4986533.8 | W13: 4560422.9 | X13: 4488709.9 | Y13: 71713.02 | Z13: 426110.88 | AA13: 345028.87 | AB13: 81082.01 | AC13: 2960366.4 | AD13: 2781001.5 | AE13: 2757612.5 | AF13: 23389.02 | AG13: 179364.88 | AH13: 159783.87 | AI13: 19581.01 | AJ13: 4601.4 | AK13: 3878.4 | AL13: 3833.4 | AM13: 45 | AN13: 723 | AO13: 556 | AP13: 167 | AQ13: 1699643 | AR13: 1482454 | AS13: 1439733 | AT13: 42721 | AU13: 217189 | AV13: 161674 | AW13: 55515 | AX13: 321923 | AY13: 293089 | AZ13: 287531 | BA13: 5558 | BB13: 28834 | BC13: 23015 | BD13: 5819 | BE13: 6000293.4 | BF13: 4234848.8 | BG13: 4049516.1 | BH13: 185332.69 | BI13: 1765444.6 | BJ13: 1589620.8 | BK13: 175823.78 | BL13: 873841.39 | BM13: 664365.71 | BN13: 643158.52 | BO13: 21207.19 | BP13: 209475.68 | BQ13: 188085.83 | BR13: 21389.85 | BS13: 304551.45 | BT13: 183652.36 | BU13: 180936.86 | BV13: 2715.5 | BW13: 120899.09 | BX13: 116578.16 | BY13: 4320.93 | BZ13: 2104596 | CA13: 1404548 | CB13: 1369594 | CC13: 34954 | CD13: 700048 | CE13: 633551 | CF13: 66497 | CG13: 2717304.5 | CH13: 1982282.7 | CI13: 1855826.7 | CJ13: 126456 | CK13: 735021.85 | CL13: 651405.85 | CM13: 83616 | CN13: 0 | CO13: 4316780.4 | CP13: 573655.76 | CQ13: 16111.97 | CR13: 79985.65 | CS13: 0 | CT13: 0 | CU13: 0 | CV13: 12030 | CW13: 11023 | CX13: 10819 | CY13: 204 | CZ13: 1007 | DA13: 804 | DB13: 203 | DC13: 10901 | DD13: 207 | DE13: 10042 | DF13: 9886 | DG13: 156 | DH13: 859 | DI13: 696 | DJ13: 163 | DK13: 837 | DL13: 715 | DM13: 693 | DN13: 22 | DO13: 122 | DP13: 92 | DQ13: 30 | DR13: 85 | DS13: 0 | DT13: 70 | DU13: 68 | DV13: 2 | DW13: 15 | DX13: 12 | DY13: 3 | DZ13: 0 | EA13: 0 | EB13: 0 | EC13: 0 | ED13: 0 | EE13: 0 | EF13: 0 | EG13: 250 | EH13: 167 | EI13: 155 | EJ13: 12 | EK13: 83 | EL13: 75 | EM13: 8 | EN13: 21 | EO13: 0 | EP13: 0 | EQ13: 21 | ER13: 0 | ES13: 0 | ET13: 0 | EU13: 0 | EV13: 0 | EW13: 0 | EX13: 0 | EY13: 0 | EZ13: 0 | FA13: 0 | FB13: 0
A14: 11 | B14: 成人手术 | C14: 普外科 | D14: 51271002 | E14: 9090319.5 | F14: 42180682 | G14: 41162 | H14: 4048 | I14: 633054.5 | J14: 481458 | K14: 253.5 | L14: 2404758.2 | M14: 11360646 | N14: 11618.15 | O14: 1.1310343e+08 | P14: 77979187 | Q14: 76433636 | R14: 1545551.3 | S14: 35124238 | T14: 33514797 | U14: 1609440.9 | V14: 16070931 | W14: 13405978 | X14: 12875910 | Y14: 530067.99 | Z14: 2664953.3 | AA14: 2048438.2 | AB14: 616515.08 | AC14: 5001681.4 | AD14: 4139600.7 | AE14: 4030793.7 | AF14: 108807 | AG14: 862080.72 | AH14: 740437.9 | AI14: 121642.82 | AJ14: 1978930.5 | AK14: 1777566 | AL14: 1720981 | AM14: 56584.99 | AN14: 201364.54 | AO14: 170022.28 | AP14: 31342.26 | AQ14: 6431501 | AR14: 5236419 | AS14: 5008437 | AT14: 227982 | AU14: 1195082 | AV14: 859698 | AW14: 335384 | AX14: 2658818.5 | AY14: 2252392.5 | AZ14: 2115698.5 | BA14: 136694 | BB14: 406426 | BC14: 278280 | BD14: 128146 | BE14: 97032494 | BF14: 64573209 | BG14: 63557726 | BH14: 1015483.3 | BI14: 32459285 | BJ14: 31466359 | BK14: 992925.84 | BL14: 17858025 | BM14: 11586074 | BN14: 11415912 | BO14: 170162.07 | BP14: 6271950.6 | BQ14: 6117553.7 | BR14: 154396.86 | BS14: 36993788 | BT14: 25001695 | BU14: 24675532 | BV14: 326162.74 | BW14: 11992093 | BX14: 11663722 | BY14: 328370.23 | BZ14: 16133649 | CA14: 10125076 | CB14: 9987979 | CC14: 137097 | CD14: 6008573 | CE14: 5833129 | CF14: 175444 | CG14: 26047033 | CH14: 17860364 | CI14: 17478303 | CJ14: 382061.5 | CK14: 8186668.8 | CL14: 7851954.1 | CM14: 334714.75 | CN14: 4316718.9 | CO14: 5223316.1 | CP14: 3888243.2 | CQ14: 2209559.5 | CR14: 429611.17 | CS14: 3432.59 | CT14: 710500.76 | CU14: 0 | CV14: 41162 | CW14: 34726 | CX14: 33026 | CY14: 1700 | CZ14: 6436 | DA14: 4533 | DB14: 1903 | DC14: 20583 | DD14: 104 | DE14: 17784 | DF14: 16854 | DG14: 930 | DH14: 2799 | DI14: 1924 | DJ14: 875 | DK14: 10436 | DL14: 8518 | DM14: 8163 | DN14: 355 | DO14: 1918 | DP14: 1366 | DQ14: 552 | DR14: 578 | DS14: 0 | DT14: 376 | DU14: 338 | DV14: 38 | DW14: 202 | DX14: 133 | DY14: 69 | DZ14: 9461 | EA14: 7954 | EB14: 7582 | EC14: 372 | ED14: 1507 | EE14: 1109 | EF14: 398 | EG14: 4048 | EH14: 2876 | EI14: 2827 | EJ14: 49 | EK14: 1172 | EL14: 1122 | EM14: 50 | EN14: 3601 | EO14: 2698 | EP14: 0 | EQ14: 903 | ER14: 1362 | ES14: 0 | ET14: 4 | EU14: 1046 | EV14: 818 | EW14: 0 | EX14: 228 | EY14: 673 | EZ14: 673 | FA14: 0 | FB14: 1624
A15: 12 | B15: 成人手术 | C15: 神经外科 | D15: 32606569 | E15: 2433465 | F15: 30173104 | G15: 10896 | H15: 2027 | I15: 2804 | J15: 126 | K15: 0 | L15: 1985667.5 | M15: 8086009.5 | N15: 0 | O15: 1.2594242e+08 | P15: 72486651 | Q15: 70666157 | R15: 1820494 | S15: 53455768 | T15: 50444499 | U15: 3011269.1 | V15: 3574320.6 | W15: 2798207.6 | X15: 2600589.1 | Y15: 197618.5 | Z15: 776112.97 | AA15: 448826.73 | AB15: 327286.24 | AC15: 1107310.6 | AD15: 918471.65 | AE15: 878689.15 | AF15: 39782.5 | AG15: 188838.97 | AH15: 131794.73 | AI15: 57044.24 | AJ15: 33545 | AK15: 26837 | AL15: 25375 | AM15: 1462 | AN15: 6708 | AO15: 3612 | AP15: 3096 | AQ15: 2010834 | AR15: 1569260 | AS15: 1439381 | AT15: 129879 | AU15: 441574 | AV15: 237725 | AW15: 203849 | AX15: 422631 | AY15: 283639 | AZ15: 257144 | BA15: 26495 | BB15: 138992 | BC15: 75695 | BD15: 63297 | BE15: 1.223681e+08 | BF15: 69688443 | BG15: 68065567 | BH15: 1622875.5 | BI15: 52679655 | BJ15: 49995672 | BK15: 2683982.8 | BL15: 13438815 | BM15: 7284582.8 | BN15: 7037636.4 | BO15: 246946.34 | BP15: 6154232.1 | BQ15: 5734524.5 | BR15: 419707.54 | BS15: 78756179 | BT15: 46867923 | BU15: 46033672 | BV15: 834250.93 | BW15: 31888256 | BX15: 30569059 | BY15: 1319196.8 | BZ15: 11686686 | CA15: 6127159 | CB15: 5960479 | CC15: 166680 | CD15: 5559527 | CE15: 5268061 | CF15: 291466 | CG15: 18486418 | CH15: 9408778.3 | CI15: 9033780.1 | CJ15: 374998.25 | CK15: 9077640.1 | CL15: 8424027.6 | CM15: 653612.5 | CN15: -25 | CO15: 1976260.4 | CP15: 1281009.6 | CQ15: 203055.89 | CR15: 113994.7 | CS15: 0 | CT15: 1075862 | CU15: 0 | CV15: 10896 | CW15: 8266 | CX15: 7547 | CY15: 719 | CZ15: 2630 | DA15: 1508 | DB15: 1122 | DC15: 6281 | DD15: 72 | DE15: 5156 | DF15: 4723 | DG15: 433 | DH15: 1125 | DI15: 659 | DJ15: 466 | DK15: 4317 | DL15: 2992 | DM15: 2720 | DN15: 272 | DO15: 1325 | DP15: 762 | DQ15: 563 | DR15: 226 | DS15: 0 | DT15: 54 | DU15: 45 | DV15: 9 | DW15: 172 | DX15: 86 | DY15: 86 | DZ15: 0 | EA15: 0 | EB15: 0 | EC15: 0 | ED15: 0 | EE15: 0 | EF15: 0 | EG15: 2027 | EH15: 1138 | EI15: 1090 | EJ15: 48 | EK15: 889 | EL15: 832 | EM15: 57 | EN15: 1759 | EO15: 826 | EP15: 499 | EQ15: 434 | ER15: 375 | ES15: 0 | ET15: 0 | EU15: 317 | EV15: 223 | EW15: 21 | EX15: 73 | EY15: 955 | EZ15: 477 | FA15: 478 | FB15: 805
... A57: 54 | B57: 医技平台 | C57: 健康管理中心 | D57: 18148596 | E57: 18148596 | F57: 0 | G57: 2734 | H57: 0 | I57: 0 | J57: 0 | K57: 0 | L57: 0 | M57: 0 | N57: 0 | O57: 18148739 | P57: 2312690.6 | Q57: 143.46 | R57: 2312547.1 | S57: 15836049 | T57: 0 | U57: 15836049 | V57: 18148739 | W57: 2312690.6 | X57: 143.46 | Y57: 2312547.1 | Z57: 15836049 | AA57: 0 | AB57: 15836049 | AC57: 143.46 | AD57: 143.46 | AE57: 143.46 | AF57: 0 | AG57: 0 | AH57: 0 | AI57: 0 | AJ57: 0 | AK57: 0 | AL57: 0 | AM57: 0 | AN57: 0 | AO57: 0 | AP57: 0 | AQ57: 120 | AR57: 0 | AS57: 0 | AT57: 0 | AU57: 120 | AV57: 0 | AW57: 120 | AX57: 18148476 | AY57: 2312547.1 | AZ57: 0 | BA57: 2312547.1 | BB57: 15835929 | BC57: 0 | BD57: 15835929 | BE57: 0 | BF57: 0 | BG57: 0 | BH57: 0 | BI57: 0 | BJ57: 0 | BK57: 0 | BL57: 0 | BM57: 0 | BN57: 0 | BO57: 0 | BP57: 0 | BQ57: 0 | BR57: 0 | BS57: 0 | BT57: 0 | BU57: 0 | BV57: 0 | BW57: 0 | BX57: 0 | BY57: 0 | BZ57: 0 | CA57: 0 | CB57: 0 | CC57: 0 | CD57: 0 | CE57: 0 | CF57: 0 | CG57: 0 | CH57: 0 | CI57: 0 | CJ57: 0 | CK57: 0 | CL57: 0 | CM57: 0 | CN57: 0 | CO57: 18148739 | CP57: 0 | CQ57: 0 | CR57: 0 | CS57: 0 | CT57: 0 | CU57: 0 | CV57: 2734 | CW57: 1011 | CX57: 0 | CY57: 1011 | CZ57: 1723 | DA57: 0 | DB57: 1723 | DC57: 2734 | DD57: 0 | DE57: 1011 | DF57: 0 | DG57: 1011 | DH57: 1723 | DI57: 0 | DJ57: 1723 | DK57: 0 | DL57: 0 | DM57: 0 | DN57: 0 | DO57: 0 | DP57: 0 | DQ57: 0 | DR57: 0 | DS57: 0 | DT57: 0 | DU57: 0 | DV57: 0 | DW57: 0 | DX57: 0 | DY57: 0 | DZ57: 0 | EA57: 0 | EB57: 0 | EC57: 0 | ED57: 0 | EE57: 0 | EF57: 0 | EG57: 0 | EH57: 0 | EI57: 0 | EJ57: 0 | EK57: 0 | EL57: 0 | EM57: 0 | EN57: 0 | EO57: 0 | EP57: 0 | EQ57: 0 | ER57: 0 | ES57: 0 | ET57: 0 | EU57: 0 | EV57: 0 | EW57: 0 | EX57: 0 | EY57: 0 | EZ57: 0 | FA57: 0 | FB57: 0
A58: 55 | C58: 镜朗特需与国际医疗部 | D58: 27848 | E58: 0 | F58: 27848 | G58: 0 | H58: 2 | I58: 0 | J58: 0 | K58: 0 | L58: 952 | M58: 0 | N58: 0 | O58: 31162.07 | P58: 31162.07 | Q58: 0 | R58: 31162.07 | S58: 0 | T58: 0 | U58: 0 | V58: 0 | W58: 0 | X58: 0 | Y58: 0 | Z58: 0 | AA58: 0 | AB58: 0 | AC58: 0 | AD58: 0 | AE58: 0 | AF58: 0 | AG58: 0 | AH58: 0 | AI58: 0 | AJ58: 0 | AK58: 0 | AL58: 0 | AM58: 0 | AN58: 0 | AO58: 0 | AP58: 0 | AQ58: 0 | AR58: 0 | AS58: 0 | AT58: 0 | AU58: 0 | AV58: 0 | AW58: 0 | AX58: 0 | AY58: 0 | AZ58: 0 | BA58: 0 | BB58: 0 | BC58: 0 | BD58: 0 | BE58: 31162.07 | BF58: 31162.07 | BG58: 0 | BH58: 31162.07 | BI58: 0 | BJ58: 0 | BK58: 0 | BL58: 1587.89 | BM58: 1587.89 | BN58: 0 | BO58: 1587.89 | BP58: 0 | BQ58: 0 | BR58: 0 | BS58: 1726.18 | BT58: 1726.18 | BU58: 0 | BV58: 1726.18 | BW58: 0 | BX58: 0 | BY58: 0 | BZ58: 8872 | CA58: 8872 | CB58: 0 | CC58: 8872 | CD58: 0 | CE58: 0 | CF58: 0 | CG58: 18976 | CH58: 18976 | CI58: 0 | CJ58: 18976 | CK58: 0 | CL58: 0 | CM58: 0 | CN58: 0 | CO58: 0 | CP58: 0 | CQ58: 0 | CR58: 0 | CS58: 0 | CT58: 31162.07 | CU58: 0 | CV58: 0 | CW58: 0 | CX58: 0 | CY58: 0 | CZ58: 0 | DA58: 0 | DB58: 0 | DC58: 0 | DD58: 0 | DE58: 0 | DF58: 0 | DG58: 0 | DH58: 0 | DI58: 0 | DJ58: 0 | DK58: 0 | DL58: 0 | DM58: 0 | DN58: 0 | DO58: 0 | DP58: 0 | DQ58: 0 | DR58: 0 | DS58: 0 | DT58: 0 | DU58: 0 | DV58: 0 | DW58: 0 | DX58: 0 | DY58: 0 | DZ58: 0 | EA58: 0 | EB58: 0 | EC58: 0 | ED58: 0 | EE58: 0 | EF58: 0 | EG58: 2 | EH58: 2 | EI58: 0 | EJ58: 2 | EK58: 0 | EL58: 0 | EM58: 0 | EN58: 0 | EO58: 0 | EP58: 0 | EQ58: 0 | ER58: 0 | ES58: 0 | ET58: 0 | EU58: 0 | EV58: 0 | EW58: 0 | EX58: 0 | EY58: 0 | EZ58: 0 | FA58: 0 | FB58: 0
A59: 56 | B59: 成人非手术 | C59: 感染科 | D59: 2437082.5 | E59: 1129853 | F59: 1307229.5 | G59: 3991 | H59: 126 | I59: 18788 | J59: 0 | K59: 0 | L59: 79477.5 | M59: 4959 | N59: 105 | O59: 3883855.2 | P59: 3283055.3 | Q59: 3246834.4 | R59: 36220.88 | S59: 600799.99 | T59: 543762.67 | U59: 57037.32 | V59: 1782299.1 | W59: 1640184.4 | X59: 1603963.5 | Y59: 36220.88 | Z59: 142114.67 | AA59: 85077.35 | AB59: 57037.32 | AC59: 620324.3 | AD59: 576583.87 | AE59: 566807 | AF59: 9776.87 | AG59: 43740.43 | AH59: 28451.09 | AI59: 15289.34 | AJ59: 32121.76 | AK59: 29329.52 | AL59: 28898.51 | AM59: 431.01 | AN59: 2792.24 | AO59: 1956.26 | AP59: 835.98 | AQ59: 995395 | AR59: 912067 | AS59: 889004 | AT59: 23063 | AU59: 83328 | AV59: 46901 | AW59: 36427 | AX59: 134458 | AY59: 122204 | AZ59: 119254 | BA59: 2950 | BB59: 12254 | BC59: 7769 | BD59: 4485 | BE59: 2101556.2 | BF59: 1642870.9 | BG59: 1642870.9 | BH59: 0 | BI59: 458685.32 | BJ59: 458685.32 | BK59: 0 | BL59: 692079.23 | BM59: 528162.02 | BN59: 528162.02 | BO59: 0 | BP59: 163917.21 | BQ59: 163917.21 | BR59: 0 | BS59: 102247.46 | BT59: 80103.35 | BU59: 80103.35 | BV59: 0 | BW59: 22144.11 | BX59: 22144.11 | BY59: 0 | BZ59: 1015644 | CA59: 799978 | CB59: 799978 | CC59: 0 | CD59: 215666 | CE59: 215666 | CF59: 0 | CG59: 291585.5 | CH59: 234627.5 | CI59: 234627.5 | CJ59: 0 | CK59: 56958 | CL59: 56958 | CM59: 0 | CN59: 1463771.1 | CO59: 0 | CP59: 39234.73 | CQ59: 279293.23 | CR59: 0 | CS59: 0 | CT59: 0 | CU59: 0 | CV59: 3991 | CW59: 3631 | CX59: 3535 | CY59: 96 | CZ59: 360 | DA59: 223 | DB59: 137 | DC59: 724 | DD59: 0 | DE59: 648 | DF59: 619 | DG59: 29 | DH59: 76 | DI59: 44 | DJ59: 32 | DK59: 120 | DL59: 98 | DM59: 92 | DN59: 6 | DO59: 22 | DP59: 16 | DQ59: 6 | DR59: 0 | DS59: 0 | DT59: 0 | DU59: 0 | DV59: 0 | DW59: 0 | DX59: 0 | DY59: 0 | DZ59: 3147 | EA59: 2885 | EB59: 2824 | EC59: 61 | ED59: 262 | EE59: 163 | EF59: 99 | EG59: 126 | EH59: 105 | EI59: 105 | EJ59: 0 | EK59: 21 | EL59: 21 | EM59: 0 | EN59: 3 | EO59: 0 | EP59: 0 | EQ59: 3 | ER59: 0 | ES59: 0 | ET59: 0 | EU59: 0 | EV59: 0 | EW59: 0 | EX59: 0 | EY59: 0 | EZ59: 0 | FA59: 0 | FB59: 20
A60: 57 | B60: 其他 | C60: 新冠核酸检测 | D60: 673 | E60: 673 | F60: 0 | G60: 0 | H60: 0 | I60: 0 | J60: 0 | K60: 0 | L60: 0 | M60: 0 | N60: 0 | O60: 743.96 | P60: 727.96 | Q60: 711.96 | R60: 16 | S60: 16 | T60: 16 | U60: 0 | V60: 743.96 | W60: 727.96 | X60: 711.96 | Y60: 16 | Z60: 16 | AA60: 16 | AB60: 0 | AC60: 70.96 | AD60: 70.96 | AE60: 70.96 | AF60: 0 | AG60: 0 | AH60: 0 | AI60: 0 | AJ60: 0 | AK60: 0 | AL60: 0 | AM60: 0 | AN60: 0 | AO60: 0 | AP60: 0 | AQ60: 673 | AR60: 657 | AS60: 641 | AT60: 16 | AU60: 16 | AV60: 16 | AW60: 0 | AX60: 0 | AY60: 0 | AZ60: 0 | BA60: 0 | BB60: 0 | BC60: 0 | BD60: 0 | BE60: 0 | BF60: 0 | BG60: 0 | BH60: 0 | BI60: 0 | BJ60: 0 | BK60: 0 | BL60: 0 | BM60: 0 | BN60: 0 | BO60: 0 | BP60: 0 | BQ60: 0 | BR60: 0 | BS60: 0 | BT60: 0 | BU60: 0 | BV60: 0 | BW60: 0 | BX60: 0 | BY60: 0 | BZ60: 0 | CA60: 0 | CB60: 0 | CC60: 0 | CD60: 0 | CE60: 0 | CF60: 0 | CG60: 0 | CH60: 0 | CI60: 0 | CJ60: 0 | CK60: 0 | CL60: 0 | CM60: 0 | CN60: 0 | CO60: 743.96 | CP60: 0 | CQ60: 0 | CR60: 0 | CS60: 0 | CT60: 0 | CU60: 0 | CV60: 0 | CW60: 0 | CX60: 0 | CY60: 0 | CZ60: 0 | DA60: 0 | DB60: 0 | DC60: 0 | DD60: 0 | DE60: 0 | DF60: 0 | DG60: 0 | DH60: 0 | DI60: 0 | DJ60: 0 | DK60: 0 | DL60: 0 | DM60: 0 | DN60: 0 | DO60: 0 | DP60: 0 | DQ60: 0 | DR60: 0 | DS60: 0 | DT60: 0 | DU60: 0 | DV60: 0 | DW60: 0 | DX60: 0 | DY60: 0 | DZ60: 0 | EA60: 0 | EB60: 0 | EC60: 0 | ED60: 0 | EE60: 0 | EF60: 0 | EG60: 0 | EH60: 0 | EI60: 0 | EJ60: 0 | EK60: 0 | EL60: 0 | EM60: 0 | EN60: 0 | EO60: 0 | EP60: 0 | EQ60: 0 | ER60: 0 | ES60: 0 | ET60: 0 | EU60: 0 | EV60: 0 | EW60: 0 | EX60: 0 | EY60: 0 | EZ60: 0 | FA60: 0 | FB60: 0
A61: 58 | B61: 成人手术 | C61: 胎儿医学与宫内儿科学诊治中心 | D61: 5198277.7 | E61: 4236787 | F61: 961490.65 | G61: 3382 | H61: 111 | I61: 1941 | J61: 241 | K61: 0 | L61: 147566 | M61: 118426 | N61: 3517.3 | O61: 5679626.9 | P61: 1993093.8 | Q61: 644276.72 | R61: 1348817.1 | S61: 3686533 | T61: 796117.31 | U61: 2890415.7 | V61: 4298047.3 | W61: 1616562.4 | X61: 313070.76 | Y61: 1303491.6 | Z61: 2681484.9 | AA61: 26122.27 | AB61: 2655362.6 | AC61: 44439.43 | AD61: 35474.3 | AE61: 31957.18 | AF61: 3517.12 | AG61: 8965.13 | AH61: 3106.48 | AI61: 5858.65 | AJ61: 16820.87 | AK61: 5541.08 | AL61: 336.58 | AM61: 5204.5 | AN61: 11279.79 | AO61: 124.79 | AP61: 11155 | AQ61: 2995186 | AR61: 1181442 | AS61: 256678 | AT61: 924764 | AU61: 1813744 | AV61: 19972 | AW61: 1793772 | AX61: 1241601 | AY61: 394105 | AZ61: 24099 | BA61: 370006 | BB61: 847496 | BC61: 2919 | BD61: 844577 | BE61: 1381579.6 | BF61: 376531.45 | BG61: 331205.96 | BH61: 45325.49 | BI61: 1005048.1 | BJ61: 769995.04 | BK61: 235053.08 | BL61: 282093.99 | BM61: 128141.07 | BN61: 108147.71 | BO61: 19993.36 | BP61: 153952.92 | BQ61: 114342.72 | BR61: 39610.2 | BS61: 137994.93 | BT61: 33819.88 | BU61: 30026.55 | BV61: 3793.33 | BW61: 104175.05 | BX61: 76864.07 | BY61: 27310.98 | BZ61: 446690.25 | CA61: 96063.5 | CB61: 93180 | CC61: 2883.5 | CD61: 350626.75 | CE61: 292879.25 | CF61: 57747.5 | CG61: 514800.4 | CH61: 118507 | CI61: 99851.7 | CJ61: 18655.3 | CK61: 396293.4 | CL61: 285909 | CM61: 110384.4 | CN61: 93389.94 | CO61: 593623.85 | CP61: 4218.27 | CQ61: 677752.63 | CR61: 2777040.1 | CS61: 152022.5 | CT61: 56972.79 | CU61: 0 | CV61: 3382 | CW61: 1881 | CX61: 860 | CY61: 1021 | CZ61: 1501 | DA61: 81 | DB61: 1420 | DC61: 1553 | DD61: 0 | DE61: 1167 | DF61: 788 | DG61: 379 | DH61: 386 | DI61: 69 | DJ61: 317 | DK61: 13 | DL61: 10 | DM61: 10 | DN61: 0 | DO61: 3 | DP61: 1 | DQ61: 2 | DR61: 1430 | DS61: 0 | DT61: 426 | DU61: 3 | DV61: 423 | DW61: 1004 | DX61: 1 | DY61: 1003 | DZ61: 386 | EA61: 278 | EB61: 59 | EC61: 219 | ED61: 108 | EE61: 10 | EF61: 98 | EG61: 111 | EH61: 30 | EI61: 28 | EJ61: 2 | EK61: 81 | EL61: 65 | EM61: 16 | EN61: 121 | EO61: 45 | EP61: 0 | EQ61: 76 | ER61: 2 | ES61: 0 | ET61: 0 | EU61: 19 | EV61: 4 | EW61: 0 | EX61: 15 | EY61: 0 | EZ61: 0 | FA61: 0 | FB61: 0
A62: 59 | B62: 医技平台 | C62: 麻醉科 | D62: 7191496 | E62: 7191496 | F62: 0 | G62: 11404 | H62: 0 | I62: 95656 | J62: 2451552 | K62: 0 | L62: 0 | M62: 0 | N62: 0 | O62: 10651560 | P62: 8779095.9 | Q62: 8115493.2 | R62: 663602.71 | S62: 1872464.1 | T62: 982043.57 | U62: 890420.58 | V62: 10651560 | W62: 8779095.9 | X62: 8115493.2 | Y62: 663602.71 | Z62: 1872464.1 | AA62: 982043.57 | AB62: 890420.58 | AC62: 895432.28 | AD62: 747163.55 | AE62: 717754.68 | AF62: 29408.87 | AG62: 148268.73 | AH62: 84962.01 | AI62: 63306.72 | AJ62: 2564631.8 | AK62: 2130081.4 | AL62: 2045553.5 | AM62: 84527.84 | AN62: 434550.42 | AO62: 247807.56 | AP62: 186742.86 | AQ62: 2905 | AR62: 2260 | AS62: 2190 | AT62: 70 | AU62: 645 | AV62: 505 | AW62: 140 | AX62: 7188591 | AY62: 5899591 | AZ62: 5349995 | BA62: 549596 | BB62: 1289000 | BC62: 648769 | BD62: 640231 | BE62: 0 | BF62: 0 | BG62: 0 | BH62: 0 | BI62: 0 | BJ62: 0 | BK62: 0 | BL62: 0 | BM62: 0 | BN62: 0 | BO62: 0 | BP62: 0 | BQ62: 0 | BR62: 0 | BS62: 0 | BT62: 0 | BU62: 0 | BV62: 0 | BW62: 0 | BX62: 0 | BY62: 0 | BZ62: 0 | CA62: 0 | CB62: 0 | CC62: 0 | CD62: 0 | CE62: 0 | CF62: 0 | CG62: 0 | CH62: 0 | CI62: 0 | CJ62: 0 | CK62: 0 | CL62: 0 | CM62: 0 | CN62: -25 | CO62: 330 | CP62: 0 | CQ62: 8446424.3 | CR62: 2204714 | CS62: 91.8 | CT62: 0 | CU62: 0 | CV62: 11404 | CW62: 9400 | CX62: 8454 | CY62: 946 | CZ62: 2004 | DA62: 1028 | DB62: 976 | DC62: 9285 | DD62: 0 | DE62: 7833 | DF62: 7535 | DG62: 298 | DH62: 1452 | DI62: 897 | DJ62: 555 | DK62: 0 | DL62: 0 | DM62: 0 | DN62: 0 | DO62: 0 | DP62: 0 | DQ62: 0 | DR62: 2119 | DS62: 0 | DT62: 1567 | DU62: 919 | DV62: 648 | DW62: 552 | DX62: 131 | DY62: 421 | DZ62: 0 | EA62: 0 | EB62: 0 | EC62: 0 | ED62: 0 | EE62: 0 | EF62: 0 | EG62: 0 | EH62: 0 | EI62: 0 | EJ62: 0 | EK62: 0 | EL62: 0 | EM62: 0 | EN62: 85 | EO62: 0 | EP62: 0 | EQ62: 85 | ER62: 0 | ES62: 0 | ET62: 0 | EU62: 0 | EV62: 0 | EW62: 0 | EX62: 0 | EY62: 0 | EZ62: 0 | FA62: 0 | FB62: 0
A63: 60 | B63: 成人非手术 | C63: 放疗科 | D63: 31987920 | E63: 18938320 | F63: 13049600 | G63: 5584 | H63: 1173 | I63: 17571950 | J63: 22 | K63: 0 | L63: 10352051 | M63: 8351 | N63: 13117.01 | O63: 45872986 | P63: 19240539 | Q63: 18928844 | R63: 311694.66 | S63: 26632447 | T63: 25587213 | U63: 1045234.6 | V63: 22216547 | W63: 12627363 | X63: 12331438 | Y63: 295925.22 | Z63: 9589184 | AA63: 8795027 | AB63: 794157.03 | AC63: 3218645.8 | AD63: 2187718 | AE63: 2150649.8 | AF63: 37068.22 | AG63: 1030927.8 | AH63: 896524.36 | AI63: 134403.42 | AJ63: 59581.56 | AK63: 13203.34 | AL63: 11999.34 | AM63: 1204 | AN63: 46378.22 | AO63: 38527.61 | AP63: 7850.61 | AQ63: 1170053 | AR63: 434830 | AS63: 408704 | AT63: 26126 | AU63: 735223 | AV63: 537272 | AW63: 197951 | AX63: 17768267 | AY63: 9991612 | AZ63: 9760085 | BA63: 231527 | BB63: 7776655 | BC63: 7322703 | BD63: 453952 | BE63: 23656439 | BF63: 6613175.7 | BG63: 6597406.3 | BH63: 15769.44 | BI63: 17043263 | BJ63: 16792186 | BK63: 251077.6 | BL63: 10093891 | BM63: 4399608.7 | BN63: 4392652.9 | BO63: 6955.83 | BP63: 5694281.8 | BQ63: 5670130.3 | BR63: 24151.5 | BS63: 512947.85 | BT63: 186153.02 | BU63: 185838.41 | BV63: 314.61 | BW63: 326794.83 | BX63: 322226.23 | BY63: 4568.6 | BZ63: 1692469 | CA63: 635954 | CB63: 628450 | CC63: 7504 | CD63: 1056515 | CE63: 1043366 | CF63: 13149 | CG63: 11357132 | CH63: 1391460 | CI63: 1390465 | CJ63: 995 | CK63: 9965671.5 | CL63: 9756463 | CM63: 209208.5 | CN63: 0 | CO63: 16753184 | CP63: 5359146.1 | CQ63: 0 | CR63: 104217.48 | CS63: 0 | CT63: 163707.13 | CU63: 0 | CV63: 5584 | CW63: 2431 | CX63: 2318 | CY63: 113 | CZ63: 3153 | DA63: 2501 | DB63: 652 | DC63: 3956 | DD63: 0 | DE63: 1605 | DF63: 1532 | DG63: 73 | DH63: 2351 | DI63: 1959 | DJ63: 392 | DK63: 1555 | DL63: 811 | DM63: 772 | DN63: 39 | DO63: 744 | DP63: 506 | DQ63: 238 | DR63: 73 | DS63: 0 | DT63: 15 | DU63: 14 | DV63: 1 | DW63: 58 | DX63: 36 | DY63: 22 | DZ63: 0 | EA63: 0 | EB63: 0 | EC63: 0 | ED63: 0 | EE63: 0 | EF63: 0 | EG63: 1173 | EH63: 393 | EI63: 392 | EJ63: 1 | EK63: 780 | EL63: 772 | EM63: 8 | EN63: 1208 | EO63: 0 | EP63: 0 | EQ63: 1208 | ER63: 0 | ES63: 0 | ET63: 0 | EU63: 0 | EV63: 0 | EW63: 0 | EX63: 0 | EY63: 0 | EZ63: 0 | FA63: 0 | FB63: 0
A64: 61 | B64: 其他 | C64: 特需门诊 | D64: -654 | E64: -654 | F64: 0 | G64: 0 | H64: 0 | I64: 6 | J64: 0 | K64: 0 | L64: 0 | M64: 0 | N64: 0 | O64: -654 | P64: -660 | Q64: -660 | R64: 0 | S64: 6 | T64: 6 | U64: 0 | V64: -654 | W64: -660 | X64: -660 | Y64: 0 | Z64: 6 | AA64: 6 | AB64: 0 | AC64: 0 | AD64: 0 | AE64: 0 | AF64: 0 | AG64: 0 | AH64: 0 | AI64: 0 | AJ64: 0 | AK64: 0 | AL64: 0 | AM64: 0 | AN64: 0 | AO64: 0 | AP64: 0 | AQ64: -660 | AR64: -660 | AS64: -660 | AT64: 0 | AU64: 0 | AV64: 0 | AW64: 0 | AX64: 6 | AY64: 0 | AZ64: 0 | BA64: 0 | BB64: 6 | BC64: 6 | BD64: 0 | BE64: 0 | BF64: 0 | BG64: 0 | BH64: 0 | BI64: 0 | BJ64: 0 | BK64: 0 | BL64: 0 | BM64: 0 | BN64: 0 | BO64: 0 | BP64: 0 | BQ64: 0 | BR64: 0 | BS64: 0 | BT64: 0 | BU64: 0 | BV64: 0 | BW64: 0 | BX64: 0 | BY64: 0 | BZ64: 0 | CA64: 0 | CB64: 0 | CC64: 0 | CD64: 0 | CE64: 0 | CF64: 0 | CG64: 0 | CH64: 0 | CI64: 0 | CJ64: 0 | CK64: 0 | CL64: 0 | CM64: 0 | CN64: 0 | CO64: 0 | CP64: 0 | CQ64: 0 | CR64: -654 | CS64: 0 | CT64: 0 | CU64: 0 | CV64: 0 | CW64: 0 | CX64: 0 | CY64: 0 | CZ64: 0 | DA64: 0 | DB64: 0 | DC64: 0 | DD64: 0 | DE64: 0 | DF64: 0 | DG64: 0 | DH64: 0 | DI64: 0 | DJ64: 0 | DK64: 0 | DL64: 0 | DM64: 0 | DN64: 0 | DO64: 0 | DP64: 0 | DQ64: 0 | DR64: 0 | DS64: 0 | DT64: 0 | DU64: 0 | DV64: 0 | DW64: 0 | DX64: 0 | DY64: 0 | DZ64: 0 | EA64: 0 | EB64: 0 | EC64: 0 | ED64: 0 | EE64: 0 | EF64: 0 | EG64: 0 | EH64: 0 | EI64: 0 | EJ64: 0 | EK64: 0 | EL64: 0 | EM64: 0 | EN64: 0 | EO64: 0 | EP64: 0 | EQ64: 0 | ER64: 0 | ES64: 0 | ET64: 0 | EU64: 0 | EV64: 0 | EW64: 0 | EX64: 0 | EY64: 0 | EZ64: 0 | FA64: 0 | FB64: 0
A65: 62 | B65: 医技平台 | C65: 病理科 | D65: 1305695 | E65: 1305695 | F65: 0 | G65: 1161 | H65: 0 | I65: 0 | J65: 0 | K65: 0 | L65: 0 | M65: 0 | N65: 0 | O65: 1305695 | P65: 941225 | Q65: 777165 | R65: 164060 | S65: 364470 | T65: 195468 | U65: 169002 | V65: 1305695 | W65: 941225 | X65: 777165 | Y65: 164060 | Z65: 364470 | AA65: 195468 | AB65: 169002 | AC65: 0 | AD65: 0 | AE65: 0 | AF65: 0 | AG65: 0 | AH65: 0 | AI65: 0 | AJ65: 0 | AK65: 0 | AL65: 0 | AM65: 0 | AN65: 0 | AO65: 0 | AP65: 0 | AQ65: 1265247 | AR65: 928425 | AS65: 771021 | AT65: 157404 | AU65: 336822 | AV65: 189324 | AW65: 147498 | AX65: 40448 | AY65: 12800 | AZ65: 6144 | BA65: 6656 | BB65: 27648 | BC65: 6144 | BD65: 21504 | BE65: 0 | BF65: 0 | BG65: 0 | BH65: 0 | BI65: 0 | BJ65: 0 | BK65: 0 | BL65: 0 | BM65: 0 | BN65: 0 | BO65: 0 | BP65: 0 | BQ65: 0 | BR65: 0 | BS65: 0 | BT65: 0 | BU65: 0 | BV65: 0 | BW65: 0 | BX65: 0 | BY65: 0 | BZ65: 0 | CA65: 0 | CB65: 0 | CC65: 0 | CD65: 0 | CE65: 0 | CF65: 0 | CG65: 0 | CH65: 0 | CI65: 0 | CJ65: 0 | CK65: 0 | CL65: 0 | CM65: 0 | CN65: 0 | CO65: 0 | CP65: 0 | CQ65: 1210852 | CR65: 94843 | CS65: 0 | CT65: 0 | CU65: 0 | CV65: 1161 | CW65: 744 | CX65: 624 | CY65: 120 | CZ65: 417 | DA65: 182 | DB65: 235 | DC65: 1003 | DD65: 0 | DE65: 694 | DF65: 600 | DG65: 94 | DH65: 309 | DI65: 158 | DJ65: 151 | DK65: 0 | DL65: 0 | DM65: 0 | DN65: 0 | DO65: 0 | DP65: 0 | DQ65: 0 | DR65: 158 | DS65: 0 | DT65: 50 | DU65: 24 | DV65: 26 | DW65: 108 | DX65: 24 | DY65: 84 | DZ65: 0 | EA65: 0 | EB65: 0 | EC65: 0 | ED65: 0 | EE65: 0 | EF65: 0 | EG65: 0 | EH65: 0 | EI65: 0 | EJ65: 0 | EK65: 0 | EL65: 0 | EM65: 0 | EN65: 1 | EO65: 0 | EP65: 0 | EQ65: 1 | ER65: 0 | ES65: 0 | ET65: 0 | EU65: 0 | EV65: 0 | EW65: 0 | EX65: 0 | EY65: 0 | EZ65: 0 | FA65: 0 | FB65: 0
A66: 63 | B66: 医技平台 | C66: 放射科 | D66: 1332417 | E66: 1332417 | F66: 0 | G66: 12359 | H66: 0 | I66: 318 | J66: 0 | K66: 0 | L66: 0 | M66: 0 | N66: 0 | O66: 1336711.1 | P66: 682163.97 | Q66: 488763.97 | R66: 193400 | S66: 654547.16 | T66: 178773 | U66: 475774.16 | V66: 1336711.1 | W66: 682163.97 | X66: 488763.97 | Y66: 193400 | Z66: 654547.16 | AA66: 178773 | AB66: 475774.16 | AC66: 2019.13 | AD66: 1281.97 | AE66: 1281.97 | AF66: 0 | AG66: 737.16 | AH66: 0 | AI66: 737.16 | AJ66: 2275 | AK66: 387 | AL66: 387 | AM66: 0 | AN66: 1888 | AO66: 1630 | AP66: 258 | AQ66: 623175 | AR66: 439067 | AS66: 322575 | AT66: 116492 | AU66: 184108 | AV66: 86127 | AW66: 97981 | AX66: 709242 | AY66: 241428 | AZ66: 164520 | BA66: 76908 | BB66: 467814 | BC66: 91016 | BD66: 376798 | BE66: 0 | BF66: 0 | BG66: 0 | BH66: 0 | BI66: 0 | BJ66: 0 | BK66: 0 | BL66: 0 | BM66: 0 | BN66: 0 | BO66: 0 | BP66: 0 | BQ66: 0 | BR66: 0 | BS66: 0 | BT66: 0 | BU66: 0 | BV66: 0 | BW66: 0 | BX66: 0 | BY66: 0 | BZ66: 0 | CA66: 0 | CB66: 0 | CC66: 0 | CD66: 0 | CE66: 0 | CF66: 0 | CG66: 0 | CH66: 0 | CI66: 0 | CJ66: 0 | CK66: 0 | CL66: 0 | CM66: 0 | CN66: 126 | CO66: 1102 | CP66: 606 | CQ66: 578780 | CR66: 756097.13 | CS66: 0 | CT66: 0 | CU66: 0 | CV66: 12359 | CW66: 8525 | CX66: 6698 | CY66: 1827 | CZ66: 3834 | DA66: 1622 | DB66: 2212 | DC66: 10588 | DD66: 121 | DE66: 7850 | DF66: 6204 | DG66: 1646 | DH66: 2738 | DI66: 1377 | DJ66: 1361 | DK66: 0 | DL66: 0 | DM66: 0 | DN66: 0 | DO66: 0 | DP66: 0 | DQ66: 0 | DR66: 1650 | DS66: 0 | DT66: 602 | DU66: 436 | DV66: 166 | DW66: 1048 | DX66: 241 | DY66: 807 | DZ66: 0 | EA66: 0 | EB66: 0 | EC66: 0 | ED66: 0 | EE66: 0 | EF66: 0 | EG66: 0 | EH66: 0 | EI66: 0 | EJ66: 0 | EK66: 0 | EL66: 0 | EM66: 0 | EN66: 32 | EO66: 0 | EP66: 0 | EQ66: 32 | ER66: 0 | ES66: 0 | ET66: 0 | EU66: 0 | EV66: 0 | EW66: 0 | EX66: 0 | EY66: 0 | EZ66: 0 | FA66: 0 | FB66: 0
A67: 64 | B67: 医技平台 | C67: 超声诊断科 | D67: 1023600 | E67: 1023600 | F67: 0 | G67: 6032 | H67: 0 | I67: 8450 | J67: 79604 | K67: 0 | L67: 0 | M67: 0 | N67: 0 | O67: 1302847.6 | P67: 1025245.4 | Q67: 924213.26 | R67: 101032.12 | S67: 277602.25 | T67: 174845.96 | U67: 102756.29 | V67: 1302847.6 | W67: 1025245.4 | X67: 924213.26 | Y67: 101032.12 | Z67: 277602.25 | AA67: 174845.96 | AB67: 102756.29 | AC67: 195368.13 | AD67: 148752.98 | AE67: 138251.86 | AF67: 10501.12 | AG67: 46615.15 | AH67: 30456.86 | AI67: 16158.29 | AJ67: 83879.5 | AK67: 70114.4 | AL67: 65044.4 | AM67: 5070 | AN67: 13765.1 | AO67: 11045.1 | AP67: 2720 | AQ67: 595296 | AR67: 470515 | AS67: 440256 | AT67: 30259 | AU67: 124781 | AV67: 83201 | AW67: 41580 | AX67: 428304 | AY67: 335863 | AZ67: 280661 | BA67: 55202 | BB67: 92441 | BC67: 50143 | BD67: 42298 | BE67: 0 | BF67: 0 | BG67: 0 | BH67: 0 | BI67: 0 | BJ67: 0 | BK67: 0 | BL67: 0 | BM67: 0 | BN67: 0 | BO67: 0 | BP67: 0 | BQ67: 0 | BR67: 0 | BS67: 0 | BT67: 0 | BU67: 0 | BV67: 0 | BW67: 0 | BX67: 0 | BY67: 0 | BZ67: 0 | CA67: 0 | CB67: 0 | CC67: 0 | CD67: 0 | CE67: 0 | CF67: 0 | CG67: 0 | CH67: 0 | CI67: 0 | CJ67: 0 | CK67: 0 | CL67: 0 | CM67: 0 | CN67: -1420 | CO67: 667 | CP67: 86277.8 | CQ67: 551393.88 | CR67: 665928.95 | CS67: 0 | CT67: 0 | CU67: 0 | CV67: 6032 | CW67: 4844 | CX67: 4495 | CY67: 349 | CZ67: 1188 | DA67: 649 | DB67: 539 | DC67: 4893 | DD67: 43 | DE67: 3906 | DF67: 3680 | DG67: 226 | DH67: 987 | DI67: 552 | DJ67: 435 | DK67: 366 | DL67: 334 | DM67: 333 | DN67: 1 | DO67: 32 | DP67: 24 | DQ67: 8 | DR67: 730 | DS67: 0 | DT67: 569 | DU67: 448 | DV67: 121 | DW67: 161 | DX67: 73 | DY67: 88 | DZ67: 0 | EA67: 0 | EB67: 0 | EC67: 0 | ED67: 0 | EE67: 0 | EF67: 0 | EG67: 0 | EH67: 0 | EI67: 0 | EJ67: 0 | EK67: 0 | EL67: 0 | EM67: 0 | EN67: 394 | EO67: 5 | EP67: 0 | EQ67: 389 | ER67: 0 | ES67: 0 | ET67: 0 | EU67: 0 | EV67: 0 | EW67: 0 | EX67: 0 | EY67: 0 | EZ67: 0 | FA67: 0 | FB67: 0
A68: 65 | B68: 其他 | C68: 临床药物试验办公室GCP | D68: 177107.5 | E68: 176300 | F68: 807.5 | G68: 716 | H68: 4 | I68: 6 | J68: 0 | K68: 0 | L68: 132 | M68: 0 | N68: 0 | O68: 192489.67 | P68: 78774.83 | Q68: 0 | R68: 78774.83 | S68: 113714.84 | T68: 0 | U68: 113714.84 | V68: 191408.9 | W68: 78774.83 | X68: 0 | Y68: 78774.83 | Z68: 112634.07 | AA68: 0 | AB68: 112634.07 | AC68: 14980.9 | AD68: 2768.83 | AE68: 0 | AF68: 2768.83 | AG68: 12212.07 | AH68: 0 | AI68: 12212.07 | AJ68: 128 | AK68: 128 | AL68: 0 | AM68: 128 | AN68: 0 | AO68: 0 | AP68: 0 | AQ68: 158394 | AR68: 65772 | AS68: 0 | AT68: 65772 | AU68: 92622 | AV68: 0 | AW68: 92622 | AX68: 17906 | AY68: 10106 | AZ68: 0 | BA68: 10106 | BB68: 7800 | BC68: 0 | BD68: 7800 | BE68: 1080.77 | BF68: 0 | BG68: 0 | BH68: 0 | BI68: 1080.77 | BJ68: 0 | BK68: 1080.77 | BL68: 110.17 | BM68: 0 | BN68: 0 | BO68: 0 | BP68: 110.17 | BQ68: 0 | BR68: 110.17 | BS68: 163.1 | BT68: 0 | BU68: 0 | BV68: 0 | BW68: 163.1 | BX68: 0 | BY68: 163.1 | BZ68: 140 | CA68: 0 | CB68: 0 | CC68: 0 | CD68: 140 | CE68: 0 | CF68: 140 | CG68: 667.5 | CH68: 0 | CI68: 0 | CJ68: 0 | CK68: 667.5 | CL68: 0 | CM68: 667.5 | CN68: 0 | CO68: 0 | CP68: 0 | CQ68: 191408.9 | CR68: 0 | CS68: 0 | CT68: 0 | CU68: 0 | CV68: 716 | CW68: 404 | CX68: 0 | CY68: 404 | CZ68: 312 | DA68: 0 | DB68: 312 | DC68: 716 | DD68: 0 | DE68: 404 | DF68: 0 | DG68: 404 | DH68: 312 | DI68: 0 | DJ68: 312 | DK68: 0 | DL68: 0 | DM68: 0 | DN68: 0 | DO68: 0 | DP68: 0 | DQ68: 0 | DR68: 0 | DS68: 0 | DT68: 0 | DU68: 0 | DV68: 0 | DW68: 0 | DX68: 0 | DY68: 0 | DZ68: 0 | EA68: 0 | EB68: 0 | EC68: 0 | ED68: 0 | EE68: 0 | EF68: 0 | EG68: 4 | EH68: 0 | EI68: 0 | EJ68: 0 | EK68: 4 | EL68: 0 | EM68: 4 | EN68: 0 | EO68: 0 | EP68: 0 | EQ68: 0 | ER68: 0 | ES68: 0 | ET68: 0 | EU68: 0 | EV68: 0 | EW68: 0 | EX68: 0 | EY68: 0 | EZ68: 0 | FA68: 0 | FB68: 0
A69: 66 | C69: 其它 | D69: 117.5 | E69: 50 | F69: 67.5 | G69: 495 | H69: 74 | I69: 0 | J69: 0 | K69: 0 | L69: 0 | M69: 0 | N69: 0 | O69: 117.5 | P69: 25 | Q69: 25 | R69: 0 | S69: 92.5 | T69: 0 | U69: 92.5 | V69: 50 | W69: 25 | X69: 25 | Y69: 0 | Z69: 25 | AA69: 0 | AB69: 25 | AC69: 0 | AD69: 0 | AE69: 0 | AF69: 0 | AG69: 0 | AH69: 0 | AI69: 0 | AJ69: 0 | AK69: 0 | AL69: 0 | AM69: 0 | AN69: 0 | AO69: 0 | AP69: 0 | AQ69: 0 | AR69: 0 | AS69: 0 | AT69: 0 | AU69: 0 | AV69: 0 | AW69: 0 | AX69: 50 | AY69: 25 | AZ69: 25 | BA69: 0 | BB69: 25 | BC69: 0 | BD69: 25 | BE69: 67.5 | BF69: 0 | BG69: 0 | BH69: 0 | BI69: 67.5 | BJ69: 0 | BK69: 67.5 | BL69: 0 | BM69: 0 | BN69: 0 | BO69: 0 | BP69: 0 | BQ69: 0 | BR69: 0 | BS69: 0 | BT69: 0 | BU69: 0 | BV69: 0 | BW69: 0 | BX69: 0 | BY69: 0 | BZ69: 0 | CA69: 0 | CB69: 0 | CC69: 0 | CD69: 0 | CE69: 0 | CF69: 0 | CG69: 67.5 | CH69: 0 | CI69: 0 | CJ69: 0 | CK69: 67.5 | CL69: 0 | CM69: 67.5 | CN69: 0 | CO69: 0 | CP69: 0 | CQ69: 1475 | CR69: 0 | CS69: 0 | CT69: 0 | CU69: 0 | CV69: 495 | CW69: 182 | CX69: 54 | CY69: 128 | CZ69: 313 | DA69: 1 | DB69: 312 | DC69: 495 | DD69: 0 | DE69: 182 | DF69: 54 | DG69: 128 | DH69: 313 | DI69: 1 | DJ69: 312 | DK69: 0 | DL69: 0 | DM69: 0 | DN69: 0 | DO69: 0 | DP69: 0 | DQ69: 0 | DR69: 0 | DS69: 0 | DT69: 0 | DU69: 0 | DV69: 0 | DW69: 0 | DX69: 0 | DY69: 0 | DZ69: 0 | EA69: 0 | EB69: 0 | EC69: 0 | ED69: 0 | EE69: 0 | EF69: 0 | EG69: 74 | EH69: 50 | EI69: 48 | EJ69: 2 | EK69: 24 | EL69: 23 | EM69: 1 | EN69: 0 | EO69: 0 | EP69: 0 | EQ69: 0 | ER69: 0 | ES69: 0 | ET69: 0 | EU69: 0 | EV69: 0 | EW69: 0 | EX69: 0 | EY69: 0 | EZ69: 0 | FA69: 0 | FB69: 0

Sheet 当月附表1
A1: 收入费用盈余表
C2: 附表-01
A3: 编制单位：上海交通大学医学院附属新华医院 | B3: 2026年04月-2026年04月 | C3: 单位：元
A4: 项 目 | B4: 本月数 | C4: 本年累计数
A5: 一、医疗业务盈余： | B5: -2014551.4 | C5: -2.1107354e+08
A6: （一）医疗服务盈余： | B6: -3434589.1 | C6: -2.3522956e+08
A7: 医疗收入 | B7: 6.7472452e+08 | C7: 2.4214619e+09
A8: 加：财政基本拨款收入 | B8: 25021857 | C8: 1.0008743e+08
A9: 加：非同级财政基本拨款收入 | B9: 0 | C9: 0
A10: 减：医疗成本 | B10: 7.0318096e+08 | C10: 2.7567789e+09
A11: （二）其他盈余： | B11: 1420037.7 | C11: 24156018
A12: 其他医疗活动收入 | B12: 4705659 | C12: 37538727
A13: 减：其他医疗活动费用 | B13: 3285621.2 | C13: 13382709
A14: （三）结转入结余分配： | B14: \
A15: 加：年初未弥补亏损 | B15: \
A16: 加：累计盈余弥补亏损 | B16: \
A17: 减：提取职工福利基金 | B17: \
A18: 转入累计盈余 | B18: \
A19: 年末未弥补亏损 | B19: \
A20: 二、医疗项目盈余： | B20: -3511852.6 | C20: -12642523
A21: 非同级财政项目拨款收入 | B21: 0 | C21: 0
A22: 减：非同级财政项目费用 | B22: 3511852.6 | C22: 12642523
A23: 三、财政项目盈余： | B23: -18215909 | C23: -11134187
A24: 财政项目拨款收入 | B24: 4050000 | C24: 75263743
A25: 减：财政项目费用 | B25: 22265909 | C25: 86397930
A26: 四、科教盈余： | B26: -18712.7 | C26: -9131998.9
A27: 科教收入 | B27: 11415814 | C27: 48031599
A28: 减：科教费用 | B28: 11434527 | C28: 57163598
A29: 本期盈余合计 | B29: -23761026 | C29: -2.4398225e+08
A30: 单位负责人： 总会计师： 财务负责人： 审核： 制表：
A31: 注：本表“医疗成本”根据“业务活动费用”“单位管理费用”科目及所属明细科目、经费性质为财政基本拨款经费、其他经费的本期发生额填列；“非同级财政项目费用”根据“业务活动费用”“单位管理费用”科目及所属明细科目、经费性质为非同级财政拨款经费的本期发生额填列。

Sheet 当月奉贤附表1
A1: 收入费用盈余表
C2: 附表-01
A3: 编制单位：上海交通大学医学院附属新华医院（奉贤） | B3: 2026年04月-2026年04月 | C3: 单位：元
A4: 项 目 | B4: 本月数 | C4: 本年累计数
A5: 一、医疗业务盈余： | B5: -26730427 | C5: -1.540078e+08
A6: （一）医疗服务盈余： | B6: -26679234 | C6: -1.5291185e+08
A7: 医疗收入 | B7: 1.4715587e+08 | C7: 4.9714633e+08
A8: 加：财政基本拨款收入 | B8: 0 | C8: 0
A9: 加：非同级财政基本拨款收入 | B9: 0 | C9: 0
A10: 减：医疗成本 | B10: 1.7383511e+08 | C10: 6.5005818e+08
A11: （二）其他盈余： | B11: -51192.89 | C11: -1095951.4
A12: 其他医疗活动收入 | B12: 462466.2 | C12: 1480481.4
A13: 减：其他医疗活动费用 | B13: 513659.09 | C13: 2576432.8
A14: （三）结转入结余分配： | B14: \
A15: 加：年初未弥补亏损 | B15: \
A16: 加：累计盈余弥补亏损 | B16: \
A17: 减：提取职工福利基金 | B17: \
A18: 转入累计盈余 | B18: \
A19: 年末未弥补亏损 | B19: \
A20: 二、医疗项目盈余： | B20: -690765.35 | C20: -2761511.4
A21: 非同级财政项目拨款收入 | B21: 0 | C21: 0
A22: 减：非同级财政项目费用 | B22: 690765.35 | C22: 2761511.4
A23: 三、财政项目盈余： | B23: -8995885.3 | C23: -35960053
A24: 财政项目拨款收入 | B24: 0 | C24: 0
A25: 减：财政项目费用 | B25: 8995885.3 | C25: 35960053
A26: 四、科教盈余： | B26: 0 | C26: -485130
A27: 科教收入 | B27: 0 | C27: 0
A28: 减：科教费用 | B28: 0 | C28: 485130
A29: 本期盈余合计 | B29: -36417078 | C29: -1.9321449e+08
A30: 单位负责人： 总会计师： 财务负责人： 审核： 制表：
A31: 注：本表“医疗成本”根据“业务活动费用”“单位管理费用”科目及所属明细科目、经费性质为财政基本拨款经费、其他经费的本期发生额填列；“非同级财政项目费用”根据“业务活动费用”“单位管理费用”科目及所属明细科目、经费性质为非同级财政拨款经费的本期发生额填列。

Sheet 上年同期附表1
A1: 收入费用盈余表 | G1: 3
C2: 附表-01
A3: 编制单位：上海交通大学医学院附属新华医院 | B3: 2025年4月 | C3: 单位：元
A4: 项 目 | B4: 本月数 | C4: 本年累计数
A5: 一、医疗业务盈余： | B5: =B6+B11 -> -20148142 | C5: =C6+C11 -> -1.7182147e+08 | H5: =SUM(H7:H28) -> 1.1847613e+09
A6: （一）医疗服务盈余： | B6: =B7+B8+B9-B10 -> -37852457 | C6: =C7+C8+C9-C10 -> -2.2697652e+08
A7: 医疗收入 | B7: 5.1643405e+08 | C7: 1.9274933e+09 | G7: 8.7776585e+08 | H7: =IF($G$1=1,C7-B7,C7-B7-G7) -> 5.3329339e+08
A8: 加：财政基本拨款收入 | B8: 21873995 | C8: 87495980 | G8: 43747990 | H8: =IF($G$1=1,C8-B8,C8-B8-G8) -> 21873995
A9: 加：非同级财政基本拨款收入 | B9: 0 | C9: 0 | G9: 0 | H9: =IF($G$1=1,C9-B9,C9-B9-G9) -> 0
A10: 减：医疗成本 | B10: 5.7616051e+08 | C10: 2.2419658e+09 | G10: 1.1387105e+09 | H10: =IF($G$1=1,C10-B10,C10-B10-G10) -> 5.2709478e+08
A11: （二）其他盈余： | B11: =B12-B13 -> 17704315 | C11: =C12-C13 -> 55155050
A12: 其他医疗活动收入 | B12: 21589996 | C12: 79070355 | G12: 29591859 | H12: =IF($G$1=1,C12-B12,C12-B12-G12) -> 27888500
A13: 减：其他医疗活动费用 | B13: 3885680.6 | C13: 23915305 | G13: 16004141 | H13: =IF($G$1=1,C13-B13,C13-B13-G13) -> 4025483.6
A14: （三）结转入结余分配： | B14: \ | C14: 0
A15: 加：年初未弥补亏损 | B15: \ | C15: 0
A16: 加：累计盈余弥补亏损 | B16: \ | C16: 0
A17: 减：提取职工福利基金 | B17: \ | C17: 0
A18: 转入累计盈余 | B18: \ | C18: 0
A19: 年末未弥补亏损 | B19: \ | C19: =C14+C15+C16-C17-C18 -> 0
A20: 二、医疗项目盈余： | B20: =B21-B22 -> -3222332.4 | C20: =C21-C22 -> -16484335
A21: 非同级财政项目拨款收入 | B21: 0 | C21: 247100 | G21: 12500 | H21: =IF($G$1=1,C21-B21,C21-B21-G21) -> 234600
A22: 减：非同级财政项目费用 | B22: 3222332.4 | C22: 16731435 | G22: 9775924.1 | H22: =IF($G$1=1,C22-B22,C22-B22-G22) -> 3733178.8
A23: 三、财政项目盈余： | B23: =B24-B25 -> -13770577 | C23: =C24-C25 -> 62499800
A24: 财政项目拨款收入 | B24: 1020880 | C24: 112122880 | G24: 98880000 | H24: =IF($G$1=1,C24-B24,C24-B24-G24) -> 12222000
A25: 减：财政项目费用 | B25: 14791457 | C25: 49623080 | G25: 22048496 | H25: =IF($G$1=1,C25-B25,C25-B25-G25) -> 12783127
A26: 四、科教盈余： | B26: =B27-B28 -> -901162.66 | C26: =C27-C28 -> -2980692.7
A27: 科教收入 | B27: 20517298 | C27: 50803813 | G27: 6679393.2 | H27: =IF($G$1=1,C27-B27,C27-B27-G27) -> 23607122
A28: 减：科教费用 | B28: 21418461 | C28: 53784506 | G28: 14360921 | H28: =IF($G$1=1,C28-B28,C28-B28-G28) -> 18005124
A29: 本期盈余合计 | B29: =B26+B23+B20+B5 -> -38042215 | C29: =C26+C23+C20+C5 -> -1.287867e+08
A30: 单位负责人： 总会计师： 财务负责人： 审核： 制表：
A31: 注：本表“医疗成本”根据“业务活动费用”“单位管理费用”科目及所属明细科目、经费性质为财政基本拨款经费、其他经费的本期发生额填列；“非同级财政项目费用”根据“业务活动费用”“单位管理费用”科目及所属明细科目、经费性质为非同级财政拨款经费的本期发生额填列。

Sheet 当月附表2
A1: 医疗收入成本表
E2: 附表-02
A3: 编制单位：上海交通大学医学院附属新华医院 | C3: 2026年04月-2026年04月 | E3: 单位：元
A4: 项 目 | B4: 本月数 | C4: 本年累计数 | D4: 项 目 | E4: 本月数 | F4: 本年累计数
A5: 一、医疗收入 | B5: 6.7472452e+08 | C5: 2.4214619e+09 | D5: 一、医疗成本 | E5: 7.0318096e+08 | F5: 2.7567789e+09
A6: 1.门急诊收入 | B6: 2.4906669e+08 | C6: 9.0007142e+08 | D6: （一）按性质分类
A7: 其中：挂号收入 | B7: 0 | C7: 0 | D7: 1.人员经费 | E7: 2.4326711e+08 | F7: 1.0464751e+09
A8: 诊察收入 | B8: 13893328 | C8: 48904239 | D8: 2.卫生材料费 | E8: 2.2400093e+08 | F8: 8.3844979e+08
A9: 检查收入 | B9: 39923656 | C9: 1.4162349e+08 | D9: 3.药品费 | E9: 1.6494777e+08 | F9: 6.0974533e+08
A10: 化验收入 | B10: 39680287 | C10: 141506284 | D10: 4.固定资产折旧费 | E10: 9584839.4 | F10: 37679770
A11: 治疗收入 | B11: 25109310 | C11: 91745779 | D11: 5.无形资产摊销费 | E11: 1621505.9 | F11: 6547097.4
A12: 手术收入 | B12: 6850817.3 | C12: 20515869 | D12: 6.提取医疗风险基金 | E12: 1026089.3 | F12: 3646195.4
A13: 卫生材料收入 | B13: 8445710 | C13: 32283285 | D13: 7.其他费用 | E13: 58732723 | F13: 2.1423561e+08
A14: 药品收入 | B14: 99947925 | C14: 3.6407089e+08 | D14: （二）按功能分类
A15: 其中：西药收入 | B15: 79464031 | C15: 2.9031192e+08 | D15: 1.业务活动费用 | E15: 6.6297359e+08 | F15: 2.6074056e+09
A16: 中成药收入 | B16: 17834636 | C16: 63953907 | D16: 2.单位管理费用 | E16: 40207375 | F16: 1.4937333e+08
A17: 中药饮片收入 | B17: 2649258.5 | C17: 9805063.6
A18: 其他门诊收入 | B18: 15215653 | C18: 59421578
A19: 2.住院收入 | B19: 4.2565783e+08 | C19: 1.5213905e+09
A20: 其中：床位收入 | B20: 16362456 | C20: 61043462
A21: 诊察收入 | B21: 6724940 | C21: 24588815
A22: 检查收入 | B22: 31500501 | C22: 1.1076812e+08
A23: 化验收入 | B23: 40519834 | C23: 1.4787642e+08
A24: 治疗收入 | B24: 17600850 | C24: 57591295
A25: 手术收入 | B25: 52695294 | C25: 1.6216913e+08
A26: 护理收入 | B26: 6138885.1 | C26: 20130266
A27: 卫生材料收入 | B27: 1.8312979e+08 | C27: 6.5300359e+08
A28: 药品收入 | B28: 65538357 | C28: 2.4624685e+08
... A32: 其他住院收入 | B32: 5446918.9 | C32: 37972541
A33: 单位负责人： | B33: 总会计师： | C33: 财务负责人： | E33: 审核： | F33: 制表：
A34: 注：本表“医疗成本”及所属明细项目，根据“业务活动费用”“单位管理费用”科目及所属明细科目、经费性质为财政基本拨款经费、其他经费（不含非同级财政项目经费）的本期发生额填列。

Sheet 当月奉贤附表2
A1: 医疗收入成本表
E2: 附表-02
A3: 编制单位：上海交通大学医学院附属新华医院（奉贤） | C3: 2026年04月-2026年04月 | E3: 单位：元
A4: 项 目 | B4: 本月数 | C4: 本年累计数 | D4: 项 目 | E4: 本月数 | F4: 本年累计数
A5: 一、医疗收入 | B5: 1.4715587e+08 | C5: 4.9714633e+08 | D5: 一、医疗成本 | E5: 1.7383511e+08 | F5: 6.5005818e+08
A6: 1.门急诊收入 | B6: 44501698 | C6: 1.5715204e+08 | D6: （一）按性质分类
A7: 其中：挂号收入 | B7: 0 | C7: 0 | D7: 1.人员经费 | E7: 63931211 | F7: 2.7269461e+08
A8: 诊察收入 | B8: 2945766 | C8: 10118909 | D8: 2.卫生材料费 | E8: 66053754 | F8: 2.179264e+08
A9: 检查收入 | B9: 10133672 | C9: 34916455 | D9: 3.药品费 | E9: 27712094 | F9: 97852477
A10: 化验收入 | B10: 7186088 | C10: 25010368 | D10: 4.固定资产折旧费 | E10: 1311512.2 | F10: 3793728.6
A11: 治疗收入 | B11: 4033489.1 | C11: 14161194 | D11: 5.无形资产摊销费 | E11: 453736.27 | F11: 1814945
A12: 手术收入 | B12: 1280312.2 | C12: 3206618.5 | D12: 6.提取医疗风险基金 | E12: 223335.34 | F12: 748321.01
A13: 卫生材料收入 | B13: 2012748.4 | C13: 7729146.4 | D13: 7.其他费用 | E13: 14149465 | F13: 55227699
A14: 药品收入 | B14: 16024890 | C14: 57661791 | D14: （二）按功能分类
A15: 其中：西药收入 | B15: 12295951 | C15: 44657669 | D15: 1.业务活动费用 | E15: 1.5734725e+08 | F15: 6.1007634e+08
A16: 中成药收入 | B16: 3279474.6 | C16: 11664098 | D16: 2.单位管理费用 | E16: 16487860 | F16: 39981840
A17: 中药饮片收入 | B17: 449464.89 | C17: 1340024.8
A18: 其他门诊收入 | B18: 884732.49 | C18: 4347560.6
A19: 2.住院收入 | B19: 1.0265418e+08 | C19: 3.3999429e+08
A20: 其中：床位收入 | B20: 5063356 | C20: 16241328
A21: 诊察收入 | B21: 778800 | C21: 2350175
A22: 检查收入 | B22: 6897708.5 | C22: 22430264
A23: 化验收入 | B23: 7928962 | C23: 26091135
A24: 治疗收入 | B24: 2734805 | C24: 8202208.5
A25: 手术收入 | B25: 13094942 | C25: 36315858
A26: 护理收入 | B26: 1085908.1 | C26: 3259830.1
A27: 卫生材料收入 | B27: 52753804 | C27: 1.7988278e+08
A28: 药品收入 | B28: 11908797 | C28: 39923121
... A32: 其他住院收入 | B32: 407092.5 | C32: 5297591.6
A33: 单位负责人： | B33: 总会计师： | C33: 财务负责人： | E33: 审核： | F33: 制表：
A34: 注：本表“医疗成本”及所属明细项目，根据“业务活动费用”“单位管理费用”科目及所属明细科目、经费性质为财政基本拨款经费、其他经费（不含非同级财政项目经费）的本期发生额填列。

Sheet 上年同期附表2
A1: 医疗收入成本表
E2: 附表-02
A3: 编制单位：上海交通大学医学院附属新华医院 | C3: 2025年4月 | E3: 单位：元
A4: 项 目 | B4: 本月数 | C4: 本年累计数 | D4: 项 目 | E4: 本月数 | F4: 本年累计数
A5: 一、医疗收入 | B5: 5.1643405e+08 | C5: 1.9274933e+09 | D5: 一、医疗成本 | E5: 5.7616051e+08 | F5: 2.2419658e+09
A6: 1.门急诊收入 | B6: 1.8637442e+08 | C6: 6.9255835e+08 | D6: （一）按性质分类
A7: 其中：挂号收入 | B7: 4095967 | C7: 13292168 | D7: 1.人员经费 | E7: 2.1578901e+08 | F7: 9.0652444e+08
A8: 诊察收入 | B8: 6400239 | C8: 24463940 | D8: 2.卫生材料费 | E8: 1.6986024e+08 | F8: 6.0372911e+08
A9: 检查收入 | B9: 30177212 | C9: 108750536 | D9: 3.药品费 | E9: 1.3387055e+08 | F9: 5.0519231e+08
A10: 化验收入 | B10: 29298483 | C10: 111487859 | D10: 4.固定资产折旧费 | E10: 8973779.1 | F10: 36365264
A11: 治疗收入 | B11: 17657358 | C11: 66671002 | D11: 5.无形资产摊销费 | E11: 1803605 | F11: 8191410.5
A12: 手术收入 | B12: 3930609.3 | C12: 14359206 | D12: 6.提取医疗风险基金 | E12: 774651.08 | F12: 2891239.9
A13: 卫生材料收入 | B13: 6571626.9 | C13: 24443188 | D13: 7.其他费用 | E13: 45088679 | F13: 1.7907202e+08
A14: 药品收入 | B14: 73125503 | C14: 2.7253949e+08 | D14: （二）按功能分类
A15: 其中：西药收入 | B15: 57501963 | C15: 2.1395832e+08 | D15: 1.业务活动费用 | E15: 5.3757252e+08 | F15: 2.0528841e+09
A16: 中成药收入 | B16: 13030931 | C16: 48736993 | D16: 2.单位管理费用 | E16: 38587982 | F16: 1.8908175e+08
A17: 中药饮片收入 | B17: 2592608.1 | C17: 9844172.3
A18: 其他门诊收入 | B18: 15117419 | C18: 56550961
A19: 2.住院收入 | B19: 3.3005964e+08 | C19: 1.2349349e+09
A20: 其中：床位收入 | B20: 11040358 | C20: 45984886
A21: 诊察收入 | B21: 5963054 | C21: 22529840
A22: 检查收入 | B22: 23848557 | C22: 88420057
A23: 化验收入 | B23: 32023312 | C23: 1.1843293e+08
A24: 治疗收入 | B24: 16939373 | C24: 67516954
A25: 手术收入 | B25: 33617975 | C25: 1.1289578e+08
A26: 护理收入 | B26: 3690459.6 | C26: 15163343
A27: 卫生材料收入 | B27: 1.3214955e+08 | C27: 4.8415361e+08
A28: 药品收入 | B28: 60457141 | C28: 2.4181013e+08
... A32: 其他住院收入 | B32: 10329858 | C32: 38027424
A33: 单位负责人： | B33: 总会计师： | C33: 财务负责人： | E33: 审核： | F33: 制表：
A34: 注：本表“医疗成本”及所属明细项目，根据“业务活动费用”“单位管理费用”科目及所属明细科目、经费性质为财政基本拨款经费、其他经费（不含非同级财政项目经费）的本期发生额填列。

Sheet 当月附表3
A1: 医疗成本费用明细表
F2: 附表-03
A3: 编制单位：上海交通大学医学院附属新华医院 | C3: 46113 | F3: 单位：元
A4: 项 目 | B4: 合 计 | D4: 业务活动费用 | F4: 单位管理费用
B5: 本月数 | C5: 累计数 | D5: 本月数 | E5: 累计数 | F5: 本月数 | G5: 累计数
A6: 医疗成本合计 | B6: 7.0318096e+08 | C6: 2.7567789e+09 | D6: 6.6297359e+08 | E6: 2.6074056e+09 | F6: 40207375 | G6: 1.4937333e+08
A7: （一）人员经费 | B7: 2.4326711e+08 | C7: 1.0464751e+09 | D7: 2.2266624e+08 | E7: 9.7666681e+08 | F7: 20600865 | G7: 69808289
A8: 工资福利费用 | B8: 2.4040986e+08 | C8: 1.0346745e+09 | D8: 2.2265907e+08 | E8: 9.7626936e+08 | F8: 17750786 | G8: 58405150
A9: 基本工资 | B9: 28655264 | C9: 1.1558891e+08 | D9: 27171051 | E9: 1.0953404e+08 | F9: 1484213.4 | G9: 6054869.4
A10: 津贴补贴 | B10: 4917660.5 | C10: 19385015 | D10: 4723404 | E10: 18621118 | F10: 194256.5 | G10: 763897
A11: 奖金 | B11: 0 | C11: 0 | D11: 0 | E11: 0 | F11: 0 | G11: 0
A12: 伙食补助费 | B12: 2608568.2 | C12: 10412568 | D12: 2507568.2 | E12: 10007068 | F12: 101000 | G12: 405500
A13: 绩效工资 | B13: 1.5742566e+08 | C13: 7.0082653e+08 | D13: 1.4949823e+08 | E13: 6.6180646e+08 | F13: 7927434 | G13: 39020070
A14: 基本养老保险缴费 | B14: 24126633 | C14: 93651811 | D14: 21141763 | E14: 88944648 | F14: 2984870 | G14: 4707163
A15: 职业年金缴费 | B15: 6507510.7 | C15: 26157647 | D15: 5082188.6 | E15: 23929952 | F15: 1425322.1 | G15: 2227695.3
A16: 基本医疗保险缴费 | B16: 6451005.8 | C16: 26794680 | D16: 5036549.2 | E16: 24586107 | F16: 1414456.6 | G16: 2208572.9
A17: 其他社会保障缴费 | B17: 1003934.1 | C17: 4155186.3 | D17: 895860.25 | E17: 3986281.7 | F17: 108073.86 | G17: 168904.62
... A33: （二）卫生材料费 | B33: 2.2400093e+08 | C33: 8.3844979e+08 | D33: 2.2415897e+08 | E33: 8.3647401e+08 | F33: -158041.9 | G33: 1975784.7
A34: 血费 | B34: 0 | C34: 2368765 | D34: 0 | E34: 2368765
A35: 氧气费 | B35: 360 | C35: 1705260 | D35: 360 | E35: 1705260
A36: 放射材料费 | B36: 76000 | C36: 329250 | D36: 76000 | E36: 329250
A37: 化验材料费 | B37: 25583417 | C37: 1.009755e+08 | D37: 25583417 | E37: 1.009755e+08
A38: 一次性医疗器械 | B38: 1.8883208e+08 | C38: 6.9444143e+08 | D38: 1.8883208e+08 | E38: 6.9444143e+08
A39: 手术器械类 | B39: 16257081 | C39: 59544970 | D39: 16257081 | E39: 59544970
A40: 植入材料和人工器官 | B40: 66565731 | C40: 2.2745656e+08 | D40: 66565731 | E40: 2.2745656e+08
A41: 各类介入器械 | B41: 67348474 | C41: 2.3704049e+08 | D41: 67348474 | E41: 2.3704049e+08
A42: 医用材料高分子生物材料 | B42: 18825796 | C42: 78335924 | D42: 18825796 | E42: 78335924
A43: 口腔材料 | B43: 163112 | C43: 1068740.7 | D43: 163112 | E43: 1068740.7
A44: 其他一次性医疗器械 | B44: 19671886 | C44: 90994746 | D44: 19671886 | E44: 90994746
A45: 不可单独收费医用消耗材料 | B45: 7640633.6 | C45: 26695934 | D45: 7640633.6 | E45: 26695934
A46: 其他卫生材料 | B46: 1868440 | C46: 11933654 | D46: 2026481.9 | E46: 9957869 | F46: -158041.9 | G46: 1975784.7
A47: （三）药品费 | B47: 1.6494777e+08 | C47: 6.0974533e+08 | D47: 1.6494777e+08 | E47: 6.0974533e+08 | F47: 0 | G47: 0
A48: 西药费 | B48: 152670608 | C48: 5.6375108e+08 | D48: 152670608 | E48: 5.6375108e+08 | F48: 0 | G48: 0
A49: 中成药费 | B49: 10127484 | C49: 38015483 | D49: 10127484 | E49: 38015483
A50: 中药饮片费 | B50: 2149673.4 | C50: 7978760.3 | D50: 2149673.4 | E50: 7978760.3
A51: （四）固定资产折旧费 | B51: 9584839.4 | C51: 37679770 | D51: 9168950.7 | E51: 35985938 | F51: 415888.64 | G51: 1693831.7
A52: （五）无形资产摊销费 | B52: 1621505.9 | C52: 6547097.4 | D52: 1543494.5 | E52: 6235051.7 | F52: 78011.43 | G52: 312045.72
A53: （六）提取医疗风险基金 | B53: 1026089.3 | C53: 3646195.4 | D53: 1026089.3 | E53: 3646195.4
A54: （七）商品和服务费用 | B54: 58732723 | C54: 2.1423561e+08 | D54: 39462071 | E54: 1.3865223e+08 | F54: 19270652 | G54: 75583383
A55: 办公费 | B55: 0 | C55: 0 | D55: 0 | E55: 0 | F55: 0 | G55: 0
A56: 印刷费 | B56: 480804.29 | C56: 1263105.2 | D56: 479876.52 | E56: 1252466.8 | F56: 927.77 | G56: 10638.33
A57: 咨询费 | B57: 0 | C57: 0 | D57: 0 | E57: 0 | F57: 0 | G57: 0
A58: 手续费 | B58: 0 | C58: 0 | D58: 0 | E58: 0 | F58: 0 | G58: 0
A59: 水费 | B59: 609232.87 | C59: 2670747.3 | D59: 510899.11 | E59: 1875922.8 | F59: 98333.76 | G59: 794824.48
A60: 电费 | B60: 3382958.5 | C60: 15157843 | D60: 2325116.6 | E60: 13517922 | F60: 1057841.9 | G60: 1639921
A61: 邮电费 | B61: 691783.57 | C61: 1450866.9 | D61: 633253.39 | E61: 983211.1 | F61: 58530.18 | G61: 467655.75
A62: 取暖费 | B62: 0 | C62: 0 | D62: 0 | E62: 0 | F62: 0 | G62: 0
A63: 物业管理费 | B63: 10461055 | C63: 41762226 | D63: 5832991.1 | E63: 35902606 | F63: 4628063.5 | G63: 5859619.4
A64: 差旅费 | B64: 153904.28 | C64: 583827.03 | D64: 84140.36 | E64: 391406.14 | F64: 69763.92 | G64: 192420.89
A65: 因公出国（境）费 | B65: 92347.11 | C65: 374588.6 | D65: 92347.11 | E65: 305345.06 | F65: 0 | G65: 69243.54
... A79: 其他商品和服务支出 | B79: 11659091 | C79: 37676063 | D79: 10902478 | E79: 27133681 | F79: 756613.41 | G79: 10542382
A80: 单位负责人： 总会计师： 财务负责人： 审核： 制表人：
A81: 注：本表“医疗成本”及所属明细项目，根据“业务活动费用”“单位管理费用”科目及所属明细科目、经费性质为财政基本拨款经费、其他经费的本期发生额填列。

Sheet 上年同期附表3
A1: 医疗成本费用明细表
F2: 附表-03
A3: 编制单位：上海交通大学医学院附属新华医院 | C3: 2025年4月 | F3: 单位：元
A4: 项 目 | B4: 合 计 | D4: 业务活动费用 | F4: 单位管理费用
B5: 本月数 | C5: 累计数 | D5: 本月数 | E5: 累计数 | F5: 本月数 | G5: 累计数
A6: 医疗成本合计 | B6: =D6+F6 -> 5.7616051e+08 | C6: =E6+G6 -> 2.2419658e+09 | D6: =D7+D33+D47+D51+D52+D53+D54 -> 5.3757252e+08 | E6: =E7+E33+E47+E51+E52+E53+E54 -> 2.0528841e+09 | F6: =F7+F33+F47+F51+F52+F54 -> 38587982 | G6: =G7+G33+G47+G51+G52+G54 -> 1.8908175e+08
A7: （一）人员经费 | B7: =D7+F7 -> 2.1578901e+08 | C7: =E7+G7 -> 9.0652444e+08 | D7: =D8+D21 -> 1.953596e+08 | E7: =E8+E21 -> 8.0780253e+08 | F7: =F8+F21 -> 20429402 | G7: =G8+G21 -> 98721903
A8: 工资福利费用 | B8: =D8+F8 -> 2.1288026e+08 | C8: =E8+G8 -> 8.9567283e+08 | D8: =SUM(D9:D20) -> 1.952165e+08 | E8: =SUM(E9:E20) -> 8.0721095e+08 | F8: =SUM(F9:F20) -> 17663755 | G8: =SUM(G9:G20) -> 88461872
A9: 基本工资 | B9: =D9+F9 -> 29106827 | C9: =E9+G9 -> 1.1920146e+08 | D9: 26342612 | E9: 1.0780775e+08 | F9: 2764215 | G9: 11393701
A10: 津贴补贴 | B10: =D10+F10 -> 4284096.5 | C10: =E10+G10 -> 16894266 | D10: 3989494 | E10: 15750928 | F10: 294602.5 | G10: 1143338
A11: 奖金 | B11: =D11+F11 -> 0 | C11: =E11+G11 -> 0 | D11: 0 | E11: 0 | F11: 0 | G11: 0
A12: 伙食补助费 | B12: =D12+F12 -> 2442500 | C12: =E12+G12 -> 9746880.7 | D12: 2272500 | E12: 9062880.7 | F12: 170000 | G12: 684000
A13: 绩效工资 | B13: =D13+F13 -> 1.3170131e+08 | C13: =E13+G13 -> 5.7591506e+08 | D13: 1.1984309e+08 | E13: 5.2101053e+08 | F13: 11858216 | G13: 54904530
A14: 基本养老保险缴费 | B14: =D14+F14 -> 21390287 | C14: =E14+G14 -> 86354524 | D14: 20299832 | E14: 77844567 | F14: 1090455 | G14: 8509956.5
A15: 职业年金缴费 | B15: =D15+F15 -> 6238871 | C15: =E15+G15 -> 25049382 | D15: 5722792.9 | E15: 20995213 | F15: 516078.11 | G15: 4054169.3
A16: 基本医疗保险缴费 | B16: =D16+F16 -> 6484952.7 | C16: =E16+G16 -> 25362476 | D16: 5967268.7 | E16: 21384143 | F16: 517684.02 | G16: 3978333
A17: 其他社会保障缴费 | B17: =D17+F17 -> 930913.54 | C17: =E17+G17 -> 3670324.1 | D17: 890824.58 | E17: 3370338.3 | F17: 40088.96 | G17: 299985.74
A18: 住房公积金 | B18: =D18+F18 -> 7651248 | C18: =E18+G18 -> 30308544 | D18: 7303266.4 | E18: 26966040 | F18: 347981.63 | G18: 3342503.9
A19: 医疗费 | B19: =D19+F19 -> 0 | C19: =E19+G19 -> 0 | D19: 0 | E19: 0 | F19: 0 | G19: 0
A20: 其他工资福利支出 | B20: =D20+F20 -> 2649251.1 | C20: =E20+G20 -> 3169917.3 | D20: 2584817.4 | E20: 3018561.6 | F20: 64433.73 | G20: 151355.69
A21: 对个人和家庭的补助费用 | B21: =D21+F21 -> 2908746.6 | C21: =E21+G21 -> 10851610 | D21: =SUM(D22:D32) -> 143099.75 | E21: =SUM(E22:E32) -> 591579.84 | F21: =SUM(F22:F32) -> 2765646.9 | G21: =SUM(G22:G32) -> 10260030
A22: 离休费 | B22: =D22+F22 -> 13083 | C22: =E22+G22 -> 66832 | D22: 0 | E22: 0 | F22: 13083 | G22: 66832
A23: 退休费 | B23: =D23+F23 -> 2276234 | C23: =E23+G23 -> 9064015 | D23: 0 | E23: 0 | F23: 2276234 | G23: 9064015
A24: 退职费 | B24: =D24+F24 -> 0 | C24: =E24+G24 -> 0 | D24: 0 | E24: 0 | F24: 0 | G24: 0
A25: 抚恤金 | B25: =D25+F25 -> 398254 | C25: =E25+G25 -> 784894 | D25: 0 | E25: 0 | F25: 398254 | G25: 784894
A26: 生活补助 | B26: =D26+F26 -> 2100 | C26: =E26+G26 -> 13400 | D26: 0 | E26: 3500 | F26: 2100 | G26: 9900
A27: 救济费 | B27: =D27+F27 -> 0 | C27: =E27+G27 -> 0 | D27: 0 | E27: 0 | F27: 0 | G27: 0
A28: 医疗补助费 | B28: =D28+F28 -> 208829.63 | C28: =E28+G28 -> 884773.27 | D28: 134153.75 | E28: 553983.84 | F28: 74675.88 | G28: 330789.43
A29: 助学金 | B29: =D29+F29 -> 0 | C29: =E29+G29 -> 0 | D29: 0 | E29: 0 | F29: 0 | G29: 0
A30: 奖励金 | B30: =D30+F30 -> 0 | C30: =E30+G30 -> 0 | D30: 0 | E30: 0 | F30: 0 | G30: 0
A31: 生产补贴 | B31: =D31+F31 -> 0 | C31: =E31+G31 -> 0 | D31: 0 | E31: 0 | F31: 0 | G31: 0
A32: 其他对个人和家庭补助支出 | B32: =D32+F32 -> 10246 | C32: =E32+G32 -> 37696 | D32: 8946 | E32: 34096 | F32: 1300 | G32: 3600
A33: （二）卫生材料费 | B33: =D33+F33 -> 1.6986024e+08 | C33: =E33+G33 -> 6.0372911e+08 | D33: =D34+D35+D36+D37+D38+D45+D46 -> 1.6878662e+08 | E33: =E34+E35+E36+E37+E38+E45+E46 -> 6.0093332e+08 | F33: 1073613 | G33: 2795790.3
A34: 血费 | B34: =D34+F34 -> 1020345 | C34: =E34+G34 -> 3048215 | D34: 1020345 | E34: 3048215
A35: 氧气费 | B35: =D35+F35 -> 390642.7 | C35: =E35+G35 -> 1742604.1 | D35: 390642.7 | E35: 1742604.1
A36: 放射材料费 | B36: =D36+F36 -> 48000 | C36: =E36+G36 -> 48000 | D36: 48000 | E36: 48000
A37: 化验材料费 | B37: =D37+F37 -> 17290533 | C37: =E37+G37 -> 67317102 | D37: 17290533 | E37: 67317102
A38: 一次性医疗器械 | B38: =D38+F38 -> 1.4019051e+08 | C38: =E38+G38 -> 4.989248e+08 | D38: =SUM(D39:D44) -> 1.4019051e+08 | E38: =SUM(E39:E44) -> 4.989248e+08
A39: 手术器械类 | B39: =D39+F39 -> 15028591 | C39: =E39+G39 -> 54017750 | D39: 15028591 | E39: 54017750
A40: 植入材料和人工器官 | B40: =D40+F40 -> 46555432 | C40: =E40+G40 -> 1.6058459e+08 | D40: 46555432 | E40: 1.6058459e+08
A41: 各类介入器械 | B41: =D41+F41 -> 43944024 | C41: =E41+G41 -> 1.59874e+08 | D41: 43944024 | E41: 1.59874e+08
A42: 医用材料高分子生物材料 | B42: =D42+F42 -> 16265731 | C42: =E42+G42 -> 57840155 | D42: 16265731 | E42: 57840155
A43: 口腔材料 | B43: =D43+F43 -> 508884 | C43: =E43+G43 -> 2161280 | D43: 508884 | E43: 2161280
A44: 其他一次性医疗器械 | B44: =D44+F44 -> 17887845 | C44: =E44+G44 -> 64447021 | D44: 17887845 | E44: 64447021
A45: 不可单独收费医用消耗材料 | B45: =D45+F45 -> 9065719.5 | C45: =E45+G45 -> 26318807 | D45: 9065719.5 | E45: 26318807
A46: 其他卫生材料 | B46: =D46+F46 -> 1854488.1 | C46: =E46+G46 -> 6329586 | D46: 780875.13 | E46: 3533795.6 | F46: =F33 -> 1073613 | G46: =G33 -> 2795790.3
A47: （三）药品费 | B47: =D47+F47 -> 1.3387055e+08 | C47: =E47+G47 -> 5.0519231e+08 | D47: =D48+D49+D50 -> 1.3387055e+08 | E47: =E48+E49+E50 -> 5.0519231e+08 | F47: 0 | G47: 0
A48: 西药费 | B48: =D48+F48 -> 1.2281874e+08 | C48: =E48+G48 -> 4.6734046e+08 | D48: 1.2281874e+08 | E48: 4.6734046e+08
A49: 中成药费 | B49: =D49+F49 -> 8897003.5 | C49: =E49+G49 -> 29688055 | D49: 8897003.5 | E49: 29688055
A50: 中药饮片费 | B50: =D50+F50 -> 2154805.2 | C50: =E50+G50 -> 8163794.1 | D50: 2154805.2 | E50: 8163794.1
A51: （四）固定资产折旧费 | B51: =D51+F51 -> 8973779.1 | C51: =E51+G51 -> 36365264 | D51: 6874943.6 | E51: 28005244 | F51: 2098835.6 | G51: 8360020.2
A52: （五）无形资产摊销费 | B52: =D52+F52 -> 1803605 | C52: =E52+G52 -> 8191410.5 | D52: 34405.82 | E52: 137623.13 | F52: 1769199.2 | G52: 8053787.3
A53: （六）提取医疗风险基金 | B53: =D53+F53 -> 774651.08 | C53: =E53+G53 -> 2891239.9 | D53: 774651.08 | E53: 2891239.9
A54: （七）商品和服务费用 | B54: =D54+F54 -> 45088679 | C54: =E54+G54 -> 1.7907202e+08 | D54: =SUM(D55:D79) -> 31871746 | E54: =SUM(E55:E79) -> 1.0792177e+08 | F54: =SUM(F55:F79) -> 13216932 | G54: =SUM(G55:G79) -> 71150249
