Workbook

Sheet 饼图
D1: 1月
F2: 自动 | I2: 自动 | J2: 自动 | K2: 自动
C3: 项 目 | D3: 2026年 | E3: 占 比 % | F3: 奉贤 | G3: 占 比 % | H3: 2025年 | I3: 占 比 % | J3: 增减额 | K3: 增减率
C4: 人员经费 | D4: 24327 | E4: 0.34595694 | F4: 6393 | G4: 0.36775196 | H4: 21579 | I4: 0.37453138 | J4: 2748 | K4: 0.12734603 | M4: =E4-I4
C5: 药品费 | D5: 16495 | E5: 0.23457721 | F5: 2771 | G5: 0.15939945 | H5: 13387 | I5: 0.23234865 | J5: 3108 | K5: 0.23216553 | M5: =E5-I5
C6: 耗材费 | D6: 22400 | E6: 0.31855286 | F6: 6605 | G6: 0.37994708 | H6: 16986 | I6: 0.29481394 | J6: 5414 | K6: 0.31873307 | M6: =E6-I6
C7: 折旧/摊销 | D7: 1120 | E7: 0.015927643 | F7: 178 | G7: 0.010239301 | H7: 1078 | I7: 0.018710081 | J7: 42 | K7: 0.038961039 | M7: =E7-I7
C8: 风险基金 | D8: 103 | E8: 0.0014647743 | F8: 22 | G8: 0.0012655315 | H8: 77 | I8: 0.0013364343 | J8: 26 | K8: 0.33766234 | L8: 自动 | M8: =E9-I9
C9: 其他费用 | D9: 5873 | E9: 0.083520578 | F9: 1415 | G9: 0.081396687 | H9: 4509 | I9: 0.078259511 | J9: 1364 | K9: 0.3025061
C10: 医疗成本合计 | D10: 70318 | E10: 1 | F10: 17384 | G10: 1 | H10: 57616 | I10: 1 | J10: 12702 | K10: 0.22045959 | L10: 自动 | M10: =E9-I9
L13: 自动 | P13: 2025年 | R13: 2024年
K14: 人员经费 | L14: =E4 | O14: 医疗风险基金 | P14: 78 | R14: 78
K15: 药品费 | L15: =E5 | O15: 能源费 | P15: 516 | R15: 472
K16: 耗材费 | L16: =E6 | O16: 物业管理费 | R16: 624
K17: 折旧/摊销 | L17: =E7 | O17: 维修护费 | R17: 1353
K18: 其他费用 | L18: =E9 | O18: 劳务费 | R18: 354
O24: 其他 | P24: =P25-P14-P15-P16-P17-P18-P19-P20-P21-P22-P23 | R24: =R25-R14-R15-R16-R17-R18-R19-R20-R21-R22-R23
C25: 2024年 | D25: 2023年 | F25: 增减额 | H25: 增减率 | O25: 总计 | P25: 4586 | R25: 4124
B26: 项 目 | C26: 1-9月 | D26: 1-9月
C27: 498726 | D27: 451737 | F27: =C27-D27 | H27: =C27/D27-1
B28: 医疗成本 | C28: 143587 | D28: 127531 | F28: =C28-D28 | H28: =C28/D28-1
B29: 其中：工资总额 | C29: 3802 | D29: 3829 | F29: =C29-D29 | H29: =C29/D29-1
B30: 其他费用 | C30: =C27+C29 | D30: =D27+D29 | F30: =C30-D30 | H30: =C30/D30-1
B31: 小 计

Sheet 医疗成本
B3: 项 目 | C3: 2026年 | D3: 占 比% | E3: 奉贤院区 | F3: 占 比% | G3: 2025年 | H3: 占 比% | I3: 增减额 | J3: 增减率 | K3: 46082
C4: 5月 | G4: 5月
B5: 人员经费 | C5: =ROUND(当月附表3!B7/10000,0) | D5: =C5/C$11 | E5: =ROUND(当月奉贤附表3!B7/10000,0) | F5: =E5/E$11 | G5: =ROUND(上年同期附表3!B7/10000,0) | H5: =G5/G$11 | I5: =C5-G5 | J5: =I5/G5 | K5: =ROUND(当月附表3!B7/10000,0)
B6: 药品费 | C6: =ROUND(当月附表3!B47/10000,0) | D6: =C6/C$11 | E6: =ROUND(当月奉贤附表3!B47/10000,0) | F6: =E6/E$11 | G6: =ROUND(上年同期附表3!B47/10000,0) | H6: =G6/G$11 | I6: =C6-G6 | J6: =I6/G6 | K6: =ROUND(当月附表3!B47/10000,0)
B7: 卫生材料费 | C7: =ROUND(当月附表3!B33/10000,0) | D7: =C7/C$11 | E7: =ROUND(当月奉贤附表3!B33/10000,0) | F7: =E7/E$11 | G7: =ROUND(上年同期附表3!B33/10000,0) | H7: =G7/G$11 | I7: =C7-G7 | J7: =I7/G7 | K7: =ROUND(当月附表3!B33/10000,0)
B8: 折旧/摊销 | C8: =C11-C10-C7-C6-C5-C9 | D8: =C8/C$11 | E8: =E11-E10-E7-E6-E5-E9 | F8: =E8/E$11 | G8: =G11-G10-G7-G6-G5-G9 | H8: =G8/G$11 | I8: =C8-G8 | J8: =I8/G8 | K8: =K11-K10-K7-K6-K5-K9
B9: 医疗风险基金 | C9: =ROUND(当月附表3!B53/10000,0) | D9: =C9/C$11 | E9: =ROUND(当月奉贤附表3!B53/10000,0) | F9: =E9/E$11 | G9: =ROUND(上年同期附表3!B53/10000,0) | H9: =G9/G$11 | I9: =C9-G9 | J9: =I9/G9 | K9: =ROUND(当月附表3!B53/10000,0)
B10: 商品和服务费 | C10: =ROUND(当月附表3!B54/10000,0) | D10: =C10/C$11 | E10: =ROUND(当月奉贤附表3!B54/10000,0) | F10: =E10/E$11 | G10: =ROUND(上年同期附表3!B54/10000,0) | H10: =G10/G$11 | I10: =C10-G10 | J10: =I10/G10 | K10: =ROUND(当月附表3!B54/10000,0)
B11: 医疗成本合计 | C11: =ROUND(当月附表3!B6/10000,0) | D11: 1 | E11: =ROUND(当月奉贤附表3!B6/10000,0) | F11: 1 | G11: =ROUND(上年同期附表3!B6/10000,0) | H11: 1 | I11: =C11-G11 | J11: =I11/G11 | K11: =ROUND(当月附表3!B6/10000,0)

Sheet 人员经费
B3: 项 目 | C3: 46143 | D3: 其中 | E3: 45778 | F3: 增减额 | G3: 增减率
D4: 奉贤院区
B5: 医疗服务收入 | C5: =ROUND((当年累计数据表!AQ3+当年累计数据表!AX3+当年累计数据表!BZ3+当年累计数据表!CG3)/10000,0) | D5: =ROUND((当年累计数据表奉贤!AQ3+当年累计数据表奉贤!AX3+当年累计数据表奉贤!BZ3+当年累计数据表奉贤!CG3)/10000,0) | E5: =ROUND((去年累计数据表!AQ3+去年累计数据表!AX3+去年累计数据表!BZ3+去年累计数据表!CG3)/10000,0) | F5: =C5-E5 | G5: =F5/E5
B6: 人员经费 | C6: =医疗成本!C5 | D6: =医疗成本!E5 | E6: =医疗成本!G5 | F6: =医疗成本!I5 | G6: =医疗成本!J5
B7: 其中：工资总额 | C7: =ROUND((当月附表3!B9+当月附表3!B10+当月附表3!B11+当月附表3!B12+当月附表3!B13+当月附表3!B20)/10000,0) | D7: =ROUND((当月奉贤附表3!B9+当月奉贤附表3!B10+当月奉贤附表3!B11+当月奉贤附表3!B12+当月奉贤附表3!B13+当月奉贤附表3!B20)/10000,0) | E7: =ROUND((上年同期附表3!B9+上年同期附表3!B10+上年同期附表3!B11+上年同期附表3!B12+上年同期附表3!B13+上年同期附表3!B20)/10000,0) | F7: =C7-E7 | G7: =F7/E7
B8: 其中：基本工资等 | C8: =ROUND((当月附表3!B9+当月附表3!B10+当月附表3!B11+当月附表3!B12+当月附表3!B20)/10000,0) | D8: =ROUND((当月奉贤附表3!B9+当月奉贤附表3!B10+当月奉贤附表3!B11+当月奉贤附表3!B12+当月奉贤附表3!B20)/10000,0) | E8: =ROUND((上年同期附表3!B9+上年同期附表3!B10+上年同期附表3!B11+上年同期附表3!B12+上年同期附表3!B20)/10000,0) | F8: =C8-E8 | G8: =F8/E8
B9: 绩效工资 | C9: =C7-C8 | D9: =D7-D8 | E9: =E7-E8 | F9: =C9-E9 | G9: =F9/E9
B10: 社保公积金 | C10: =ROUND((当月附表3!B14+当月附表3!B15+当月附表3!B16+当月附表3!B17+当月附表3!B18)/10000,0) | D10: =ROUND((当月奉贤附表3!B14+当月奉贤附表3!B15+当月奉贤附表3!B16+当月奉贤附表3!B17+当月奉贤附表3!B18)/10000,0) | E10: =ROUND((上年同期附表3!B14+上年同期附表3!B15+上年同期附表3!B16+上年同期附表3!B17+上年同期附表3!B18)/10000,0) | F10: =C10-E10 | G10: =F10/E10

Sheet 水电煤
B2: 项 目 | C2: 46143 | D2: 其中 | E2: 45778 | F2: 增减额 | G2: 增减率
D3: 奉贤院区
B4: 能耗成本 | C4: =C5+C6+C7 | D4: =D5+D6+D7 | E4: =E5+E6+E7 | F4: =C4-E4 | G4: =F4/E4
B5: 其中：水费 | C5: =ROUND(当月附表3!B59/10000,0) | D5: =ROUND(当月奉贤附表3!B59/10000,0) | E5: =ROUND(上年同期附表3!B59/10000,0) | F5: =C5-E5 | G5: =F5/E5
B6: 电费 | C6: =ROUND(当月附表3!B60/10000,0) | D6: =ROUND(当月奉贤附表3!B60/10000,0) | E6: =ROUND(上年同期附表3!B60/10000,0) | F6: =C6-E6 | G6: =F6/E6
B7: 燃气费 | C7: =ROUND(当月附表3!B72/10000,0) | D7: =ROUND(当月奉贤附表3!B72/10000,0) | E7: =ROUND(上年同期附表3!B72/10000,0) | F7: =C7-E7 | G7: =F7/E7

Sheet 预算完成情况
B2: 项 目 | C2: 执行率指标 | J2: 年终
C3: 核定数 | D3: 执行数 | E3: 执行率 | F3: 与时间节点比较 | H3: 0.333 | J3: 17532 | K3: =J3*(1-H3)
B4: 医疗收入 | C4: 750000 | D4: =收支结余!C4 | E4: =D4/C4 | F4: =E4-$H$3 | K4: =D6-K3 | L4: =K4/C6
B5: 医疗成本 | C5: 768743 | D5: =收支结余!C6 | E5: =D5/C5 | F5: =E5-$H$3
B6: 工资总额 | C6: 225000 | D6: =人员经费!C7 | E6: =D6/C6 | F6: =E6-$H$3

Sheet 收支结余
B2: 项 目 | C2: 46143 | D2: 其中 | E2: 45778 | F2: 增减额 | G2: 增减率
D3: 奉贤院区
B4: 医疗收入 | C4: =ROUND(当年累计数据表!O3/10000,0) | D4: =ROUND(当年累计数据表奉贤!O3/10000,0) | E4: =ROUND(去年累计数据表!O3/10000,0) | F4: =C4-E4 | G4: =F4/E4
B5: 加：财政基本拨款收入 | C5: 2502 | D5: 0 | E5: 2411 | F5: =C5-E5 | G5: =F5/E5
B6: 减：医疗成本 | C6: =医疗成本!C11 | D6: =医疗成本!E11 | E6: =医疗成本!G11 | F6: =C6-E6 | G6: =F6/E6
B7: 医疗服务盈余 | C7: =C4+C5-C6 | D7: =D4+D5-D6 | E7: =E4+E5-E6 | F7: =C7-E7 | G7: =F7/E7
B8: 其他盈余 | C8: =C9-C7 | D8: =D9-D7 | E8: =E9-E7 | F8: =C8-E8 | G8: -
B9: 收支结余 | C9: =ROUND(当月附表1!B5/10000,0) | D9: =ROUND(当月奉贤附表1!B5/10000,0) | E9: =ROUND(上年同期附表1!B5/10000,0) | F9: =C9-E9 | G9: -
B16: 项 目 | C16: 46113 | D16: 45748 | E16: 增减额 | F16: 增减率
B17: 新华医疗开发公司 | E17: =C17-D17 | F17: =E17/D17

Sheet 商品服务
B2: 项 目 | C2: 46143 | D2: 其中 | E2: 45778 | F2: 增减额 | G2: 增减率
D3: 奉贤院区
B4: 商品服务 | C4: =ROUND(当月附表3!B54/10000,0) | D4: =ROUND(当月奉贤附表3!B54/10000,0) | E4: =ROUND(上年同期附表3!B54/10000,0) | F4: =C4-E4 | G4: =F4/E4
B5: 其中：能源成本 | C5: =水电煤!C4 | D5: =水电煤!D4 | E5: =水电煤!E4 | F5: =C5-E5 | G5: =F5/E5
B6: 维修护费 | C6: 683 | D6: 183 | E6: 719 | F6: =C6-E6 | G6: =F6/E6
B7: 物业管理费 | C7: 1182 | D7: 388 | E7: 729 | F7: =C7-E7 | G7: =F7/E7
B8: 委托业务费 | C8: =ROUND(当月附表3!B74/10000,0) | D8: =ROUND(当月奉贤附表3!B74/10000,0) | E8: =ROUND(上年同期附表3!B74/10000,0) | F8: =C8-E8 | G8: =F8/E8
B9: 劳务费 | C9: =ROUND(当月附表3!B73/10000,0) | D9: =ROUND(当月奉贤附表3!B73/10000,0) | E9: =ROUND(上年同期附表3!B73/10000,0) | F9: =C9-E9 | G9: =F9/E9
B10: 专用材料费 | C10: =ROUND(当月附表3!B71/10000,0) | D10: =ROUND(当月奉贤附表3!B71/10000,0) | E10: =ROUND(上年同期附表3!B71/10000,0) | F10: =C10-E10 | G10: =F10/E10
B11: 供应室外包成本 | C11: 470 | D11: 104 | E11: 575 | F11: =C11-E11 | G11: =F11/E11
B12: 租赁费 | C12: =ROUND(当月附表3!B67/10000,0) | D12: =ROUND(当月奉贤附表3!B67/10000,0) | E12: =ROUND(上年同期附表3!B67/10000,0) | F12: =C12-E12 | G12: =F12/E12
B13: 其他 | C13: =C4-C5-C6-C7-C8-C9-C10-C11-C12 | D13: =D4-D5-D6-D7-D8-D9-D10-D11-D12 | E13: =E4-E5-E6-E7-E8-E9-E10-E11-E12 | F13: =C13-E13 | G13: =F13/E13
C24: =C11+C13 | D24: =D11+D13 | E24: =E11+E13 | F24: =F11+F13 | G24: =F24/E24

Sheet 物业管理
B3: 项 目 | C3: 46143 | D3: 其中 | E3: 45778 | F3: 增减额 | G3: 增减率 | I3: 项 目 | J3: 46143 | K3: 其中 | L3: 45778 | M3: 增减额 | N3: 增减率
D4: 奉贤院区 | K4: 奉贤院区
B5: 物业管理费 | C5: =商品服务!C7 | D5: =商品服务!D7 | E5: =商品服务!E7 | F5: =C5-E5 | G5: =F5/E5 | I5: 物业管理费 | J5: =商品服务!C7 | K5: =商品服务!D7 | L5: =商品服务!E7 | M5: =J5-L5 | N5: =M5/L5
B6: 其中： 电梯驾驶服务 | C6: 58 | D6: 26 | E6: 0 | F6: =C6-E6 | G6: =F6/E6 | I6: 其中： 电梯驾驶服务 | J6: 58 | K6: 26 | L6: 0 | M6: =J6-L6 | N6: =M6/L6
B7: 保安管理 | C7: 197 | D7: 58 | E7: 145 | F7: =C7-E7 | G7: =F7/E7 | I7: 保安管理 | J7: 197 | K7: 58 | L7: 145 | M7: =J7-L7 | N7: =M7/L7
B8: 运送服务费 | C8: 212 | D8: 87 | E8: 78 | F8: =C8-E8 | G8: =F8/E8 | I8: 运送服务费 | J8: 212 | K8: 87 | L8: 78 | M8: =J8-L8 | N8: =M8/L8
B9: 保洁服务 | C9: 481 | D9: 113 | E9: 361 | F9: =C9-E9 | G9: =F9/E9 | I9: 保洁服务 | J9: 481 | K9: 113 | L9: 361 | M9: =J9-L9 | N9: =M9/L9
B10: 被服洗涤 | C10: 73 | D10: 29 | E10: 58 | F10: =C10-E10 | G10: =F10/E10 | I10: 被服洗涤 | J10: 73 | K10: 29 | L10: 58 | M10: =J10-L10 | N10: =M10/L10
B11: 会务 | C11: 75 | D11: 27 | E11: 60 | F11: =C11-E11 | G11: =F11/E11 | I11: 物业其他 | J11: =J5-J6-J7-J8-J9-J10 | K11: =K5-K6-K7-K8-K9-K10 | L11: =L5-L6-L7-L8-L9-L10 | M11: =J11-L11 | N11: =M11/L11
B12: 绿化 | C12: 3 | D12: 0 | E12: 0 | F12: =C12-E12 | G12: =F12/E12
B13: 垃圾清运 | C13: 18 | D13: 2 | E13: 0 | F13: =C13-E13 | G13: =F13/E13
B14: 危险废弃物 | C14: 2 | D14: 1 | E14: 0 | F14: =C14-E14 | G14: =F14/E14
B15: 医废处置 | C15: 16 | D15: 10 | E15: 0 | F15: =C15-E15 | G15: =F15/E15
B16: 医废收运 | C16: 20 | D16: 8 | E16: 27 | F16: =C16-E16 | G16: =F16/E16
B17: 交通管理服务费 | C17: 6 | D17: 1 | E17: 0
B18: 园区物业管理 | C18: =C5-C6-C7-C8-C9-C10-C11-C12-C13-C14-C15-C16-C17 | D18: =D5-D6-D7-D8-D9-D10-D11-D12-D13-D14-D15-D16-D17 | E18: =E5-E6-E7-E8-E9-E10-E11-E12-E13-E14-E15-E16-E17 | F18: =C18-E18 | G18: =F18/E18

Sheet 维修护费
B1: 项 目 | C1: 46143 | D1: 其中 | E1: 45778 | F1: 增减额 | G1: 增减率
D2: 奉贤院区 | I2: 柯渡
B3: 维修费 | C3: =商品服务!C6 | D3: =商品服务!D6 | E3: =商品服务!E6 | F3: =C3-E3 | G3: =F3/E3
B4: 其中：网络维修 | C4: 55 | D4: 11 | E4: 219 | F4: =C4-E4 | G4: =F4/E4
B5: 设备维修 | C5: 347 | D5: 81 | E5: 421 | F5: =C5-E5 | G5: =F5/E5 | H5: 1114 | I5: 100 | J5: 1146
B6: 后勤维修 | C6: 199 | D6: 91 | E6: 59 | F6: =C6-E6 | G6: =F6/E6
B7: 房屋维修 | C7: 83 | D7: 0 | E7: 20 | F7: =C7-E7 | G7: =F7/E7

Sheet 后勤维修
C3: 项 目 | D3: 46143 | E3: 其中 | F3: 45778 | G3: 增减额 | H3: 增减率 | K3: 项 目 | L3: 46113 | M3: 其中 | N3: 45748 | O3: 增减额 | P3: 增减率
E4: 奉贤院区 | M4: 奉贤院区
C5: 后勤维修费 | D5: =维修护费!C6 | E5: =维修护费!D6 | F5: =维修护费!E6 | G5: =D5-F5 | H5: =G5/F5 | K5: 后勤维修费 | L5: =维修护费!C6 | M5: =维修护费!D6 | N5: =维修护费!E6 | O5: =L5-N5 | P5: =O5/N5
C6: 其中：物业维修 | D6: 70 | E6: 34 | F6: 45 | G6: =D6-F6 | H6: =G6/F6 | K6: 其中：物业维修 | L6: 70 | M6: 34 | N6: 45 | O6: =L6-N6 | P6: =O6/N6
C7: 电梯运行 | D7: 12 | E7: 2 | F7: 0 | G7: =D7-F7 | H7: =G7/F7 | K7: 通用设施设备管理 | L7: 0 | M7: 0 | N7: 0 | O7: =L7-N7 | P7: =O7/N7
C8: 通用设施 | D8: 0 | E8: 0 | F8: 0 | G8: =D8-F8 | H8: =G8/F8 | K8: 空调运行管理费 | L8: 43 | M8: 13 | N8: 0 | O8: =L8-N8 | P8: =O8/N8
C9: 空调运行管理费 | D9: 43 | E9: 13 | F9: 0 | G9: =D9-F9 | H9: =G9/F9 | K9: 其他 | L9: =L5-L6-L7-L8 | M9: =M5-M6-M7-M8 | N9: =N5-N6-N7-N8 | O9: =L9-N9 | P9: =O9/N9
C10: 电站运行 | D10: 16 | E10: 9 | F10: 9 | G10: =D10-F10 | H10: =G10/F10
C11: 给排水锅炉 | D11: 18 | E11: 12 | F11: 4 | G11: =D11-F11 | H11: =G11/F11
C12: 后勤智能化 | D12: 8 | E12: 5 | F12: 0 | G12: =D12-F12 | H12: =G12/F12
C13: 污水处理站 | D13: 20 | E13: 11 | F13: 0 | G13: =D13-F13 | H13: =G13/F13
C14: 污水管线 | D14: 2 | E14: 0 | F14: 0 | G14: =D14-F14 | H14: =G14/F14
C15: 医用气体 | D15: 9 | E15: 5 | F15: 0 | G15: =D15-F15 | H15: =G15/F15
C16: 其他 | D16: =D5-D6-D7-D8-D9-D10-D11-D12-D13-D14-D15 | E16: =E5-E6-E7-E8-E9-E10-E11-E12-E13-E14-E15 | F16: =F5-F6-F7-F8-F9-F10-F11-F12-F13-F14-F15 | G16: =D16-F16 | H16: =G16/F16

Sheet 卫生材料
B2: 项 目 | C2: 46143 | D2: 其中 | E2: 45778 | F2: 增减额 | G2: 增减率
D3: 奉贤院区
B4: 卫生材料收入 | C4: =ROUND((当年累计数据表!AJ3+当年累计数据表!BS3)/10000,0) | D4: =ROUND((当年累计数据表奉贤!AJ3+当年累计数据表奉贤!BS3)/10000,0) | E4: =ROUND((去年累计数据表!AJ3+去年累计数据表!BS3)/10000,0) | F4: =C4-E4 | G4: =F4/E4
B5: 卫生材料费 | C5: =医疗成本!C7 | D5: =医疗成本!E7 | E5: =医疗成本!G7 | F5: =C5-E5 | G5: =F5/E5
B6: 其中：可收费 | C6: =C5-C7 | D6: =D5-D7 | E6: =E5-E7 | F6: =C6-E6 | G6: =F6/E6 | I6: 调整
B7: 不可收费 | C7: 3490 | D7: 714 | E7: 2764 | F7: =C7-E7 | G7: =F7/E7 | I7: 101
B8: 其中：检验试剂 | C8: 2558 | D8: 567 | E8: 1729 | F8: =C8-E8 | G8: =F8/E8
B9: 其他不可收费卫生材料 | C9: =C7-C8 | D9: =D7-D8 | E9: =E7-E8 | F9: =F7-F8 | G9: =F9/E9
B11: 项 目 | C11: 46143 | D11: 其中：奉贤院区 | E11: 45778 | F11: 增减额 | G11: 增减率
B12: 检验试剂成本 | C12: =C8 | D12: =D8 | E12: =E8 | F12: =F8 | G12: =G8
B13: 其中：医学检验科 | C13: 2059 | D13: 395 | E13: 1373 | F13: =C13-E13 | G13: =F13/E13
B14: 化验收入 | C14: =ROUND((当月附表2!B10+当月附表2!B23)/10000,0) | D14: =ROUND((当月奉贤附表2!B10+当月奉贤附表2!B23)/10000,0) | E14: =ROUND((上年同期附表2!B10+上年同期附表2!B23)/10000,0) | F14: =C14-E14 | G14: =F14/E14
B15: 成本收入比重 | C15: =C12/C14 | D15: =D12/D14 | E15: =E12/E14 | F15: =C15-E15 | G15: -
B16: 门急诊人次 | C16: =ROUND(当年累计数据表!G3/10000,2) | D16: =ROUND(当年累计数据表奉贤!G3/10000,2) | E16: =ROUND(去年累计数据表!G3/10000,2) | F16: =C16-E16 | G16: =F16/E16
B17: 住院人次 | C17: =ROUND(当年累计数据表!H3/10000,2) | D17: =ROUND(当年累计数据表奉贤!H3/10000,2) | E17: =ROUND(去年累计数据表!H3/10000,2) | F17: =C17-E17 | G17: =F17/E17

Sheet 当年累计数据表
A1: 日期范围：20260501-20260531 | D1: 25 | O1: 1=2+5=8+43 | P1: 2=3+4 | Q1: 3 | R1: 4 | S1: 5=6+7 | T1: 6 | U1: 7 | V1: 8=9+12=15+22+29+36 | W1: 9=10+11 | X1: 10 | Y1: 11 | Z1: 12=13+14 | AA1: 13 | AB1: 14 | AC1: 15=16+19 | AD1: 16=17+18 | AE1: 17 | AF1: 18 | AG1: 19=20+21 | AH1: 20 | AI1: 21 | AJ1: 22=23+26 | AK1: 23=24+25 | AL1: 24 | AM1: 25 | AN1: 26=27+28 | AO1: 27 | AP1: 28 | AQ1: 29=30+33 | AR1: 30=31+32 | AS1: 31 | AT1: 32 | AU1: 33=34+35 | AV1: 34 | AW1: 35 | AX1: 36=37+40 | AY1: 37=38+39 | AZ1: 38 | BA1: 39 | BB1: 40=41+42 | BC1: 41 | BD1: 42 | BE1: 43=50+57+64+71=44+47 | BF1: 44=45+46 | BG1: 45 | BH1: 46 | BI1: 47=48+49 | BJ1: 48 | BK1: 49 | BL1: 50=51+54 | BM1: 51=52+53 | BN1: 52 | BO1: 53 | BP1: 54=55+56 | BQ1: 55 | BR1: 56 | BS1: 57=58+61 | BT1: 58=59+60 | BU1: 59 | BV1: 60 | BW1: 61=62+63 | BX1: 62 | BY1: 63 | BZ1: 64=65+68 | CA1: 65=66+67 | CB1: 66 | CC1: 67 | CD1: 68=69+70 | CE1: 69 | CF1: 70 | CG1: 71=72+75 | CH1: 72=73+74 | CI1: 73 | CJ1: 74 | CK1: 75=76+77 | CL1: 76 | CM1: 77 | CV1: 78=85+93+100+108+86+101=79+82 | CW1: 79=80+81 | CX1: 80 | CY1: 81 | CZ1: 82=83+84 | DA1: 83 | DB1: 84 | DC1: 85=87+90=78-93-100-108-86-101 | DD1: 86 | DE1: 87=88+89 | DF1: 88 | DG1: 89 | DH1: 90=91+92 | DI1: 91 | DJ1: 92 | DK1: 93=94+97 | DL1: 94=95+96 | DM1: 95 | DN1: 96 | DO1: 97=98+99 | DP1: 98 | DQ1: 99 | DR1: 100=102+105 | DS1: 101 | DT1: 102=103+104 | DU1: 103 | DV1: 104 | DW1: 105=106+107 | DX1: 106 | DY1: 107 | DZ1: 108=109+112 | EA1: 109=110+111 | EB1: 110 | EC1: 111 | ED1: 112=113+114 | EE1: 113 | EF1: 114 | EG1: 115=116+119 | EH1: 116=117+118 | EI1: 117 | EJ1: 118 | EK1: 119=120+121 | EL1: 120 | EM1: 121 | EN1: 122=123+124+125 | EO1: 123 | EP1: 124 | EQ1: 125 | EU1: 126=127+128+129 | EV1: 127 | EW1: 128 | EX1: 129 | EY1: 130=131+132 | EZ1: 131 | FA1: 132 | FB1: 133
A2: 序号 | B2: 科室类别 | C2: 科室名称 | D2: 医疗收入不含药耗 | E2: 门急诊收入不含药耗 | F2: 住院收入不含药耗 | G2: 门急诊人次 | H2: 住院人次 | I2: 门急诊治疗收入 | J2: 门急诊手术收入 | K2: 门诊中药饮片收入 | L2: 住院治疗收入 | M2: 住院手术收入 | N2: 住院中药饮片收入 | O2: 医疗收入 | P2: 其中本地病人医疗收入 | Q2: 其中本地病人医保医疗收入 | R2: 其中本地病人自费医疗收入 | S2: 其中异地病人医疗收入 | T2: 其中异地病人医保医疗收入 | U2: 其中异地病人自费医疗收入 | V2: 门急诊收入 | W2: 其中本地病人医疗收入 | X2: 其中本地病人医保医疗收入 | Y2: 其中本地病人自费医疗收入 | Z2: 其中异地病人医疗收入 | AA2: 其中异地病人医保医疗收入 | AB2: 其中异地病人自费医疗收入 | AC2: 门急诊药品收入 | AD2: 其中本地病人医疗收入 | AE2: 其中本地病人医保医疗收入 | AF2: 其中本地病人自费医疗收入 | AG2: 其中异地病人医疗收入 | AH2: 其中异地病人医保医疗收入 | AI2: 其中异地病人自费医疗收入 | AJ2: 门急诊耗材收入 | AK2: 其中本地病人医疗收入 | AL2: 其中本地病人医保医疗收入 | AM2: 其中本地病人自费医疗收入 | AN2: 其中异地病人医疗收入 | AO2: 其中异地病人医保医疗收入 | AP2: 其中异地病人自费医疗收入 | AQ2: 门急诊检查化验收入 | AR2: 其中本地病人医疗收入 | AS2: 其中本地病人医保医疗收入 | AT2: 其中本地病人自费医疗收入 | AU2: 其中异地病人医疗收入 | AV2: 其中异地病人医保医疗收入 | AW2: 其中异地病人自费医疗收入 | AX2: 门急诊劳务收入 | AY2: 其中本地病人医疗收入 | AZ2: 其中本地病人医保医疗收入 | BA2: 其中本地病人自费医疗收入 | BB2: 其中异地病人医疗收入 | BC2: 其中异地病人医保医疗收入 | BD2: 其中异地病人自费医疗收入 | BE2: 住院收入 | BF2: 其中本地病人医疗收入 | BG2: 其中本地病人医保医疗收入 | BH2: 其中本地病人自费医疗收入 | BI2: 其中异地病人医疗收入 | BJ2: 其中异地病人医保医疗收入 | BK2: 其中异地病人自费医疗收入 | BL2: 住院药品收入 | BM2: 其中本地病人医疗收入 | BN2: 其中本地病人医保医疗收入 | BO2: 其中本地病人自费医疗收入 | BP2: 其中异地病人医疗收入 | BQ2: 其中异地病人医保医疗收入 | BR2: 其中异地病人自费医疗收入 | BS2: 住院耗材收入 | BT2: 其中本地病人医疗收入 | BU2: 其中本地病人医保医疗收入 | BV2: 其中本地病人自费医疗收入 | BW2: 其中异地病人医疗收入 | BX2: 其中异地病人医保医疗收入 | BY2: 其中异地病人自费医疗收入 | BZ2: 住院检查化验收入 | CA2: 其中本地病人医疗收入 | CB2: 其中本地病人医保医疗收入 | CC2: 其中本地病人自费医疗收入 | CD2: 其中异地病人医疗收入 | CE2: 其中异地病人医保医疗收入 | CF2: 其中异地病人自费医疗收入 | CG2: 住院劳务收入 | CH2: 其中本地病人医疗收入 | CI2: 其中本地病人医保医疗收入 | CJ2: 其中本地病人自费医疗收入 | CK2: 其中异地病人医疗收入 | CL2: 其中异地病人医保医疗收入 | CM2: 其中异地病人自费医疗收入 | CN2: 急诊收入 | CO2: 普通门诊收入 | CP2: 专家门诊收入 | CQ2: 专病门诊收入 | CR2: 特需门诊收入 | CS2: MDT门诊收入 | CT2: 镜朗诊疗部收入 | CU2: 特需病房收入 | CV2: 门急诊人次 | CW2: 其中本地病人人次 | CX2: 其中本地病人医保人次 | CY2: 其中本地病人自费人次 | CZ2: 其中异地病人人次 | DA2: 其中异地病人医保人次 | DB2: 其中异地病人自费人次 | DC2: 普通门诊 (普通+专病) | DD2: 互联网普通门诊人次 | DE2: 其中本地病人人次 | DF2: 其中本地病人医保人次 | DG2: 其中本地病人自费人次 | DH2: 其中异地病人人次 | DI2: 其中异地病人医保人次 | DJ2: 其中异地病人自费人次 | DK2: 专家门诊 | DL2: 其中本地病人人次 | DM2: 其中本地病人医保人次 | DN2: 其中本地病人自费人次 | DO2: 其中异地病人人次 | DP2: 其中异地病人医保人次 | DQ2: 其中异地病人自费人次 | DR2: 特需门诊 (特需+MDT) | DS2: 互联网特需门诊人次 | DT2: 其中本地病人人次 | DU2: 其中本地病人医保人次 | DV2: 其中本地病人自费人次 | DW2: 其中异地病人人次 | DX2: 其中异地病人医保人次 | DY2: 其中异地病人自费人次 | DZ2: 急诊人次 | EA2: 其中本地病人人次 | EB2: 其中本地病人医保人次 | EC2: 其中本地病人自费人次 | ED2: 其中异地病人人次 | EE2: 其中异地病人医保人次 | EF2: 其中异地病人自费人次 | EG2: 住院人次 | EH2: 其中本地病人人次 | EI2: 其中本地病人医保人次 | EJ2: 其中本地病人自费人次 | EK2: 其中异地病人人次 | EL2: 其中异地病人医保人次 | EM2: 其中异地病人自费人次 | EN2: 手术人次与操作人次 | EO2: 手术人次 | EP2: 介入人次 | EQ2: 操作人次(治疗+诊断) | ER2: 微创手术人次（手术） | ES2: 微创手术人次（介入） | ET2: 微创手术人次（操作） | EU2: 三级手术 | EV2: 三级手术(手术) | EW2: 三级手术(介入) | EX2: 三级手术(操作) | EY2: 四级手术 | EZ2: 四级手术(手术) | FA2: 四级手术(介入) | FB2: 重点病种人次
A3: 小计： | D3: 3.0476275e+08 | E3: 1.3394059e+08 | F3: 1.7082215e+08 | G3: 454375 | H3: 15504 | I3: 23830756 | J3: 6184160 | K3: 2586256.2 | L3: 16825765 | M3: 43941230 | N3: 45012.893 | O3: 6.3529023e+08 | P3: 4.2623201e+08 | Q3: 3.8965963e+08 | R3: 36572379 | S3: 2.0905823e+08 | T3: 1.8480133e+08 | U3: 24256892 | V3: 2.3200361e+08 | W3: 1.8996545e+08 | X3: 1.7410947e+08 | Y3: 15855974 | Z3: 42038161 | AA3: 22706819 | AB3: 19331342 | AC3: 89682950 | AD3: 78384687 | AE3: 75588660 | AF3: 2796026.4 | AG3: 11298263 | AH3: 8423575.2 | AI3: 2874688 | AJ3: 8380067.3 | AK3: 7318139 | AL3: 6502668.1 | AM3: 815470.86 | AN3: 1061928.4 | AO3: 674129.09 | AP3: 387799.29 | AQ3: 75571406 | AR3: 61913801 | AS3: 56450220 | AT3: 5463581.5 | AU3: 13657604 | AV3: 7242125 | AW3: 6415479.5 | AX3: 58369187 | AY3: 42348822 | AZ3: 35567927 | BA3: 6780895.2 | BB3: 16020365 | BC3: 6366989.5 | BD3: 9653375.3 | BE3: 4.0328662e+08 | BF3: 2.3626656e+08 | BG3: 2.1555015e+08 | BH3: 20716405 | BI3: 1.6702007e+08 | BJ3: 1.6209452e+08 | BK3: 4925549.6 | BL3: 62594215 | BM3: 32952610 | BN3: 30905034 | BO3: 2047575.8 | BP3: 29641606 | BQ3: 28710226 | BR3: 931379.52 | BS3: 1.6987025e+08 | BT3: 1.0297809e+08 | BU3: 96111702 | BV3: 6866390.2 | BW3: 66892163 | BX3: 65945066 | BY3: 947097.29 | BZ3: 70668172 | CA3: 43124066 | CB3: 39793004 | CC3: 3331061.3 | CD3: 27544107 | CE3: 26995138 | CF3: 548968.25 | CG3: 1.0015398e+08 | CH3: 57211792 | CI3: 48740414 | CJ3: 8471377.5 | CK3: 42942190 | CL3: 40444085 | CM3: 2498104.5 | CN3: 30495394 | CO3: 82165321 | CP3: 57649478 | CQ3: 31223223 | CR3: 30181622 | CS3: 287165.52 | CT3: 8248119.2 | CU3: 0 | CV3: 454375 | CW3: 388783 | CX3: 355506 | CY3: 33277 | CZ3: 65592 | DA3: 35080 | DB3: 30512 | DC3: 245641 | DD3: 5812 | DE3: 216653 | DF3: 201402 | DG3: 15251 | DH3: 28988 | DI3: 16639 | DJ3: 12349 | DK3: 100478 | DL3: 82051 | DM3: 75437 | DN3: 6614 | DO3: 18427 | DP3: 10589 | DQ3: 7838 | DR3: 38113 | DS3: 143 | DT3: 28296 | DU3: 23810 | DV3: 4486 | DW3: 9817 | DX3: 3878 | DY3: 5939 | DZ3: 64188 | EA3: 56960 | EB3: 51037 | EC3: 5923 | ED3: 7228 | EE3: 3920 | EF3: 3308 | EG3: 15504 | EH3: 9790 | EI3: 8851 | EJ3: 939 | EK3: 5714 | EL3: 5439 | EM3: 275 | EN3: 12341 | EO3: 6537 | EP3: 892 | EQ3: 4912 | ER3: 1693 | ES3: 0 | ET3: 104 | EU3: 3260 | EV3: 2655 | EW3: 450 | EX3: 155 | EY3: 2174 | EZ3: 1920 | FA3: 254 | FB3: 4850
A4: 1 | B4: 成人非手术 | C4: 内科 | D4: 190440 | E4: 190440 | F4: 0 | G4: 986 | H4: 0 | I4: 166 | J4: 0 | K4: 0 | L4: 0 | M4: 0 | N4: 0 | O4: 460164.38 | P4: 431894.92 | Q4: 411754.28 | R4: 20140.64 | S4: 28269.46 | T4: 23236.39 | U4: 5033.07 | V4: 460164.38 | W4: 431894.92 | X4: 411754.28 | Y4: 20140.64 | Z4: 28269.46 | AA4: 23236.39 | AB4: 5033.07 | AC4: 268433.31 | AD4: 255132.85 | AE4: 250892.41 | AF4: 4240.44 | AG4: 13300.46 | AH4: 11166.39 | AI4: 2134.07 | AJ4: 1291.07 | AK4: 1167.07 | AL4: 992.87 | AM4: 174.2 | AN4: 124 | AO4: 43 | AP4: 81 | AQ4: 158181 | AR4: 145137 | AS4: 135482 | AT4: 9655 | AU4: 13044 | AV4: 10606 | AW4: 2438 | AX4: 32259 | AY4: 30458 | AZ4: 24387 | BA4: 6071 | BB4: 1801 | BC4: 1421 | BD4: 380 | BE4: 0 | BF4: 0 | BG4: 0 | BH4: 0 | BI4: 0 | BJ4: 0 | BK4: 0 | BL4: 0 | BM4: 0 | BN4: 0 | BO4: 0 | BP4: 0 | BQ4: 0 | BR4: 0 | BS4: 0 | BT4: 0 | BU4: 0 | BV4: 0 | BW4: 0 | BX4: 0 | BY4: 0 | BZ4: 0 | CA4: 0 | CB4: 0 | CC4: 0 | CD4: 0 | CE4: 0 | CF4: 0 | CG4: 0 | CH4: 0 | CI4: 0 | CJ4: 0 | CK4: 0 | CL4: 0 | CM4: 0 | CN4: 0 | CO4: 243161.06 | CP4: 106247.51 | CQ4: 89883.11 | CR4: 20872.7 | CS4: 0 | CT4: 0 | CU4: 0 | CV4: 986 | CW4: 905 | CX4: 871 | CY4: 34 | CZ4: 81 | DA4: 51 | DB4: 30 | DC4: 744 | DD4: 60 | DE4: 690 | DF4: 678 | DG4: 12 | DH4: 54 | DI4: 42 | DJ4: 12 | DK4: 164 | DL4: 154 | DM4: 151 | DN4: 3 | DO4: 10 | DP4: 8 | DQ4: 2 | DR4: 18 | DS4: 0 | DT4: 17 | DU4: 6 | DV4: 11 | DW4: 1 | DX4: 1 | DY4: 0 | DZ4: 0 | EA4: 0 | EB4: 0 | EC4: 0 | ED4: 0 | EE4: 0 | EF4: 0 | EG4: 0 | EH4: 0 | EI4: 0 | EJ4: 0 | EK4: 0 | EL4: 0 | EM4: 0 | EN4: 0 | EO4: 0 | EP4: 0 | EQ4: 0 | ER4: 0 | ES4: 0 | ET4: 0 | EU4: 0 | EV4: 0 | EW4: 0 | EX4: 0 | EY4: 0 | EZ4: 0 | FA4: 0 | FB4: 0
A5: 2 | B5: 成人非手术 | C5: 呼吸内科 | D5: 5468271.5 | E5: 2160548 | F5: 3307723.5 | G5: 10165 | H5: 329 | I5: 13988 | J5: 0 | K5: 0 | L5: 184144 | M5: 3028 | N5: 357 | O5: 10135078 | P5: 7341275.5 | Q5: 7170240 | R5: 171035.42 | S5: 2793802.4 | T5: 2629179.5 | U5: 164622.94 | V5: 4323553.8 | W5: 3800574.6 | X5: 3693507.8 | Y5: 107066.81 | Z5: 522979.17 | AA5: 376311.66 | AB5: 146667.51 | AC5: 2094052.2 | AD5: 1820730.2 | AE5: 1785224.4 | AF5: 35505.81 | AG5: 273321.98 | AH5: 206927.47 | AI5: 66394.51 | AJ5: 68953.58 | AK5: 61664.39 | AL5: 59755.39 | AM5: 1909 | AN5: 7289.19 | AO5: 5025.19 | AP5: 2264 | AQ5: 1793278 | AR5: 1596099 | AS5: 1540079 | AT5: 56020 | AU5: 197179 | AV5: 132375 | AW5: 64804 | AX5: 367270 | AY5: 322081 | AZ5: 308449 | BA5: 13632 | BB5: 45189 | BC5: 31984 | BD5: 13205 | BE5: 5811524.1 | BF5: 3540700.8 | BG5: 3476732.2 | BH5: 63968.61 | BI5: 2270823.2 | BJ5: 2252867.8 | BK5: 17955.43 | BL5: 2295779.5 | BM5: 1357648.3 | BN5: 1338779.2 | BO5: 18869.13 | BP5: 938131.13 | BQ5: 933832.06 | BR5: 4299.07 | BS5: 208021.12 | BT5: 126593 | BU5: 124679.02 | BV5: 1913.98 | BW5: 81428.12 | BX5: 80860.76 | BY5: 567.36 | BZ5: 2631940 | CA5: 1639312 | CB5: 1607724 | CC5: 31588 | CD5: 992628 | CE5: 982412 | CF5: 10216 | CG5: 675783.5 | CH5: 417147.5 | CI5: 405550 | CJ5: 11597.5 | CK5: 258636 | CL5: 255763 | CM5: 2873 | CN5: -75 | CO5: 2687317 | CP5: 1324630 | CQ5: 82831.97 | CR5: 228774.86 | CS5: 0 | CT5: 0 | CU5: 0 | CV5: 10165 | CW5: 9019 | CX5: 8712 | CY5: 307 | CZ5: 1146 | DA5: 796 | DB5: 350 | DC5: 7596 | DD5: 67 | DE5: 6812 | DF5: 6598 | DG5: 214 | DH5: 784 | DI5: 538 | DJ5: 246 | DK5: 2223 | DL5: 1908 | DM5: 1835 | DN5: 73 | DO5: 315 | DP5: 225 | DQ5: 90 | DR5: 277 | DS5: 2 | DT5: 234 | DU5: 215 | DV5: 19 | DW5: 43 | DX5: 33 | DY5: 10 | DZ5: 0 | EA5: 0 | EB5: 0 | EC5: 0 | ED5: 0 | EE5: 0 | EF5: 0 | EG5: 329 | EH5: 211 | EI5: 208 | EJ5: 3 | EK5: 118 | EL5: 117 | EM5: 1 | EN5: 208 | EO5: 1 | EP5: 0 | EQ5: 207 | ER5: 0 | ES5: 0 | ET5: 0 | EU5: 0 | EV5: 0 | EW5: 0 | EX5: 0 | EY5: 0 | EZ5: 0 | FA5: 0 | FB5: 96
A6: 3 | B6: 成人非手术 | C6: 消化内科（内窥镜诊治部） | D6: 10993209 | E6: 6703879 | F6: 4289330.3 | G6: 21193 | H6: 715 | I6: 462650 | J6: 11400 | K6: 0 | L6: 388024.5 | M6: 530013 | N6: 1270.5 | O6: 19743331 | P6: 15905375 | Q6: 15202208 | R6: 703167.44 | S6: 3837955.5 | T6: 3325493.6 | U6: 512461.95 | V6: 11740377 | W6: 10223424 | X6: 9655598.4 | Y6: 567825.92 | Z6: 1516952.3 | AA6: 1030491 | AB6: 486461.38 | AC6: 4352330.7 | AD6: 3847348.4 | AE6: 3737102.5 | AF6: 110245.92 | AG6: 504982.34 | AH6: 361485.96 | AI6: 143496.38 | AJ6: 684167 | AK6: 590578 | AL6: 567458 | AM6: 23120 | AN6: 93589 | AO6: 74826 | AP6: 18763 | AQ6: 4818752 | AR6: 4187500 | AS6: 4021101 | AT6: 166399 | AU6: 631252 | AV6: 439240 | AW6: 192012 | AX6: 1885127 | AY6: 1597998 | AZ6: 1329937 | BA6: 268061 | BB6: 287129 | BC6: 154939 | BD6: 132190 | BE6: 8002954 | BF6: 5681950.8 | BG6: 5546609.3 | BH6: 135341.52 | BI6: 2321003.2 | BJ6: 2295002.6 | BK6: 26000.57 | BL6: 1456545.6 | BM6: 1018119 | BN6: 996355.35 | BO6: 21763.65 | BP6: 438426.6 | BQ6: 433303.66 | BR6: 5122.94 | BS6: 2257078.1 | BT6: 1630048 | BU6: 1604531.4 | BV6: 25516.57 | BW6: 627030.1 | BX6: 626054.97 | BY6: 975.13 | BZ6: 2695778.8 | CA6: 1867159.8 | CB6: 1816779 | CC6: 50380.8 | CD6: 828619 | CE6: 814964 | CF6: 13655 | CG6: 1593551.5 | CH6: 1166624 | CI6: 1128943.5 | CJ6: 37680.5 | CK6: 426927.5 | CL6: 420680 | CM6: 6247.5 | CN6: -50 | CO6: 5691556 | CP6: 2812994.7 | CQ6: 1761913.4 | CR6: 1473912.6 | CS6: 0 | CT6: 39371.86 | CU6: 0 | CV6: 21193 | CW6: 18498 | CX6: 17574 | CY6: 924 | CZ6: 2695 | DA6: 1790 | DB6: 905 | DC6: 14414 | DD6: 248 | DE6: 12695 | DF6: 12224 | DG6: 471 | DH6: 1719 | DI6: 1139 | DJ6: 580 | DK6: 5374 | DL6: 4624 | DM6: 4420 | DN6: 204 | DO6: 750 | DP6: 552 | DQ6: 198 | DR6: 1157 | DS6: 0 | DT6: 946 | DU6: 705 | DV6: 241 | DW6: 211 | DX6: 94 | DY6: 117 | DZ6: 0 | EA6: 0 | EB6: 0 | EC6: 0 | ED6: 0 | EE6: 0 | EF6: 0 | EG6: 715 | EH6: 513 | EI6: 501 | EJ6: 12 | EK6: 202 | EL6: 200 | EM6: 2 | EN6: 824 | EO6: 2 | EP6: 0 | EQ6: 822 | ER6: 0 | ES6: 0 | ET6: 99 | EU6: 78 | EV6: 1 | EW6: 0 | EX6: 77 | EY6: 0 | EZ6: 0 | FA6: 0 | FB6: 54
A7: 4 | B7: 成人非手术 | C7: 神经内科 | D7: 6279402.5 | E7: 3160499.5 | F7: 3118903 | G7: 13784 | H7: 301 | I7: 1076 | J7: 0 | K7: 77841.38 | L7: 180154 | M7: 74721 | N7: 803.6 | O7: 14467950 | P7: 11696477 | Q7: 11441253 | R7: 255224.24 | S7: 2771473 | T7: 2559079.8 | U7: 212393.27 | V7: 6854147.3 | W7: 6063633.2 | X7: 5827974.5 | Y7: 235658.68 | Z7: 790514.12 | AA7: 578120.85 | AB7: 212393.27 | AC7: 3683703.5 | AD7: 3338045 | AE7: 3243302 | AF7: 94743.04 | AG7: 345658.48 | AH7: 264417.21 | AI7: 81241.27 | AJ7: 9944.36 | AK7: 7888.72 | AL7: 7510.08 | AM7: 378.64 | AN7: 2055.64 | AO7: 1711.64 | AP7: 344 | AQ7: 2599627 | AR7: 2243434 | AS7: 2131853 | AT7: 111581 | AU7: 356193 | AV7: 254445 | AW7: 101748 | AX7: 560872.5 | AY7: 474265.5 | AZ7: 445309.5 | BA7: 28956 | BB7: 86607 | BC7: 57547 | BD7: 29060 | BE7: 7613802.7 | BF7: 5632843.8 | BG7: 5613278.2 | BH7: 19565.56 | BI7: 1980958.9 | BJ7: 1980958.9 | BK7: 0 | BL7: 1333451.4 | BM7: 1050578.6 | BN7: 1044611.9 | BO7: 5966.7 | BP7: 282872.86 | BQ7: 282872.86 | BR7: 0 | BS7: 3161448.3 | BT7: 2145121.7 | BU7: 2144832.3 | BV7: 289.36 | BW7: 1016326.6 | BX7: 1016326.6 | BY7: 0 | BZ7: 2213935 | CA7: 1701049 | CB7: 1689618 | CC7: 11431 | CD7: 512886 | CE7: 512886 | CF7: 0 | CG7: 904968 | CH7: 736094.5 | CI7: 734216 | CJ7: 1878.5 | CK7: 168873.5 | CL7: 168873.5 | CM7: 0 | CN7: 0 | CO7: 3345242.9 | CP7: 1429690.2 | CQ7: 1166977.8 | CR7: 912236.48 | CS7: 0 | CT7: 0 | CU7: 0 | CV7: 13784 | CW7: 12289 | CX7: 11790 | CY7: 499 | CZ7: 1495 | DA7: 1013 | DB7: 482 | DC7: 10314 | DD7: 261 | DE7: 9378 | DF7: 9062 | DG7: 316 | DH7: 936 | DI7: 627 | DJ7: 309 | DK7: 2305 | DL7: 1979 | DM7: 1884 | DN7: 95 | DO7: 326 | DP7: 249 | DQ7: 77 | DR7: 904 | DS7: 0 | DT7: 697 | DU7: 622 | DV7: 75 | DW7: 207 | DX7: 134 | DY7: 73 | DZ7: 0 | EA7: 0 | EB7: 0 | EC7: 0 | ED7: 0 | EE7: 0 | EF7: 0 | EG7: 301 | EH7: 237 | EI7: 234 | EJ7: 3 | EK7: 64 | EL7: 64 | EM7: 0 | EN7: 105 | EO7: 0 | EP7: 36 | EQ7: 69 | ER7: 0 | ES7: 0 | ET7: 0 | EU7: 6 | EV7: 0 | EW7: 6 | EX7: 0 | EY7: 30 | EZ7: 0 | FA7: 30 | FB7: 99
A8: 5 | B8: 成人非手术 | C8: 心血管内科 | D8: 16364810 | E8: 3955095 | F8: 12409715 | G8: 32529 | H8: 1186 | I8: 4676 | J8: 0 | K8: 0 | L8: 164607.75 | M8: 2580951.5 | N8: 97.5 | O8: 63680331 | P8: 47547833 | Q8: 47147948 | R8: 399884.99 | S8: 16132498 | T8: 15840886 | U8: 291612.16 | V8: 13771868 | W8: 12665014 | X8: 12484549 | Y8: 180465.6 | Z8: 1106854.2 | AA8: 886645.26 | AB8: 220208.9 | AC8: 9775565.7 | AD8: 9123385.5 | AE8: 9040423.9 | AF8: 82961.6 | AG8: 652180.16 | AH8: 556948.26 | AI8: 95231.9 | AJ8: 41207.8 | AK8: 35412.8 | AL8: 33993.8 | AM8: 1419 | AN8: 5795 | AO8: 3602 | AP8: 2193 | AQ8: 2837491 | AR8: 2511157 | AS8: 2440701 | AT8: 70456 | AU8: 326334 | AV8: 237803 | AW8: 88531 | AX8: 1117604 | AY8: 995059 | AZ8: 969430 | BA8: 25629 | BB8: 122545 | BC8: 88292 | BD8: 34253 | BE8: 49908462 | BF8: 34882818 | BG8: 34663399 | BH8: 219419.39 | BI8: 15025644 | BJ8: 14954241 | BK8: 71403.26 | BL8: 2436157.6 | BM8: 1790204.6 | BN8: 1777009.4 | BO8: 13195.19 | BP8: 645952.93 | BQ8: 640716.81 | BR8: 5236.12 | BS8: 35062590 | BT8: 24126042 | BU8: 24022986 | BV8: 103055.7 | BW8: 10936548 | BX8: 10895294 | BY8: 41254.64 | BZ8: 7930500 | CA8: 5767731 | CB8: 5705519 | CC8: 62212 | CD8: 2162769 | CE8: 2151102 | CF8: 11667 | CG8: 4479214.8 | CH8: 3198841 | CI8: 3157884.5 | CJ8: 40956.5 | CK8: 1280373.8 | CL8: 1267128.2 | CM8: 13245.5 | CN8: -25 | CO8: 6409354.3 | CP8: 4847064.3 | CQ8: 2127559.4 | CR8: 387890.44 | CS8: 0 | CT8: 41859.82 | CU8: 0 | CV8: 32529 | CW8: 29584 | CX8: 28994 | CY8: 590 | CZ8: 2945 | DA8: 2260 | DB8: 685 | DC8: 21990 | DD8: 499 | DE8: 20170 | DF8: 19849 | DG8: 321 | DH8: 1820 | DI8: 1405 | DJ8: 415 | DK8: 9567 | DL8: 8568 | DM8: 8324 | DN8: 244 | DO8: 999 | DP8: 784 | DQ8: 215 | DR8: 473 | DS8: 0 | DT8: 372 | DU8: 355 | DV8: 17 | DW8: 101 | DX8: 62 | DY8: 39 | DZ8: 0 | EA8: 0 | EB8: 0 | EC8: 0 | ED8: 0 | EE8: 0 | EF8: 0 | EG8: 1186 | EH8: 869 | EI8: 858 | EJ8: 11 | EK8: 317 | EL8: 315 | EM8: 2 | EN8: 1030 | EO8: 167 | EP8: 473 | EQ8: 390 | ER8: 0 | ES8: 0 | ET8: 0 | EU8: 467 | EV8: 163 | EW8: 304 | EX8: 0 | EY8: 25 | EZ8: 3 | FA8: 22 | FB8: 230
A9: 6 | B9: 成人非手术 | C9: 血液内科 | D9: 2250983.5 | E9: 259051 | F9: 1991932.5 | G9: 1387 | H9: 439 | I9: 1032 | J9: 0 | K9: 0 | L9: 208692 | M9: 2192 | N9: 259.56 | O9: 9333747.5 | P9: 3939958.8 | Q9: 3884466.5 | R9: 55492.33 | S9: 5393788.7 | T9: 5374452.2 | U9: 19336.45 | V9: 1110257.2 | W9: 909956.16 | X9: 891440.76 | Y9: 18515.4 | Z9: 200301.06 | AA9: 180964.61 | AB9: 19336.45 | AC9: 844297.92 | AD9: 712643.86 | AE9: 703246.46 | AF9: 9397.4 | AG9: 131654.06 | AH9: 122454.61 | AI9: 9199.45 | AJ9: 6908.3 | AK9: 6822.3 | AL9: 6672.3 | AM9: 150 | AN9: 86 | AO9: 43 | AP9: 43 | AQ9: 206794 | AR9: 150243 | AS9: 143449 | AT9: 6794 | AU9: 56551 | AV9: 49294 | AW9: 7257 | AX9: 52257 | AY9: 40247 | AZ9: 38073 | BA9: 2174 | BB9: 12010 | BC9: 9173 | BD9: 2837 | BE9: 8223490.3 | BF9: 3030002.7 | BG9: 2993025.7 | BH9: 36976.93 | BI9: 5193487.6 | BJ9: 5193487.6 | BK9: 0 | BL9: 5859374.7 | BM9: 2237778.1 | BN9: 2228668 | BO9: 9110.1 | BP9: 3621596.6 | BQ9: 3621596.6 | BR9: 0 | BS9: 372183.07 | BT9: 71265.03 | BU9: 70062.2 | BV9: 1202.83 | BW9: 300918.04 | BX9: 300918.04 | BY9: 0 | BZ9: 1271761 | CA9: 542160 | CB9: 534104 | CC9: 8056 | CD9: 729601 | CE9: 729601 | CF9: 0 | CG9: 720171.5 | CH9: 178799.5 | CI9: 160191.5 | CJ9: 18608 | CK9: 541372 | CL9: 541372 | CM9: 0 | CN9: 0 | CO9: 279437.79 | CP9: 684566.74 | CQ9: 125257.87 | CR9: 20994.82 | CS9: 0 | CT9: 30270.71 | CU9: 0 | CV9: 1387 | CW9: 1079 | CX9: 1023 | CY9: 56 | CZ9: 308 | DA9: 256 | DB9: 52 | DC9: 871 | DD9: 0 | DE9: 667 | DF9: 633 | DG9: 34 | DH9: 204 | DI9: 173 | DJ9: 31 | DK9: 496 | DL9: 400 | DM9: 379 | DN9: 21 | DO9: 96 | DP9: 80 | DQ9: 16 | DR9: 20 | DS9: 0 | DT9: 12 | DU9: 11 | DV9: 1 | DW9: 8 | DX9: 3 | DY9: 5 | DZ9: 0 | EA9: 0 | EB9: 0 | EC9: 0 | ED9: 0 | EE9: 0 | EF9: 0 | EG9: 439 | EH9: 204 | EI9: 201 | EJ9: 3 | EK9: 235 | EL9: 235 | EM9: 0 | EN9: 307 | EO9: 0 | EP9: 0 | EQ9: 307 | ER9: 0 | ES9: 0 | ET9: 0 | EU9: 0 | EV9: 0 | EW9: 0 | EX9: 0 | EY9: 0 | EZ9: 0 | FA9: 0 | FB9: 24
A10: 7 | B10: 成人非手术 | C10: 肾脏风湿免疫科 | D10: 7311864.5 | E10: 5303081 | F10: 2008783.5 | G10: 8053 | H10: 245 | I10: 3658168 | J10: 0 | K10: 0 | L10: 146264.5 | M10: 21182 | N10: 0 | O10: 13207228 | P10: 11580471 | Q10: 11427629 | R10: 152842.34 | S10: 1626757.1 | T10: 1511943.7 | U10: 114813.42 | V10: 10061749 | W10: 9272025 | X10: 9153032.5 | Y10: 118992.46 | Z10: 789723.67 | AA10: 674910.25 | AB10: 114813.42 | AC10: 3755767.8 | AD10: 3441433 | AE10: 3393696.9 | AF10: 47736.15 | AG10: 314334.84 | AH10: 257902.96 | AI10: 56431.88 | AJ10: 1002899.8 | AK10: 958189.96 | AL10: 946484.65 | AM10: 11705.31 | AN10: 44709.83 | AO10: 42378.29 | AP10: 2331.54 | AQ10: 1366987 | AR10: 1214980 | AS10: 1187139 | AT10: 27841 | AU10: 152007 | AV10: 112391 | AW10: 39616 | AX10: 3936094 | AY10: 3657422 | AZ10: 3625712 | BA10: 31710 | BB10: 278672 | BC10: 262238 | BD10: 16434 | BE10: 3145479.4 | BF10: 2308446 | BG10: 2274596.1 | BH10: 33849.88 | BI10: 837033.45 | BJ10: 837033.45 | BK10: 0 | BL10: 895729.92 | BM10: 649457.36 | BN10: 638053.76 | BO10: 11403.6 | BP10: 246272.56 | BQ10: 246272.56 | BR10: 0 | BS10: 240966.01 | BT10: 194514.62 | BU10: 194336.34 | BV10: 178.28 | BW10: 46451.39 | BX10: 46451.39 | BY10: 0 | BZ10: 1492599 | CA10: 1087092 | CB10: 1067239 | CC10: 19853 | CD10: 405507 | CE10: 405507 | CF10: 0 | CG10: 516184.5 | CH10: 377382 | CI10: 374967 | CJ10: 2415 | CK10: 138802.5 | CL10: 138802.5 | CM10: 0 | CN10: 0 | CO10: 1453184.4 | CP10: 1434535.5 | CQ10: 6971380 | CR10: 202648.74 | CS10: 0 | CT10: 0 | CU10: 0 | CV10: 8053 | CW10: 7209 | CX10: 7008 | CY10: 201 | CZ10: 844 | DA10: 620 | DB10: 224 | DC10: 5939 | DD10: 111 | DE10: 5379 | DF10: 5240 | DG10: 139 | DH10: 560 | DI10: 419 | DJ10: 141 | DK10: 1865 | DL10: 1622 | DM10: 1566 | DN10: 56 | DO10: 243 | DP10: 177 | DQ10: 66 | DR10: 138 | DS10: 0 | DT10: 106 | DU10: 102 | DV10: 4 | DW10: 32 | DX10: 22 | DY10: 10 | DZ10: 0 | EA10: 0 | EB10: 0 | EC10: 0 | ED10: 0 | EE10: 0 | EF10: 0 | EG10: 245 | EH10: 181 | EI10: 176 | EJ10: 5 | EK10: 64 | EL10: 64 | EM10: 0 | EN10: 61 | EO10: 10 | EP10: 0 | EQ10: 51 | ER10: 0 | ES10: 0 | ET10: 0 | EU10: 0 | EV10: 0 | EW10: 0 | EX10: 0 | EY10: 0 | EZ10: 0 | FA10: 0 | FB10: 136
A11: 8 | B11: 成人非手术 | C11: 内分泌科 | D11: 6100953.5 | E11: 4175385 | F11: 1925568.5 | G11: 17407 | H11: 202 | I11: 6970 | J11: 574 | K11: 0 | L11: 195804 | M11: 9748 | N11: 0 | O11: 10521720 | P11: 9372690.9 | Q11: 9180521.3 | R11: 192169.6 | S11: 1149029.6 | T11: 1003175.6 | U11: 145853.95 | V11: 8078531.8 | W11: 7419690.1 | X11: 7227520.5 | Y11: 192169.6 | Z11: 658841.76 | AA11: 512987.81 | AB11: 145853.95 | AC11: 3827825.4 | AD11: 3554399.7 | AE11: 3493726.5 | AF11: 60673.2 | AG11: 273425.76 | AH11: 230946.21 | AI11: 42479.55 | AJ11: 75321.4 | AK11: 70635.4 | AL11: 69579 | AM11: 1056.4 | AN11: 4686 | AO11: 3397.6 | AP11: 1288.4 | AQ11: 3534589 | AR11: 3221056 | AS11: 3116399 | AT11: 104657 | AU11: 313533 | AV11: 232478 | AW11: 81055 | AX11: 640796 | AY11: 573599 | AZ11: 547816 | BA11: 25783 | BB11: 67197 | BC11: 46166 | BD11: 21031 | BE11: 2443188.6 | BF11: 1953000.8 | BG11: 1953000.8 | BH11: 0 | BI11: 490187.79 | BJ11: 490187.79 | BK11: 0 | BL11: 468706.79 | BM11: 377179.47 | BN11: 377179.47 | BO11: 0 | BP11: 91527.32 | BQ11: 91527.32 | BR11: 0 | BS11: 48913.3 | BT11: 36926.83 | BU11: 36926.83 | BV11: 0 | BW11: 11986.47 | BX11: 11986.47 | BY11: 0 | BZ11: 1483750 | CA11: 1185820 | CB11: 1185820 | CC11: 0 | CD11: 297930 | CE11: 297930 | CF11: 0 | CG11: 441818.5 | CH11: 353074.5 | CI11: 353074.5 | CJ11: 0 | CK11: 88744 | CL11: 88744 | CM11: 0 | CN11: -25 | CO11: 4264574.2 | CP11: 2549082.9 | CQ11: 850924.02 | CR11: 413950.7 | CS11: 0 | CT11: 0 | CU11: 0 | CV11: 17407 | CW11: 15835 | CX11: 15360 | CY11: 475 | CZ11: 1572 | DA11: 1188 | DB11: 384 | DC11: 11767 | DD11: 200 | DE11: 10743 | DF11: 10446 | DG11: 297 | DH11: 1024 | DI11: 796 | DJ11: 228 | DK11: 4895 | DL11: 4446 | DM11: 4306 | DN11: 140 | DO11: 449 | DP11: 341 | DQ11: 108 | DR11: 537 | DS11: 8 | DT11: 450 | DU11: 413 | DV11: 37 | DW11: 87 | DX11: 51 | DY11: 36 | DZ11: 0 | EA11: 0 | EB11: 0 | EC11: 0 | ED11: 0 | EE11: 0 | EF11: 0 | EG11: 202 | EH11: 161 | EI11: 160 | EJ11: 1 | EK11: 41 | EL11: 41 | EM11: 0 | EN11: 2 | EO11: 0 | EP11: 0 | EQ11: 2 | ER11: 0 | ES11: 0 | ET11: 0 | EU11: 0 | EV11: 0 | EW11: 0 | EX11: 0 | EY11: 0 | EZ11: 0 | FA11: 0 | FB11: 179
A12: 9 | B12: 成人非手术 | C12: 老年医学科 | D12: 3963449.5 | E12: 224416 | F12: 3739033.5 | G12: 2025 | H12: 80 | I12: 7430 | J12: 0 | K12: 42064.32 | L12: 632551 | M12: 16102 | N12: 15516.45 | O12: 6922375.9 | P12: 6905819.2 | Q12: 6690594.7 | R12: 215224.59 | S12: 16556.7 | T12: 13724.2 | U12: 2832.5 | V12: 1229141.9 | W12: 1212585.2 | X12: 1209281.5 | Y12: 3303.74 | Z12: 16556.7 | AA12: 13724.2 | AB12: 2832.5 | AC12: 998788.75 | AD12: 988078.05 | AE12: 986143.31 | AF12: 1934.74 | AG12: 10710.7 | AH12: 9105.2 | AI12: 1605.5 | AJ12: 5937.18 | AK12: 5851.18 | AL12: 5808.18 | AM12: 43 | AN12: 86 | AO12: 86 | AP12: 0 | AQ12: 164644 | AR12: 159740 | AS12: 158756 | AT12: 984 | AU12: 4904 | AV12: 3838 | AW12: 1066 | AX12: 59772 | AY12: 58916 | AZ12: 58574 | BA12: 342 | BB12: 856 | BC12: 695 | BD12: 161 | BE12: 5693234 | BF12: 5693234 | BG12: 5481313.2 | BH12: 211920.85 | BI12: 0 | BJ12: 0 | BK12: 0 | BL12: 1796818.9 | BM12: 1796818.9 | BN12: 1723381.6 | BO12: 73437.3 | BP12: 0 | BQ12: 0 | BR12: 0 | BS12: 157381.63 | BT12: 157381.63 | BU12: 149127.58 | BV12: 8254.05 | BW12: 0 | BX12: 0 | BY12: 0 | BZ12: 1793588 | CA12: 1793588 | CB12: 1725237 | CC12: 68351 | CD12: 0 | CE12: 0 | CF12: 0 | CG12: 1945445.5 | CH12: 1945445.5 | CI12: 1883567 | CJ12: 61878.5 | CK12: 0 | CL12: 0 | CM12: 0 | CN12: 0 | CO12: 1225927.9 | CP12: 0 | CQ12: 25 | CR12: 3189 | CS12: 0 | CT12: 0 | CU12: 0 | CV12: 2025 | CW12: 1998 | CX12: 1989 | CY12: 9 | CZ12: 27 | DA12: 25 | DB12: 2 | DC12: 2023 | DD12: 0 | DE12: 1997 | DF12: 1989 | DG12: 8 | DH12: 26 | DI12: 25 | DJ12: 1 | DK12: 0 | DL12: 0 | DM12: 0 | DN12: 0 | DO12: 0 | DP12: 0 | DQ12: 0 | DR12: 2 | DS12: 0 | DT12: 1 | DU12: 0 | DV12: 1 | DW12: 1 | DX12: 0 | DY12: 1 | DZ12: 0 | EA12: 0 | EB12: 0 | EC12: 0 | ED12: 0 | EE12: 0 | EF12: 0 | EG12: 80 | EH12: 80 | EI12: 79 | EJ12: 1 | EK12: 0 | EL12: 0 | EM12: 0 | EN12: 45 | EO12: 0 | EP12: 0 | EQ12: 45 | ER12: 0 | ES12: 0 | ET12: 0 | EU12: 0 | EV12: 0 | EW12: 0 | EX12: 0 | EY12: 0 | EZ12: 0 | FA12: 0 | FB12: 0
A13: 10 | B13: 成人非手术 | C13: 全科医学科 | D13: 2436244.2 | E13: 622677 | F13: 1813567.2 | G13: 3280 | H13: 112 | I13: 442 | J13: 0 | K13: 0 | L13: 86412.25 | M13: 46645 | N13: 129.15 | O13: 3556463.9 | P13: 2615182.3 | Q13: 2571299.6 | R13: 43882.75 | S13: 941281.55 | T13: 860156.36 | U13: 81125.19 | V13: 1337199.9 | W13: 1235124.2 | X13: 1215734.4 | Y13: 19389.86 | Z13: 102075.63 | AA13: 91752.81 | AB13: 10322.82 | AC13: 712973.85 | AD13: 675293.22 | AE13: 669067.36 | AF13: 6225.86 | AG13: 37680.63 | AH13: 36408.81 | AI13: 1271.82 | AJ13: 1549 | AK13: 1337 | AL13: 1294 | AM13: 43 | AN13: 212 | AO13: 212 | AP13: 0 | AQ13: 533811 | AR13: 477066 | AS13: 465421 | AT13: 11645 | AU13: 56745 | AV13: 48884 | AW13: 7861 | AX13: 88866 | AY13: 81428 | AZ13: 79952 | BA13: 1476 | BB13: 7438 | BC13: 6248 | BD13: 1190 | BE13: 2219264 | BF13: 1380058.1 | BG13: 1355565.2 | BH13: 24492.89 | BI13: 839205.92 | BJ13: 768403.55 | BK13: 70802.37 | BL13: 269274.98 | BM13: 189565.57 | BN13: 186354 | BO13: 3211.57 | BP13: 79709.41 | BQ13: 71308.74 | BR13: 8400.67 | BS13: 136421.79 | BT13: 76839.28 | BU13: 76330.96 | BV13: 508.32 | BW13: 59582.51 | BX13: 58132.31 | BY13: 1450.2 | BZ13: 740337 | CA13: 378704 | CB13: 376162 | CC13: 2542 | CD13: 361633 | CE13: 345654 | CF13: 15979 | CG13: 1073230.2 | CH13: 734949.25 | CI13: 716718.25 | CJ13: 18231 | CK13: 338281 | CL13: 293308.5 | CM13: 44972.5 | CN13: 0 | CO13: 1144695.1 | CP13: 162070.64 | CQ13: 5149.07 | CR13: 25285.01 | CS13: 0 | CT13: 0 | CU13: 0 | CV13: 3280 | CW13: 3003 | CX13: 2942 | CY13: 61 | CZ13: 277 | DA13: 228 | DB13: 49 | DC13: 2952 | DD13: 58 | DE13: 2710 | DF13: 2662 | DG13: 48 | DH13: 242 | DI13: 196 | DJ13: 46 | DK13: 241 | DL13: 212 | DM13: 209 | DN13: 3 | DO13: 29 | DP13: 28 | DQ13: 1 | DR13: 29 | DS13: 0 | DT13: 28 | DU13: 27 | DV13: 1 | DW13: 1 | DX13: 1 | DY13: 0 | DZ13: 0 | EA13: 0 | EB13: 0 | EC13: 0 | ED13: 0 | EE13: 0 | EF13: 0 | EG13: 112 | EH13: 67 | EI13: 65 | EJ13: 2 | EK13: 45 | EL13: 43 | EM13: 2 | EN13: 11 | EO13: 0 | EP13: 0 | EQ13: 11 | ER13: 0 | ES13: 0 | ET13: 0 | EU13: 0 | EV13: 0 | EW13: 0 | EX13: 0 | EY13: 0 | EZ13: 0 | FA13: 0 | FB13: 0
A14: 11 | B14: 成人手术 | C14: 普外科 | D14: 15156262 | E14: 2647631 | F14: 12508631 | G14: 11567 | H14: 1090 | I14: 185514 | J14: 136076 | K14: 45 | L14: 911564.25 | M14: 3927381.5 | N14: 2167.5 | O14: 30993485 | P14: 20694947 | Q14: 19903233 | R14: 791714.32 | S14: 10298539 | T14: 9972803.8 | U14: 325734.75 | V14: 4240925.1 | W14: 3345677 | X14: 3206041.5 | Y14: 139635.5 | Z14: 895248.1 | AA14: 676621.11 | AB14: 218626.99 | AC14: 1132111 | AD14: 848573.45 | AE14: 824101.82 | AF14: 24471.63 | AG14: 283537.55 | AH14: 240384.11 | AI14: 43153.44 | AJ14: 461183.11 | AK14: 406888.56 | AL14: 393337.69 | AM14: 13550.87 | AN14: 54294.55 | AO14: 38841 | AP14: 15453.55 | AQ14: 1910274 | AR14: 1475413 | AS14: 1405170 | AT14: 70243 | AU14: 434861 | AV14: 319090 | AW14: 115771 | AX14: 737357 | AY14: 614802 | AZ14: 583432 | BA14: 31370 | BB14: 122555 | BC14: 78306 | BD14: 44249 | BE14: 26752560 | BF14: 17349270 | BG14: 16697191 | BH14: 652078.82 | BI14: 9403290.5 | BJ14: 9296182.7 | BK14: 107107.76 | BL14: 4709261.8 | BM14: 2931038.4 | BN14: 2841117.9 | BO14: 89920.45 | BP14: 1778223.4 | BQ14: 1756727.6 | BR14: 21495.84 | BS14: 9534667.3 | BT14: 6359459 | BU14: 6161297.7 | BV14: 198161.37 | BW14: 3175208.3 | BX14: 3139946.1 | BY14: 35262.17 | BZ14: 4526843 | CA14: 2707625 | CB14: 2621419 | CC14: 86206 | CD14: 1819218 | CE14: 1796747 | CF14: 22471 | CG14: 7981788.2 | CH14: 5351147.5 | CI14: 5073356.5 | CJ14: 277791 | CK14: 2630640.8 | CL14: 2602762 | CM14: 27878.75 | CN14: 1147547.2 | CO14: 1449234.1 | CP14: 1027895.6 | CQ14: 533761.7 | CR14: 82536.51 | CS14: 0 | CT14: 260282.86 | CU14: 0 | CV14: 11567 | CW14: 9553 | CX14: 9098 | CY14: 455 | CZ14: 2014 | DA14: 1402 | DB14: 612 | DC14: 5646 | DD14: 23 | DE14: 4799 | DF14: 4559 | DG14: 240 | DH14: 847 | DI14: 585 | DJ14: 262 | DK14: 3010 | DL14: 2365 | DM14: 2261 | DN14: 104 | DO14: 645 | DP14: 454 | DQ14: 191 | DR14: 122 | DS14: 0 | DT14: 83 | DU14: 75 | DV14: 8 | DW14: 39 | DX14: 24 | DY14: 15 | DZ14: 2766 | EA14: 2285 | EB14: 2182 | EC14: 103 | ED14: 481 | EE14: 339 | EF14: 142 | EG14: 1090 | EH14: 750 | EI14: 721 | EJ14: 29 | EK14: 340 | EL14: 337 | EM14: 3 | EN14: 948 | EO14: 719 | EP14: 0 | EQ14: 229 | ER14: 409 | ES14: 0 | ET14: 0 | EU14: 288 | EV14: 234 | EW14: 0 | EX14: 54 | EY14: 201 | EZ14: 201 | FA14: 0 | FB14: 391
A15: 12 | B15: 成人手术 | C15: 神经外科 | D15: 9739809.2 | E15: 546218 | F15: 9193591.2 | G15: 2789 | H15: 588 | I15: 316 | J15: 0 | K15: 0 | L15: 666722.5 | M15: 2726276.2 | N15: 0 | O15: 36575367 | P15: 19813626 | Q15: 18934585 | R15: 879041.01 | S15: 16761741 | T15: 16654070 | U15: 107670.99 | V15: 851805.58 | W15: 677847.95 | X15: 621501.24 | Y15: 56346.71 | Z15: 173957.63 | AA15: 112742.8 | AB15: 61214.83 | AC15: 295413.58 | AD15: 249778.95 | AE15: 234809.24 | AF15: 14969.71 | AG15: 45634.63 | AH15: 33994.8 | AI15: 11639.83 | AJ15: 10174 | AK15: 8411 | AL15: 7938 | AM15: 473 | AN15: 1763 | AO15: 989 | AP15: 774 | AQ15: 436952 | AR15: 348015 | AS15: 313922 | AT15: 34093 | AU15: 88937 | AV15: 54208 | AW15: 34729 | AX15: 109266 | AY15: 71643 | AZ15: 64832 | BA15: 6811 | BB15: 37623 | BC15: 23551 | BD15: 14072 | BE15: 35723562 | BF15: 19135779 | BG15: 18313084 | BH15: 822694.3 | BI15: 16587783 | BJ15: 16541327 | BK15: 46456.16 | BL15: 3575350.8 | BM15: 1772766.7 | BN15: 1660095.6 | BO15: 112671.08 | BP15: 1802584.1 | BQ15: 1800882.9 | BR15: 1701.18 | BS15: 22954619 | BT15: 13012275 | BU15: 12619669 | BV15: 392605.97 | BW15: 9942344.7 | BX15: 9921519.7 | BY15: 20824.98 | BZ15: 3570783 | CA15: 1728856 | CB15: 1626190 | CC15: 102666 | CD15: 1841927 | CE15: 1839054 | CF15: 2873 | CG15: 5622808.2 | CH15: 2621881 | CI15: 2407129.8 | CJ15: 214751.25 | CK15: 3000927.2 | CL15: 2979870.2 | CM15: 21057 | CN15: 0 | CO15: 470210.91 | CP15: 307264.94 | CQ15: 48518.82 | CR15: 25810.91 | CS15: 0 | CT15: 216953.1 | CU15: 0 | CV15: 2789 | CW15: 2083 | CX15: 1891 | CY15: 192 | CZ15: 706 | DA15: 438 | DB15: 268 | DC15: 1580 | DD15: 16 | DE15: 1303 | DF15: 1178 | DG15: 125 | DH15: 277 | DI15: 167 | DJ15: 110 | DK15: 1133 | DL15: 753 | DM15: 689 | DN15: 64 | DO15: 380 | DP15: 241 | DQ15: 139 | DR15: 60 | DS15: 0 | DT15: 13 | DU15: 11 | DV15: 2 | DW15: 47 | DX15: 30 | DY15: 17 | DZ15: 0 | EA15: 0 | EB15: 0 | EC15: 0 | ED15: 0 | EE15: 0 | EF15: 0 | EG15: 588 | EH15: 316 | EI15: 296 | EJ15: 20 | EK15: 272 | EL15: 270 | EM15: 2 | EN15: 526 | EO15: 225 | EP15: 191 | EQ15: 110 | ER15: 107 | ES15: 0 | ET15: 0 | EU15: 96 | EV15: 71 | EW15: 10 | EX15: 15 | EY15: 291 | EZ15: 110 | FA15: 181 | FB15: 219
... A66: 63 | B66: 其他 | C66: 临床药物试验办公室GCP | D66: 49322 | E66: 49322 | F66: 0 | G66: 132 | H66: 0 | I66: 40 | J66: 0 | K66: 0 | L66: 0 | M66: 0 | N66: 0 | O66: 49354 | P66: 12650 | Q66: 0 | R66: 12650 | S66: 36704 | T66: 0 | U66: 36704 | V66: 49354 | W66: 12650 | X66: 0 | Y66: 12650 | Z66: 36704 | AA66: 0 | AB66: 36704 | AC66: 0 | AD66: 0 | AE66: 0 | AF66: 0 | AG66: 0 | AH66: 0 | AI66: 0 | AJ66: 32 | AK66: 0 | AL66: 0 | AM66: 0 | AN66: 32 | AO66: 0 | AP66: 32 | AQ66: 45982 | AR66: 10900 | AS66: 0 | AT66: 10900 | AU66: 35082 | AV66: 0 | AW66: 35082 | AX66: 3340 | AY66: 1750 | AZ66: 0 | BA66: 1750 | BB66: 1590 | BC66: 0 | BD66: 1590 | BE66: 0 | BF66: 0 | BG66: 0 | BH66: 0 | BI66: 0 | BJ66: 0 | BK66: 0 | BL66: 0 | BM66: 0 | BN66: 0 | BO66: 0 | BP66: 0 | BQ66: 0 | BR66: 0 | BS66: 0 | BT66: 0 | BU66: 0 | BV66: 0 | BW66: 0 | BX66: 0 | BY66: 0 | BZ66: 0 | CA66: 0 | CB66: 0 | CC66: 0 | CD66: 0 | CE66: 0 | CF66: 0 | CG66: 0 | CH66: 0 | CI66: 0 | CJ66: 0 | CK66: 0 | CL66: 0 | CM66: 0 | CN66: 0 | CO66: 0 | CP66: 0 | CQ66: 49354 | CR66: 0 | CS66: 0 | CT66: 0 | CU66: 0 | CV66: 132 | CW66: 70 | CX66: 0 | CY66: 70 | CZ66: 62 | DA66: 0 | DB66: 62 | DC66: 132 | DD66: 0 | DE66: 70 | DF66: 0 | DG66: 70 | DH66: 62 | DI66: 0 | DJ66: 62 | DK66: 0 | DL66: 0 | DM66: 0 | DN66: 0 | DO66: 0 | DP66: 0 | DQ66: 0 | DR66: 0 | DS66: 0 | DT66: 0 | DU66: 0 | DV66: 0 | DW66: 0 | DX66: 0 | DY66: 0 | DZ66: 0 | EA66: 0 | EB66: 0 | EC66: 0 | ED66: 0 | EE66: 0 | EF66: 0 | EG66: 0 | EH66: 0 | EI66: 0 | EJ66: 0 | EK66: 0 | EL66: 0 | EM66: 0 | EN66: 0 | EO66: 0 | EP66: 0 | EQ66: 0 | ER66: 0 | ES66: 0 | ET66: 0 | EU66: 0 | EV66: 0 | EW66: 0 | EX66: 0 | EY66: 0 | EZ66: 0 | FA66: 0 | FB66: 0
A67: 64 | C67: 其它 | D67: 0 | E67: 0 | F67: 0 | G67: 151 | H67: 25 | I67: 0 | J67: 0 | K67: 0 | L67: 0 | M67: 0 | N67: 0 | O67: 461875.28 | P67: 375685.16 | Q67: 292336.4 | R67: 83348.76 | S67: 86190.12 | T67: 60390.12 | U67: 25800 | V67: 0 | W67: 0 | X67: 0 | Y67: 0 | Z67: 0 | AA67: 0 | AB67: 0 | AC67: 0 | AD67: 0 | AE67: 0 | AF67: 0 | AG67: 0 | AH67: 0 | AI67: 0 | AJ67: 0 | AK67: 0 | AL67: 0 | AM67: 0 | AN67: 0 | AO67: 0 | AP67: 0 | AQ67: 0 | AR67: 0 | AS67: 0 | AT67: 0 | AU67: 0 | AV67: 0 | AW67: 0 | AX67: 0 | AY67: 0 | AZ67: 0 | BA67: 0 | BB67: 0 | BC67: 0 | BD67: 0 | BE67: 461875.28 | BF67: 375685.16 | BG67: 292336.4 | BH67: 83348.76 | BI67: 86190.12 | BJ67: 60390.12 | BK67: 25800 | BL67: 0 | BM67: 0 | BN67: 0 | BO67: 0 | BP67: 0 | BQ67: 0 | BR67: 0 | BS67: 461875.28 | BT67: 375685.16 | BU67: 292336.4 | BV67: 83348.76 | BW67: 86190.12 | BX67: 60390.12 | BY67: 25800 | BZ67: 0 | CA67: 0 | CB67: 0 | CC67: 0 | CD67: 0 | CE67: 0 | CF67: 0 | CG67: 0 | CH67: 0 | CI67: 0 | CJ67: 0 | CK67: 0 | CL67: 0 | CM67: 0 | CN67: 0 | CO67: 0 | CP67: 0 | CQ67: 0 | CR67: 0 | CS67: 0 | CT67: 103200 | CU67: 0 | CV67: 151 | CW67: 34 | CX67: 0 | CY67: 34 | CZ67: 117 | DA67: 0 | DB67: 117 | DC67: 151 | DD67: 0 | DE67: 34 | DF67: 0 | DG67: 34 | DH67: 117 | DI67: 0 | DJ67: 117 | DK67: 0 | DL67: 0 | DM67: 0 | DN67: 0 | DO67: 0 | DP67: 0 | DQ67: 0 | DR67: 0 | DS67: 0 | DT67: 0 | DU67: 0 | DV67: 0 | DW67: 0 | DX67: 0 | DY67: 0 | DZ67: 0 | EA67: 0 | EB67: 0 | EC67: 0 | ED67: 0 | EE67: 0 | EF67: 0 | EG67: 25 | EH67: 8 | EI67: 2 | EJ67: 6 | EK67: 17 | EL67: 15 | EM67: 2 | EN67: 1 | EO67: 1 | EP67: 0 | EQ67: 0 | ER67: 0 | ES67: 0 | ET67: 0 | EU67: 0 | EV67: 0 | EW67: 0 | EX67: 0 | EY67: 0 | EZ67: 0 | FA67: 0 | FB67: 0

Sheet 当年累计数据表奉贤
A1: 日期范围：20260501-20260531 | D1: 25 | O1: 1=2+5=8+43 | P1: 2=3+4 | Q1: 3 | R1: 4 | S1: 5=6+7 | T1: 6 | U1: 7 | V1: 8=9+12=15+22+29+36 | W1: 9=10+11 | X1: 10 | Y1: 11 | Z1: 12=13+14 | AA1: 13 | AB1: 14 | AC1: 15=16+19 | AD1: 16=17+18 | AE1: 17 | AF1: 18 | AG1: 19=20+21 | AH1: 20 | AI1: 21 | AJ1: 22=23+26 | AK1: 23=24+25 | AL1: 24 | AM1: 25 | AN1: 26=27+28 | AO1: 27 | AP1: 28 | AQ1: 29=30+33 | AR1: 30=31+32 | AS1: 31 | AT1: 32 | AU1: 33=34+35 | AV1: 34 | AW1: 35 | AX1: 36=37+40 | AY1: 37=38+39 | AZ1: 38 | BA1: 39 | BB1: 40=41+42 | BC1: 41 | BD1: 42 | BE1: 43=50+57+64+71=44+47 | BF1: 44=45+46 | BG1: 45 | BH1: 46 | BI1: 47=48+49 | BJ1: 48 | BK1: 49 | BL1: 50=51+54 | BM1: 51=52+53 | BN1: 52 | BO1: 53 | BP1: 54=55+56 | BQ1: 55 | BR1: 56 | BS1: 57=58+61 | BT1: 58=59+60 | BU1: 59 | BV1: 60 | BW1: 61=62+63 | BX1: 62 | BY1: 63 | BZ1: 64=65+68 | CA1: 65=66+67 | CB1: 66 | CC1: 67 | CD1: 68=69+70 | CE1: 69 | CF1: 70 | CG1: 71=72+75 | CH1: 72=73+74 | CI1: 73 | CJ1: 74 | CK1: 75=76+77 | CL1: 76 | CM1: 77 | CV1: 78=85+93+100+108+86+101=79+82 | CW1: 79=80+81 | CX1: 80 | CY1: 81 | CZ1: 82=83+84 | DA1: 83 | DB1: 84 | DC1: 85=87+90=78-93-100-108-86-101 | DD1: 86 | DE1: 87=88+89 | DF1: 88 | DG1: 89 | DH1: 90=91+92 | DI1: 91 | DJ1: 92 | DK1: 93=94+97 | DL1: 94=95+96 | DM1: 95 | DN1: 96 | DO1: 97=98+99 | DP1: 98 | DQ1: 99 | DR1: 100=102+105 | DS1: 101 | DT1: 102=103+104 | DU1: 103 | DV1: 104 | DW1: 105=106+107 | DX1: 106 | DY1: 107 | DZ1: 108=109+112 | EA1: 109=110+111 | EB1: 110 | EC1: 111 | ED1: 112=113+114 | EE1: 113 | EF1: 114 | EG1: 115=116+119 | EH1: 116=117+118 | EI1: 117 | EJ1: 118 | EK1: 119=120+121 | EL1: 120 | EM1: 121 | EN1: 122=123+124+125 | EO1: 123 | EP1: 124 | EQ1: 125 | EU1: 126=127+128+129 | EV1: 127 | EW1: 128 | EX1: 129 | EY1: 130=131+132 | EZ1: 131 | FA1: 132 | FB1: 133
A2: 序号 | B2: 科室类别 | C2: 科室名称 | D2: 医疗收入不含药耗 | E2: 门急诊收入不含药耗 | F2: 住院收入不含药耗 | G2: 门急诊人次 | H2: 住院人次 | I2: 门急诊治疗收入 | J2: 门急诊手术收入 | K2: 门诊中药饮片收入 | L2: 住院治疗收入 | M2: 住院手术收入 | N2: 住院中药饮片收入 | O2: 医疗收入 | P2: 其中本地病人医疗收入 | Q2: 其中本地病人医保医疗收入 | R2: 其中本地病人自费医疗收入 | S2: 其中异地病人医疗收入 | T2: 其中异地病人医保医疗收入 | U2: 其中异地病人自费医疗收入 | V2: 门急诊收入 | W2: 其中本地病人医疗收入 | X2: 其中本地病人医保医疗收入 | Y2: 其中本地病人自费医疗收入 | Z2: 其中异地病人医疗收入 | AA2: 其中异地病人医保医疗收入 | AB2: 其中异地病人自费医疗收入 | AC2: 门急诊药品收入 | AD2: 其中本地病人医疗收入 | AE2: 其中本地病人医保医疗收入 | AF2: 其中本地病人自费医疗收入 | AG2: 其中异地病人医疗收入 | AH2: 其中异地病人医保医疗收入 | AI2: 其中异地病人自费医疗收入 | AJ2: 门急诊耗材收入 | AK2: 其中本地病人医疗收入 | AL2: 其中本地病人医保医疗收入 | AM2: 其中本地病人自费医疗收入 | AN2: 其中异地病人医疗收入 | AO2: 其中异地病人医保医疗收入 | AP2: 其中异地病人自费医疗收入 | AQ2: 门急诊检查化验收入 | AR2: 其中本地病人医疗收入 | AS2: 其中本地病人医保医疗收入 | AT2: 其中本地病人自费医疗收入 | AU2: 其中异地病人医疗收入 | AV2: 其中异地病人医保医疗收入 | AW2: 其中异地病人自费医疗收入 | AX2: 门急诊劳务收入 | AY2: 其中本地病人医疗收入 | AZ2: 其中本地病人医保医疗收入 | BA2: 其中本地病人自费医疗收入 | BB2: 其中异地病人医疗收入 | BC2: 其中异地病人医保医疗收入 | BD2: 其中异地病人自费医疗收入 | BE2: 住院收入 | BF2: 其中本地病人医疗收入 | BG2: 其中本地病人医保医疗收入 | BH2: 其中本地病人自费医疗收入 | BI2: 其中异地病人医疗收入 | BJ2: 其中异地病人医保医疗收入 | BK2: 其中异地病人自费医疗收入 | BL2: 住院药品收入 | BM2: 其中本地病人医疗收入 | BN2: 其中本地病人医保医疗收入 | BO2: 其中本地病人自费医疗收入 | BP2: 其中异地病人医疗收入 | BQ2: 其中异地病人医保医疗收入 | BR2: 其中异地病人自费医疗收入 | BS2: 住院耗材收入 | BT2: 其中本地病人医疗收入 | BU2: 其中本地病人医保医疗收入 | BV2: 其中本地病人自费医疗收入 | BW2: 其中异地病人医疗收入 | BX2: 其中异地病人医保医疗收入 | BY2: 其中异地病人自费医疗收入 | BZ2: 住院检查化验收入 | CA2: 其中本地病人医疗收入 | CB2: 其中本地病人医保医疗收入 | CC2: 其中本地病人自费医疗收入 | CD2: 其中异地病人医疗收入 | CE2: 其中异地病人医保医疗收入 | CF2: 其中异地病人自费医疗收入 | CG2: 住院劳务收入 | CH2: 其中本地病人医疗收入 | CI2: 其中本地病人医保医疗收入 | CJ2: 其中本地病人自费医疗收入 | CK2: 其中异地病人医疗收入 | CL2: 其中异地病人医保医疗收入 | CM2: 其中异地病人自费医疗收入 | CN2: 急诊收入 | CO2: 普通门诊收入 | CP2: 专家门诊收入 | CQ2: 专病门诊收入 | CR2: 特需门诊收入 | CS2: MDT门诊收入 | CT2: 镜朗诊疗部收入 | CU2: 特需病房收入 | CV2: 门急诊人次 | CW2: 其中本地病人人次 | CX2: 其中本地病人医保人次 | CY2: 其中本地病人自费人次 | CZ2: 其中异地病人人次 | DA2: 其中异地病人医保人次 | DB2: 其中异地病人自费人次 | DC2: 普通门诊 (普通+专病) | DD2: 互联网普通门诊人次 | DE2: 其中本地病人人次 | DF2: 其中本地病人医保人次 | DG2: 其中本地病人自费人次 | DH2: 其中异地病人人次 | DI2: 其中异地病人医保人次 | DJ2: 其中异地病人自费人次 | DK2: 专家门诊 | DL2: 其中本地病人人次 | DM2: 其中本地病人医保人次 | DN2: 其中本地病人自费人次 | DO2: 其中异地病人人次 | DP2: 其中异地病人医保人次 | DQ2: 其中异地病人自费人次 | DR2: 特需门诊 (特需+MDT) | DS2: 互联网特需门诊人次 | DT2: 其中本地病人人次 | DU2: 其中本地病人医保人次 | DV2: 其中本地病人自费人次 | DW2: 其中异地病人人次 | DX2: 其中异地病人医保人次 | DY2: 其中异地病人自费人次 | DZ2: 急诊人次 | EA2: 其中本地病人人次 | EB2: 其中本地病人医保人次 | EC2: 其中本地病人自费人次 | ED2: 其中异地病人人次 | EE2: 其中异地病人医保人次 | EF2: 其中异地病人自费人次 | EG2: 住院人次 | EH2: 其中本地病人人次 | EI2: 其中本地病人医保人次 | EJ2: 其中本地病人自费人次 | EK2: 其中异地病人人次 | EL2: 其中异地病人医保人次 | EM2: 其中异地病人自费人次 | EN2: 手术人次与操作人次 | EO2: 手术人次 | EP2: 介入人次 | EQ2: 操作人次(治疗+诊断) | ER2: 微创手术人次（手术） | ES2: 微创手术人次（介入） | ET2: 微创手术人次（操作） | EU2: 三级手术 | EV2: 三级手术(手术) | EW2: 三级手术(介入) | EX2: 三级手术(操作) | EY2: 四级手术 | EZ2: 四级手术(手术) | FA2: 四级手术(介入) | FB2: 重点病种人次
A3: 小计： | D3: 62648278 | E3: 25025509 | F3: 37622769 | G3: 95116 | H3: 3578 | I3: 3560692.2 | J3: 1219717.8 | K3: 448212.16 | L3: 2720225 | M3: 10946942 | N3: 4343.17 | O3: 1.4263148e+08 | P3: 1.0429655e+08 | Q3: 96341160 | R3: 7955391.7 | S3: 38334926 | T3: 35898735 | U3: 2436191.3 | V3: 41796775 | W3: 35927381 | X3: 32801690 | Y3: 3125690.8 | Z3: 5869393.7 | AA3: 3750504.2 | AB3: 2118889.4 | AC3: 14746208 | AD3: 12946543 | AE3: 12221683 | AF3: 724859.66 | AG3: 1799665 | AH3: 1326873.9 | AI3: 472791.15 | AJ3: 2025058.1 | AK3: 1782756 | AL3: 1462999.4 | AM3: 319756.63 | AN3: 242302.15 | AO3: 142095.37 | AP3: 100206.78 | AQ3: 16440181 | AR3: 13998399 | AS3: 12777987 | AT3: 1220412 | AU3: 2441782 | AV3: 1538162 | AW3: 903620 | AX3: 8585328 | AY3: 7199683.5 | AZ3: 6339021 | BA3: 860662.55 | BB3: 1385644.5 | BC3: 743373 | BD3: 642271.5 | BE3: 1.008347e+08 | BF3: 68369171 | BG3: 63539470 | BH3: 4829700.8 | BI3: 32465532 | BJ3: 32148231 | BK3: 317301.85 | BL3: 11466479 | BM3: 6677764.3 | BN3: 6228071.7 | BO3: 449692.63 | BP3: 4788714.9 | BQ3: 4711439.6 | BR3: 77275.3 | BS3: 51745455 | BT3: 35931529 | BU3: 33315333 | BV3: 2616195.8 | BW3: 15813926 | BX3: 15707976 | BY3: 105950.05 | BZ3: 15170809 | CA3: 10335539 | CB3: 9792617.5 | CC3: 542921.5 | CD3: 4835270 | CE3: 4765515 | CF3: 69755 | CG3: 22451960 | CH3: 15424339 | CI3: 14203448 | CJ3: 1220890.9 | CK3: 7027621.4 | CL3: 6963299.9 | CM3: 64321.5 | CN3: 9309038.3 | CO3: 14403938 | CP3: 11553205 | CQ3: 4798578.3 | CR3: 1729731.6 | CS3: 1848 | CT3: 246911.2 | CU3: 0 | CV3: 95116 | CW3: 81739 | CX3: 73571 | CY3: 8168 | CZ3: 13377 | DA3: 7850 | DB3: 5527 | DC3: 47744 | DD3: 0 | DE3: 41468 | DF3: 37712 | DG3: 3756 | DH3: 6276 | DI3: 3566 | DJ3: 2710 | DK3: 24947 | DL3: 20818 | DM3: 18744 | DN3: 2074 | DO3: 4129 | DP3: 2480 | DQ3: 1649 | DR3: 2513 | DS3: 0 | DT3: 1983 | DU3: 1745 | DV3: 238 | DW3: 530 | DX3: 276 | DY3: 254 | DZ3: 19912 | EA3: 17470 | EB3: 15370 | EC3: 2100 | ED3: 2442 | EE3: 1528 | EF3: 914 | EG3: 3578 | EH3: 2523 | EI3: 2342 | EJ3: 181 | EK3: 1055 | EL3: 1036 | EM3: 19 | EN3: 2970 | EO3: 1789 | EP3: 310 | EQ3: 871 | ER3: 503 | ES3: 0 | ET3: 38 | EU3: 939 | EV3: 749 | EW3: 151 | EX3: 39 | EY3: 622 | EZ3: 518 | FA3: 104 | FB3: 1260
A4: 1 | B4: 成人非手术 | C4: 内科 | D4: 0 | E4: 0 | F4: 0 | G4: 31 | H4: 0 | I4: 0 | J4: 0 | K4: 0 | L4: 0 | M4: 0 | N4: 0 | O4: 0 | P4: 0 | Q4: 0 | R4: 0 | S4: 0 | T4: 0 | U4: 0 | V4: 0 | W4: 0 | X4: 0 | Y4: 0 | Z4: 0 | AA4: 0 | AB4: 0 | AC4: 0 | AD4: 0 | AE4: 0 | AF4: 0 | AG4: 0 | AH4: 0 | AI4: 0 | AJ4: 0 | AK4: 0 | AL4: 0 | AM4: 0 | AN4: 0 | AO4: 0 | AP4: 0 | AQ4: 0 | AR4: 0 | AS4: 0 | AT4: 0 | AU4: 0 | AV4: 0 | AW4: 0 | AX4: 0 | AY4: 0 | AZ4: 0 | BA4: 0 | BB4: 0 | BC4: 0 | BD4: 0 | BE4: 0 | BF4: 0 | BG4: 0 | BH4: 0 | BI4: 0 | BJ4: 0 | BK4: 0 | BL4: 0 | BM4: 0 | BN4: 0 | BO4: 0 | BP4: 0 | BQ4: 0 | BR4: 0 | BS4: 0 | BT4: 0 | BU4: 0 | BV4: 0 | BW4: 0 | BX4: 0 | BY4: 0 | BZ4: 0 | CA4: 0 | CB4: 0 | CC4: 0 | CD4: 0 | CE4: 0 | CF4: 0 | CG4: 0 | CH4: 0 | CI4: 0 | CJ4: 0 | CK4: 0 | CL4: 0 | CM4: 0 | CN4: 0 | CO4: 0 | CP4: 0 | CQ4: 0 | CR4: 0 | CS4: 0 | CT4: 0 | CU4: 0 | CV4: 31 | CW4: 23 | CX4: 22 | CY4: 1 | CZ4: 8 | DA4: 8 | DB4: 0 | DC4: 31 | DD4: 0 | DE4: 23 | DF4: 22 | DG4: 1 | DH4: 8 | DI4: 8 | DJ4: 0 | DK4: 0 | DL4: 0 | DM4: 0 | DN4: 0 | DO4: 0 | DP4: 0 | DQ4: 0 | DR4: 0 | DS4: 0 | DT4: 0 | DU4: 0 | DV4: 0 | DW4: 0 | DX4: 0 | DY4: 0 | DZ4: 0 | EA4: 0 | EB4: 0 | EC4: 0 | ED4: 0 | EE4: 0 | EF4: 0 | EG4: 0 | EH4: 0 | EI4: 0 | EJ4: 0 | EK4: 0 | EL4: 0 | EM4: 0 | EN4: 0 | EO4: 0 | EP4: 0 | EQ4: 0 | ER4: 0 | ES4: 0 | ET4: 0 | EU4: 0 | EV4: 0 | EW4: 0 | EX4: 0 | EY4: 0 | EZ4: 0 | FA4: 0 | FB4: 0
A5: 2 | B5: 成人非手术 | C5: 呼吸内科 | D5: 1492087.5 | E5: 729483 | F5: 762604.5 | G5: 2861 | H5: 66 | I5: 72 | J5: 0 | K5: 0 | L5: 31050 | M5: 198 | N5: 0 | O5: 2443922 | P5: 1900866.8 | Q5: 1825747.1 | R5: 75119.7 | S5: 543055.21 | T5: 490756.03 | U5: 52299.18 | V5: 1285888.1 | W5: 1134877.4 | X5: 1082651.9 | Y5: 52225.49 | Z5: 151010.63 | AA5: 98711.45 | AB5: 52299.18 | AC5: 538467.06 | AD5: 482354.43 | AE5: 464227.94 | AF5: 18126.49 | AG5: 56112.63 | AH5: 37531.45 | AI5: 18581.18 | AJ5: 17938 | AK5: 15387 | AL5: 14470 | AM5: 917 | AN5: 2551 | AO5: 1634 | AP5: 917 | AQ5: 641094 | AR5: 560451 | AS5: 531983 | AT5: 28468 | AU5: 80643 | AV5: 51729 | AW5: 28914 | AX5: 88389 | AY5: 76685 | AZ5: 71971 | BA5: 4714 | BB5: 11704 | BC5: 7817 | BD5: 3887 | BE5: 1158034 | BF5: 765989.4 | BG5: 743095.19 | BH5: 22894.21 | BI5: 392044.58 | BJ5: 392044.58 | BK5: 0 | BL5: 329564.42 | BM5: 231209.41 | BN5: 221831.51 | BO5: 9377.9 | BP5: 98355.01 | BQ5: 98355.01 | BR5: 0 | BS5: 65865.06 | BT5: 39661.99 | BU5: 39171.18 | BV5: 490.81 | BW5: 26203.07 | BX5: 26203.07 | BY5: 0 | BZ5: 552040 | CA5: 347870 | CB5: 342748 | CC5: 5122 | CD5: 204170 | CE5: 204170 | CF5: 0 | CG5: 210564.5 | CH5: 147248 | CI5: 139344.5 | CJ5: 7903.5 | CK5: 63316.5 | CL5: 63316.5 | CM5: 0 | CN5: -75 | CO5: 1013880.6 | CP5: 250795.93 | CQ5: 0 | CR5: 21211.5 | CS5: 0 | CT5: 0 | CU5: 0 | CV5: 2861 | CW5: 2487 | CX5: 2341 | CY5: 146 | CZ5: 374 | DA5: 242 | DB5: 132 | DC5: 2304 | DD5: 0 | DE5: 2009 | DF5: 1897 | DG5: 112 | DH5: 295 | DI5: 191 | DJ5: 104 | DK5: 505 | DL5: 433 | DM5: 403 | DN5: 30 | DO5: 72 | DP5: 44 | DQ5: 28 | DR5: 52 | DS5: 0 | DT5: 45 | DU5: 41 | DV5: 4 | DW5: 7 | DX5: 7 | DY5: 0 | DZ5: 0 | EA5: 0 | EB5: 0 | EC5: 0 | ED5: 0 | EE5: 0 | EF5: 0 | EG5: 66 | EH5: 47 | EI5: 46 | EJ5: 1 | EK5: 19 | EL5: 19 | EM5: 0 | EN5: 34 | EO5: 0 | EP5: 0 | EQ5: 34 | ER5: 0 | ES5: 0 | ET5: 0 | EU5: 0 | EV5: 0 | EW5: 0 | EX5: 0 | EY5: 0 | EZ5: 0 | FA5: 0 | FB5: 29
A6: 3 | B6: 成人非手术 | C6: 消化内科（内窥镜诊治部） | D6: 3553867.5 | E6: 2126973 | F6: 1426894.5 | G6: 6673 | H6: 232 | I6: 165336 | J6: 1500 | K6: 0 | L6: 147745 | M6: 182460 | N6: 256.5 | O6: 6207710.7 | P6: 5136097 | Q6: 4913642.8 | R6: 222454.26 | S6: 1071613.6 | T6: 926567.53 | U6: 145046.12 | V6: 3496699.4 | W6: 3076970.9 | X6: 2925507 | Y6: 151463.91 | Z6: 419728.48 | AA6: 274682.36 | AB6: 145046.12 | AC6: 1146421.4 | AD6: 1010513.9 | AE6: 966869.97 | AF6: 43643.91 | AG6: 135907.48 | AH6: 94132.36 | AI6: 41775.12 | AJ6: 223305 | AK6: 203384 | AL6: 192697 | AM6: 10687 | AN6: 19921 | AO6: 12879 | AP6: 7042 | AQ6: 1740895 | AR6: 1522299 | AS6: 1442698 | AT6: 79601 | AU6: 218596 | AV6: 138018 | AW6: 80578 | AX6: 386078 | AY6: 340774 | AZ6: 323242 | BA6: 17532 | BB6: 45304 | BC6: 29653 | BD6: 15651 | BE6: 2711011.3 | BF6: 2059126.2 | BG6: 1988135.8 | BH6: 70990.35 | BI6: 651885.17 | BJ6: 651885.17 | BK6: 0 | BL6: 391943.2 | BM6: 299805.64 | BN6: 290033.85 | BO6: 9771.79 | BP6: 92137.56 | BQ6: 92137.56 | BR6: 0 | BS6: 892173.64 | BT6: 681515.53 | BU6: 659662.97 | BV6: 21852.56 | BW6: 210658.11 | BX6: 210658.11 | BY6: 0 | BZ6: 762326 | CA6: 567854 | CB6: 545066 | CC6: 22788 | CD6: 194472 | CE6: 194472 | CF6: 0 | CG6: 664568.5 | CH6: 509951 | CI6: 493373 | CJ6: 16578 | CK6: 154617.5 | CL6: 154617.5 | CM6: 0 | CN6: -25 | CO6: 2177168.4 | CP6: 526476.61 | CQ6: 650898.07 | CR6: 142156.33 | CS6: 0 | CT6: 14181.69 | CU6: 0 | CV6: 6673 | CW6: 5814 | CX6: 5485 | CY6: 329 | CZ6: 859 | DA6: 543 | DB6: 316 | DC6: 5390 | DD6: 0 | DE6: 4688 | DF6: 4428 | DG6: 260 | DH6: 702 | DI6: 437 | DJ6: 265 | DK6: 1076 | DL6: 957 | DM6: 900 | DN6: 57 | DO6: 119 | DP6: 84 | DQ6: 35 | DR6: 207 | DS6: 0 | DT6: 169 | DU6: 157 | DV6: 12 | DW6: 38 | DX6: 22 | DY6: 16 | DZ6: 0 | EA6: 0 | EB6: 0 | EC6: 0 | ED6: 0 | EE6: 0 | EF6: 0 | EG6: 232 | EH6: 181 | EI6: 174 | EJ6: 7 | EK6: 51 | EL6: 51 | EM6: 0 | EN6: 227 | EO6: 2 | EP6: 0 | EQ6: 225 | ER6: 0 | ES6: 0 | ET6: 38 | EU6: 25 | EV6: 1 | EW6: 0 | EX6: 24 | EY6: 0 | EZ6: 0 | FA6: 0 | FB6: 7
A7: 4 | B7: 成人非手术 | C7: 神经内科 | D7: 1900750 | E7: 938351 | F7: 962399 | G7: 2699 | H7: 90 | I7: 96 | J7: 0 | K7: 522.48 | L7: 46351 | M7: 30555 | N7: 0 | O7: 4235715.7 | P7: 3033627.1 | Q7: 2930418.1 | R7: 103209 | S7: 1202088.5 | T7: 1135579.4 | U7: 66509.19 | V7: 1677600.9 | W7: 1427631 | X7: 1335087.3 | Y7: 92543.64 | Z7: 249969.93 | AA7: 183460.74 | AB7: 66509.19 | AC7: 735594.89 | AD7: 641330.96 | AE7: 603402.32 | AF7: 37928.64 | AG7: 94263.93 | AH7: 73394.74 | AI7: 20869.19 | AJ7: 3655 | AK7: 3053 | AL7: 2752 | AM7: 301 | AN7: 602 | AO7: 516 | AP7: 86 | AQ7: 791682 | AR7: 663019 | AS7: 618588 | AT7: 44431 | AU7: 128663 | AV7: 91559 | AW7: 37104 | AX7: 146669 | AY7: 120228 | AZ7: 110345 | BA7: 9883 | BB7: 26441 | BC7: 17991 | BD7: 8450 | BE7: 2558114.8 | BF7: 1605996.2 | BG7: 1595330.8 | BH7: 10665.36 | BI7: 952118.61 | BJ7: 952118.61 | BK7: 0 | BL7: 377212.72 | BM7: 302490.57 | BN7: 297900.07 | BO7: 4590.5 | BP7: 74722.15 | BQ7: 74722.15 | BR7: 0 | BS7: 1218503.1 | BT7: 569569.1 | BU7: 569322.74 | BV7: 246.36 | BW7: 648933.96 | BX7: 648933.96 | BY7: 0 | BZ7: 624680 | CA7: 474453 | CB7: 469642 | CC7: 4811 | CD7: 150227 | CE7: 150227 | CF7: 0 | CG7: 337719 | CH7: 259483.5 | CI7: 258466 | CJ7: 1017.5 | CK7: 78235.5 | CL7: 78235.5 | CM7: 0 | CN7: -40 | CO7: 689197.99 | CP7: 419236.6 | CQ7: 258172.17 | CR7: 310994.13 | CS7: 0 | CT7: 0 | CU7: 0 | CV7: 2699 | CW7: 2302 | CX7: 2145 | CY7: 157 | CZ7: 397 | DA7: 276 | DB7: 121 | DC7: 1639 | DD7: 0 | DE7: 1432 | DF7: 1339 | DG7: 93 | DH7: 207 | DI7: 139 | DJ7: 68 | DK7: 712 | DL7: 591 | DM7: 554 | DN7: 37 | DO7: 121 | DP7: 88 | DQ7: 33 | DR7: 348 | DS7: 0 | DT7: 279 | DU7: 252 | DV7: 27 | DW7: 69 | DX7: 49 | DY7: 20 | DZ7: 0 | EA7: 0 | EB7: 0 | EC7: 0 | ED7: 0 | EE7: 0 | EF7: 0 | EG7: 90 | EH7: 70 | EI7: 68 | EJ7: 2 | EK7: 20 | EL7: 20 | EM7: 0 | EN7: 40 | EO7: 0 | EP7: 13 | EQ7: 27 | ER7: 0 | ES7: 0 | ET7: 0 | EU7: 3 | EV7: 0 | EW7: 3 | EX7: 0 | EY7: 10 | EZ7: 0 | FA7: 10 | FB7: 39
A8: 5 | B8: 成人非手术 | C8: 心血管内科 | D8: 4969508.5 | E8: 998835 | F8: 3970673.5 | G8: 6544 | H8: 371 | I8: 960 | J8: 0 | K8: 0 | L8: 36441 | M8: 813117 | N8: 30 | O8: 17362434 | P8: 12859950 | Q8: 12648764 | R8: 211186.37 | S8: 4502484 | T8: 4349361.4 | U8: 153122.69 | V8: 2701516.9 | W8: 2391446 | X8: 2318273.3 | Y8: 73172.76 | Z8: 310070.82 | AA8: 228351.39 | AB8: 81719.43 | AC8: 1688279.1 | AD8: 1524481.2 | AE8: 1495290.5 | AF8: 29190.76 | AG8: 163797.82 | AH8: 132616.39 | AI8: 31181.43 | AJ8: 14402.8 | AK8: 12123.8 | AL8: 11564.8 | AM8: 559 | AN8: 2279 | AO8: 1204 | AP8: 1075 | AQ8: 780374 | AR8: 664531 | AS8: 628890 | AT8: 35641 | AU8: 115843 | AV8: 73914 | AW8: 41929 | AX8: 218461 | AY8: 190310 | AZ8: 182528 | BA8: 7782 | BB8: 28151 | BC8: 20617 | BD8: 7534 | BE8: 14660918 | BF8: 10468504 | BG8: 10330491 | BH8: 138013.61 | BI8: 4192413.2 | BJ8: 4121010 | BK8: 71403.26 | BL8: 691466.24 | BM8: 512417.89 | BN8: 503409.58 | BO8: 9008.31 | BP8: 179048.35 | BQ8: 173812.23 | BR8: 5236.12 | BS8: 9998777.8 | BT8: 7088726.4 | BU8: 7007672.1 | BV8: 81054.3 | BW8: 2910051.4 | BX8: 2868796.7 | BY8: 41254.64 | BZ8: 2369817 | CA8: 1721004 | CB8: 1692772 | CC8: 28232 | CD8: 648813 | CE8: 637146 | CF8: 11667 | CG8: 1600856.5 | CH8: 1146356 | CI8: 1126637 | CJ8: 19719 | CK8: 454500.5 | CL8: 441255 | CM8: 13245.5 | CN8: -25 | CO8: 1493911.5 | CP8: 1074598.5 | CQ8: 107471.63 | CR8: 25535.19 | CS8: 0 | CT8: 0 | CU8: 0 | CV8: 6544 | CW8: 5726 | CX8: 5500 | CY8: 226 | CZ8: 818 | DA8: 595 | DB8: 223 | DC8: 4201 | DD8: 0 | DE8: 3695 | DF8: 3577 | DG8: 118 | DH8: 506 | DI8: 362 | DJ8: 144 | DK8: 2302 | DL8: 1997 | DM8: 1889 | DN8: 108 | DO8: 305 | DP8: 228 | DQ8: 77 | DR8: 41 | DS8: 0 | DT8: 34 | DU8: 34 | DV8: 0 | DW8: 7 | DX8: 5 | DY8: 2 | DZ8: 0 | EA8: 0 | EB8: 0 | EC8: 0 | ED8: 0 | EE8: 0 | EF8: 0 | EG8: 371 | EH8: 272 | EI8: 266 | EJ8: 6 | EK8: 99 | EL8: 97 | EM8: 2 | EN8: 328 | EO8: 47 | EP8: 171 | EQ8: 110 | ER8: 0 | ES8: 0 | ET8: 0 | EU8: 164 | EV8: 47 | EW8: 117 | EX8: 0 | EY8: 5 | EZ8: 0 | FA8: 5 | FB8: 60
A9: 6 | B9: 成人非手术 | C9: 血液内科 | D9: 31864 | E9: 31864 | F9: 0 | G9: 216 | H9: 0 | I9: 66 | J9: 0 | K9: 0 | L9: 0 | M9: 0 | N9: 0 | O9: 98461.53 | P9: 90683.25 | Q9: 88292.85 | R9: 2390.4 | S9: 7778.28 | T9: 6388.3 | U9: 1389.98 | V9: 98461.53 | W9: 90683.25 | X9: 88292.85 | Y9: 2390.4 | Z9: 7778.28 | AA9: 6388.3 | AB9: 1389.98 | AC9: 66554.53 | AD9: 63168.25 | AE9: 62357.85 | AF9: 810.4 | AG9: 3386.28 | AH9: 3290.3 | AI9: 95.98 | AJ9: 43 | AK9: 43 | AL9: 43 | AM9: 0 | AN9: 0 | AO9: 0 | AP9: 0 | AQ9: 24248 | AR9: 20979 | AS9: 19849 | AT9: 1130 | AU9: 3269 | AV9: 2300 | AW9: 969 | AX9: 7616 | AY9: 6493 | AZ9: 6043 | BA9: 450 | BB9: 1123 | BC9: 798 | BD9: 325 | BE9: 0 | BF9: 0 | BG9: 0 | BH9: 0 | BI9: 0 | BJ9: 0 | BK9: 0 | BL9: 0 | BM9: 0 | BN9: 0 | BO9: 0 | BP9: 0 | BQ9: 0 | BR9: 0 | BS9: 0 | BT9: 0 | BU9: 0 | BV9: 0 | BW9: 0 | BX9: 0 | BY9: 0 | BZ9: 0 | CA9: 0 | CB9: 0 | CC9: 0 | CD9: 0 | CE9: 0 | CF9: 0 | CG9: 0 | CH9: 0 | CI9: 0 | CJ9: 0 | CK9: 0 | CL9: 0 | CM9: 0 | CN9: 0 | CO9: 29680.1 | CP9: 68781.43 | CQ9: 0 | CR9: 0 | CS9: 0 | CT9: 0 | CU9: 0 | CV9: 216 | CW9: 184 | CX9: 172 | CY9: 12 | CZ9: 32 | DA9: 23 | DB9: 9 | DC9: 130 | DD9: 0 | DE9: 109 | DF9: 103 | DG9: 6 | DH9: 21 | DI9: 16 | DJ9: 5 | DK9: 86 | DL9: 75 | DM9: 69 | DN9: 6 | DO9: 11 | DP9: 7 | DQ9: 4 | DR9: 0 | DS9: 0 | DT9: 0 | DU9: 0 | DV9: 0 | DW9: 0 | DX9: 0 | DY9: 0 | DZ9: 0 | EA9: 0 | EB9: 0 | EC9: 0 | ED9: 0 | EE9: 0 | EF9: 0 | EG9: 0 | EH9: 0 | EI9: 0 | EJ9: 0 | EK9: 0 | EL9: 0 | EM9: 0 | EN9: 0 | EO9: 0 | EP9: 0 | EQ9: 0 | ER9: 0 | ES9: 0 | ET9: 0 | EU9: 0 | EV9: 0 | EW9: 0 | EX9: 0 | EY9: 0 | EZ9: 0 | FA9: 0 | FB9: 0
A10: 7 | B10: 成人非手术 | C10: 肾脏风湿免疫科 | D10: 1475518 | E10: 1131765 | F10: 343753 | G10: 2078 | H10: 45 | I10: 590155 | J10: 0 | K10: 0 | L10: 25239 | M10: 3561 | N10: 0 | O10: 2390558.7 | P10: 2025069.9 | Q10: 1996178.5 | R10: 28891.35 | S10: 365488.8 | T10: 343812.45 | U10: 21676.35 | V10: 1914252.4 | W10: 1724880.5 | X10: 1695989.1 | Y10: 28891.35 | Z10: 189371.93 | AA10: 167695.58 | AB10: 21676.35 | AC10: 706604.43 | AD10: 648966.5 | AE10: 635664.15 | AF10: 13302.35 | AG10: 57637.93 | AH10: 53125.58 | AI10: 4512.35 | AJ10: 75883 | AK10: 72107 | AL10: 72107 | AM10: 0 | AN10: 3776 | AO10: 3776 | AP10: 0 | AQ10: 469545 | AR10: 409900 | AS10: 396845 | AT10: 13055 | AU10: 59645 | AV10: 45059 | AW10: 14586 | AX10: 662220 | AY10: 593907 | AZ10: 591373 | BA10: 2534 | BB10: 68313 | BC10: 65735 | BD10: 2578 | BE10: 476306.26 | BF10: 300189.39 | BG10: 300189.39 | BH10: 0 | BI10: 176116.87 | BJ10: 176116.87 | BK10: 0 | BL10: 104584.79 | BM10: 65787.76 | BN10: 65787.76 | BO10: 0 | BP10: 38797.03 | BQ10: 38797.03 | BR10: 0 | BS10: 27968.47 | BT10: 18859.13 | BU10: 18859.13 | BV10: 0 | BW10: 9109.34 | BX10: 9109.34 | BY10: 0 | BZ10: 242303 | CA10: 154916 | CB10: 154916 | CC10: 0 | CD10: 87387 | CE10: 87387 | CF10: 0 | CG10: 101450 | CH10: 60626.5 | CI10: 60626.5 | CJ10: 0 | CK10: 40823.5 | CL10: 40823.5 | CM10: 0 | CN10: 0 | CO10: 536838.37 | CP10: 331092.2 | CQ10: 945251.37 | CR10: 101070.49 | CS10: 0 | CT10: 0 | CU10: 0 | CV10: 2078 | CW10: 1817 | CX10: 1741 | CY10: 76 | CZ10: 261 | DA10: 187 | DB10: 74 | DC10: 1594 | DD10: 0 | DE10: 1402 | DF10: 1343 | DG10: 59 | DH10: 192 | DI10: 138 | DJ10: 54 | DK10: 411 | DL10: 359 | DM10: 345 | DN10: 14 | DO10: 52 | DP10: 35 | DQ10: 17 | DR10: 73 | DS10: 0 | DT10: 56 | DU10: 53 | DV10: 3 | DW10: 17 | DX10: 14 | DY10: 3 | DZ10: 0 | EA10: 0 | EB10: 0 | EC10: 0 | ED10: 0 | EE10: 0 | EF10: 0 | EG10: 45 | EH10: 31 | EI10: 31 | EJ10: 0 | EK10: 14 | EL10: 14 | EM10: 0 | EN10: 15 | EO10: 1 | EP10: 0 | EQ10: 14 | ER10: 0 | ES10: 0 | ET10: 0 | EU10: 0 | EV10: 0 | EW10: 0 | EX10: 0 | EY10: 0 | EZ10: 0 | FA10: 0 | FB10: 34
A11: 8 | B11: 成人非手术 | C11: 内分泌科 | D11: 884415 | E11: 884415 | F11: 0 | G11: 3046 | H11: 0 | I11: 36 | J11: 574 | K11: 0 | L11: 0 | M11: 0 | N11: 0 | O11: 1456023.9 | P11: 1310031.7 | Q11: 1251873.8 | R11: 58157.87 | S11: 145992.19 | T11: 103912.89 | U11: 42079.3 | V11: 1456023.9 | W11: 1310031.7 | X11: 1251873.8 | Y11: 58157.87 | Z11: 145992.19 | AA11: 103912.89 | AB11: 42079.3 | AC11: 562847.28 | AD11: 510312.49 | AE11: 492984.22 | AF11: 17328.27 | AG11: 52534.79 | AH11: 40049.89 | AI11: 12484.9 | AJ11: 8761.6 | AK11: 7874.2 | AL11: 7669.6 | AM11: 204.6 | AN11: 887.4 | AO11: 516 | AP11: 371.4 | AQ11: 769455 | AR11: 690227 | AS11: 655194 | AT11: 35033 | AU11: 79228 | AV11: 53752 | AW11: 25476 | AX11: 114960 | AY11: 101618 | AZ11: 96026 | BA11: 5592 | BB11: 13342 | BC11: 9595 | BD11: 3747 | BE11: 0 | BF11: 0 | BG11: 0 | BH11: 0 | BI11: 0 | BJ11: 0 | BK11: 0 | BL11: 0 | BM11: 0 | BN11: 0 | BO11: 0 | BP11: 0 | BQ11: 0 | BR11: 0 | BS11: 0 | BT11: 0 | BU11: 0 | BV11: 0 | BW11: 0 | BX11: 0 | BY11: 0 | BZ11: 0 | CA11: 0 | CB11: 0 | CC11: 0 | CD11: 0 | CE11: 0 | CF11: 0 | CG11: 0 | CH11: 0 | CI11: 0 | CJ11: 0 | CK11: 0 | CL11: 0 | CM11: 0 | CN11: 0 | CO11: 718238.88 | CP11: 694136.47 | CQ11: 0 | CR11: 43648.53 | CS11: 0 | CT11: 0 | CU11: 0 | CV11: 3046 | CW11: 2691 | CX11: 2556 | CY11: 135 | CZ11: 355 | DA11: 253 | DB11: 102 | DC11: 1514 | DD11: 0 | DE11: 1340 | DF11: 1284 | DG11: 56 | DH11: 174 | DI11: 121 | DJ11: 53 | DK11: 1457 | DL11: 1284 | DM11: 1212 | DN11: 72 | DO11: 173 | DP11: 126 | DQ11: 47 | DR11: 75 | DS11: 0 | DT11: 67 | DU11: 60 | DV11: 7 | DW11: 8 | DX11: 6 | DY11: 2 | DZ11: 0 | EA11: 0 | EB11: 0 | EC11: 0 | ED11: 0 | EE11: 0 | EF11: 0 | EG11: 0 | EH11: 0 | EI11: 0 | EJ11: 0 | EK11: 0 | EL11: 0 | EM11: 0 | EN11: 0 | EO11: 0 | EP11: 0 | EQ11: 0 | ER11: 0 | ES11: 0 | ET11: 0 | EU11: 0 | EV11: 0 | EW11: 0 | EX11: 0 | EY11: 0 | EZ11: 0 | FA11: 0 | FB11: 0
A12: 9 | B12: 成人手术 | C12: 普外科 | D12: 4281436.2 | E12: 910151 | F12: 3371285.2 | G12: 3530 | H12: 313 | I12: 40725 | J12: 22636 | K12: 0 | L12: 251061.25 | M12: 1041823 | N12: 427.5 | O12: 8384687.4 | P12: 6430022.8 | Q12: 6298437.3 | R12: 131585.51 | S12: 1954664.5 | T12: 1883834.9 | U12: 70829.64 | V12: 1227740.8 | W12: 1022111.2 | X12: 969930.41 | Y12: 52180.84 | Z12: 205629.58 | AA12: 134799.94 | AB12: 70829.64 | AC12: 246160.94 | AD12: 204431.28 | AE12: 197707.61 | AF12: 6723.67 | AG12: 41729.66 | AH12: 29982.25 | AI12: 11747.41 | AJ12: 71428.89 | AK12: 63956.97 | AL12: 61528.8 | AM12: 2428.17 | AN12: 7471.92 | AO12: 5426.69 | AP12: 2045.23 | AQ12: 722658 | AR12: 595095 | AS12: 561378 | AT12: 33717 | AU12: 127563 | AV12: 80911 | AW12: 46652 | AX12: 187493 | AY12: 158628 | AZ12: 149316 | BA12: 9312 | BB12: 28865 | BC12: 18480 | BD12: 10385 | BE12: 7156946.5 | BF12: 5407911.6 | BG12: 5328506.9 | BH12: 79404.67 | BI12: 1749035 | BJ12: 1749035 | BK12: 0 | BL12: 1092321.7 | BM12: 808020.62 | BN12: 798389.59 | BO12: 9631.03 | BP12: 284301.11 | BQ12: 284301.11 | BR12: 0 | BS12: 2693339.5 | BT12: 2037978.4 | BU12: 2007764.8 | BV12: 30213.64 | BW12: 655361.1 | BX12: 655361.1 | BY12: 0 | BZ12: 1126147 | CA12: 827296 | CB12: 811677 | CC12: 15619 | CD12: 298851 | CE12: 298851 | CF12: 0 | CG12: 2245138.2 | CH12: 1734616.5 | CI12: 1710675.5 | CJ12: 23941 | CK12: 510521.75 | CL12: 510521.75 | CM12: 0 | CN12: 568765.66 | CO12: 219173.34 | CP12: 341211.19 | CQ12: 89852.53 | CR12: 8713.11 | CS12: 0 | CT12: 9463.52 | CU12: 0 | CV12: 3530 | CW12: 2929 | CX12: 2742 | CY12: 187 | CZ12: 601 | DA12: 375 | DB12: 226 | DC12: 1210 | DD12: 0 | DE12: 1030 | DF12: 957 | DG12: 73 | DH12: 180 | DI12: 112 | DJ12: 68 | DK12: 1085 | DL12: 884 | DM12: 834 | DN12: 50 | DO12: 201 | DP12: 118 | DQ12: 83 | DR12: 30 | DS12: 0 | DT12: 20 | DU12: 20 | DV12: 0 | DW12: 10 | DX12: 7 | DY12: 3 | DZ12: 1205 | EA12: 995 | EB12: 931 | EC12: 64 | ED12: 210 | EE12: 138 | EF12: 72 | EG12: 313 | EH12: 244 | EI12: 238 | EJ12: 6 | EK12: 69 | EL12: 69 | EM12: 0 | EN12: 282 | EO12: 227 | EP12: 0 | EQ12: 55 | ER12: 151 | ES12: 0 | ET12: 0 | EU12: 102 | EV12: 88 | EW12: 0 | EX12: 14 | EY12: 47 | EZ12: 47 | FA12: 0 | FB12: 138
A13: 10 | B13: 成人手术 | C13: 神经外科 | D13: 3534166 | E13: 265530 | F13: 3268636 | G13: 1270 | H13: 228 | I13: 256 | J13: 0 | K13: 0 | L13: 186303.75 | M13: 1025526.8 | N13: 0 | O13: 16169423 | P13: 10419652 | Q13: 10126396 | R13: 293255.82 | S13: 5749770.9 | T13: 5719633.9 | U13: 30136.98 | V13: 426576.48 | W13: 356480.59 | X13: 318919.62 | Y13: 37560.97 | Z13: 70095.89 | AA13: 39958.91 | AB13: 30136.98 | AC13: 156058.48 | AD13: 134274.59 | AE13: 126587.62 | AF13: 7686.97 | AG13: 21783.89 | AH13: 14101.91 | AI13: 7681.98 | AJ13: 4988 | AK13: 3956 | AL13: 3526 | AM13: 430 | AN13: 1032 | AO13: 473 | AP13: 559 | AQ13: 225344 | AR13: 186559 | AS13: 161004 | AT13: 25555 | AU13: 38785 | AV13: 20284 | AW13: 18501 | AX13: 40186 | AY13: 31691 | AZ13: 27802 | BA13: 3889 | BB13: 8495 | BC13: 5100 | BD13: 3395 | BE13: 15742846 | BF13: 10063171 | BG13: 9807476.6 | BH13: 255694.85 | BI13: 5679675 | BJ13: 5679675 | BK13: 0 | BL13: 1222420.3 | BM13: 706439.28 | BN13: 674550.12 | BO13: 31889.16 | BP13: 515981.03 | BQ13: 515981.03 | BR13: 0 | BS13: 11251790 | BT13: 7527102.6 | BU13: 7386480 | BV13: 140622.69 | BW13: 3724687.5 | BX13: 3724687.5 | BY13: 0 | BZ13: 1261532 | CA13: 723758 | CB13: 689500 | CC13: 34258 | CD13: 537774 | CE13: 537774 | CF13: 0 | CG13: 2007104 | CH13: 1105871.5 | CI13: 1056946.5 | CJ13: 48925 | CK13: 901232.5 | CL13: 901232.5 | CM13: 0 | CN13: 0 | CO13: 277328.64 | CP13: 121933.78 | CQ13: 27314.06 | CR13: 0 | CS13: 0 | CT13: 22427.06 | CU13: 0 | CV13: 1270 | CW13: 1019 | CX13: 897 | CY13: 122 | CZ13: 251 | DA13: 151 | DB13: 100 | DC13: 906 | DD13: 0 | DE13: 743 | DF13: 654 | DG13: 89 | DH13: 163 | DI13: 94 | DJ13: 69 | DK13: 364 | DL13: 276 | DM13: 243 | DN13: 33 | DO13: 88 | DP13: 57 | DQ13: 31 | DR13: 0 | DS13: 0 | DT13: 0 | DU13: 0 | DV13: 0 | DW13: 0 | DX13: 0 | DY13: 0 | DZ13: 0 | EA13: 0 | EB13: 0 | EC13: 0 | ED13: 0 | EE13: 0 | EF13: 0 | EG13: 228 | EH13: 147 | EI13: 139 | EJ13: 8 | EK13: 81 | EL13: 81 | EM13: 0 | EN13: 197 | EO13: 66 | EP13: 86 | EQ13: 45 | ER13: 30 | ES13: 0 | ET13: 0 | EU13: 16 | EV13: 12 | EW13: 3 | EX13: 1 | EY13: 121 | EZ13: 38 | FA13: 83 | FB13: 84
A14: 11 | B14: 成人手术 | C14: 骨科 | D14: 5884594 | E14: 1483465 | F14: 4401129 | G14: 7534 | H14: 364 | I14: 47351 | J14: 17555 | K14: 0 | L14: 324702.75 | M14: 2144705.2 | N14: 0 | O14: 16917633 | P14: 13487881 | Q14: 9984307.9 | R14: 3503572.8 | S14: 3429752.8 | T14: 3127080.2 | U14: 302672.54 | V14: 2859226.9 | W14: 2407706.9 | X14: 1685237.8 | Y14: 722469.12 | Z14: 451519.93 | AA14: 194296.53 | AB14: 257223.4 | AC14: 763448.72 | AD14: 642372.5 | AE14: 484505.01 | AF14: 157867.49 | AG14: 121076.22 | AH14: 51557.94 | AI14: 69518.28 | AJ14: 612313.15 | AK14: 530128.94 | AL14: 294864.81 | AM14: 235264.13 | AN14: 82184.21 | AO14: 29609.59 | AP14: 52574.62 | AQ14: 1159950 | AR14: 967501 | AS14: 705787 | AT14: 261714 | AU14: 192449 | AV14: 86945 | AW14: 105504 | AX14: 323515 | AY14: 267704.5 | AZ14: 200081 | BA14: 67623.5 | BB14: 55810.5 | BC14: 26184 | BD14: 29626.5 | BE14: 14058407 | BF14: 11080174 | BG14: 8299070.1 | BH14: 2781103.7 | BI14: 2978232.8 | BJ14: 2932783.7 | BK14: 45449.14 | BL14: 1081542.2 | BM14: 847124.22 | BN14: 626657.51 | BO14: 220466.71 | BP14: 234417.95 | BQ14: 229429.56 | BR14: 4988.39 | BS14: 8575735.4 | BT14: 6784714 | BU14: 4994748.6 | BV14: 1789965.5 | BW14: 1791021.4 | BX14: 1765519.6 | BY14: 25501.75 | BZ14: 899895 | CA14: 703113 | CB14: 554396 | CC14: 148717 | CD14: 196782 | CE14: 194433 | CF14: 2349 | CG14: 3501234 | CH14: 2745222.5 | CI14: 2123268 | CJ14: 621954.5 | CK14: 756011.5 | CL14: 743401.5 | CM14: 12610 | CN14: 1311112 | CO14: 781300.82 | CP14: 737574.41 | CQ14: 0 | CR14: 29239.6 | CS14: 0 | CT14: 0 | CU14: 0 | CV14: 7534 | CW14: 6247 | CX14: 4835 | CY14: 1412 | CZ14: 1287 | DA14: 594 | DB14: 693 | DC14: 2889 | DD14: 0 | DE14: 2408 | DF14: 1982 | DG14: 426 | DH14: 481 | DI14: 220 | DJ14: 261 | DK14: 2780 | DL14: 2323 | DM14: 1932 | DN14: 391 | DO14: 457 | DP14: 246 | DQ14: 211 | DR14: 69 | DS14: 0 | DT14: 55 | DU14: 44 | DV14: 11 | DW14: 14 | DX14: 9 | DY14: 5 | DZ14: 1796 | EA14: 1461 | EB14: 877 | EC14: 584 | ED14: 335 | EE14: 119 | EF14: 216 | EG14: 364 | EH14: 288 | EI14: 220 | EJ14: 68 | EK14: 76 | EL14: 73 | EM14: 3 | EN14: 330 | EO14: 324 | EP14: 0 | EQ14: 6 | ER14: 109 | ES14: 0 | ET14: 0 | EU14: 125 | EV14: 125 | EW14: 0 | EX14: 0 | EY14: 75 | EZ14: 75 | FA14: 0 | FB14: 139
A15: 12 | B15: 成人手术 | C15: 泌尿外科 | D15: 3599639 | E15: 604335 | F15: 2995304 | G15: 3265 | H15: 314 | I15: 49174 | J15: 4852 | K15: 0 | L15: 712941.75 | M15: 668764.25 | N15: 112.5 | O15: 6101226.1 | P15: 4893541.8 | Q15: 4770222.4 | R15: 123319.38 | S15: 1207684.3 | T15: 1138913.6 | U15: 68770.69 | V15: 1333965 | W15: 1111916.1 | X15: 1062039.1 | Y15: 49877.01 | Z15: 222048.95 | AA15: 165084.4 | AB15: 56964.55 | AC15: 629696.42 | AD15: 533991.11 | AE15: 521074.71 | AF15: 12916.4 | AG15: 95705.31 | AH15: 80478.07 | AI15: 15227.24 | AJ15: 99933.62 | AK15: 79754.98 | AL15: 74217.37 | AM15: 5537.61 | AN15: 20178.64 | AO15: 15177.33 | AP15: 5001.31 | AQ15: 438793 | AR15: 360848 | AS15: 338491 | AT15: 22357 | AU15: 77945 | AV15: 50063 | AW15: 27882 | AX15: 165542 | AY15: 137322 | AZ15: 128256 | BA15: 9066 | BB15: 28220 | BC15: 19366 | BD15: 8854 | BE15: 4767261 | BF15: 3781625.7 | BG15: 3708183.3 | BH15: 73442.37 | BI15: 985635.32 | BJ15: 973829.18 | BK15: 11806.14 | BL15: 545557.95 | BM15: 427398.8 | BN15: 421286.86 | BO15: 6111.94 | BP15: 118159.15 | BQ15: 117302.51 | BR15: 856.64 | BS15: 1226399.1 | BT15: 964333.16 | BU15: 948760.23 | BV15: 15572.93 | BW15: 262065.92 | BX15: 261504.92 | BY15: 561 | BZ15: 999858 | CA15: 796725 | CB15: 790728 | CC15: 5997 | CD15: 203133 | CE15: 203133 | CF15: 0 | CG15: 1995446 | CH15: 1593168.8 | CI15: 1547408.2 | CJ15: 45760.5 | CK15: 402277.25 | CL15: 391888.75 | CM15: 10388.5 | CN15: 198565.33 | CO15: 464544.47 | CP15: 664152.36 | CQ15: 0 | CR15: 6702.88 | CS15: 0 | CT15: 51750.47 | CU15: 0 | CV15: 3265 | CW15: 2757 | CX15: 2584 | CY15: 173 | CZ15: 508 | DA15: 333 | DB15: 175 | DC15: 1519 | DD15: 0 | DE15: 1296 | DF15: 1213 | DG15: 83 | DH15: 223 | DI15: 146 | DJ15: 77 | DK15: 1182 | DL15: 1001 | DM15: 953 | DN15: 48 | DO15: 181 | DP15: 124 | DQ15: 57 | DR15: 11 | DS15: 0 | DT15: 7 | DU15: 6 | DV15: 1 | DW15: 4 | DX15: 3 | DY15: 1 | DZ15: 553 | EA15: 453 | EB15: 412 | EC15: 41 | ED15: 100 | EE15: 60 | EF15: 40 | EG15: 314 | EH15: 251 | EI15: 244 | EJ15: 7 | EK15: 63 | EL15: 62 | EM15: 1 | EN15: 291 | EO15: 217 | EP15: 0 | EQ15: 74 | ER15: 35 | ES15: 0 | ET15: 0 | EU15: 148 | EV15: 148 | EW15: 0 | EX15: 0 | EY15: 45 | EZ15: 45 | FA15: 0 | FB15: 96
... A58: 55 | B58: 医技平台 | C58: 超声诊断科 | D58: 17034 | E58: 17034 | F58: 0 | G58: 36 | H58: 0 | I58: 0 | J58: 3018 | K58: 0 | L58: 0 | M58: 0 | N58: 0 | O58: 21659.18 | P58: 19215.18 | Q58: 18317.65 | R58: 897.53 | S58: 2444 | T58: 2444 | U58: 0 | V58: 21659.18 | W58: 19215.18 | X58: 18317.65 | Y58: 897.53 | Z58: 2444 | AA58: 2444 | AB58: 0 | AC58: 3075.18 | AD58: 3075.18 | AE58: 2562.65 | AF58: 512.53 | AG58: 0 | AH58: 0 | AI58: 0 | AJ58: 1550 | AK58: 1360 | AL58: 1360 | AM58: 0 | AN58: 190 | AO58: 190 | AP58: 0 | AQ58: 12636 | AR58: 11141 | AS58: 10821 | AT58: 320 | AU58: 1495 | AV58: 1495 | AW58: 0 | AX58: 4398 | AY58: 3639 | AZ58: 3574 | BA58: 65 | BB58: 759 | BC58: 759 | BD58: 0 | BE58: 0 | BF58: 0 | BG58: 0 | BH58: 0 | BI58: 0 | BJ58: 0 | BK58: 0 | BL58: 0 | BM58: 0 | BN58: 0 | BO58: 0 | BP58: 0 | BQ58: 0 | BR58: 0 | BS58: 0 | BT58: 0 | BU58: 0 | BV58: 0 | BW58: 0 | BX58: 0 | BY58: 0 | BZ58: 0 | CA58: 0 | CB58: 0 | CC58: 0 | CD58: 0 | CE58: 0 | CF58: 0 | CG58: 0 | CH58: 0 | CI58: 0 | CJ58: 0 | CK58: 0 | CL58: 0 | CM58: 0 | CN58: 0 | CO58: 2713 | CP58: 12024.12 | CQ58: 6922.06 | CR58: 0 | CS58: 0 | CT58: 0 | CU58: 0 | CV58: 36 | CW58: 31 | CX58: 29 | CY58: 2 | CZ58: 5 | DA58: 5 | DB58: 0 | DC58: 4 | DD58: 0 | DE58: 3 | DF58: 2 | DG58: 1 | DH58: 1 | DI58: 1 | DJ58: 0 | DK58: 32 | DL58: 28 | DM58: 27 | DN58: 1 | DO58: 4 | DP58: 4 | DQ58: 0 | DR58: 0 | DS58: 0 | DT58: 0 | DU58: 0 | DV58: 0 | DW58: 0 | DX58: 0 | DY58: 0 | DZ58: 0 | EA58: 0 | EB58: 0 | EC58: 0 | ED58: 0 | EE58: 0 | EF58: 0 | EG58: 0 | EH58: 0 | EI58: 0 | EJ58: 0 | EK58: 0 | EL58: 0 | EM58: 0 | EN58: 14 | EO58: 0 | EP58: 0 | EQ58: 14 | ER58: 0 | ES58: 0 | ET58: 0 | EU58: 0 | EV58: 0 | EW58: 0 | EX58: 0 | EY58: 0 | EZ58: 0 | FA58: 0 | FB58: 0
A59: 56 | C59: 其它 | D59: 0 | E59: 0 | F59: 0 | G59: 151 | H59: 0 | I59: 0 | J59: 0 | K59: 0 | L59: 0 | M59: 0 | N59: 0 | O59: 461875.28 | P59: 375685.16 | Q59: 292336.4 | R59: 83348.76 | S59: 86190.12 | T59: 60390.12 | U59: 25800 | V59: 0 | W59: 0 | X59: 0 | Y59: 0 | Z59: 0 | AA59: 0 | AB59: 0 | AC59: 0 | AD59: 0 | AE59: 0 | AF59: 0 | AG59: 0 | AH59: 0 | AI59: 0 | AJ59: 0 | AK59: 0 | AL59: 0 | AM59: 0 | AN59: 0 | AO59: 0 | AP59: 0 | AQ59: 0 | AR59: 0 | AS59: 0 | AT59: 0 | AU59: 0 | AV59: 0 | AW59: 0 | AX59: 0 | AY59: 0 | AZ59: 0 | BA59: 0 | BB59: 0 | BC59: 0 | BD59: 0 | BE59: 461875.28 | BF59: 375685.16 | BG59: 292336.4 | BH59: 83348.76 | BI59: 86190.12 | BJ59: 60390.12 | BK59: 25800 | BL59: 0 | BM59: 0 | BN59: 0 | BO59: 0 | BP59: 0 | BQ59: 0 | BR59: 0 | BS59: 461875.28 | BT59: 375685.16 | BU59: 292336.4 | BV59: 83348.76 | BW59: 86190.12 | BX59: 60390.12 | BY59: 25800 | BZ59: 0 | CA59: 0 | CB59: 0 | CC59: 0 | CD59: 0 | CE59: 0 | CF59: 0 | CG59: 0 | CH59: 0 | CI59: 0 | CJ59: 0 | CK59: 0 | CL59: 0 | CM59: 0 | CN59: 0 | CO59: 0 | CP59: 0 | CQ59: 0 | CR59: 0 | CS59: 0 | CT59: 103200 | CU59: 0 | CV59: 151 | CW59: 34 | CX59: 0 | CY59: 34 | CZ59: 117 | DA59: 0 | DB59: 117 | DC59: 151 | DD59: 0 | DE59: 34 | DF59: 0 | DG59: 34 | DH59: 117 | DI59: 0 | DJ59: 117 | DK59: 0 | DL59: 0 | DM59: 0 | DN59: 0 | DO59: 0 | DP59: 0 | DQ59: 0 | DR59: 0 | DS59: 0 | DT59: 0 | DU59: 0 | DV59: 0 | DW59: 0 | DX59: 0 | DY59: 0 | DZ59: 0 | EA59: 0 | EB59: 0 | EC59: 0 | ED59: 0 | EE59: 0 | EF59: 0 | EG59: 0 | EH59: 0 | EI59: 0 | EJ59: 0 | EK59: 0 | EL59: 0 | EM59: 0 | EN59: 0 | EO59: 0 | EP59: 0 | EQ59: 0 | ER59: 0 | ES59: 0 | ET59: 0 | EU59: 0 | EV59: 0 | EW59: 0 | EX59: 0 | EY59: 0 | EZ59: 0 | FA59: 0 | FB59: 0

Sheet 去年累计数据表
A1: 日期范围：20250501-20250531 | D1: 25 | O1: 1=2+5=8+43 | P1: 2=3+4 | Q1: 3 | R1: 4 | S1: 5=6+7 | T1: 6 | U1: 7 | V1: 8=9+12=15+22+29+36 | W1: 9=10+11 | X1: 10 | Y1: 11 | Z1: 12=13+14 | AA1: 13 | AB1: 14 | AC1: 15=16+19 | AD1: 16=17+18 | AE1: 17 | AF1: 18 | AG1: 19=20+21 | AH1: 20 | AI1: 21 | AJ1: 22=23+26 | AK1: 23=24+25 | AL1: 24 | AM1: 25 | AN1: 26=27+28 | AO1: 27 | AP1: 28 | AQ1: 29=30+33 | AR1: 30=31+32 | AS1: 31 | AT1: 32 | AU1: 33=34+35 | AV1: 34 | AW1: 35 | AX1: 36=37+40 | AY1: 37=38+39 | AZ1: 38 | BA1: 39 | BB1: 40=41+42 | BC1: 41 | BD1: 42 | BE1: 43=50+57+64+71=44+47 | BF1: 44=45+46 | BG1: 45 | BH1: 46 | BI1: 47=48+49 | BJ1: 48 | BK1: 49 | BL1: 50=51+54 | BM1: 51=52+53 | BN1: 52 | BO1: 53 | BP1: 54=55+56 | BQ1: 55 | BR1: 56 | BS1: 57=58+61 | BT1: 58=59+60 | BU1: 59 | BV1: 60 | BW1: 61=62+63 | BX1: 62 | BY1: 63 | BZ1: 64=65+68 | CA1: 65=66+67 | CB1: 66 | CC1: 67 | CD1: 68=69+70 | CE1: 69 | CF1: 70 | CG1: 71=72+75 | CH1: 72=73+74 | CI1: 73 | CJ1: 74 | CK1: 75=76+77 | CL1: 76 | CM1: 77 | CV1: 78=85+93+100+108+86+101=79+82 | CW1: 79=80+81 | CX1: 80 | CY1: 81 | CZ1: 82=83+84 | DA1: 83 | DB1: 84 | DC1: 85=87+90=78-93-100-108-86-101 | DD1: 86 | DE1: 87=88+89 | DF1: 88 | DG1: 89 | DH1: 90=91+92 | DI1: 91 | DJ1: 92 | DK1: 93=94+97 | DL1: 94=95+96 | DM1: 95 | DN1: 96 | DO1: 97=98+99 | DP1: 98 | DQ1: 99 | DR1: 100=102+105 | DS1: 101 | DT1: 102=103+104 | DU1: 103 | DV1: 104 | DW1: 105=106+107 | DX1: 106 | DY1: 107 | DZ1: 108=109+112 | EA1: 109=110+111 | EB1: 110 | EC1: 111 | ED1: 112=113+114 | EE1: 113 | EF1: 114 | EG1: 115=116+119 | EH1: 116=117+118 | EI1: 117 | EJ1: 118 | EK1: 119=120+121 | EL1: 120 | EM1: 121 | EN1: 122=123+124+125 | EO1: 123 | EP1: 124 | EQ1: 125 | EU1: 126=127+128+129 | EV1: 127 | EW1: 128 | EX1: 129 | EY1: 130=131+132 | EZ1: 131 | FA1: 132 | FB1: 133
A2: 序号 | B2: 科室类别 | C2: 科室名称 | D2: 医疗收入不含药耗 | E2: 门急诊收入不含药耗 | F2: 住院收入不含药耗 | G2: 门急诊人次 | H2: 住院人次 | I2: 门急诊治疗收入 | J2: 门急诊手术收入 | K2: 门诊中药饮片收入 | L2: 住院治疗收入 | M2: 住院手术收入 | N2: 住院中药饮片收入 | O2: 医疗收入 | P2: 其中本地病人医疗收入 | Q2: 其中本地病人医保医疗收入 | R2: 其中本地病人自费医疗收入 | S2: 其中异地病人医疗收入 | T2: 其中异地病人医保医疗收入 | U2: 其中异地病人自费医疗收入 | V2: 门急诊收入 | W2: 其中本地病人医疗收入 | X2: 其中本地病人医保医疗收入 | Y2: 其中本地病人自费医疗收入 | Z2: 其中异地病人医疗收入 | AA2: 其中异地病人医保医疗收入 | AB2: 其中异地病人自费医疗收入 | AC2: 门急诊药品收入 | AD2: 其中本地病人医疗收入 | AE2: 其中本地病人医保医疗收入 | AF2: 其中本地病人自费医疗收入 | AG2: 其中异地病人医疗收入 | AH2: 其中异地病人医保医疗收入 | AI2: 其中异地病人自费医疗收入 | AJ2: 门急诊耗材收入 | AK2: 其中本地病人医疗收入 | AL2: 其中本地病人医保医疗收入 | AM2: 其中本地病人自费医疗收入 | AN2: 其中异地病人医疗收入 | AO2: 其中异地病人医保医疗收入 | AP2: 其中异地病人自费医疗收入 | AQ2: 门急诊检查化验收入 | AR2: 其中本地病人医疗收入 | AS2: 其中本地病人医保医疗收入 | AT2: 其中本地病人自费医疗收入 | AU2: 其中异地病人医疗收入 | AV2: 其中异地病人医保医疗收入 | AW2: 其中异地病人自费医疗收入 | AX2: 门急诊劳务收入 | AY2: 其中本地病人医疗收入 | AZ2: 其中本地病人医保医疗收入 | BA2: 其中本地病人自费医疗收入 | BB2: 其中异地病人医疗收入 | BC2: 其中异地病人医保医疗收入 | BD2: 其中异地病人自费医疗收入 | BE2: 住院收入 | BF2: 其中本地病人医疗收入 | BG2: 其中本地病人医保医疗收入 | BH2: 其中本地病人自费医疗收入 | BI2: 其中异地病人医疗收入 | BJ2: 其中异地病人医保医疗收入 | BK2: 其中异地病人自费医疗收入 | BL2: 住院药品收入 | BM2: 其中本地病人医疗收入 | BN2: 其中本地病人医保医疗收入 | BO2: 其中本地病人自费医疗收入 | BP2: 其中异地病人医疗收入 | BQ2: 其中异地病人医保医疗收入 | BR2: 其中异地病人自费医疗收入 | BS2: 住院耗材收入 | BT2: 其中本地病人医疗收入 | BU2: 其中本地病人医保医疗收入 | BV2: 其中本地病人自费医疗收入 | BW2: 其中异地病人医疗收入 | BX2: 其中异地病人医保医疗收入 | BY2: 其中异地病人自费医疗收入 | BZ2: 住院检查化验收入 | CA2: 其中本地病人医疗收入 | CB2: 其中本地病人医保医疗收入 | CC2: 其中本地病人自费医疗收入 | CD2: 其中异地病人医疗收入 | CE2: 其中异地病人医保医疗收入 | CF2: 其中异地病人自费医疗收入 | CG2: 住院劳务收入 | CH2: 其中本地病人医疗收入 | CI2: 其中本地病人医保医疗收入 | CJ2: 其中本地病人自费医疗收入 | CK2: 其中异地病人医疗收入 | CL2: 其中异地病人医保医疗收入 | CM2: 其中异地病人自费医疗收入 | CN2: 急诊收入 | CO2: 普通门诊收入 | CP2: 专家门诊收入 | CQ2: 专病门诊收入 | CR2: 特需门诊收入 | CS2: MDT门诊收入 | CT2: 镜朗诊疗部收入 | CU2: 特需病房收入 | CV2: 门急诊人次 | CW2: 其中本地病人人次 | CX2: 其中本地病人医保人次 | CY2: 其中本地病人自费人次 | CZ2: 其中异地病人人次 | DA2: 其中异地病人医保人次 | DB2: 其中异地病人自费人次 | DC2: 普通门诊 (普通+专病) | DD2: 互联网普通门诊人次 | DE2: 其中本地病人人次 | DF2: 其中本地病人医保人次 | DG2: 其中本地病人自费人次 | DH2: 其中异地病人人次 | DI2: 其中异地病人医保人次 | DJ2: 其中异地病人自费人次 | DK2: 专家门诊 | DL2: 其中本地病人人次 | DM2: 其中本地病人医保人次 | DN2: 其中本地病人自费人次 | DO2: 其中异地病人人次 | DP2: 其中异地病人医保人次 | DQ2: 其中异地病人自费人次 | DR2: 特需门诊 (特需+MDT) | DS2: 互联网特需门诊人次 | DT2: 其中本地病人人次 | DU2: 其中本地病人医保人次 | DV2: 其中本地病人自费人次 | DW2: 其中异地病人人次 | DX2: 其中异地病人医保人次 | DY2: 其中异地病人自费人次 | DZ2: 急诊人次 | EA2: 其中本地病人人次 | EB2: 其中本地病人医保人次 | EC2: 其中本地病人自费人次 | ED2: 其中异地病人人次 | EE2: 其中异地病人医保人次 | EF2: 其中异地病人自费人次 | EG2: 住院人次 | EH2: 其中本地病人人次 | EI2: 其中本地病人医保人次 | EJ2: 其中本地病人自费人次 | EK2: 其中异地病人人次 | EL2: 其中异地病人医保人次 | EM2: 其中异地病人自费人次 | EN2: 手术人次与操作人次 | EO2: 手术人次 | EP2: 介入人次 | EQ2: 操作人次(治疗+诊断) | ER2: 微创手术人次（手术） | ES2: 微创手术人次（介入） | ET2: 微创手术人次（操作） | EU2: 三级手术 | EV2: 三级手术(手术) | EW2: 三级手术(介入) | EX2: 三级手术(操作) | EY2: 四级手术 | EZ2: 四级手术(手术) | FA2: 四级手术(介入) | FB2: 重点病种人次
A3: 小计： | D3: 2.2736088e+08 | E3: 97233114 | F3: 1.3012777e+08 | G3: 338994 | H3: 13003 | I3: 16745706 | J3: 3555656.4 | K3: 2487959 | L3: 15288069 | M3: 26472725 | N3: 84038.57 | O3: 4.8012503e+08 | P3: 3.1042097e+08 | Q3: 2.8369187e+08 | R3: 26729097 | S3: 1.6970406e+08 | T3: 1.3903474e+08 | U3: 30669322 | V3: 1.709079e+08 | W3: 1.4258172e+08 | X3: 1.2959603e+08 | Y3: 12985694 | Z3: 28326182 | AA3: 12529387 | AB3: 15796795 | AC3: 67288362 | AD3: 60189147 | AE3: 57732458 | AF3: 2456688.9 | AG3: 7099214.8 | AH3: 4218233.3 | AI3: 2880981.5 | AJ3: 6386427.3 | AK3: 5723032.5 | AL3: 5185892 | AM3: 537140.5 | AN3: 663394.82 | AO3: 342962.49 | AP3: 320432.33 | AQ3: 54278068 | AR3: 43921589 | AS3: 39407210 | AT3: 4514379 | AU3: 10356479 | AV3: 4533481 | AW3: 5822998 | AX3: 42955046 | AY3: 32747952 | AZ3: 27270467 | BA3: 5477485.7 | BB3: 10207094 | BC3: 3434710.3 | BD3: 6772383.5 | BE3: 3.0921713e+08 | BF3: 1.6783925e+08 | BG3: 1.5409584e+08 | BH3: 13743403 | BI3: 1.4137788e+08 | BJ3: 1.2650535e+08 | BK3: 14872527 | BL3: 58232391 | BM3: 30098082 | BN3: 27802501 | BO3: 2295581.5 | BP3: 28134308 | BQ3: 25967292 | BR3: 2167016.1 | BS3: 1.2085697e+08 | BT3: 68932238 | BU3: 64976079 | BV3: 3956158.9 | BW3: 51924731 | BX3: 47812010 | BY3: 4112721 | BZ3: 53351035 | CA3: 30000898 | CB3: 28051918 | CC3: 1948980 | CD3: 23350136 | CE3: 21067875 | CF3: 2282261.7 | CG3: 76776732 | CH3: 38808028 | CI3: 33265345 | CJ3: 5542682.5 | CK3: 37968704 | CL3: 31658176 | CM3: 6310528.1 | CN3: 21565506 | CO3: 60135521 | CP3: 40537135 | CQ3: 23569740 | CR3: 24434005 | CS3: 665792.12 | CT3: 8989468.3 | CU3: 0 | CV3: 338994 | CW3: 288093 | CX3: 261435 | CY3: 26658 | CZ3: 50901 | DA3: 22420 | DB3: 28481 | DC3: 183608 | DD3: 3671 | DE3: 162556 | DF3: 150469 | DG3: 12087 | DH3: 21052 | DI3: 10355 | DJ3: 10697 | DK3: 73423 | DL3: 58820 | DM3: 53316 | DN3: 5504 | DO3: 14603 | DP3: 6997 | DQ3: 7606 | DR3: 33211 | DS3: 97 | DT3: 23884 | DU3: 19563 | DV3: 4321 | DW3: 9327 | DX3: 2914 | DY3: 6413 | DZ3: 44984 | EA3: 39669 | EB3: 35582 | EC3: 4087 | ED3: 5315 | EE3: 2116 | EF3: 3199 | EG3: 13003 | EH3: 7733 | EI3: 7078 | EJ3: 655 | EK3: 5270 | EL3: 4539 | EM3: 731 | EN3: 10654 | EO3: 5005 | EP3: 554 | EQ3: 5095 | ER3: 1255 | ES3: 0 | ET3: 113 | EU3: 2013 | EV3: 1589 | EW3: 300 | EX3: 124 | EY3: 1716 | EZ3: 1575 | FA3: 141 | FB3: 2757
A4: 1 | B4: 成人非手术 | C4: 内科 | D4: 146843 | E4: 146843 | F4: 0 | G4: 739 | H4: 0 | I4: 480 | J4: 0 | K4: 0 | L4: 0 | M4: 0 | N4: 0 | O4: 349574.07 | P4: 324942.87 | Q4: 312249.81 | R4: 12693.06 | S4: 24631.2 | T4: 22856.77 | U4: 1774.43 | V4: 349574.07 | W4: 324942.87 | X4: 312249.81 | Y4: 12693.06 | Z4: 24631.2 | AA4: 22856.77 | AB4: 1774.43 | AC4: 201815.67 | AD4: 195184.47 | AE4: 191853.21 | AF4: 3331.26 | AG4: 6631.2 | AH4: 6147.77 | AI4: 483.43 | AJ4: 915.4 | AK4: 915.4 | AL4: 769.6 | AM4: 145.8 | AN4: 0 | AO4: 0 | AP4: 0 | AQ4: 121169 | AR4: 104454 | AS4: 97846 | AT4: 6608 | AU4: 16715 | AV4: 15679 | AW4: 1036 | AX4: 25674 | AY4: 24389 | AZ4: 21781 | BA4: 2608 | BB4: 1285 | BC4: 1030 | BD4: 255 | BE4: 0 | BF4: 0 | BG4: 0 | BH4: 0 | BI4: 0 | BJ4: 0 | BK4: 0 | BL4: 0 | BM4: 0 | BN4: 0 | BO4: 0 | BP4: 0 | BQ4: 0 | BR4: 0 | BS4: 0 | BT4: 0 | BU4: 0 | BV4: 0 | BW4: 0 | BX4: 0 | BY4: 0 | BZ4: 0 | CA4: 0 | CB4: 0 | CC4: 0 | CD4: 0 | CE4: 0 | CF4: 0 | CG4: 0 | CH4: 0 | CI4: 0 | CJ4: 0 | CK4: 0 | CL4: 0 | CM4: 0 | CN4: 0 | CO4: 193952.2 | CP4: 113874.54 | CQ4: 33437.48 | CR4: 8309.85 | CS4: 0 | CT4: 0 | CU4: 0 | CV4: 739 | CW4: 696 | CX4: 677 | CY4: 19 | CZ4: 43 | DA4: 35 | DB4: 8 | DC4: 557 | DD4: 0 | DE4: 526 | DF4: 518 | DG4: 8 | DH4: 31 | DI4: 26 | DJ4: 5 | DK4: 173 | DL4: 161 | DM4: 154 | DN4: 7 | DO4: 12 | DP4: 9 | DQ4: 3 | DR4: 9 | DS4: 0 | DT4: 9 | DU4: 5 | DV4: 4 | DW4: 0 | DX4: 0 | DY4: 0 | DZ4: 0 | EA4: 0 | EB4: 0 | EC4: 0 | ED4: 0 | EE4: 0 | EF4: 0 | EG4: 0 | EH4: 0 | EI4: 0 | EJ4: 0 | EK4: 0 | EL4: 0 | EM4: 0 | EN4: 0 | EO4: 0 | EP4: 0 | EQ4: 0 | ER4: 0 | ES4: 0 | ET4: 0 | EU4: 0 | EV4: 0 | EW4: 0 | EX4: 0 | EY4: 0 | EZ4: 0 | FA4: 0 | FB4: 0
A5: 2 | B5: 成人非手术 | C5: 呼吸内科 | D5: 3936522 | E5: 1426784 | F5: 2509738 | G5: 7273 | H5: 234 | I5: 12728 | J5: 0 | K5: 0 | L5: 137855 | M5: 975 | N5: 1524.66 | O5: 8117333.9 | P5: 5804551.9 | Q5: 5616173.5 | R5: 188378.39 | S5: 2312782 | T5: 2152318.7 | U5: 160463.33 | V5: 3166081.3 | W5: 2825380.2 | X5: 2736679.2 | Y5: 88701.04 | Z5: 340701.12 | AA5: 214909.89 | AB5: 125791.23 | AC5: 1695682.2 | AD5: 1508057.1 | AE5: 1477384.1 | AF5: 30673.04 | AG5: 187625.12 | AH5: 124441.89 | AI5: 63183.23 | AJ5: 43615.1 | AK5: 38957.1 | AL5: 37235.1 | AM5: 1722 | AN5: 4658 | AO5: 3028 | AP5: 1630 | AQ5: 1145666 | AR5: 1030484 | AS5: 985105 | AT5: 45379 | AU5: 115182 | AV5: 68730 | AW5: 46452 | AX5: 281118 | AY5: 247882 | AZ5: 236955 | BA5: 10927 | BB5: 33236 | BC5: 18710 | BD5: 14526 | BE5: 4951252.6 | BF5: 2979171.7 | BG5: 2879494.3 | BH5: 99677.35 | BI5: 1972080.9 | BJ5: 1937408.8 | BK5: 34672.1 | BL5: 2270395.9 | BM5: 1358434.3 | BN5: 1317822 | BO5: 40612.24 | BP5: 911961.65 | BQ5: 908900.89 | BR5: 3060.76 | BS5: 171118.67 | BT5: 102110.93 | BU5: 98748.32 | BV5: 3362.61 | BW5: 69007.74 | BX5: 66459.4 | BY5: 2548.34 | BZ5: 2034501 | CA5: 1228509 | CB5: 1194016 | CC5: 34493 | CD5: 805992 | CE5: 779552 | CF5: 26440 | CG5: 475237 | CH5: 290117.5 | CI5: 268908 | CJ5: 21209.5 | CK5: 185119.5 | CL5: 182496.5 | CM5: 2623 | CN5: -25 | CO5: 1921787.3 | CP5: 939586.63 | CQ5: 108899.66 | CR5: 195807.77 | CS5: 0 | CT5: 27432.8 | CU5: 0 | CV5: 7273 | CW5: 6545 | CX5: 6338 | CY5: 207 | CZ5: 728 | DA5: 449 | DB5: 279 | DC5: 5473 | DD5: 51 | DE5: 4988 | DF5: 4855 | DG5: 133 | DH5: 485 | DI5: 296 | DJ5: 189 | DK5: 1498 | DL5: 1297 | DM5: 1239 | DN5: 58 | DO5: 201 | DP5: 133 | DQ5: 68 | DR5: 250 | DS5: 1 | DT5: 211 | DU5: 197 | DV5: 14 | DW5: 39 | DX5: 18 | DY5: 21 | DZ5: 0 | EA5: 0 | EB5: 0 | EC5: 0 | ED5: 0 | EE5: 0 | EF5: 0 | EG5: 234 | EH5: 148 | EI5: 145 | EJ5: 3 | EK5: 86 | EL5: 84 | EM5: 2 | EN5: 159 | EO5: 1 | EP5: 0 | EQ5: 158 | ER5: 0 | ES5: 0 | ET5: 0 | EU5: 0 | EV5: 0 | EW5: 0 | EX5: 0 | EY5: 0 | EZ5: 0 | FA5: 0 | FB5: 38
A6: 3 | B6: 成人非手术 | C6: 消化内科（内窥镜诊治部） | D6: 7699914 | E6: 4699592 | F6: 3000322 | G6: 13958 | H6: 492 | I6: 271894 | J6: 27900 | K6: 0 | L6: 261115.5 | M6: 83795 | N6: 954.3 | O6: 13599114 | P6: 10985901 | Q6: 10545401 | R6: 440499.79 | S6: 2613213 | T6: 2170252.5 | U6: 442960.47 | V6: 8242959.7 | W6: 7206306.2 | X6: 6783472.3 | Y6: 422833.84 | Z6: 1036653.5 | AA6: 642502.92 | AB6: 394150.62 | AC6: 3038485.5 | AD6: 2669953 | AE6: 2579574.1 | AF6: 90378.84 | AG6: 368532.54 | AH6: 241635.92 | AI6: 126896.62 | AJ6: 504882.2 | AK6: 437543.2 | AL6: 426466.2 | AM6: 11077 | AN6: 67339 | AO6: 48690 | AP6: 18649 | AQ6: 3226628 | AR6: 2852119 | AS6: 2760069 | AT6: 92050 | AU6: 374509 | AV6: 247422 | AW6: 127087 | AX6: 1472964 | AY6: 1246691 | AZ6: 1017363 | BA6: 229328 | BB6: 226273 | BC6: 104755 | BD6: 121518 | BE6: 5356154.2 | BF6: 3779594.8 | BG6: 3761928.9 | BH6: 17665.95 | BI6: 1576559.4 | BJ6: 1527749.6 | BK6: 48809.85 | BL6: 920538.73 | BM6: 621459.12 | BN6: 616747.43 | BO6: 4711.69 | BP6: 299079.61 | BQ6: 292373.7 | BR6: 6705.91 | BS6: 1435293.5 | BT6: 1035474.2 | BU6: 1034884.4 | BV6: 589.76 | BW6: 399819.3 | BX6: 391702.86 | BY6: 8116.44 | BZ6: 2116565 | CA6: 1484173 | CB6: 1474746 | CC6: 9427 | CD6: 632392 | CE6: 605119 | CF6: 27273 | CG6: 883757 | CH6: 638488.5 | CI6: 635551 | CJ6: 2937.5 | CK6: 245268.5 | CL6: 238554 | CM6: 6714.5 | CN6: 305 | CO6: 3635524.6 | CP6: 2050832.1 | CQ6: 1165294.7 | CR6: 1390953.2 | CS6: 0 | CT6: 0 | CU6: 0 | CV6: 13958 | CW6: 12352 | CX6: 11760 | CY6: 592 | CZ6: 1606 | DA6: 995 | DB6: 611 | DC6: 9197 | DD6: 202 | DE6: 8238 | DF6: 7990 | DG6: 248 | DH6: 959 | DI6: 631 | DJ6: 328 | DK6: 3564 | DL6: 3112 | DM6: 2983 | DN6: 129 | DO6: 452 | DP6: 292 | DQ6: 160 | DR6: 995 | DS6: 0 | DT6: 810 | DU6: 605 | DV6: 205 | DW6: 185 | DX6: 72 | DY6: 113 | DZ6: 0 | EA6: 0 | EB6: 0 | EC6: 0 | ED6: 0 | EE6: 0 | EF6: 0 | EG6: 492 | EH6: 365 | EI6: 361 | EJ6: 4 | EK6: 127 | EL6: 122 | EM6: 5 | EN6: 639 | EO6: 0 | EP6: 0 | EQ6: 639 | ER6: 0 | ES6: 0 | ET6: 92 | EU6: 70 | EV6: 0 | EW6: 0 | EX6: 70 | EY6: 0 | EZ6: 0 | FA6: 0 | FB6: 44
A7: 4 | B7: 成人非手术 | C7: 神经内科 | D7: 4145539 | E7: 1862176.5 | F7: 2283362.5 | G7: 10485 | H7: 217 | I7: 886 | J7: 0 | K7: 126648.15 | L7: 192255 | M7: 4000 | N7: 1002.92 | O7: 9536740.8 | P7: 7922371.3 | Q7: 7749818.1 | R7: 172553.22 | S7: 1614369.5 | T7: 1429080.9 | U7: 185288.65 | V7: 4738974.1 | W7: 4275100 | X7: 4147824.9 | Y7: 127275.09 | Z7: 463874.07 | AA7: 327154.11 | AB7: 136719.96 | AC7: 2876642.4 | AD7: 2642896.9 | AE7: 2575958.8 | AF7: 66938.09 | AG7: 233745.57 | AH7: 171452.61 | AI7: 62292.96 | AJ7: 155.16 | AK7: 155.16 | AL7: 155.16 | AM7: 0 | AN7: 0 | AO7: 0 | AP7: 0 | AQ7: 1500431 | AR7: 1317213 | AS7: 1272939 | AT7: 44274 | AU7: 183218 | AV7: 126874 | AW7: 56344 | AX7: 361745.5 | AY7: 314835 | AZ7: 298772 | BA7: 16063 | BB7: 46910.5 | BC7: 28827.5 | BD7: 18083 | BE7: 4797766.8 | BF7: 3647271.3 | BG7: 3601993.2 | BH7: 45278.13 | BI7: 1150495.5 | BJ7: 1101926.8 | BK7: 48568.69 | BL7: 1010117.3 | BM7: 769669.89 | BN7: 760704.86 | BO7: 8965.03 | BP7: 240447.37 | BQ7: 232217.38 | BR7: 8229.99 | BS7: 1504287 | BT7: 1146622.4 | BU7: 1145585.8 | BV7: 1036.6 | BW7: 357664.6 | BX7: 354510.4 | BY7: 3154.2 | BZ7: 1738740 | CA7: 1299402 | CB7: 1274987 | CC7: 24415 | CD7: 439338 | CE7: 408338 | CF7: 31000 | CG7: 544622.5 | CH7: 431577 | CI7: 420715.5 | CJ7: 10861.5 | CK7: 113045.5 | CL7: 106861 | CM7: 6184.5 | CN7: 0 | CO7: 2338290.5 | CP7: 1212368.6 | CQ7: 874733.88 | CR7: 313581.16 | CS7: 0 | CT7: 0 | CU7: 0 | CV7: 10485 | CW7: 9497 | CX7: 9184 | CY7: 313 | CZ7: 988 | DA7: 615 | DB7: 373 | DC7: 7980 | DD7: 175 | DE7: 7353 | DF7: 7135 | DG7: 218 | DH7: 627 | DI7: 406 | DJ7: 221 | DK7: 2123 | DL7: 1827 | DM7: 1765 | DN7: 62 | DO7: 296 | DP7: 180 | DQ7: 116 | DR7: 207 | DS7: 0 | DT7: 156 | DU7: 133 | DV7: 23 | DW7: 51 | DX7: 28 | DY7: 23 | DZ7: 0 | EA7: 0 | EB7: 0 | EC7: 0 | ED7: 0 | EE7: 0 | EF7: 0 | EG7: 217 | EH7: 163 | EI7: 160 | EJ7: 3 | EK7: 54 | EL7: 51 | EM7: 3 | EN7: 45 | EO7: 0 | EP7: 10 | EQ7: 35 | ER7: 0 | ES7: 0 | ET7: 0 | EU7: 3 | EV7: 0 | EW7: 3 | EX7: 0 | EY7: 7 | EZ7: 0 | FA7: 7 | FB7: 59
A8: 5 | B8: 成人非手术 | C8: 心血管一科 | D8: 3830336 | E8: 1264980 | F8: 2565356 | G8: 8981 | H8: 304 | I8: 546 | J8: 0 | K8: 0 | L8: 676498 | M8: 0 | N8: 833.38 | O8: 20693253 | P8: 15166405 | Q8: 15117290 | R8: 49115.81 | S8: 5526847.4 | T8: 5458087.3 | U8: 68760.04 | V8: 3918955.9 | W8: 3602559.8 | X8: 3553443.9 | Y8: 49115.81 | Z8: 316396.17 | AA8: 247636.13 | AB8: 68760.04 | AC8: 2653568.1 | AD8: 2484118 | AE8: 2460101.1 | AF8: 24016.81 | AG8: 169450.17 | AH8: 145127.13 | AI8: 24323.04 | AJ8: 407.8 | AK8: 407.8 | AL8: 407.8 | AM8: 0 | AN8: 0 | AO8: 0 | AP8: 0 | AQ8: 921783 | AR8: 816639 | AS8: 799010 | AT8: 17629 | AU8: 105144 | AV8: 74430 | AW8: 30714 | AX8: 343197 | AY8: 301395 | AZ8: 293925 | BA8: 7470 | BB8: 41802 | BC8: 28079 | BD8: 13723 | BE8: 16774297 | BF8: 11563846 | BG8: 11563846 | BH8: 0 | BI8: 5210451.2 | BJ8: 5210451.2 | BK8: 0 | BL8: 520282 | BM8: 378832.25 | BN8: 378832.25 | BO8: 0 | BP8: 141449.75 | BQ8: 141449.75 | BR8: 0 | BS8: 13688659 | BT8: 9370655.3 | BU8: 9370655.3 | BV8: 0 | BW8: 4318003.5 | BX8: 4318003.5 | BY8: 0 | BZ8: 1596249.5 | CA8: 1141145.5 | CB8: 1141145.5 | CC8: 0 | CD8: 455104 | CE8: 455104 | CF8: 0 | CG8: 969106.5 | CH8: 673212.5 | CI8: 673212.5 | CJ8: 0 | CK8: 295894 | CL8: 295894 | CM8: 0 | CN8: -25 | CO8: 1675782.8 | CP8: 1394068.5 | CQ8: 668424.86 | CR8: 180679.74 | CS8: 0 | CT8: 0 | CU8: 0 | CV8: 8981 | CW8: 8230 | CX8: 8085 | CY8: 145 | CZ8: 751 | DA8: 561 | DB8: 190 | DC8: 5981 | DD8: 196 | DE8: 5570 | DF8: 5477 | DG8: 93 | DH8: 411 | DI8: 311 | DJ8: 100 | DK8: 2588 | DL8: 2301 | DM8: 2261 | DN8: 40 | DO8: 287 | DP8: 222 | DQ8: 65 | DR8: 216 | DS8: 0 | DT8: 165 | DU8: 155 | DV8: 10 | DW8: 51 | DX8: 28 | DY8: 23 | DZ8: 0 | EA8: 0 | EB8: 0 | EC8: 0 | ED8: 0 | EE8: 0 | EF8: 0 | EG8: 304 | EH8: 218 | EI8: 218 | EJ8: 0 | EK8: 86 | EL8: 86 | EM8: 0 | EN8: 224 | EO8: 68 | EP8: 67 | EQ8: 89 | ER8: 0 | ES8: 0 | ET8: 0 | EU8: 91 | EV8: 68 | EW8: 23 | EX8: 0 | EY8: 35 | EZ8: 0 | FA8: 35 | FB8: 136
A9: 6 | B9: 成人非手术 | C9: 血液内科 | D9: 1593347 | E9: 245825 | F9: 1347522 | G9: 1148 | H9: 383 | I9: 1626 | J9: 126 | K9: 0 | L9: 68607 | M9: 11336 | N9: 0 | O9: 8710755.1 | P9: 4259439.4 | Q9: 3475044.5 | R9: 784394.92 | S9: 4451315.7 | T9: 3981342.6 | U9: 469973.02 | V9: 904498.42 | W9: 737230.38 | X9: 711055.25 | Y9: 26175.13 | Z9: 167268.04 | AA9: 146371.5 | AB9: 20896.54 | AC9: 639221.68 | AD9: 538426.28 | AE9: 530612.15 | AF9: 7814.13 | AG9: 100795.4 | AH9: 91571.86 | AI9: 9223.54 | AJ9: 19451.74 | AK9: 18535.1 | AL9: 18535.1 | AM9: 0 | AN9: 916.64 | AO9: 916.64 | AP9: 0 | AQ9: 203063 | AR9: 146908 | AS9: 130181 | AT9: 16727 | AU9: 56155 | AV9: 46125 | AW9: 10030 | AX9: 42762 | AY9: 33361 | AZ9: 31727 | BA9: 1634 | BB9: 9401 | BC9: 7758 | BD9: 1643 | BE9: 7806256.7 | BF9: 3522209 | BG9: 2763989.2 | BH9: 758219.79 | BI9: 4284047.6 | BJ9: 3834971.1 | BK9: 449076.48 | BL9: 6202941.6 | BM9: 2891375.1 | BN9: 2148269.4 | BO9: 743105.74 | BP9: 3311566.4 | BQ9: 2882908 | BR9: 428658.46 | BS9: 255793.08 | BT9: 81353.89 | BU9: 76392.84 | BV9: 4961.05 | BW9: 174439.19 | BX9: 168653.67 | BY9: 5785.52 | BZ9: 981859 | CA9: 412034 | CB9: 406732 | CC9: 5302 | CD9: 569825 | CE9: 557491 | CF9: 12334 | CG9: 365663 | CH9: 137446 | CI9: 132595 | CJ9: 4851 | CK9: 228217 | CL9: 225918.5 | CM9: 2298.5 | CN9: 0 | CO9: 273998.34 | CP9: 475044.04 | CQ9: 129707.6 | CR9: 25748.44 | CS9: 0 | CT9: 0 | CU9: 0 | CV9: 1148 | CW9: 906 | CX9: 875 | CY9: 31 | CZ9: 242 | DA9: 190 | DB9: 52 | DC9: 673 | DD9: 0 | DE9: 517 | DF9: 503 | DG9: 14 | DH9: 156 | DI9: 123 | DJ9: 33 | DK9: 460 | DL9: 381 | DM9: 366 | DN9: 15 | DO9: 79 | DP9: 60 | DQ9: 19 | DR9: 15 | DS9: 0 | DT9: 8 | DU9: 6 | DV9: 2 | DW9: 7 | DX9: 7 | DY9: 0 | DZ9: 0 | EA9: 0 | EB9: 0 | EC9: 0 | ED9: 0 | EE9: 0 | EF9: 0 | EG9: 383 | EH9: 180 | EI9: 169 | EJ9: 11 | EK9: 203 | EL9: 197 | EM9: 6 | EN9: 300 | EO9: 1 | EP9: 0 | EQ9: 299 | ER9: 0 | ES9: 0 | ET9: 0 | EU9: 0 | EV9: 0 | EW9: 0 | EX9: 0 | EY9: 0 | EZ9: 0 | FA9: 0 | FB9: 11
A10: 7 | B10: 成人非手术 | C10: 肾脏风湿免疫科 | D10: 5160723 | E10: 3648021 | F10: 1512702 | G10: 5602 | H10: 175 | I10: 2778978 | J10: 0 | K10: 0 | L10: 113414.5 | M10: 28115 | N10: 0 | O10: 10320417 | P10: 9316722.9 | Q10: 9248533.9 | R10: 68189.01 | S10: 1003694.3 | T10: 868539.58 | U10: 135154.71 | V10: 7953055 | W10: 7491167.3 | X10: 7431920.3 | Y10: 59247.04 | Z10: 461887.7 | AA10: 367606.22 | AB10: 94281.48 | AC10: 3099202.1 | AD10: 2918977.2 | AE10: 2883663.6 | AF10: 35313.58 | AG10: 180224.88 | AH10: 148855.96 | AI10: 31368.92 | AJ10: 1205832 | AK10: 1151058.1 | AL10: 1148536.7 | AM10: 2521.46 | AN10: 54773.82 | AO10: 43239.26 | AP10: 11534.56 | AQ10: 673527 | AR10: 605310 | AS10: 595356 | AT10: 9954 | AU10: 68217 | AV10: 45252 | AW10: 22965 | AX10: 2974494 | AY10: 2815822 | AZ10: 2804364 | BA10: 11458 | BB10: 158672 | BC10: 130259 | BD10: 28413 | BE10: 2367362.2 | BF10: 1825555.6 | BG10: 1816613.6 | BH10: 8941.97 | BI10: 541806.59 | BJ10: 500933.36 | BK10: 40873.23 | BL10: 699076.25 | BM10: 534222.56 | BN10: 533682.49 | BO10: 540.07 | BP10: 164853.69 | BQ10: 158686.46 | BR10: 6167.23 | BS10: 155583.92 | BT10: 119207.52 | BU10: 119206.12 | BV10: 1.4 | BW10: 36376.4 | BX10: 35886.4 | BY10: 490 | BZ10: 1145083.5 | CA10: 865754.5 | CB10: 858201.5 | CC10: 7553 | CD10: 279329 | CE10: 248591 | CF10: 30738 | CG10: 367618.5 | CH10: 306371 | CI10: 305523.5 | CJ10: 847.5 | CK10: 61247.5 | CL10: 57769.5 | CM10: 3478 | CN10: 70 | CO10: 1003027.1 | CP10: 983125.41 | CQ10: 5897248.2 | CR10: 69534.33 | CS10: 0 | CT10: 0 | CU10: 0 | CV10: 5602 | CW10: 5105 | CX10: 4994 | CY10: 111 | CZ10: 497 | DA10: 335 | DB10: 162 | DC10: 4215 | DD10: 80 | DE10: 3893 | DF10: 3819 | DG10: 74 | DH10: 322 | DI10: 223 | DJ10: 99 | DK10: 1223 | DL10: 1076 | DM10: 1045 | DN10: 31 | DO10: 147 | DP10: 100 | DQ10: 47 | DR10: 84 | DS10: 0 | DT10: 61 | DU10: 57 | DV10: 4 | DW10: 23 | DX10: 11 | DY10: 12 | DZ10: 0 | EA10: 0 | EB10: 0 | EC10: 0 | ED10: 0 | EE10: 0 | EF10: 0 | EG10: 175 | EH10: 132 | EI10: 131 | EJ10: 1 | EK10: 43 | EL10: 41 | EM10: 2 | EN10: 55 | EO10: 9 | EP10: 0 | EQ10: 46 | ER10: 0 | ES10: 0 | ET10: 0 | EU10: 0 | EV10: 0 | EW10: 0 | EX10: 0 | EY10: 0 | EZ10: 0 | FA10: 0 | FB10: 19
A11: 8 | B11: 成人非手术 | C11: 内分泌科 | D11: 4561051.5 | E11: 2640101 | F11: 1920950.5 | G11: 12553 | H11: 206 | I11: 7578 | J11: 0 | K11: 0 | L11: 208201 | M11: 57 | N11: 0 | O11: 8626991.6 | P11: 7539916.8 | Q11: 7452125.3 | R11: 87791.58 | S11: 1087074.8 | T11: 951719.66 | U11: 135355.1 | V11: 6122348.8 | W11: 5672893.3 | X11: 5585101.7 | Y11: 87791.58 | Z11: 449455.58 | AA11: 333495.47 | AB11: 115960.11 | AC11: 3401454.6 | AD11: 3178309.9 | AE11: 3144384.5 | AF11: 33925.38 | AG11: 223144.78 | AH11: 173799.67 | AI11: 49345.11 | AJ11: 80793.2 | AK11: 75218.4 | AL11: 74116.2 | AM11: 1102.2 | AN11: 5574.8 | AO11: 4672.8 | AP11: 902 | AQ11: 2218072 | AR11: 2034661 | AS11: 1992891 | AT11: 41770 | AU11: 183411 | AV11: 129942 | AW11: 53469 | AX11: 422029 | AY11: 384704 | AZ11: 373710 | BA11: 10994 | BB11: 37325 | BC11: 25081 | BD11: 12244 | BE11: 2504642.8 | BF11: 1867023.6 | BG11: 1867023.6 | BH11: 0 | BI11: 637619.18 | BJ11: 618224.19 | BK11: 19394.99 | BL11: 527687 | BM11: 387986.67 | BN11: 387986.67 | BO11: 0 | BP11: 139700.33 | BQ11: 136445.44 | BR11: 3254.89 | BS11: 56005.25 | BT11: 41011.9 | BU11: 41011.9 | BV11: 0 | BW11: 14993.35 | BX11: 14583.25 | BY11: 410.1 | BZ11: 1476390 | CA11: 1103711 | CB11: 1103711 | CC11: 0 | CD11: 372679 | CE11: 359800 | CF11: 12879 | CG11: 444560.5 | CH11: 334314 | CI11: 334314 | CJ11: 0 | CK11: 110246.5 | CL11: 107395.5 | CM11: 2851 | CN11: -10 | CO11: 3421064.8 | CP11: 1623828.4 | CQ11: 903780.19 | CR11: 173419.42 | CS11: 256 | CT11: 0 | CU11: 0 | CV11: 12553 | CW11: 11561 | CX11: 11316 | CY11: 245 | CZ11: 992 | DA11: 702 | DB11: 290 | DC11: 9387 | DD11: 127 | DE11: 8659 | DF11: 8488 | DG11: 171 | DH11: 728 | DI11: 513 | DJ11: 215 | DK11: 2823 | DL11: 2596 | DM11: 2539 | DN11: 57 | DO11: 227 | DP11: 169 | DQ11: 58 | DR11: 216 | DS11: 0 | DT11: 183 | DU11: 169 | DV11: 14 | DW11: 33 | DX11: 19 | DY11: 14 | DZ11: 0 | EA11: 0 | EB11: 0 | EC11: 0 | ED11: 0 | EE11: 0 | EF11: 0 | EG11: 206 | EH11: 153 | EI11: 153 | EJ11: 0 | EK11: 53 | EL11: 51 | EM11: 2 | EN11: 0 | EO11: 0 | EP11: 0 | EQ11: 0 | ER11: 0 | ES11: 0 | ET11: 0 | EU11: 0 | EV11: 0 | EW11: 0 | EX11: 0 | EY11: 0 | EZ11: 0 | FA11: 0 | FB11: 187
A12: 9 | B12: 成人非手术 | C12: 老年医学科 | D12: 3902178.5 | E12: 174394.5 | F12: 3727784 | G12: 1994 | H12: 63 | I12: 8102 | J12: 0 | K12: 82056.71 | L12: 1088731.5 | M12: 11523 | N12: 19369.49 | O12: 6817190.3 | P12: 6802610.3 | Q12: 6799297.4 | R12: 3312.92 | S12: 14580.02 | T12: 14366.02 | U12: 214 | V12: 1288376 | W12: 1273795.9 | X12: 1270483 | Y12: 3312.92 | Z12: 14580.02 | AA12: 14366.02 | AB12: 214 | AC12: 1111396.8 | AD12: 1102175.8 | AE12: 1099517.8 | AF12: 2657.92 | AG12: 9221.02 | AH12: 9221.02 | AI12: 0 | AJ12: 2584.7 | AK12: 2511.7 | AL12: 2511.7 | AM12: 0 | AN12: 73 | AO12: 73 | AP12: 0 | AQ12: 114336 | AR12: 109639 | AS12: 109109 | AT12: 530 | AU12: 4697 | AV12: 4508 | AW12: 189 | AX12: 60058.5 | AY12: 59469.5 | AZ12: 59344.5 | BA12: 125 | BB12: 589 | BC12: 564 | BD12: 25 | BE12: 5528814.3 | BF12: 5528814.3 | BG12: 5528814.3 | BH12: 0 | BI12: 0 | BJ12: 0 | BK12: 0 | BL12: 1646242.1 | BM12: 1646242.1 | BN12: 1646242.1 | BO12: 0 | BP12: 0 | BQ12: 0 | BR12: 0 | BS12: 154788.28 | BT12: 154788.28 | BU12: 154788.28 | BV12: 0 | BW12: 0 | BX12: 0 | BY12: 0 | BZ12: 1535500 | CA12: 1535500 | CB12: 1535500 | CC12: 0 | CD12: 0 | CE12: 0 | CF12: 0 | CG12: 2192284 | CH12: 2192284 | CI12: 2192284 | CJ12: 0 | CK12: 0 | CL12: 0 | CM12: 0 | CN12: 0 | CO12: 1288326 | CP12: 0 | CQ12: 50 | CR12: 0 | CS12: 0 | CT12: 0 | CU12: 0 | CV12: 1994 | CW12: 1972 | CX12: 1967 | CY12: 5 | CZ12: 22 | DA12: 21 | DB12: 1 | DC12: 1994 | DD12: 0 | DE12: 1972 | DF12: 1967 | DG12: 5 | DH12: 22 | DI12: 21 | DJ12: 1 | DK12: 0 | DL12: 0 | DM12: 0 | DN12: 0 | DO12: 0 | DP12: 0 | DQ12: 0 | DR12: 0 | DS12: 0 | DT12: 0 | DU12: 0 | DV12: 0 | DW12: 0 | DX12: 0 | DY12: 0 | DZ12: 0 | EA12: 0 | EB12: 0 | EC12: 0 | ED12: 0 | EE12: 0 | EF12: 0 | EG12: 63 | EH12: 63 | EI12: 63 | EJ12: 0 | EK12: 0 | EL12: 0 | EM12: 0 | EN12: 27 | EO12: 0 | EP12: 0 | EQ12: 27 | ER12: 0 | ES12: 0 | ET12: 0 | EU12: 0 | EV12: 0 | EW12: 0 | EX12: 0 | EY12: 0 | EZ12: 0 | FA12: 0 | FB12: 0
A13: 10 | B13: 成人非手术 | C13: 全科医学科 | D13: 1561845.5 | E13: 437442 | F13: 1124403.5 | G13: 2493 | H13: 83 | I13: 1620 | J13: 0 | K13: 0 | L13: 60878 | M13: 750 | N13: 0 | O13: 2435258.2 | P13: 1966099.6 | Q13: 1945347.3 | R13: 20752.26 | S13: 469158.65 | T13: 410660.26 | U13: 58498.39 | V13: 1011805.6 | W13: 931692.52 | X13: 917915.25 | Y13: 13777.27 | Z13: 80113.04 | AA13: 66053.33 | AB13: 14059.71 | AC13: 573798.16 | AD13: 541913.12 | AE13: 537222.85 | AF13: 4690.27 | AG13: 31885.04 | AH13: 29158.33 | AI13: 2726.71 | AJ13: 565.4 | AK13: 454.4 | AL13: 454.4 | AM13: 0 | AN13: 111 | AO13: 111 | AP13: 0 | AQ13: 368615 | AR13: 325774 | AS13: 317874 | AT13: 7900 | AU13: 42841 | AV13: 32699 | AW13: 10142 | AX13: 68827 | AY13: 63551 | AZ13: 62364 | BA13: 1187 | BB13: 5276 | BC13: 4085 | BD13: 1191 | BE13: 1423452.6 | BF13: 1034407 | BG13: 1027432 | BH13: 6974.99 | BI13: 389045.61 | BJ13: 344606.93 | BK13: 44438.68 | BL13: 220633.04 | BM13: 167981.85 | BN13: 167966.36 | BO13: 15.49 | BP13: 52651.19 | BQ13: 48685.01 | BR13: 3966.18 | BS13: 78416.1 | BT13: 46794.68 | BU13: 46794.68 | BV13: 0 | BW13: 31621.42 | BX13: 30390.92 | BY13: 1230.5 | BZ13: 533572 | CA13: 357020 | CB13: 352090 | CC13: 4930 | CD13: 176552 | CE13: 152532 | CF13: 24020 | CG13: 590831.5 | CH13: 462610.5 | CI13: 460581 | CJ13: 2029.5 | CK13: 128221 | CL13: 112999 | CM13: 15222 | CN13: 0 | CO13: 896459.12 | CP13: 101756.43 | CQ13: 4011.28 | CR13: 9578.73 | CS13: 0 | CT13: 0 | CU13: 0 | CV13: 2493 | CW13: 2298 | CX13: 2260 | CY13: 38 | CZ13: 195 | DA13: 154 | DB13: 41 | DC13: 2255 | DD13: 36 | DE13: 2085 | DF13: 2052 | DG13: 33 | DH13: 170 | DI13: 137 | DJ13: 33 | DK13: 190 | DL13: 167 | DM13: 165 | DN13: 2 | DO13: 23 | DP13: 15 | DQ13: 8 | DR13: 12 | DS13: 0 | DT13: 12 | DU13: 10 | DV13: 2 | DW13: 0 | DX13: 0 | DY13: 0 | DZ13: 0 | EA13: 0 | EB13: 0 | EC13: 0 | ED13: 0 | EE13: 0 | EF13: 0 | EG13: 83 | EH13: 56 | EI13: 55 | EJ13: 1 | EK13: 27 | EL13: 23 | EM13: 4 | EN13: 6 | EO13: 0 | EP13: 0 | EQ13: 6 | ER13: 0 | ES13: 0 | ET13: 0 | EU13: 0 | EV13: 0 | EW13: 0 | EX13: 0 | EY13: 0 | EZ13: 0 | FA13: 0 | FB13: 0
A14: 11 | B14: 成人非手术 | C14: 心血管二科 | D14: 6151785.8 | E14: 1331878 | F14: 4819907.8 | G14: 12041 | H14: 420 | I14: 620 | J14: 0 | K14: 0 | L14: 1115631 | M14: 42301.25 | N14: 0 | O14: 19087013 | P14: 15292110 | Q14: 15160187 | R14: 131922.84 | S14: 3794902.6 | T14: 3706088.6 | U14: 88814.03 | V14: 5635828.8 | W14: 5252609.7 | X14: 5186749.5 | Y14: 65860.23 | Z14: 383219.08 | AA14: 313352.4 | AB14: 69866.68 | AC14: 4303622.6 | AD14: 4058450.5 | AE14: 4025954.3 | AF14: 32496.23 | AG14: 245172.08 | AH14: 207546.4 | AI14: 37625.68 | AJ14: 328.18 | AK14: 290.18 | AL14: 290.18 | AM14: 0 | AN14: 38 | AO14: 0 | AP14: 38 | AQ14: 964455 | AR14: 858282 | AS14: 833367 | AT14: 24915 | AU14: 106173 | AV14: 84095 | AW14: 22078 | AX14: 367423 | AY14: 335587 | AZ14: 327138 | BA14: 8449 | BB14: 31836 | BC14: 21711 | BD14: 10125 | BE14: 13451184 | BF14: 10039501 | BG14: 9973437.9 | BH14: 66062.61 | BI14: 3411683.5 | BJ14: 3392736.2 | BK14: 18947.35 | BL14: 778396.51 | BM14: 607784.47 | BN14: 604011.36 | BO14: 3773.11 | BP14: 170612.04 | BQ14: 168419.69 | BR14: 2192.35 | BS14: 7852879.8 | BT14: 5809578.5 | BU14: 5780628.5 | BV14: 28950 | BW14: 2043301.2 | BX14: 2039717.7 | BY14: 3583.5 | BZ14: 3229287.5 | CA14: 2429119.5 | CB14: 2400636.5 | CC14: 28483 | CD14: 800168 | CE14: 788613 | CF14: 11555 | CG14: 1590620.2 | CH14: 1193018 | CI14: 1188161.5 | CJ14: 4856.5 | CK14: 397602.25 | CL14: 395985.75 | CM14: 1616.5 | CN14: 0 | CO14: 2369320.9 | CP14: 1841568.3 | CQ14: 1384303.6 | CR14: 40635.96 | CS14: 0 | CT14: 0 | CU14: 0 | CV14: 12041 | CW14: 11176 | CX14: 11018 | CY14: 158 | CZ14: 865 | DA14: 659 | DB14: 206 | DC14: 8617 | DD14: 131 | DE14: 8097 | DF14: 8010 | DG14: 87 | DH14: 520 | DI14: 407 | DJ14: 113 | DK14: 3255 | DL14: 2922 | DM14: 2861 | DN14: 61 | DO14: 333 | DP14: 250 | DQ14: 83 | DR14: 38 | DS14: 0 | DT14: 28 | DU14: 20 | DV14: 8 | DW14: 10 | DX14: 2 | DY14: 8 | DZ14: 0 | EA14: 0 | EB14: 0 | EC14: 0 | ED14: 0 | EE14: 0 | EF14: 0 | EG14: 420 | EH14: 310 | EI14: 307 | EJ14: 3 | EK14: 110 | EL14: 108 | EM14: 2 | EN14: 391 | EO14: 2 | EP14: 233 | EQ14: 156 | ER14: 0 | ES14: 0 | ET14: 0 | EU14: 160 | EV14: 0 | EW14: 160 | EX14: 0 | EY14: 2 | EZ14: 2 | FA14: 0 | FB14: 151
A15: 12 | B15: 成人手术 | C15: 普外科 | D15: 9981453.8 | E15: 1747744 | F15: 8233709.8 | G15: 7865 | H15: 824 | I15: 148043 | J15: 109866 | K15: 45 | L15: 429715 | M15: 2149094.8 | N15: 862.5 | O15: 22551116 | P15: 14231212 | Q15: 13719852 | R15: 511359.95 | S15: 8319904 | T15: 7691051.1 | U15: 628852.93 | V15: 3309746.2 | W15: 2730616.1 | X15: 2624683.8 | Y15: 105932.31 | Z15: 579130.06 | AA15: 416174 | AB15: 162956.06 | AC15: 1190942.5 | AD15: 974079.54 | AE15: 940187.95 | AF15: 33891.59 | AG15: 216862.98 | AH15: 179807.74 | AI15: 37055.24 | AJ15: 371059.65 | AK15: 349591.57 | AL15: 340937.85 | AM15: 8653.72 | AN15: 21468.08 | AO15: 12411.26 | AP15: 9056.82 | AQ15: 1174142 | AR15: 918213 | AS15: 888802 | AT15: 29411 | AU15: 255929 | AV15: 177973 | AW15: 77956 | AX15: 573602 | AY15: 488732 | AZ15: 454756 | BA15: 33976 | BB15: 84870 | BC15: 45982 | BD15: 38888 | BE15: 19241370 | BF15: 11500596 | BG15: 11095168 | BH15: 405427.64 | BI15: 7740774 | BJ15: 7274877.1 | BK15: 465896.87 | BL15: 3869406 | BM15: 2249128.6 | BN15: 2155121.3 | BO15: 94007.31 | BP15: 1620277.3 | BQ15: 1543745.8 | BR15: 76531.51 | BS15: 7138254 | BT15: 4467222.1 | BU15: 4331175.2 | BV15: 136046.83 | BW15: 2671031.9 | BX15: 2500379 | BY15: 170652.86 | BZ15: 3286459.5 | CA15: 1775762 | CB15: 1727898 | CC15: 47864 | CD15: 1510697.5 | CE15: 1436380.5 | CF15: 74317 | CG15: 4947250.2 | CH15: 3008483 | CI15: 2880973.5 | CJ15: 127509.5 | CK15: 1938767.2 | CL15: 1794371.8 | CM15: 144395.5 | CN15: 777562.09 | CO15: 1233736.4 | CP15: 831580.4 | CQ15: 370282.58 | CR15: 94901.18 | CS15: 1658.48 | CT15: 278936.62 | CU15: 0 | CV15: 7865 | CW15: 6595 | CX15: 6331 | CY15: 264 | CZ15: 1270 | DA15: 829 | DB15: 441 | DC15: 4134 | DD15: 21 | DE15: 3632 | DF15: 3484 | DG15: 148 | DH15: 502 | DI15: 320 | DJ15: 182 | DK15: 1922 | DL15: 1507 | DM15: 1458 | DN15: 49 | DO15: 415 | DP15: 271 | DQ15: 144 | DR15: 155 | DS15: 0 | DT15: 93 | DU15: 78 | DV15: 15 | DW15: 62 | DX15: 30 | DY15: 32 | DZ15: 1633 | EA15: 1344 | EB15: 1293 | EC15: 51 | ED15: 289 | EE15: 208 | EF15: 81 | EG15: 824 | EH15: 528 | EI15: 513 | EJ15: 15 | EK15: 296 | EL15: 271 | EM15: 25 | EN15: 750 | EO15: 559 | EP15: 0 | EQ15: 191 | ER15: 239 | ES15: 0 | ET15: 1 | EU15: 169 | EV15: 135 | EW15: 0 | EX15: 34 | EY15: 181 | EZ15: 181 | FA15: 0 | FB15: 323
... A68: 65 | B68: 其他 | C68: 临床药物试验办公室GCP | D68: 100 | E68: 100 | F68: 0 | G68: 4 | H68: 0 | I68: 0 | J68: 0 | K68: 0 | L68: 0 | M68: 0 | N68: 0 | O68: 100 | P68: 25 | Q68: 0 | R68: 25 | S68: 75 | T68: 0 | U68: 75 | V68: 100 | W68: 25 | X68: 0 | Y68: 25 | Z68: 75 | AA68: 0 | AB68: 75 | AC68: 0 | AD68: 0 | AE68: 0 | AF68: 0 | AG68: 0 | AH68: 0 | AI68: 0 | AJ68: 0 | AK68: 0 | AL68: 0 | AM68: 0 | AN68: 0 | AO68: 0 | AP68: 0 | AQ68: 0 | AR68: 0 | AS68: 0 | AT68: 0 | AU68: 0 | AV68: 0 | AW68: 0 | AX68: 100 | AY68: 25 | AZ68: 0 | BA68: 25 | BB68: 75 | BC68: 0 | BD68: 75 | BE68: 0 | BF68: 0 | BG68: 0 | BH68: 0 | BI68: 0 | BJ68: 0 | BK68: 0 | BL68: 0 | BM68: 0 | BN68: 0 | BO68: 0 | BP68: 0 | BQ68: 0 | BR68: 0 | BS68: 0 | BT68: 0 | BU68: 0 | BV68: 0 | BW68: 0 | BX68: 0 | BY68: 0 | BZ68: 0 | CA68: 0 | CB68: 0 | CC68: 0 | CD68: 0 | CE68: 0 | CF68: 0 | CG68: 0 | CH68: 0 | CI68: 0 | CJ68: 0 | CK68: 0 | CL68: 0 | CM68: 0 | CN68: 0 | CO68: 0 | CP68: 0 | CQ68: 100 | CR68: 0 | CS68: 0 | CT68: 0 | CU68: 0 | CV68: 4 | CW68: 1 | CX68: 0 | CY68: 1 | CZ68: 3 | DA68: 0 | DB68: 3 | DC68: 4 | DD68: 0 | DE68: 1 | DF68: 0 | DG68: 1 | DH68: 3 | DI68: 0 | DJ68: 3 | DK68: 0 | DL68: 0 | DM68: 0 | DN68: 0 | DO68: 0 | DP68: 0 | DQ68: 0 | DR68: 0 | DS68: 0 | DT68: 0 | DU68: 0 | DV68: 0 | DW68: 0 | DX68: 0 | DY68: 0 | DZ68: 0 | EA68: 0 | EB68: 0 | EC68: 0 | ED68: 0 | EE68: 0 | EF68: 0 | EG68: 0 | EH68: 0 | EI68: 0 | EJ68: 0 | EK68: 0 | EL68: 0 | EM68: 0 | EN68: 0 | EO68: 0 | EP68: 0 | EQ68: 0 | ER68: 0 | ES68: 0 | ET68: 0 | EU68: 0 | EV68: 0 | EW68: 0 | EX68: 0 | EY68: 0 | EZ68: 0 | FA68: 0 | FB68: 0

Sheet 当年连续累计数据表
A1: 日期范围：20260101-20260531 | D1: 25 | O1: 1=2+5=8+43 | P1: 2=3+4 | Q1: 3 | R1: 4 | S1: 5=6+7 | T1: 6 | U1: 7 | V1: 8=9+12=15+22+29+36 | W1: 9=10+11 | X1: 10 | Y1: 11 | Z1: 12=13+14 | AA1: 13 | AB1: 14 | AC1: 15=16+19 | AD1: 16=17+18 | AE1: 17 | AF1: 18 | AG1: 19=20+21 | AH1: 20 | AI1: 21 | AJ1: 22=23+26 | AK1: 23=24+25 | AL1: 24 | AM1: 25 | AN1: 26=27+28 | AO1: 27 | AP1: 28 | AQ1: 29=30+33 | AR1: 30=31+32 | AS1: 31 | AT1: 32 | AU1: 33=34+35 | AV1: 34 | AW1: 35 | AX1: 36=37+40 | AY1: 37=38+39 | AZ1: 38 | BA1: 39 | BB1: 40=41+42 | BC1: 41 | BD1: 42 | BE1: 43=50+57+64+71=44+47 | BF1: 44=45+46 | BG1: 45 | BH1: 46 | BI1: 47=48+49 | BJ1: 48 | BK1: 49 | BL1: 50=51+54 | BM1: 51=52+53 | BN1: 52 | BO1: 53 | BP1: 54=55+56 | BQ1: 55 | BR1: 56 | BS1: 57=58+61 | BT1: 58=59+60 | BU1: 59 | BV1: 60 | BW1: 61=62+63 | BX1: 62 | BY1: 63 | BZ1: 64=65+68 | CA1: 65=66+67 | CB1: 66 | CC1: 67 | CD1: 68=69+70 | CE1: 69 | CF1: 70 | CG1: 71=72+75 | CH1: 72=73+74 | CI1: 73 | CJ1: 74 | CK1: 75=76+77 | CL1: 76 | CM1: 77 | CV1: 78=85+93+100+108+86+101=79+82 | CW1: 79=80+81 | CX1: 80 | CY1: 81 | CZ1: 82=83+84 | DA1: 83 | DB1: 84 | DC1: 85=87+90=78-93-100-108-86-101 | DD1: 86 | DE1: 87=88+89 | DF1: 88 | DG1: 89 | DH1: 90=91+92 | DI1: 91 | DJ1: 92 | DK1: 93=94+97 | DL1: 94=95+96 | DM1: 95 | DN1: 96 | DO1: 97=98+99 | DP1: 98 | DQ1: 99 | DR1: 100=102+105 | DS1: 101 | DT1: 102=103+104 | DU1: 103 | DV1: 104 | DW1: 105=106+107 | DX1: 106 | DY1: 107 | DZ1: 108=109+112 | EA1: 109=110+111 | EB1: 110 | EC1: 111 | ED1: 112=113+114 | EE1: 113 | EF1: 114 | EG1: 115=116+119 | EH1: 116=117+118 | EI1: 117 | EJ1: 118 | EK1: 119=120+121 | EL1: 120 | EM1: 121 | EN1: 122=123+124+125 | EO1: 123 | EP1: 124 | EQ1: 125 | EU1: 126=127+128+129 | EV1: 127 | EW1: 128 | EX1: 129 | EY1: 130=131+132 | EZ1: 131 | FA1: 132 | FB1: 133
A2: 序号 | B2: 科室类别 | C2: 科室名称 | D2: 医疗收入不含药耗 | E2: 门急诊收入不含药耗 | F2: 住院收入不含药耗 | G2: 门急诊人次 | H2: 住院人次 | I2: 门急诊治疗收入 | J2: 门急诊手术收入 | K2: 门诊中药饮片收入 | L2: 住院治疗收入 | M2: 住院手术收入 | N2: 住院中药饮片收入 | O2: 医疗收入 | P2: 其中本地病人医疗收入 | Q2: 其中本地病人医保医疗收入 | R2: 其中本地病人自费医疗收入 | S2: 其中异地病人医疗收入 | T2: 其中异地病人医保医疗收入 | U2: 其中异地病人自费医疗收入 | V2: 门急诊收入 | W2: 其中本地病人医疗收入 | X2: 其中本地病人医保医疗收入 | Y2: 其中本地病人自费医疗收入 | Z2: 其中异地病人医疗收入 | AA2: 其中异地病人医保医疗收入 | AB2: 其中异地病人自费医疗收入 | AC2: 门急诊药品收入 | AD2: 其中本地病人医疗收入 | AE2: 其中本地病人医保医疗收入 | AF2: 其中本地病人自费医疗收入 | AG2: 其中异地病人医疗收入 | AH2: 其中异地病人医保医疗收入 | AI2: 其中异地病人自费医疗收入 | AJ2: 门急诊耗材收入 | AK2: 其中本地病人医疗收入 | AL2: 其中本地病人医保医疗收入 | AM2: 其中本地病人自费医疗收入 | AN2: 其中异地病人医疗收入 | AO2: 其中异地病人医保医疗收入 | AP2: 其中异地病人自费医疗收入 | AQ2: 门急诊检查化验收入 | AR2: 其中本地病人医疗收入 | AS2: 其中本地病人医保医疗收入 | AT2: 其中本地病人自费医疗收入 | AU2: 其中异地病人医疗收入 | AV2: 其中异地病人医保医疗收入 | AW2: 其中异地病人自费医疗收入 | AX2: 门急诊劳务收入 | AY2: 其中本地病人医疗收入 | AZ2: 其中本地病人医保医疗收入 | BA2: 其中本地病人自费医疗收入 | BB2: 其中异地病人医疗收入 | BC2: 其中异地病人医保医疗收入 | BD2: 其中异地病人自费医疗收入 | BE2: 住院收入 | BF2: 其中本地病人医疗收入 | BG2: 其中本地病人医保医疗收入 | BH2: 其中本地病人自费医疗收入 | BI2: 其中异地病人医疗收入 | BJ2: 其中异地病人医保医疗收入 | BK2: 其中异地病人自费医疗收入 | BL2: 住院药品收入 | BM2: 其中本地病人医疗收入 | BN2: 其中本地病人医保医疗收入 | BO2: 其中本地病人自费医疗收入 | BP2: 其中异地病人医疗收入 | BQ2: 其中异地病人医保医疗收入 | BR2: 其中异地病人自费医疗收入 | BS2: 住院耗材收入 | BT2: 其中本地病人医疗收入 | BU2: 其中本地病人医保医疗收入 | BV2: 其中本地病人自费医疗收入 | BW2: 其中异地病人医疗收入 | BX2: 其中异地病人医保医疗收入 | BY2: 其中异地病人自费医疗收入 | BZ2: 住院检查化验收入 | CA2: 其中本地病人医疗收入 | CB2: 其中本地病人医保医疗收入 | CC2: 其中本地病人自费医疗收入 | CD2: 其中异地病人医疗收入 | CE2: 其中异地病人医保医疗收入 | CF2: 其中异地病人自费医疗收入 | CG2: 住院劳务收入 | CH2: 其中本地病人医疗收入 | CI2: 其中本地病人医保医疗收入 | CJ2: 其中本地病人自费医疗收入 | CK2: 其中异地病人医疗收入 | CL2: 其中异地病人医保医疗收入 | CM2: 其中异地病人自费医疗收入 | CN2: 急诊收入 | CO2: 普通门诊收入 | CP2: 专家门诊收入 | CQ2: 专病门诊收入 | CR2: 特需门诊收入 | CS2: MDT门诊收入 | CT2: 镜朗诊疗部收入 | CU2: 特需病房收入 | CV2: 门急诊人次 | CW2: 其中本地病人人次 | CX2: 其中本地病人医保人次 | CY2: 其中本地病人自费人次 | CZ2: 其中异地病人人次 | DA2: 其中异地病人医保人次 | DB2: 其中异地病人自费人次 | DC2: 普通门诊 (普通+专病) | DD2: 互联网普通门诊人次 | DE2: 其中本地病人人次 | DF2: 其中本地病人医保人次 | DG2: 其中本地病人自费人次 | DH2: 其中异地病人人次 | DI2: 其中异地病人医保人次 | DJ2: 其中异地病人自费人次 | DK2: 专家门诊 | DL2: 其中本地病人人次 | DM2: 其中本地病人医保人次 | DN2: 其中本地病人自费人次 | DO2: 其中异地病人人次 | DP2: 其中异地病人医保人次 | DQ2: 其中异地病人自费人次 | DR2: 特需门诊 (特需+MDT) | DS2: 互联网特需门诊人次 | DT2: 其中本地病人人次 | DU2: 其中本地病人医保人次 | DV2: 其中本地病人自费人次 | DW2: 其中异地病人人次 | DX2: 其中异地病人医保人次 | DY2: 其中异地病人自费人次 | DZ2: 急诊人次 | EA2: 其中本地病人人次 | EB2: 其中本地病人医保人次 | EC2: 其中本地病人自费人次 | ED2: 其中异地病人人次 | EE2: 其中异地病人医保人次 | EF2: 其中异地病人自费人次 | EG2: 住院人次 | EH2: 其中本地病人人次 | EI2: 其中本地病人医保人次 | EJ2: 其中本地病人自费人次 | EK2: 其中异地病人人次 | EL2: 其中异地病人医保人次 | EM2: 其中异地病人自费人次 | EN2: 手术人次与操作人次 | EO2: 手术人次 | EP2: 介入人次 | EQ2: 操作人次(治疗+诊断) | ER2: 微创手术人次（手术） | ES2: 微创手术人次（介入） | ET2: 微创手术人次（操作） | EU2: 三级手术 | EV2: 三级手术(手术) | EW2: 三级手术(介入) | EX2: 三级手术(操作) | EY2: 四级手术 | EZ2: 四级手术(手术) | FA2: 四级手术(介入) | FB2: 重点病种人次
A3: 小计： | D3: 1.4241363e+09 | E3: 6.3638626e+08 | F3: 7.8775003e+08 | G3: 2107614 | H3: 72972 | I3: 1.1415967e+08 | J3: 25552275 | K3: 12414001 | L3: 73837491 | M3: 1.8444064e+08 | N3: 216023.94 | O3: 3.0465051e+09 | P3: 2.0563791e+09 | Q3: 1.8939368e+09 | R3: 1.6244233e+08 | S3: 9.90126e+08 | T3: 8.3252559e+08 | U3: 1.576004e+08 | V3: 1.1286407e+09 | W3: 9.278458e+08 | X3: 8.4832794e+08 | Y3: 79517867 | Z3: 2.0079493e+08 | AA3: 1.0382604e+08 | AB3: 96968892 | AC3: 4.5158299e+08 | AD3: 3.9623686e+08 | AE3: 3.8179193e+08 | AF3: 14444928 | AG3: 55346138 | AH3: 39950281 | AI3: 15395857 | AJ3: 40671481 | AK3: 35667335 | AL3: 31428305 | AM3: 4239029.5 | AN3: 5004146.7 | AO3: 2998419.7 | AP3: 2005726.9 | AQ3: 3.5863664e+08 | AR3: 2.9315362e+08 | AS3: 2.6658623e+08 | AT3: 26567386 | AU3: 65483025 | AV3: 33081368 | AW3: 32401658 | AX3: 2.7774961e+08 | AY3: 2.0278799e+08 | AZ3: 1.6852147e+08 | BA3: 34266524 | BB3: 74961622 | BC3: 27795971 | BD3: 47165651 | BE3: 1.9178644e+09 | BF3: 1.1285333e+09 | BG3: 1.0456089e+09 | BH3: 82924462 | BI3: 7.8933106e+08 | BJ3: 7.2869955e+08 | BK3: 60631512 | BL3: 3.0891526e+08 | BM3: 1.6778815e+08 | BN3: 1.5991648e+08 | BO3: 7871668.6 | BP3: 1.4112711e+08 | BQ3: 1.3268141e+08 | BR3: 8445702.4 | BS3: 8.2119911e+08 | BT3: 5.0137541e+08 | BU3: 4.7227617e+08 | BV3: 29099243 | BW3: 3.198237e+08 | BX3: 3.024135e+08 | BY3: 17410207 | BZ3: 3.2825236e+08 | CA3: 2.0044418e+08 | CB3: 1.8767319e+08 | CC3: 12770993 | CD3: 1.2780818e+08 | CE3: 1.1949632e+08 | CF3: 8311856.2 | CG3: 4.5949767e+08 | CH3: 2.589256e+08 | CI3: 2.2574304e+08 | CJ3: 33182557 | CK3: 2.0057207e+08 | CL3: 1.7410832e+08 | CM3: 26463747 | CN3: 1.4624332e+08 | CO3: 4.0373212e+08 | CP3: 2.8304014e+08 | CQ3: 1.5193282e+08 | CR3: 1.4229751e+08 | CS3: 1391456.4 | CT3: 46732502 | CU3: 0 | CV3: 2107614 | CW3: 1797573 | CX3: 1639434 | CY3: 158139 | CZ3: 310041 | DA3: 159683 | DB3: 150358 | DC3: 1153328 | DD3: 26077 | DE3: 1016024 | DF3: 942308 | DG3: 73716 | DH3: 137304 | DI3: 76776 | DJ3: 60528 | DK3: 474394 | DL3: 386219 | DM3: 354130 | DN3: 32089 | DO3: 88175 | DP3: 48547 | DQ3: 39628 | DR3: 175208 | DS3: 679 | DT3: 126624 | DU3: 105190 | DV3: 21434 | DW3: 48584 | DX3: 18046 | DY3: 30538 | DZ3: 277928 | EA3: 246993 | EB3: 220740 | EC3: 26253 | ED3: 30935 | EE3: 16136 | EF3: 14799 | EG3: 72972 | EH3: 45527 | EI3: 41756 | EJ3: 3771 | EK3: 27445 | EL3: 24696 | EM3: 2749 | EN3: 59319 | EO3: 31203 | EP3: 4121 | EQ3: 23995 | ER3: 7919 | ES3: 0 | ET3: 476 | EU3: 15099 | EV3: 12283 | EW3: 2087 | EX3: 729 | EY3: 10517 | EZ3: 9453 | FA3: 1064 | FB3: 23804
A4: 1 | B4: 成人非手术 | C4: 内科 | D4: 873034 | E4: 873034 | F4: 0 | G4: 4796 | H4: 0 | I4: 2200 | J4: 0 | K4: 0 | L4: 0 | M4: 0 | N4: 0 | O4: 2291217.7 | P4: 2135244.4 | Q4: 2081971.5 | R4: 53272.85 | S4: 155973.29 | T4: 125124.22 | U4: 30849.07 | V4: 2291217.7 | W4: 2135244.4 | X4: 2081971.5 | Y4: 53272.85 | Z4: 155973.29 | AA4: 125124.22 | AB4: 30849.07 | AC4: 1411912.4 | AD4: 1349134.2 | AE4: 1340574.5 | AF4: 8559.65 | AG4: 62778.29 | AH4: 55387.22 | AI4: 7391.07 | AJ4: 6271.23 | AK4: 5178.23 | AL4: 5004.03 | AM4: 174.2 | AN4: 1093 | AO4: 922 | AP4: 171 | AQ4: 728696 | AR4: 647374 | AS4: 613739 | AT4: 33635 | AU4: 81322 | AV4: 61644 | AW4: 19678 | AX4: 144338 | AY4: 133558 | AZ4: 122654 | BA4: 10904 | BB4: 10780 | BC4: 7171 | BD4: 3609 | BE4: 0 | BF4: 0 | BG4: 0 | BH4: 0 | BI4: 0 | BJ4: 0 | BK4: 0 | BL4: 0 | BM4: 0 | BN4: 0 | BO4: 0 | BP4: 0 | BQ4: 0 | BR4: 0 | BS4: 0 | BT4: 0 | BU4: 0 | BV4: 0 | BW4: 0 | BX4: 0 | BY4: 0 | BZ4: 0 | CA4: 0 | CB4: 0 | CC4: 0 | CD4: 0 | CE4: 0 | CF4: 0 | CG4: 0 | CH4: 0 | CI4: 0 | CJ4: 0 | CK4: 0 | CL4: 0 | CM4: 0 | CN4: 0 | CO4: 1307210.8 | CP4: 637494.42 | CQ4: 297214.03 | CR4: 49298.4 | CS4: 0 | CT4: 0 | CU4: 0 | CV4: 4796 | CW4: 4442 | CX4: 4313 | CY4: 129 | CZ4: 354 | DA4: 237 | DB4: 117 | DC4: 3666 | DD4: 182 | DE4: 3446 | DF4: 3382 | DG4: 64 | DH4: 220 | DI4: 174 | DJ4: 46 | DK4: 905 | DL4: 833 | DM4: 820 | DN4: 13 | DO4: 72 | DP4: 58 | DQ4: 14 | DR4: 43 | DS4: 0 | DT4: 36 | DU4: 17 | DV4: 19 | DW4: 7 | DX4: 3 | DY4: 4 | DZ4: 0 | EA4: 0 | EB4: 0 | EC4: 0 | ED4: 0 | EE4: 0 | EF4: 0 | EG4: 0 | EH4: 0 | EI4: 0 | EJ4: 0 | EK4: 0 | EL4: 0 | EM4: 0 | EN4: 0 | EO4: 0 | EP4: 0 | EQ4: 0 | ER4: 0 | ES4: 0 | ET4: 0 | EU4: 0 | EV4: 0 | EW4: 0 | EX4: 0 | EY4: 0 | EZ4: 0 | FA4: 0 | FB4: 0
A5: 2 | B5: 成人非手术 | C5: 呼吸内科 | D5: 26442134 | E5: 10983440 | F5: 15458694 | G5: 49674 | H5: 1572 | I5: 62966 | J5: 0 | K5: 0 | L5: 933568.5 | M5: 9129 | N5: 1870.45 | O5: 50293904 | P5: 37600657 | Q5: 36856989 | R5: 743667.9 | S5: 12693247 | T5: 11775102 | U5: 918144.93 | V5: 22618900 | W5: 19875795 | X5: 19281054 | Y5: 594741.62 | Z5: 2743105 | AA5: 1948645.2 | AB5: 794459.81 | AC5: 11303876 | AD5: 9855805.5 | AE5: 9652092.3 | AF5: 203713.22 | AG5: 1448070.2 | AH5: 1081727.4 | AI5: 366342.81 | AJ5: 331584.49 | AK5: 294378.66 | AL5: 284180.26 | AM5: 10198.4 | AN5: 37205.83 | AO5: 24953.83 | AP5: 12252 | AQ5: 9176130 | AR5: 8152061 | AS5: 7843088 | AT5: 308973 | AU5: 1024069 | AV5: 689680 | AW5: 334389 | AX5: 1807310 | AY5: 1573550 | AZ5: 1501693 | BA5: 71857 | BB5: 233760 | BC5: 152284 | BD5: 81476 | BE5: 27675003 | BF5: 17724862 | BG5: 17575936 | BH5: 148926.28 | BI5: 9950141.6 | BJ5: 9826456.4 | BK5: 123685.12 | BL5: 11283246 | BM5: 7001403.4 | BN5: 6941376.8 | BO5: 60026.54 | BP5: 4281842.6 | BQ5: 4249819.2 | BR5: 32023.41 | BS5: 933063.44 | BT5: 600447.51 | BU5: 596120.77 | BV5: 4326.74 | BW5: 332615.93 | BX5: 326549.72 | BY5: 6066.21 | BZ5: 12132384 | CA5: 7949444 | CB5: 7882078 | CC5: 67366 | CD5: 4182940 | CE5: 4111203 | CF5: 71737 | CG5: 3326310 | CH5: 2173567 | CI5: 2156360 | CJ5: 17207 | CK5: 1152743 | CL5: 1138884.5 | CM5: 13858.5 | CN5: 0 | CO5: 14168921 | CP5: 6775984.2 | CQ5: 456817.14 | CR5: 1217178.1 | CS5: 0 | CT5: 13098.03 | CU5: 0 | CV5: 49674 | CW5: 44202 | CX5: 42592 | CY5: 1610 | CZ5: 5472 | DA5: 3712 | DB5: 1760 | DC5: 37205 | DD5: 299 | DE5: 33391 | DF5: 32266 | DG5: 1125 | DH5: 3814 | DI5: 2559 | DJ5: 1255 | DK5: 10769 | DL5: 9399 | DM5: 9009 | DN5: 390 | DO5: 1370 | DP5: 986 | DQ5: 384 | DR5: 1392 | DS5: 9 | DT5: 1116 | DU5: 1029 | DV5: 87 | DW5: 276 | DX5: 166 | DY5: 110 | DZ5: 0 | EA5: 0 | EB5: 0 | EC5: 0 | ED5: 0 | EE5: 0 | EF5: 0 | EG5: 1572 | EH5: 1031 | EI5: 1022 | EJ5: 9 | EK5: 541 | EL5: 534 | EM5: 7 | EN5: 1053 | EO5: 7 | EP5: 0 | EQ5: 1046 | ER5: 1 | ES5: 0 | ET5: 1 | EU5: 1 | EV5: 1 | EW5: 0 | EX5: 0 | EY5: 0 | EZ5: 0 | FA5: 0 | FB5: 434
A6: 3 | B6: 成人非手术 | C6: 消化内科（内窥镜诊治部） | D6: 50979324 | E6: 31927183 | F6: 19052141 | G6: 105463 | H6: 3180 | I6: 2183451 | J6: 79250 | K6: 0 | L6: 1685391.5 | M6: 1335300 | N6: 8391.9 | O6: 92240719 | P6: 75999334 | Q6: 72838983 | R6: 3160351.4 | S6: 16241384 | T6: 13446812 | U6: 2794572.4 | V6: 58201378 | W6: 51030017 | X6: 48233834 | Y6: 2796183 | Z6: 7171360.6 | AA6: 4740729.4 | AB6: 2430631.2 | AC6: 23308537 | AD6: 20709017 | AE6: 20104733 | AF6: 604283.99 | AG6: 2599520.6 | AH6: 1818618.4 | AI6: 780902.2 | AJ6: 2965657.2 | AK6: 2589659.2 | AL6: 2491389.2 | AM6: 98270 | AN6: 375998 | AO6: 285373 | AP6: 90625 | AQ6: 22878228 | AR6: 20028117 | AS6: 19215248 | AT6: 812869 | AU6: 2850111 | AV6: 1968464 | AW6: 881647 | AX6: 9048955 | AY6: 7703224 | AZ6: 6422464 | BA6: 1280760 | BB6: 1345731 | BC6: 668274 | BD6: 677457 | BE6: 34039341 | BF6: 24969318 | BG6: 24605149 | BH6: 364168.38 | BI6: 9070023.6 | BJ6: 8706082.4 | BK6: 363941.19 | BL6: 6193365.6 | BM6: 4451673.8 | BN6: 4400172 | BO6: 51501.88 | BP6: 1741691.7 | BQ6: 1671998.5 | BR6: 69693.22 | BS6: 8793834.7 | BT6: 6578215.8 | BU6: 6504240.1 | BV6: 73975.7 | BW6: 2215618.9 | BX6: 2129916.9 | BY6: 85701.97 | BZ6: 12375381 | CA6: 8864767.8 | CB6: 8745099 | CC6: 119668.8 | CD6: 3510613 | CE6: 3361483 | CF6: 149130 | CG6: 6676760.1 | CH6: 5074660.1 | CI6: 4955638.1 | CJ6: 119022 | CK6: 1602100 | CL6: 1542684 | CM6: 59416 | CN6: -40 | CO6: 29051874 | CP6: 13964705 | CQ6: 8210386.1 | CR6: 6974411.7 | CS6: 0 | CT6: 213810.07 | CU6: 0 | CV6: 105463 | CW6: 92905 | CX6: 88528 | CY6: 4377 | CZ6: 12558 | DA6: 8162 | DB6: 4396 | DC6: 72938 | DD6: 1233 | DE6: 64811 | DF6: 62459 | DG6: 2352 | DH6: 8127 | DI6: 5332 | DJ6: 2795 | DK6: 25798 | DL6: 22456 | DM6: 21569 | DN6: 887 | DO6: 3342 | DP6: 2382 | DQ6: 960 | DR6: 5494 | DS6: 0 | DT6: 4485 | DU6: 3379 | DV6: 1106 | DW6: 1009 | DX6: 418 | DY6: 591 | DZ6: 0 | EA6: 0 | EB6: 0 | EC6: 0 | ED6: 0 | EE6: 0 | EF6: 0 | EG6: 3180 | EH6: 2368 | EI6: 2333 | EJ6: 35 | EK6: 812 | EL6: 776 | EM6: 36 | EN6: 3677 | EO6: 6 | EP6: 0 | EQ6: 3671 | ER6: 0 | ES6: 0 | ET6: 399 | EU6: 301 | EV6: 5 | EW6: 0 | EX6: 296 | EY6: 0 | EZ6: 0 | FA6: 0 | FB6: 269
A7: 4 | B7: 成人非手术 | C7: 神经内科 | D7: 31181736 | E7: 15272034 | F7: 15909702 | G7: 68613 | H7: 1391 | I7: 4474 | J7: 0 | K7: 405168.72 | L7: 932574.5 | M7: 215725 | N7: 10005.93 | O7: 73215169 | P7: 58816574 | Q7: 57581910 | R7: 1234663.7 | S7: 14398595 | T7: 13092643 | U7: 1305951.7 | V7: 34428458 | W7: 30563612 | X7: 29490615 | Y7: 1072997.8 | Z7: 3864845.3 | AA7: 2828833.7 | AB7: 1036011.7 | AC7: 19114704 | AD7: 17369191 | AE7: 16920555 | AF7: 448635.97 | AG7: 1745513 | AH7: 1320518.5 | AI7: 424994.49 | AJ7: 41719.94 | AK7: 33621.12 | AL7: 31675.3 | AM7: 1945.82 | AN7: 8098.82 | AO7: 6097.64 | AP7: 2001.18 | AQ7: 12592302 | AR7: 10855038 | AS7: 10354167 | AT7: 500871 | AU7: 1737264 | AV7: 1253836 | AW7: 483428 | AX7: 2679732 | AY7: 2305762.5 | AZ7: 2184217.5 | BA7: 121545 | BB7: 373969.5 | BC7: 248381.5 | BD7: 125588 | BE7: 38786712 | BF7: 28252962 | BG7: 28091296 | BH7: 161665.87 | BI7: 10533750 | BJ7: 10263810 | BK7: 269940.07 | BL7: 6487496.5 | BM7: 4932283.9 | BN7: 4886560.5 | BO7: 45723.43 | BP7: 1555212.6 | BQ7: 1502358.7 | BR7: 52853.88 | BS7: 16389513 | BT7: 11404852 | BU7: 11398084 | BV7: 6767.94 | BW7: 4984660.7 | BX7: 4913151.5 | BY7: 71509.19 | BZ7: 11539255 | CA7: 8551417 | CB7: 8479054 | CC7: 72363 | CD7: 2987838 | CE7: 2874030 | CF7: 113808 | CG7: 4370447 | CH7: 3364408.5 | CI7: 3327597 | CJ7: 36811.5 | CK7: 1006038.5 | CL7: 974269.5 | CM7: 31769 | CN7: 40 | CO7: 17108122 | CP7: 7503049.3 | CQ7: 5905679.8 | CR7: 3911606.5 | CS7: 0 | CT7: 0 | CU7: 0 | CV7: 68613 | CW7: 61467 | CX7: 59065 | CY7: 2402 | CZ7: 7146 | DA7: 4880 | DB7: 2266 | DC7: 51277 | DD7: 1299 | DE7: 46681 | DF7: 45104 | DG7: 1577 | DH7: 4596 | DI7: 3172 | DJ7: 1424 | DK7: 12305 | DL7: 10603 | DM7: 10097 | DN7: 506 | DO7: 1702 | DP7: 1219 | DQ7: 483 | DR7: 3732 | DS7: 0 | DT7: 2972 | DU7: 2721 | DV7: 251 | DW7: 760 | DX7: 485 | DY7: 275 | DZ7: 0 | EA7: 0 | EB7: 0 | EC7: 0 | ED7: 0 | EE7: 0 | EF7: 0 | EG7: 1391 | EH7: 1047 | EI7: 1035 | EJ7: 12 | EK7: 344 | EL7: 332 | EM7: 12 | EN7: 509 | EO7: 3 | EP7: 148 | EQ7: 358 | ER7: 0 | ES7: 0 | ET7: 0 | EU7: 27 | EV7: 1 | EW7: 26 | EX7: 0 | EY7: 124 | EZ7: 2 | FA7: 122 | FB7: 429
A8: 5 | B8: 成人非手术 | C8: 心血管内科 | D8: 77904794 | E8: 19906073 | F8: 57998721 | G8: 158578 | H8: 5478 | I8: 22280 | J8: 0 | K8: 0 | L8: 928713.25 | M8: 12073319 | N8: 2150.93 | O8: 3.0813788e+08 | P8: 2.3754249e+08 | Q8: 2.3530225e+08 | R8: 2240236.9 | S8: 70595396 | T8: 68706451 | U8: 1888944.3 | V8: 72896102 | W8: 67230255 | X8: 66241256 | Y8: 988999.04 | Z8: 5665847.3 | AA8: 4626719.9 | AB8: 1039127.5 | AC8: 52764585 | AD8: 49228415 | AE8: 48764905 | AF8: 463510.04 | AG8: 3536169.3 | AH8: 3046758.9 | AI8: 489410.47 | AJ8: 225444.2 | AK8: 196431.2 | AL8: 189356.2 | AM8: 7075 | AN8: 29013 | AO8: 20352 | AP8: 8661 | AQ8: 14474431 | AR8: 12960426 | AS8: 12580163 | AT8: 380263 | AU8: 1514005 | AV8: 1132240 | AW8: 381765 | AX8: 5431642 | AY8: 4844982 | AZ8: 4706831 | BA8: 138151 | BB8: 586660 | BC8: 427369 | BD8: 159291 | BE8: 2.3524178e+08 | BF8: 1.7031223e+08 | BG8: 1.6906099e+08 | BH8: 1251237.9 | BI8: 64929548 | BJ8: 64079732 | BK8: 849816.81 | BL8: 12674555 | BM8: 9726165.6 | BN8: 9660166.8 | BO8: 65998.76 | BP8: 2948389.2 | BQ8: 2899289.5 | BR8: 49099.61 | BS8: 1.645685e+08 | BT8: 1.1734828e+08 | BU8: 1.165179e+08 | BV8: 830380.14 | BW8: 47220226 | BX8: 46718970 | BY8: 501255.45 | BZ8: 37078531 | CA8: 27790230 | CB8: 27597591 | CC8: 192639 | CD8: 9288301 | CE8: 9091656 | CF8: 196645 | CG8: 20920190 | CH8: 15447558 | CI8: 15285338 | CJ8: 162220 | CK8: 5472632.2 | CL8: 5369815.5 | CM8: 102816.75 | CN8: 0 | CO8: 33523053 | CP8: 25832504 | CQ8: 11574002 | CR8: 1966543.4 | CS8: 0 | CT8: 75657.29 | CU8: 0 | CV8: 158578 | CW8: 144984 | CX8: 142117 | CY8: 2867 | CZ8: 13594 | DA8: 10511 | DB8: 3083 | DC8: 107245 | DD8: 2330 | DE8: 99122 | DF8: 97494 | DG8: 1628 | DH8: 8123 | DI8: 6324 | DJ8: 1799 | DK8: 46690 | DL8: 41828 | DM8: 40736 | DN8: 1092 | DO8: 4862 | DP8: 3827 | DQ8: 1035 | DR8: 2313 | DS8: 0 | DT8: 1782 | DU8: 1672 | DV8: 110 | DW8: 531 | DX8: 333 | DY8: 198 | DZ8: 0 | EA8: 0 | EB8: 0 | EC8: 0 | ED8: 0 | EE8: 0 | EF8: 0 | EG8: 5478 | EH8: 4091 | EI8: 4056 | EJ8: 35 | EK8: 1387 | EL8: 1357 | EM8: 30 | EN8: 4924 | EO8: 734 | EP8: 2295 | EQ8: 1895 | ER8: 0 | ES8: 0 | ET8: 0 | EU8: 2122 | EV8: 707 | EW8: 1415 | EX8: 0 | EY8: 142 | EZ8: 19 | FA8: 123 | FB8: 1654
A9: 6 | B9: 成人非手术 | C9: 血液内科 | D9: 10414563 | E9: 1280878 | F9: 9133685 | G9: 6619 | H9: 1949 | I9: 5886 | J9: 0 | K9: 0 | L9: 713633.5 | M9: 18871 | N9: 778.68 | O9: 42148641 | P9: 21116471 | Q9: 20935997 | R9: 180473.82 | S9: 21032170 | T9: 20797838 | U9: 234332 | V9: 5513586 | W9: 4648628.1 | X9: 4541214 | Y9: 107414.14 | Z9: 864957.85 | AA9: 718520.36 | AB9: 146437.49 | AC9: 4188416.5 | AD9: 3602461.5 | AE9: 3530921.4 | AF9: 71540.14 | AG9: 585954.95 | AH9: 491525.46 | AI9: 94429.49 | AJ9: 44291.5 | AK9: 40433.6 | AL9: 38863.6 | AM9: 1570 | AN9: 3857.9 | AO9: 2308.9 | AP9: 1549 | AQ9: 1033889 | AR9: 808273 | AS9: 783244 | AT9: 25029 | AU9: 225616 | AV9: 186587 | AW9: 39029 | AX9: 246989 | AY9: 197460 | AZ9: 188185 | BA9: 9275 | BB9: 49529 | BC9: 38099 | BD9: 11430 | BE9: 36635055 | BF9: 16467843 | BG9: 16394783 | BH9: 73059.68 | BI9: 20167212 | BJ9: 20079318 | BK9: 87894.51 | BL9: 26137265 | BM9: 11854440 | BN9: 11822706 | BO9: 31733.91 | BP9: 14282825 | BQ9: 14234322 | BR9: 48502.99 | BS9: 1364105.2 | BT9: 498797.41 | BU9: 494413.14 | BV9: 4384.27 | BW9: 865307.77 | BX9: 861227.25 | BY9: 4080.52 | BZ9: 6242233 | CA9: 2979697 | CB9: 2965038 | CC9: 14659 | CD9: 3262536 | CE9: 3234494 | CF9: 28042 | CG9: 2891452 | CH9: 1134908.5 | CI9: 1112626 | CJ9: 22282.5 | CK9: 1756543.5 | CL9: 1749274.5 | CM9: 7269 | CN9: -25 | CO9: 1607626.8 | CP9: 3097303.1 | CQ9: 695411.73 | CR9: 113244.39 | CS9: 0 | CT9: 30270.71 | CU9: 0 | CV9: 6619 | CW9: 5246 | CX9: 5033 | CY9: 213 | CZ9: 1373 | DA9: 1098 | DB9: 275 | DC9: 4150 | DD9: 0 | DE9: 3199 | DF9: 3086 | DG9: 113 | DH9: 951 | DI9: 769 | DJ9: 182 | DK9: 2366 | DL9: 1969 | DM9: 1877 | DN9: 92 | DO9: 397 | DP9: 315 | DQ9: 82 | DR9: 103 | DS9: 0 | DT9: 78 | DU9: 70 | DV9: 8 | DW9: 25 | DX9: 14 | DY9: 11 | DZ9: 0 | EA9: 0 | EB9: 0 | EC9: 0 | ED9: 0 | EE9: 0 | EF9: 0 | EG9: 1949 | EH9: 922 | EI9: 913 | EJ9: 9 | EK9: 1027 | EL9: 1021 | EM9: 6 | EN9: 1451 | EO9: 0 | EP9: 0 | EQ9: 1451 | ER9: 0 | ES9: 0 | ET9: 0 | EU9: 0 | EV9: 0 | EW9: 0 | EX9: 0 | EY9: 0 | EZ9: 0 | FA9: 0 | FB9: 160
A10: 7 | B10: 成人非手术 | C10: 肾脏风湿免疫科 | D10: 36132693 | E10: 26350933 | F10: 9781760 | G10: 38530 | H10: 1128 | I10: 17890538 | J10: 0 | K10: 0 | L10: 715763.5 | M10: 151371 | N10: 0 | O10: 64920819 | P10: 57075376 | Q10: 56416687 | R10: 658688.68 | S10: 7845442.7 | T10: 7186433.1 | U10: 659009.56 | V10: 49635472 | W10: 45885759 | X10: 45362603 | Y10: 523156.03 | Z10: 3749713.1 | AA10: 3145588.6 | AB10: 604124.48 | AC10: 18610034 | AD10: 17086187 | AE10: 16871082 | AF10: 215105.33 | AG10: 1523846.3 | AH10: 1224317.7 | AI10: 299528.58 | AJ10: 4674505.8 | AK10: 4461621 | AL10: 4429583.2 | AM10: 32037.7 | AN10: 212884.8 | AO10: 183585.9 | AP10: 29298.9 | AQ10: 7109397 | AR10: 6395293 | AS10: 6246331 | AT10: 148962 | AU10: 714104 | AV10: 551338 | AW10: 162766 | AX10: 19241536 | AY10: 17942658 | AZ10: 17815607 | BA10: 127051 | BB10: 1298878 | BC10: 1186347 | BD10: 112531 | BE10: 15285346 | BF10: 11189617 | BG10: 11054084 | BH10: 135532.65 | BI10: 4095729.5 | BJ10: 4040844.5 | BK10: 54885.08 | BL10: 4409792.6 | BM10: 3175357 | BN10: 3150683.4 | BO10: 24673.62 | BP10: 1234435.6 | BQ10: 1220259.1 | BR10: 14176.55 | BS10: 1093793.7 | BT10: 850191.27 | BU10: 844975.24 | BV10: 5216.03 | BW10: 243602.43 | BX10: 243130.4 | BY10: 472.03 | BZ10: 7203780 | CA10: 5245787 | CB10: 5162884 | CC10: 82903 | CD10: 1957993 | CE10: 1922787 | CF10: 35206 | CG10: 2577980 | CH10: 1918281.5 | CI10: 1895541.5 | CJ10: 22740 | CK10: 659698.5 | CL10: 654668 | CM10: 5030.5 | CN10: -19 | CO10: 6958183.7 | CP10: 7330720.1 | CQ10: 34570191 | CR10: 776371.56 | CS10: 0 | CT10: 0 | CU10: 0 | CV10: 38530 | CW10: 34487 | CX10: 33555 | CY10: 932 | CZ10: 4043 | DA10: 2940 | DB10: 1103 | DC10: 28295 | DD10: 527 | DE10: 25554 | DF10: 24880 | DG10: 674 | DH10: 2741 | DI10: 2006 | DJ10: 735 | DK10: 9043 | DL10: 7946 | DM10: 7725 | DN10: 221 | DO10: 1097 | DP10: 823 | DQ10: 274 | DR10: 665 | DS10: 0 | DT10: 503 | DU10: 478 | DV10: 25 | DW10: 162 | DX10: 106 | DY10: 56 | DZ10: 0 | EA10: 0 | EB10: 0 | EC10: 0 | ED10: 0 | EE10: 0 | EF10: 0 | EG10: 1128 | EH10: 831 | EI10: 818 | EJ10: 13 | EK10: 297 | EL10: 291 | EM10: 6 | EN10: 314 | EO10: 63 | EP10: 0 | EQ10: 251 | ER10: 0 | ES10: 0 | ET10: 0 | EU10: 1 | EV10: 1 | EW10: 0 | EX10: 0 | EY10: 0 | EZ10: 0 | FA10: 0 | FB10: 695
A11: 8 | B11: 成人非手术 | C11: 内分泌科 | D11: 26642854 | E11: 17720780 | F11: 8922073.5 | G11: 81888 | H11: 941 | I11: 25730 | J11: 2400 | K11: 0 | L11: 911679.5 | M11: 24424 | N11: 0 | O11: 51068187 | P11: 45796584 | Q11: 44916437 | R11: 880147.22 | S11: 5271603 | T11: 4485299.2 | U11: 786303.77 | V11: 39736016 | W11: 36557657 | X11: 35722046 | Y11: 835610.62 | Z11: 3178358.9 | AA11: 2474158.7 | AB11: 704200.22 | AC11: 21614235 | AD11: 20051295 | AE11: 19730761 | AF11: 320534.02 | AG11: 1562939.7 | AH11: 1300158.1 | AI11: 262781.62 | AJ11: 401001.2 | AK11: 372005 | AL11: 365841.4 | AM11: 6163.6 | AN11: 28996.2 | AO11: 23496.6 | AP11: 5499.6 | AQ11: 14816470 | AR11: 13518455 | AS11: 13110981 | AT11: 407474 | AU11: 1298015 | AV11: 948824 | AW11: 349191 | AX11: 2904310 | AY11: 2615902 | AZ11: 2514463 | BA11: 101439 | BB11: 288408 | BC11: 201680 | BD11: 86728 | BE11: 11332171 | BF11: 9238927 | BG11: 9194390.4 | BH11: 44536.6 | BI11: 2093244.1 | BJ11: 2011140.5 | BK11: 82103.55 | BL11: 2188240.9 | BM11: 1784662.2 | BN11: 1777326.2 | BO11: 7336.06 | BP11: 403578.66 | BQ11: 385614.6 | BR11: 17964.06 | BS11: 221856.7 | BT11: 177685.78 | BU11: 177010.74 | BV11: 675.04 | BW11: 44170.92 | BX11: 42890.43 | BY11: 1280.49 | BZ11: 6874030 | CA11: 5601862 | CB11: 5573093 | CC11: 28769 | CD11: 1272168 | CE11: 1222441 | CF11: 49727 | CG11: 2048043.5 | CH11: 1674717 | CI11: 1666960.5 | CJ11: 7756.5 | CK11: 373326.5 | CL11: 360194.5 | CM11: 13132 | CN11: -25 | CO11: 21498181 | CP11: 12916837 | CQ11: 3739715.7 | CR11: 1578779.8 | CS11: 2501.64 | CT11: 0 | CU11: 0 | CV11: 81888 | CW11: 74524 | CX11: 72412 | CY11: 2112 | CZ11: 7364 | DA11: 5465 | DB11: 1899 | DC11: 55840 | DD11: 914 | DE11: 50940 | DF11: 49625 | DG11: 1315 | DH11: 4900 | DI11: 3716 | DJ11: 1184 | DK11: 23074 | DL11: 20952 | DM11: 20283 | DN11: 669 | DO11: 2122 | DP11: 1568 | DQ11: 554 | DR11: 2045 | DS11: 15 | DT11: 1743 | DU11: 1630 | DV11: 113 | DW11: 302 | DX11: 179 | DY11: 123 | DZ11: 0 | EA11: 0 | EB11: 0 | EC11: 0 | ED11: 0 | EE11: 0 | EF11: 0 | EG11: 941 | EH11: 772 | EI11: 760 | EJ11: 12 | EK11: 169 | EL11: 158 | EM11: 11 | EN11: 6 | EO11: 0 | EP11: 0 | EQ11: 6 | ER11: 0 | ES11: 0 | ET11: 0 | EU11: 0 | EV11: 0 | EW11: 0 | EX11: 0 | EY11: 0 | EZ11: 0 | FA11: 0 | FB11: 878
A12: 9 | B12: 成人非手术 | C12: 老年医学科 | D12: 20550010 | E12: 1100484.5 | F12: 19449526 | G12: 10441 | H12: 335 | I12: 38675 | J12: 0 | K12: 261561.49 | L12: 3763650.5 | M12: 102851.5 | N12: 46235.51 | O12: 37188621 | P12: 37078220 | Q12: 36840679 | R12: 237541.56 | S12: 110401.11 | T12: 72114.47 | U12: 38286.64 | V12: 7076667.2 | W12: 6966266.1 | X12: 6940645.4 | Y12: 25620.71 | Z12: 110401.11 | AA12: 72114.47 | AB12: 38286.64 | AC12: 5951274.8 | AD12: 5867501.7 | AE12: 5850556.9 | AF12: 16944.71 | AG12: 83773.11 | AH12: 54650.47 | AI12: 29122.64 | AJ12: 24907.93 | AK12: 24512.93 | AL12: 24469.93 | AM12: 43 | AN12: 395 | AO12: 350 | AP12: 45 | AQ12: 788199 | AR12: 768613 | AS12: 761428 | AT12: 7185 | AU12: 19586 | AV12: 13487 | AW12: 6099 | AX12: 312285.5 | AY12: 305638.5 | AZ12: 304190.5 | BA12: 1448 | BB12: 6647 | BC12: 3627 | BD12: 3020 | BE12: 30111954 | BF12: 30111954 | BG12: 29900033 | BH12: 211920.85 | BI12: 0 | BJ12: 0 | BK12: 0 | BL12: 9757113.7 | BM12: 9757113.7 | BN12: 9683676.4 | BO12: 73437.3 | BP12: 0 | BQ12: 0 | BR12: 0 | BS12: 905315.02 | BT12: 905315.02 | BU12: 897060.97 | BV12: 8254.05 | BW12: 0 | BX12: 0 | BY12: 0 | BZ12: 8824627.5 | CA12: 8824627.5 | CB12: 8756276.5 | CC12: 68351 | CD12: 0 | CE12: 0 | CF12: 0 | CG12: 10624898 | CH12: 10624898 | CI12: 10563020 | CJ12: 61878.5 | CK12: 0 | CL12: 0 | CM12: 0 | CN12: 0 | CO12: 7041654.2 | CP12: 0 | CQ12: 275 | CR12: 34738 | CS12: 0 | CT12: 0 | CU12: 0 | CV12: 10441 | CW12: 10276 | CX12: 10241 | CY12: 35 | CZ12: 165 | DA12: 132 | DB12: 33 | DC12: 10417 | DD12: 0 | DE12: 10271 | DF12: 10241 | DG12: 30 | DH12: 146 | DI12: 132 | DJ12: 14 | DK12: 0 | DL12: 0 | DM12: 0 | DN12: 0 | DO12: 0 | DP12: 0 | DQ12: 0 | DR12: 24 | DS12: 0 | DT12: 5 | DU12: 0 | DV12: 5 | DW12: 19 | DX12: 0 | DY12: 19 | DZ12: 0 | EA12: 0 | EB12: 0 | EC12: 0 | ED12: 0 | EE12: 0 | EF12: 0 | EG12: 335 | EH12: 335 | EI12: 334 | EJ12: 1 | EK12: 0 | EL12: 0 | EM12: 0 | EN12: 183 | EO12: 0 | EP12: 0 | EQ12: 183 | ER12: 0 | ES12: 0 | ET12: 0 | EU12: 0 | EV12: 0 | EW12: 0 | EX12: 0 | EY12: 0 | EZ12: 0 | FA12: 0 | FB12: 0
A13: 10 | B13: 成人非手术 | C13: 全科医学科 | D13: 9279710.8 | E13: 2644243 | F13: 6635467.8 | G13: 15310 | H13: 362 | I13: 890 | J13: 0 | K13: 0 | L13: 307826.25 | M13: 161116.05 | N13: 129.15 | O13: 14543291 | P13: 11411953 | Q13: 11109526 | R13: 302427.46 | S13: 3131338 | T13: 2794806.1 | U13: 336531.98 | V13: 6323733.7 | W13: 5797046.2 | X13: 5704444.3 | Y13: 92601.88 | Z13: 526687.51 | AA13: 436781.68 | AB13: 89905.83 | AC13: 3673340.3 | AD13: 3456294.8 | AE13: 3426679.9 | AF13: 29614.88 | AG13: 217045.51 | AH13: 196192.68 | AI13: 20852.83 | AJ13: 6150.4 | AK13: 5215.4 | AL13: 5127.4 | AM13: 88 | AN13: 935 | AO13: 768 | AP13: 167 | AQ13: 2233454 | AR13: 1960944 | AS13: 1905154 | AT13: 55790 | AU13: 272510 | AV13: 210558 | AW13: 61952 | AX13: 410789 | AY13: 374592 | AZ13: 367483 | BA13: 7109 | BB13: 36197 | BC13: 29263 | BD13: 6934 | BE13: 8219557.4 | BF13: 5614906.9 | BG13: 5405081.3 | BH13: 209825.58 | BI13: 2604650.5 | BJ13: 2358024.4 | BK13: 246626.15 | BL13: 1143116.4 | BM13: 853931.28 | BN13: 829512.52 | BO13: 24418.76 | BP13: 289185.09 | BQ13: 259394.57 | BR13: 29790.52 | BS13: 440973.24 | BT13: 260491.64 | BU13: 257267.82 | BV13: 3223.82 | BW13: 180481.6 | BX13: 174710.47 | BY13: 5771.13 | BZ13: 2844933 | CA13: 1783252 | CB13: 1745756 | CC13: 37496 | CD13: 1061681 | CE13: 979205 | CF13: 82476 | CG13: 3790534.8 | CH13: 2717232 | CI13: 2572545 | CJ13: 144687 | CK13: 1073302.9 | CL13: 944714.35 | CM13: 128588.5 | CN13: 0 | CO13: 5461475.6 | CP13: 735726.4 | CQ13: 21261.04 | CR13: 105270.66 | CS13: 0 | CT13: 0 | CU13: 0 | CV13: 15310 | CW13: 14028 | CX13: 13761 | CY13: 267 | CZ13: 1282 | DA13: 1032 | DB13: 250 | DC13: 13853 | DD13: 265 | DE13: 12753 | DF13: 12548 | DG13: 205 | DH13: 1100 | DI13: 892 | DJ13: 208 | DK13: 1078 | DL13: 928 | DM13: 902 | DN13: 26 | DO13: 150 | DP13: 120 | DQ13: 30 | DR13: 114 | DS13: 0 | DT13: 98 | DU13: 95 | DV13: 3 | DW13: 16 | DX13: 13 | DY13: 3 | DZ13: 0 | EA13: 0 | EB13: 0 | EC13: 0 | ED13: 0 | EE13: 0 | EF13: 0 | EG13: 362 | EH13: 234 | EI13: 220 | EJ13: 14 | EK13: 128 | EL13: 118 | EM13: 10 | EN13: 31 | EO13: 0 | EP13: 0 | EQ13: 31 | ER13: 0 | ES13: 0 | ET13: 0 | EU13: 0 | EV13: 0 | EW13: 0 | EX13: 0 | EY13: 0 | EZ13: 0 | FA13: 0 | FB13: 0
A14: 11 | B14: 成人手术 | C14: 普外科 | D14: 66427264 | E14: 11737950 | F14: 54689313 | G14: 52728 | H14: 5138 | I14: 818568.5 | J14: 617534 | K14: 298.5 | L14: 3316322.5 | M14: 15288028 | N14: 13785.65 | O14: 1.4409691e+08 | P14: 98674684 | Q14: 96336869 | R14: 2337815.3 | S14: 45422227 | T14: 43487601 | U14: 1934625.9 | V14: 20311857 | W14: 16752205 | X14: 16081952 | Y14: 670253.21 | Z14: 3559651.6 | AA14: 2725059.3 | AB14: 834592.35 | AC14: 6133792.4 | AD14: 4988174.1 | AE14: 4854895.5 | AF14: 133278.63 | AG14: 1145618.3 | AH14: 980822.01 | AI14: 164796.26 | AJ14: 2440113.6 | AK14: 2184471.3 | AL14: 2114318.7 | AM14: 70152.58 | AN14: 255642.37 | AO14: 208863.28 | AP14: 46779.09 | AQ14: 8341775 | AR14: 6712462 | AS14: 6413607 | AT14: 298855 | AU14: 1629313 | AV14: 1178788 | AW14: 450525 | AX14: 3396175.5 | AY14: 2867097.5 | AZ14: 2699130.5 | BA14: 167967 | BB14: 529078 | BC14: 356586 | BD14: 172492 | BE14: 1.2378505e+08 | BF14: 81922479 | BG14: 80254917 | BH14: 1667562.1 | BI14: 41862576 | BJ14: 40762542 | BK14: 1100033.6 | BL14: 22567286 | BM14: 14517112 | BN14: 14257030 | BO14: 260082.52 | BP14: 8050174 | BQ14: 7874281.3 | BR14: 175892.7 | BS14: 46528455 | BT14: 31361154 | BU14: 30836830 | BV14: 524324.11 | BW14: 15167301 | BX14: 14803669 | BY14: 363632.4 | BZ14: 20660492 | CA14: 12832701 | CB14: 12609398 | CC14: 223303 | CD14: 7827791 | CE14: 7629876 | CF14: 197915 | CG14: 34028821 | CH14: 23211512 | CI14: 22551659 | CJ14: 659852.5 | CK14: 10817310 | CL14: 10454716 | CM14: 362593.5 | CN14: 5464291.1 | CO14: 6672575.2 | CP14: 4916138.8 | CQ14: 2743296.2 | CR14: 512147.68 | CS14: 3432.59 | CT14: 970783.62 | CU14: 0 | CV14: 52728 | CW14: 44274 | CX14: 42123 | CY14: 2151 | CZ14: 8454 | DA14: 5935 | DB14: 2519 | DC14: 26228 | DD14: 127 | DE14: 22581 | DF14: 21412 | DG14: 1169 | DH14: 3647 | DI14: 2509 | DJ14: 1138 | DK14: 13446 | DL14: 10879 | DM14: 10424 | DN14: 455 | DO14: 2567 | DP14: 1820 | DQ14: 747 | DR14: 700 | DS14: 0 | DT14: 459 | DU14: 413 | DV14: 46 | DW14: 241 | DX14: 157 | DY14: 84 | DZ14: 12227 | EA14: 10240 | EB14: 9764 | EC14: 476 | ED14: 1987 | EE14: 1448 | EF14: 539 | EG14: 5138 | EH14: 3626 | EI14: 3548 | EJ14: 78 | EK14: 1512 | EL14: 1459 | EM14: 53 | EN14: 4542 | EO14: 3411 | EP14: 0 | EQ14: 1131 | ER14: 1765 | ES14: 0 | ET14: 3 | EU14: 1313 | EV14: 1049 | EW14: 0 | EX14: 264 | EY14: 874 | EZ14: 874 | FA14: 0 | FB14: 2069
A15: 12 | B15: 成人手术 | C15: 神经外科 | D15: 42346379 | E15: 2979683 | F15: 39366696 | G15: 13685 | H15: 2615 | I15: 3120 | J15: 126 | K15: 0 | L15: 2652390 | M15: 10812286 | N15: 0 | O15: 1.6251779e+08 | P15: 92300995 | Q15: 89600742 | R15: 2700253.3 | S15: 70216790 | T15: 67098568 | U15: 3118221.8 | V15: 4426126.2 | W15: 3476773.9 | X15: 3222090.4 | Y15: 254683.5 | Z15: 949352.31 | AA15: 561569.53 | AB15: 387782.78 | AC15: 1402724.2 | AD15: 1169132.9 | AE15: 1113498.4 | AF15: 55634.5 | AG15: 233591.31 | AH15: 165789.53 | AI15: 67801.78 | AJ15: 43719 | AK15: 35248 | AL15: 33313 | AM15: 1935 | AN15: 8471 | AO15: 4601 | AP15: 3870 | AQ15: 2447786 | AR15: 1917086 | AS15: 1753303 | AT15: 163783 | AU15: 530700 | AV15: 291933 | AW15: 238767 | AX15: 531897 | AY15: 355307 | AZ15: 321976 | BA15: 33331 | BB15: 176590 | BC15: 99246 | BD15: 77344 | BE15: 1.5809166e+08 | BF15: 88824221 | BG15: 86378652 | BH15: 2445569.8 | BI15: 69267438 | BJ15: 66536999 | BK15: 2730439 | BL15: 17014166 | BM15: 9057349.5 | BN15: 8697732.1 | BO15: 359617.42 | BP15: 7956816.2 | BQ15: 7535407.5 | BR15: 421408.72 | BS15: 1.017108e+08 | BT15: 59880198 | BU15: 58653341 | BV15: 1226856.9 | BW15: 41830600 | BX15: 40490579 | BY15: 1340021.8 | BZ15: 15257469 | CA15: 7856015 | CB15: 7586669 | CC15: 269346 | CD15: 7401454 | CE15: 7107115 | CF15: 294339 | CG15: 24109227 | CH15: 12030659 | CI15: 11440910 | CJ15: 589749.5 | CK15: 12078567 | CL15: 11403898 | CM15: 674669.5 | CN15: -25 | CO15: 2446471.3 | CP15: 1588274.6 | CQ15: 251574.71 | CR15: 139805.61 | CS15: 0 | CT15: 1292815.1 | CU15: 0 | CV15: 13685 | CW15: 10349 | CX15: 9438 | CY15: 911 | CZ15: 3336 | DA15: 1946 | DB15: 1390 | DC15: 7861 | DD15: 88 | DE15: 6458 | DF15: 5901 | DG15: 557 | DH15: 1403 | DI15: 826 | DJ15: 577 | DK15: 5450 | DL15: 3746 | DM15: 3409 | DN15: 337 | DO15: 1704 | DP15: 1003 | DQ15: 701 | DR15: 286 | DS15: 0 | DT15: 67 | DU15: 56 | DV15: 11 | DW15: 219 | DX15: 116 | DY15: 103 | DZ15: 0 | EA15: 0 | EB15: 0 | EC15: 0 | ED15: 0 | EE15: 0 | EF15: 0 | EG15: 2615 | EH15: 1454 | EI15: 1386 | EJ15: 68 | EK15: 1161 | EL15: 1102 | EM15: 59 | EN15: 2284 | EO15: 1050 | EP15: 690 | EQ15: 544 | ER15: 482 | ES15: 0 | ET15: 0 | EU15: 410 | EV15: 292 | EW15: 30 | EX15: 88 | EY15: 1251 | EZ15: 591 | FA15: 660 | FB15: 1042
... A57: 54 | B57: 医技平台 | C57: 健康管理中心 | D57: 22643670 | E57: 22643670 | F57: 0 | G57: 3489 | H57: 0 | I57: 0 | J57: 0 | K57: 0 | L57: 0 | M57: 0 | N57: 0 | O57: 22643813 | P57: 2687298.6 | Q57: 143.46 | R57: 2687155.1 | S57: 19956515 | T57: 0 | U57: 19956515 | V57: 22643813 | W57: 2687298.6 | X57: 143.46 | Y57: 2687155.1 | Z57: 19956515 | AA57: 0 | AB57: 19956515 | AC57: 143.46 | AD57: 143.46 | AE57: 143.46 | AF57: 0 | AG57: 0 | AH57: 0 | AI57: 0 | AJ57: 0 | AK57: 0 | AL57: 0 | AM57: 0 | AN57: 0 | AO57: 0 | AP57: 0 | AQ57: 120 | AR57: 0 | AS57: 0 | AT57: 0 | AU57: 120 | AV57: 0 | AW57: 120 | AX57: 22643550 | AY57: 2687155.1 | AZ57: 0 | BA57: 2687155.1 | BB57: 19956395 | BC57: 0 | BD57: 19956395 | BE57: 0 | BF57: 0 | BG57: 0 | BH57: 0 | BI57: 0 | BJ57: 0 | BK57: 0 | BL57: 0 | BM57: 0 | BN57: 0 | BO57: 0 | BP57: 0 | BQ57: 0 | BR57: 0 | BS57: 0 | BT57: 0 | BU57: 0 | BV57: 0 | BW57: 0 | BX57: 0 | BY57: 0 | BZ57: 0 | CA57: 0 | CB57: 0 | CC57: 0 | CD57: 0 | CE57: 0 | CF57: 0 | CG57: 0 | CH57: 0 | CI57: 0 | CJ57: 0 | CK57: 0 | CL57: 0 | CM57: 0 | CN57: 0 | CO57: 22643813 | CP57: 0 | CQ57: 0 | CR57: 0 | CS57: 0 | CT57: 0 | CU57: 0 | CV57: 3489 | CW57: 1265 | CX57: 0 | CY57: 1265 | CZ57: 2224 | DA57: 0 | DB57: 2224 | DC57: 3489 | DD57: 0 | DE57: 1265 | DF57: 0 | DG57: 1265 | DH57: 2224 | DI57: 0 | DJ57: 2224 | DK57: 0 | DL57: 0 | DM57: 0 | DN57: 0 | DO57: 0 | DP57: 0 | DQ57: 0 | DR57: 0 | DS57: 0 | DT57: 0 | DU57: 0 | DV57: 0 | DW57: 0 | DX57: 0 | DY57: 0 | DZ57: 0 | EA57: 0 | EB57: 0 | EC57: 0 | ED57: 0 | EE57: 0 | EF57: 0 | EG57: 0 | EH57: 0 | EI57: 0 | EJ57: 0 | EK57: 0 | EL57: 0 | EM57: 0 | EN57: 0 | EO57: 0 | EP57: 0 | EQ57: 0 | ER57: 0 | ES57: 0 | ET57: 0 | EU57: 0 | EV57: 0 | EW57: 0 | EX57: 0 | EY57: 0 | EZ57: 0 | FA57: 0 | FB57: 0
A58: 55 | C58: 镜朗特需与国际医疗部 | D58: 27848 | E58: 0 | F58: 27848 | G58: 0 | H58: 2 | I58: 0 | J58: 0 | K58: 0 | L58: 952 | M58: 0 | N58: 0 | O58: 31162.07 | P58: 31162.07 | Q58: 0 | R58: 31162.07 | S58: 0 | T58: 0 | U58: 0 | V58: 0 | W58: 0 | X58: 0 | Y58: 0 | Z58: 0 | AA58: 0 | AB58: 0 | AC58: 0 | AD58: 0 | AE58: 0 | AF58: 0 | AG58: 0 | AH58: 0 | AI58: 0 | AJ58: 0 | AK58: 0 | AL58: 0 | AM58: 0 | AN58: 0 | AO58: 0 | AP58: 0 | AQ58: 0 | AR58: 0 | AS58: 0 | AT58: 0 | AU58: 0 | AV58: 0 | AW58: 0 | AX58: 0 | AY58: 0 | AZ58: 0 | BA58: 0 | BB58: 0 | BC58: 0 | BD58: 0 | BE58: 31162.07 | BF58: 31162.07 | BG58: 0 | BH58: 31162.07 | BI58: 0 | BJ58: 0 | BK58: 0 | BL58: 1587.89 | BM58: 1587.89 | BN58: 0 | BO58: 1587.89 | BP58: 0 | BQ58: 0 | BR58: 0 | BS58: 1726.18 | BT58: 1726.18 | BU58: 0 | BV58: 1726.18 | BW58: 0 | BX58: 0 | BY58: 0 | BZ58: 8872 | CA58: 8872 | CB58: 0 | CC58: 8872 | CD58: 0 | CE58: 0 | CF58: 0 | CG58: 18976 | CH58: 18976 | CI58: 0 | CJ58: 18976 | CK58: 0 | CL58: 0 | CM58: 0 | CN58: 0 | CO58: 0 | CP58: 0 | CQ58: 0 | CR58: 0 | CS58: 0 | CT58: 31162.07 | CU58: 0 | CV58: 0 | CW58: 0 | CX58: 0 | CY58: 0 | CZ58: 0 | DA58: 0 | DB58: 0 | DC58: 0 | DD58: 0 | DE58: 0 | DF58: 0 | DG58: 0 | DH58: 0 | DI58: 0 | DJ58: 0 | DK58: 0 | DL58: 0 | DM58: 0 | DN58: 0 | DO58: 0 | DP58: 0 | DQ58: 0 | DR58: 0 | DS58: 0 | DT58: 0 | DU58: 0 | DV58: 0 | DW58: 0 | DX58: 0 | DY58: 0 | DZ58: 0 | EA58: 0 | EB58: 0 | EC58: 0 | ED58: 0 | EE58: 0 | EF58: 0 | EG58: 2 | EH58: 2 | EI58: 0 | EJ58: 2 | EK58: 0 | EL58: 0 | EM58: 0 | EN58: 0 | EO58: 0 | EP58: 0 | EQ58: 0 | ER58: 0 | ES58: 0 | ET58: 0 | EU58: 0 | EV58: 0 | EW58: 0 | EX58: 0 | EY58: 0 | EZ58: 0 | FA58: 0 | FB58: 0
A59: 56 | B59: 成人非手术 | C59: 感染科 | D59: 3118823.5 | E59: 1435088 | F59: 1683735.5 | G59: 5195 | H59: 168 | I59: 26850 | J59: 0 | K59: 0 | L59: 102247 | M59: 5665 | N59: 315 | O59: 4987394.3 | P59: 4236946 | Q59: 4189738.1 | R59: 47207.93 | S59: 750448.26 | T59: 670709.13 | U59: 79739.13 | V59: 2262508.8 | W59: 2094321.9 | X59: 2047113.9 | Y59: 47207.93 | Z59: 168186.93 | AA59: 104252.28 | AB59: 63934.65 | AC59: 781288.78 | AD59: 729493.49 | AE59: 716535.79 | AF59: 12957.7 | AG59: 51795.29 | AH59: 35098.36 | AI59: 16696.93 | AJ59: 46132.03 | AK59: 42520.39 | AL59: 41597.16 | AM59: 923.23 | AN59: 3611.64 | AO59: 2598.92 | AP59: 1012.72 | AQ59: 1257568 | AR59: 1159952 | AS59: 1130988 | AT59: 28964 | AU59: 97616 | AV59: 56642 | AW59: 40974 | AX59: 177520 | AY59: 162356 | AZ59: 157993 | BA59: 4363 | BB59: 15164 | BC59: 9913 | BD59: 5251 | BE59: 2724885.5 | BF59: 2142624.2 | BG59: 2142624.2 | BH59: 0 | BI59: 582261.33 | BJ59: 566456.85 | BK59: 15804.48 | BL59: 921000.37 | BM59: 703030.29 | BN59: 703030.29 | BO59: 0 | BP59: 217970.08 | BQ59: 211255.32 | BR59: 6714.76 | BS59: 120149.63 | BT59: 95812.38 | BU59: 95812.38 | BV59: 0 | BW59: 24337.25 | BX59: 24024.53 | BY59: 312.72 | BZ59: 1308757 | CA59: 1038513 | CB59: 1038513 | CC59: 0 | CD59: 270244 | CE59: 262863 | CF59: 7381 | CG59: 374978.5 | CH59: 305268.5 | CI59: 305268.5 | CJ59: 0 | CK59: 69710 | CL59: 68314 | CM59: 1396 | CN59: 1856942.7 | CO59: 0 | CP59: 46167.98 | CQ59: 359398.13 | CR59: 0 | CS59: 0 | CT59: 0 | CU59: 0 | CV59: 5195 | CW59: 4750 | CX59: 4613 | CY59: 137 | CZ59: 445 | DA59: 284 | DB59: 161 | DC59: 934 | DD59: 0 | DE59: 829 | DF59: 786 | DG59: 43 | DH59: 105 | DI59: 64 | DJ59: 41 | DK59: 153 | DL59: 126 | DM59: 116 | DN59: 10 | DO59: 27 | DP59: 19 | DQ59: 8 | DR59: 0 | DS59: 0 | DT59: 0 | DU59: 0 | DV59: 0 | DW59: 0 | DX59: 0 | DY59: 0 | DZ59: 4108 | EA59: 3795 | EB59: 3711 | EC59: 84 | ED59: 313 | EE59: 201 | EF59: 112 | EG59: 168 | EH59: 141 | EI59: 141 | EJ59: 0 | EK59: 27 | EL59: 27 | EM59: 0 | EN59: 7 | EO59: 0 | EP59: 0 | EQ59: 7 | ER59: 0 | ES59: 0 | ET59: 0 | EU59: 0 | EV59: 0 | EW59: 0 | EX59: 0 | EY59: 0 | EZ59: 0 | FA59: 0 | FB59: 24
A60: 57 | B60: 其他 | C60: 新冠核酸检测 | D60: 933 | E60: 933 | F60: 0 | G60: 0 | H60: 0 | I60: 0 | J60: 0 | K60: 0 | L60: 0 | M60: 0 | N60: 0 | O60: 1003.96 | P60: 987.96 | Q60: 971.96 | R60: 16 | S60: 16 | T60: 16 | U60: 0 | V60: 1003.96 | W60: 987.96 | X60: 971.96 | Y60: 16 | Z60: 16 | AA60: 16 | AB60: 0 | AC60: 70.96 | AD60: 70.96 | AE60: 70.96 | AF60: 0 | AG60: 0 | AH60: 0 | AI60: 0 | AJ60: 0 | AK60: 0 | AL60: 0 | AM60: 0 | AN60: 0 | AO60: 0 | AP60: 0 | AQ60: 933 | AR60: 917 | AS60: 901 | AT60: 16 | AU60: 16 | AV60: 16 | AW60: 0 | AX60: 0 | AY60: 0 | AZ60: 0 | BA60: 0 | BB60: 0 | BC60: 0 | BD60: 0 | BE60: 0 | BF60: 0 | BG60: 0 | BH60: 0 | BI60: 0 | BJ60: 0 | BK60: 0 | BL60: 0 | BM60: 0 | BN60: 0 | BO60: 0 | BP60: 0 | BQ60: 0 | BR60: 0 | BS60: 0 | BT60: 0 | BU60: 0 | BV60: 0 | BW60: 0 | BX60: 0 | BY60: 0 | BZ60: 0 | CA60: 0 | CB60: 0 | CC60: 0 | CD60: 0 | CE60: 0 | CF60: 0 | CG60: 0 | CH60: 0 | CI60: 0 | CJ60: 0 | CK60: 0 | CL60: 0 | CM60: 0 | CN60: 0 | CO60: 1003.96 | CP60: 0 | CQ60: 0 | CR60: 0 | CS60: 0 | CT60: 0 | CU60: 0 | CV60: 0 | CW60: 0 | CX60: 0 | CY60: 0 | CZ60: 0 | DA60: 0 | DB60: 0 | DC60: 0 | DD60: 0 | DE60: 0 | DF60: 0 | DG60: 0 | DH60: 0 | DI60: 0 | DJ60: 0 | DK60: 0 | DL60: 0 | DM60: 0 | DN60: 0 | DO60: 0 | DP60: 0 | DQ60: 0 | DR60: 0 | DS60: 0 | DT60: 0 | DU60: 0 | DV60: 0 | DW60: 0 | DX60: 0 | DY60: 0 | DZ60: 0 | EA60: 0 | EB60: 0 | EC60: 0 | ED60: 0 | EE60: 0 | EF60: 0 | EG60: 0 | EH60: 0 | EI60: 0 | EJ60: 0 | EK60: 0 | EL60: 0 | EM60: 0 | EN60: 0 | EO60: 0 | EP60: 0 | EQ60: 0 | ER60: 0 | ES60: 0 | ET60: 0 | EU60: 0 | EV60: 0 | EW60: 0 | EX60: 0 | EY60: 0 | EZ60: 0 | FA60: 0 | FB60: 0
A61: 58 | B61: 成人手术 | C61: 胎儿医学与宫内儿科学诊治中心 | D61: 6874214.2 | E61: 5622191 | F61: 1252023.2 | G61: 4292 | H61: 117 | I61: 2606 | J61: 241 | K61: 0 | L61: 175831 | M61: 154038.5 | N61: 4065.68 | O61: 7460213.5 | P61: 2738242.6 | Q61: 799965.55 | R61: 1938277 | S61: 4721970.9 | T61: 952927.83 | U61: 3769043.1 | V61: 5707139.7 | W61: 2184540.6 | X61: 411258.29 | Y61: 1773282.3 | Z61: 3522599 | AA61: 32959.83 | AB61: 3489639.2 | AC61: 62156.11 | AD61: 50703.36 | AE61: 45818.1 | AF61: 4885.26 | AG61: 11452.75 | AH61: 3545.04 | AI61: 7907.71 | AJ61: 22792.56 | AK61: 8311.77 | AL61: 622.19 | AM61: 7689.58 | AN61: 14480.79 | AO61: 124.79 | AP61: 14356 | AQ61: 4020247 | AR61: 1603682.5 | AS61: 333659 | AT61: 1270023.5 | AU61: 2416564.5 | AV61: 25946 | AW61: 2390618.5 | AX61: 1601944 | AY61: 521843 | AZ61: 31159 | BA61: 490684 | BB61: 1080101 | BC61: 3344 | BD61: 1076757 | BE61: 1753073.8 | BF61: 553701.93 | BG61: 388707.26 | BH61: 164994.67 | BI61: 1199371.9 | BJ61: 919968 | BK61: 279403.9 | BL61: 333128.08 | BM61: 156779.78 | BN61: 119990.98 | BO61: 36788.8 | BP61: 176348.3 | BQ61: 130945.21 | BR61: 45403.09 | BS61: 167922.5 | BT61: 45675.55 | BU61: 36494.08 | BV61: 9181.47 | BW61: 122246.95 | BX61: 89479.29 | BY61: 32767.66 | BZ61: 553797.75 | CA61: 136013 | CB61: 109370.5 | CC61: 26642.5 | CD61: 417784.75 | CE61: 348977 | CF61: 68807.75 | CG61: 698225.5 | CH61: 215233.6 | CI61: 122851.7 | CJ61: 92381.9 | CK61: 482991.9 | CL61: 350566.5 | CM61: 132425.4 | CN61: 105268.87 | CO61: 722093.41 | CP61: 7030.29 | CQ61: 937123.86 | CR61: 3749623.7 | CS61: 186815.5 | CT61: 143351.93 | CU61: 0 | CV61: 4292 | CW61: 2378 | CX61: 1127 | CY61: 1251 | CZ61: 1914 | DA61: 98 | DB61: 1816 | DC61: 2025 | DD61: 0 | DE61: 1514 | DF61: 1040 | DG61: 474 | DH61: 511 | DI61: 86 | DJ61: 425 | DK61: 17 | DL61: 14 | DM61: 14 | DN61: 0 | DO61: 3 | DP61: 1 | DQ61: 2 | DR61: 1847 | DS61: 0 | DT61: 558 | DU61: 3 | DV61: 555 | DW61: 1289 | DX61: 1 | DY61: 1288 | DZ61: 403 | EA61: 292 | EB61: 70 | EC61: 222 | ED61: 111 | EE61: 10 | EF61: 101 | EG61: 117 | EH61: 34 | EI61: 30 | EJ61: 4 | EK61: 83 | EL61: 67 | EM61: 16 | EN61: 121 | EO61: 45 | EP61: 0 | EQ61: 76 | ER61: 2 | ES61: 0 | ET61: 0 | EU61: 19 | EV61: 4 | EW61: 0 | EX61: 15 | EY61: 0 | EZ61: 0 | FA61: 0 | FB61: 0
A62: 59 | B62: 医技平台 | C62: 麻醉科 | D62: 9232236 | E62: 9232236 | F62: 0 | G62: 14440 | H62: 0 | I62: 95610 | J62: 4130016 | K62: 0 | L62: 0 | M62: 0 | N62: 0 | O62: 13569415 | P62: 11188992 | Q62: 10314725 | R62: 874267.8 | S62: 2380422.2 | T62: 1287112.6 | U62: 1093309.6 | V62: 13569415 | W62: 11188992 | X62: 10314725 | Y62: 874267.8 | Z62: 2380422.2 | AA62: 1287112.6 | AB62: 1093309.6 | AC62: 1134468.5 | AD62: 947037.7 | AE62: 908372.9 | AF62: 38664.8 | AG62: 187430.79 | AH62: 110603.75 | AI62: 76827.04 | AJ62: 3202710.1 | AK62: 2657404.7 | AL62: 2548013.7 | AM62: 109391 | AN62: 545305.42 | AO62: 320514.86 | AP62: 224790.56 | AQ62: 3440 | AR62: 2580 | AS62: 2510 | AT62: 70 | AU62: 860 | AV62: 645 | AW62: 215 | AX62: 9228796 | AY62: 7581970 | AZ62: 6855828 | BA62: 726142 | BB62: 1646826 | BC62: 855349 | BD62: 791477 | BE62: 0 | BF62: 0 | BG62: 0 | BH62: 0 | BI62: 0 | BJ62: 0 | BK62: 0 | BL62: 0 | BM62: 0 | BN62: 0 | BO62: 0 | BP62: 0 | BQ62: 0 | BR62: 0 | BS62: 0 | BT62: 0 | BU62: 0 | BV62: 0 | BW62: 0 | BX62: 0 | BY62: 0 | BZ62: 0 | CA62: 0 | CB62: 0 | CC62: 0 | CD62: 0 | CE62: 0 | CF62: 0 | CG62: 0 | CH62: 0 | CI62: 0 | CJ62: 0 | CK62: 0 | CL62: 0 | CM62: 0 | CN62: -25 | CO62: 330 | CP62: 0 | CQ62: 10727214 | CR62: 2841778.7 | CS62: 91.8 | CT62: 0 | CU62: 0 | CV62: 14440 | CW62: 11903 | CX62: 10663 | CY62: 1240 | CZ62: 2537 | DA62: 1332 | DB62: 1205 | DC62: 11716 | DD62: 0 | DE62: 9866 | DF62: 9474 | DG62: 392 | DH62: 1850 | DI62: 1161 | DJ62: 689 | DK62: 0 | DL62: 0 | DM62: 0 | DN62: 0 | DO62: 0 | DP62: 0 | DQ62: 0 | DR62: 2724 | DS62: 0 | DT62: 2037 | DU62: 1189 | DV62: 848 | DW62: 687 | DX62: 171 | DY62: 516 | DZ62: 0 | EA62: 0 | EB62: 0 | EC62: 0 | ED62: 0 | EE62: 0 | EF62: 0 | EG62: 0 | EH62: 0 | EI62: 0 | EJ62: 0 | EK62: 0 | EL62: 0 | EM62: 0 | EN62: 111 | EO62: 0 | EP62: 0 | EQ62: 111 | ER62: 0 | ES62: 0 | ET62: 0 | EU62: 0 | EV62: 0 | EW62: 0 | EX62: 0 | EY62: 0 | EZ62: 0 | FA62: 0 | FB62: 0
A63: 60 | B63: 成人非手术 | C63: 放疗科 | D63: 40980164 | E63: 24090821 | F63: 16889342 | G63: 7124 | H63: 1508 | I63: 22348563 | J63: 44 | K63: 0 | L63: 13632000 | M63: 11647 | N63: 19120.52 | O63: 57617014 | P63: 23189178 | Q63: 22778852 | R63: 410325.47 | S63: 34427836 | T63: 33171120 | U63: 1256716.5 | V63: 28187582 | W63: 15329686 | X63: 14937967 | Y63: 391718.17 | Z63: 12857897 | AA63: 11862685 | AB63: 995211.76 | AC63: 4020140.9 | AD63: 2566692.9 | AE63: 2518805.7 | AF63: 47887.17 | AG63: 1453447.9 | AH63: 1301187.6 | AI63: 152260.33 | AJ63: 76620.62 | AK63: 17561.68 | AL63: 16228.68 | AM63: 1333 | AN63: 59058.94 | AO63: 50601.51 | AP63: 8457.43 | AQ63: 1489221 | AR63: 546890 | AS63: 518850 | AT63: 28040 | AU63: 942331 | AV63: 724784 | AW63: 217547 | AX63: 22601600 | AY63: 12198541 | AZ63: 11884083 | BA63: 314458 | BB63: 10403059 | BC63: 9786112 | BD63: 616947 | BE63: 29429431 | BF63: 7859492.2 | BG63: 7840884.9 | BH63: 18607.3 | BI63: 21569939 | BJ63: 21308434 | BK63: 261504.71 | BL63: 11924884 | BM63: 5201391.1 | BN63: 5192897.7 | BO63: 8493.48 | BP63: 6723492.9 | BQ63: 6696436.6 | BR63: 27056.29 | BS63: 615204.86 | BT63: 217391.08 | BU63: 216930.26 | BV63: 460.82 | BW63: 397813.78 | BX63: 391421.36 | BY63: 6392.42 | BZ63: 2035008 | CA63: 761630 | CB63: 753424 | CC63: 8206 | CD63: 1273378 | CE63: 1256342 | CF63: 17036 | CG63: 14854334 | CH63: 1679080 | CI63: 1677633 | CJ63: 1447 | CK63: 13175254 | CL63: 12964234 | CM63: 211020 | CN63: 0 | CO63: 21188270 | CP63: 6878112.3 | CQ63: 0 | CR63: 121199.95 | CS63: 0 | CT63: 163707.13 | CU63: 0 | CV63: 7124 | CW63: 3039 | CX63: 2904 | CY63: 135 | CZ63: 4085 | DA63: 3304 | DB63: 781 | DC63: 4926 | DD63: 0 | DE63: 1947 | DF63: 1859 | DG63: 88 | DH63: 2979 | DI63: 2534 | DJ63: 445 | DK63: 2103 | DL63: 1070 | DM63: 1024 | DN63: 46 | DO63: 1033 | DP63: 724 | DQ63: 309 | DR63: 95 | DS63: 0 | DT63: 22 | DU63: 21 | DV63: 1 | DW63: 73 | DX63: 46 | DY63: 27 | DZ63: 0 | EA63: 0 | EB63: 0 | EC63: 0 | ED63: 0 | EE63: 0 | EF63: 0 | EG63: 1508 | EH63: 488 | EI63: 486 | EJ63: 2 | EK63: 1020 | EL63: 1010 | EM63: 10 | EN63: 1548 | EO63: 0 | EP63: 0 | EQ63: 1548 | ER63: 0 | ES63: 0 | ET63: 0 | EU63: 0 | EV63: 0 | EW63: 0 | EX63: 0 | EY63: 0 | EZ63: 0 | FA63: 0 | FB63: 0
A64: 61 | B64: 其他 | C64: 特需门诊 | D64: -654 | E64: -654 | F64: 0 | G64: 0 | H64: 0 | I64: 6 | J64: 0 | K64: 0 | L64: 0 | M64: 0 | N64: 0 | O64: -654 | P64: -660 | Q64: -660 | R64: 0 | S64: 6 | T64: 6 | U64: 0 | V64: -654 | W64: -660 | X64: -660 | Y64: 0 | Z64: 6 | AA64: 6 | AB64: 0 | AC64: 0 | AD64: 0 | AE64: 0 | AF64: 0 | AG64: 0 | AH64: 0 | AI64: 0 | AJ64: 0 | AK64: 0 | AL64: 0 | AM64: 0 | AN64: 0 | AO64: 0 | AP64: 0 | AQ64: -660 | AR64: -660 | AS64: -660 | AT64: 0 | AU64: 0 | AV64: 0 | AW64: 0 | AX64: 6 | AY64: 0 | AZ64: 0 | BA64: 0 | BB64: 6 | BC64: 6 | BD64: 0 | BE64: 0 | BF64: 0 | BG64: 0 | BH64: 0 | BI64: 0 | BJ64: 0 | BK64: 0 | BL64: 0 | BM64: 0 | BN64: 0 | BO64: 0 | BP64: 0 | BQ64: 0 | BR64: 0 | BS64: 0 | BT64: 0 | BU64: 0 | BV64: 0 | BW64: 0 | BX64: 0 | BY64: 0 | BZ64: 0 | CA64: 0 | CB64: 0 | CC64: 0 | CD64: 0 | CE64: 0 | CF64: 0 | CG64: 0 | CH64: 0 | CI64: 0 | CJ64: 0 | CK64: 0 | CL64: 0 | CM64: 0 | CN64: 0 | CO64: 0 | CP64: 0 | CQ64: 0 | CR64: -654 | CS64: 0 | CT64: 0 | CU64: 0 | CV64: 0 | CW64: 0 | CX64: 0 | CY64: 0 | CZ64: 0 | DA64: 0 | DB64: 0 | DC64: 0 | DD64: 0 | DE64: 0 | DF64: 0 | DG64: 0 | DH64: 0 | DI64: 0 | DJ64: 0 | DK64: 0 | DL64: 0 | DM64: 0 | DN64: 0 | DO64: 0 | DP64: 0 | DQ64: 0 | DR64: 0 | DS64: 0 | DT64: 0 | DU64: 0 | DV64: 0 | DW64: 0 | DX64: 0 | DY64: 0 | DZ64: 0 | EA64: 0 | EB64: 0 | EC64: 0 | ED64: 0 | EE64: 0 | EF64: 0 | EG64: 0 | EH64: 0 | EI64: 0 | EJ64: 0 | EK64: 0 | EL64: 0 | EM64: 0 | EN64: 0 | EO64: 0 | EP64: 0 | EQ64: 0 | ER64: 0 | ES64: 0 | ET64: 0 | EU64: 0 | EV64: 0 | EW64: 0 | EX64: 0 | EY64: 0 | EZ64: 0 | FA64: 0 | FB64: 0
A65: 62 | B65: 医技平台 | C65: 病理科 | D65: 1785353 | E65: 1785353 | F65: 0 | G65: 1526 | H65: 0 | I65: 720 | J65: 44 | K65: 0 | L65: 0 | M65: 0 | N65: 0 | O65: 1786553 | P65: 1307380 | Q65: 1092755 | R65: 214625 | S65: 479173 | T65: 257859 | U65: 221314 | V65: 1786553 | W65: 1307380 | X65: 1092755 | Y65: 214625 | Z65: 479173 | AA65: 257859 | AB65: 221314 | AC65: 0 | AD65: 0 | AE65: 0 | AF65: 0 | AG65: 0 | AH65: 0 | AI65: 0 | AJ65: 1200 | AK65: 0 | AL65: 0 | AM65: 0 | AN65: 1200 | AO65: 600 | AP65: 600 | AQ65: 1728269 | AR65: 1288692 | AS65: 1083539 | AT65: 205153 | AU65: 439577 | AV65: 247149 | AW65: 192428 | AX65: 57084 | AY65: 18688 | AZ65: 9216 | BA65: 9472 | BB65: 38396 | BC65: 10110 | BD65: 28286 | BE65: 0 | BF65: 0 | BG65: 0 | BH65: 0 | BI65: 0 | BJ65: 0 | BK65: 0 | BL65: 0 | BM65: 0 | BN65: 0 | BO65: 0 | BP65: 0 | BQ65: 0 | BR65: 0 | BS65: 0 | BT65: 0 | BU65: 0 | BV65: 0 | BW65: 0 | BX65: 0 | BY65: 0 | BZ65: 0 | CA65: 0 | CB65: 0 | CC65: 0 | CD65: 0 | CE65: 0 | CF65: 0 | CG65: 0 | CH65: 0 | CI65: 0 | CJ65: 0 | CK65: 0 | CL65: 0 | CM65: 0 | CN65: 0 | CO65: 0 | CP65: 0 | CQ65: 1650064 | CR65: 136489 | CS65: 0 | CT65: 0 | CU65: 0 | CV65: 1526 | CW65: 998 | CX65: 842 | CY65: 156 | CZ65: 528 | DA65: 244 | DB65: 284 | DC65: 1306 | DD65: 0 | DE65: 925 | DF65: 806 | DG65: 119 | DH65: 381 | DI65: 206 | DJ65: 175 | DK65: 0 | DL65: 0 | DM65: 0 | DN65: 0 | DO65: 0 | DP65: 0 | DQ65: 0 | DR65: 220 | DS65: 0 | DT65: 73 | DU65: 36 | DV65: 37 | DW65: 147 | DX65: 38 | DY65: 109 | DZ65: 0 | EA65: 0 | EB65: 0 | EC65: 0 | ED65: 0 | EE65: 0 | EF65: 0 | EG65: 0 | EH65: 0 | EI65: 0 | EJ65: 0 | EK65: 0 | EL65: 0 | EM65: 0 | EN65: 3 | EO65: 2 | EP65: 0 | EQ65: 1 | ER65: 2 | ES65: 0 | ET65: 0 | EU65: 0 | EV65: 0 | EW65: 0 | EX65: 0 | EY65: 0 | EZ65: 0 | FA65: 0 | FB65: 0
A66: 63 | B66: 医技平台 | C66: 放射科 | D66: 1662718 | E66: 1662718 | F66: 0 | G66: 15677 | H66: 0 | I66: 390 | J66: 3300 | K66: 0 | L66: 0 | M66: 0 | N66: 0 | O66: 1669591.8 | P66: 870799.85 | Q66: 629245.85 | R66: 241554 | S66: 798791.92 | T66: 224387.76 | U66: 574404.16 | V66: 1669591.8 | W66: 870799.85 | X66: 629245.85 | Y66: 241554 | Z66: 798791.92 | AA66: 224387.76 | AB66: 574404.16 | AC66: 2532.77 | AD66: 1308.85 | AE66: 1308.85 | AF66: 0 | AG66: 1223.92 | AH66: 53.76 | AI66: 1170.16 | AJ66: 4341 | AK66: 2324 | AL66: 2324 | AM66: 0 | AN66: 2017 | AO66: 1716 | AP66: 301 | AQ66: 799788 | AR66: 567539 | AS66: 419229 | AT66: 148310 | AU66: 232249 | AV66: 110546 | AW66: 121703 | AX66: 862930 | AY66: 299628 | AZ66: 206384 | BA66: 93244 | BB66: 563302 | BC66: 112072 | BD66: 451230 | BE66: 0 | BF66: 0 | BG66: 0 | BH66: 0 | BI66: 0 | BJ66: 0 | BK66: 0 | BL66: 0 | BM66: 0 | BN66: 0 | BO66: 0 | BP66: 0 | BQ66: 0 | BR66: 0 | BS66: 0 | BT66: 0 | BU66: 0 | BV66: 0 | BW66: 0 | BX66: 0 | BY66: 0 | BZ66: 0 | CA66: 0 | CB66: 0 | CC66: 0 | CD66: 0 | CE66: 0 | CF66: 0 | CG66: 0 | CH66: 0 | CI66: 0 | CJ66: 0 | CK66: 0 | CL66: 0 | CM66: 0 | CN66: 126 | CO66: 1382 | CP66: 646 | CQ66: 738836 | CR66: 928601.77 | CS66: 0 | CT66: 0 | CU66: 0 | CV66: 15677 | CW66: 10913 | CX66: 8600 | CY66: 2313 | CZ66: 4764 | DA66: 2073 | DB66: 2691 | DC66: 13515 | DD66: 161 | DE66: 10078 | DF66: 7984 | DG66: 2094 | DH66: 3437 | DI66: 1769 | DJ66: 1668 | DK66: 0 | DL66: 0 | DM66: 0 | DN66: 0 | DO66: 0 | DP66: 0 | DQ66: 0 | DR66: 2001 | DS66: 0 | DT66: 740 | DU66: 538 | DV66: 202 | DW66: 1261 | DX66: 297 | DY66: 964 | DZ66: 0 | EA66: 0 | EB66: 0 | EC66: 0 | ED66: 0 | EE66: 0 | EF66: 0 | EG66: 0 | EH66: 0 | EI66: 0 | EJ66: 0 | EK66: 0 | EL66: 0 | EM66: 0 | EN66: 52 | EO66: 0 | EP66: 0 | EQ66: 52 | ER66: 0 | ES66: 0 | ET66: 0 | EU66: 0 | EV66: 0 | EW66: 0 | EX66: 0 | EY66: 0 | EZ66: 0 | FA66: 0 | FB66: 0
A67: 64 | B67: 医技平台 | C67: 超声诊断科 | D67: 1283268 | E67: 1283268 | F67: 0 | G67: 7643 | H67: 0 | I67: 10670 | J67: 103288 | K67: 0 | L67: 0 | M67: 0 | N67: 0 | O67: 1640426.7 | P67: 1295419 | Q67: 1180564.9 | R67: 114854.11 | S67: 345007.71 | T67: 218331.18 | U67: 126676.53 | V67: 1640426.7 | W67: 1295419 | X67: 1180564.9 | Y67: 114854.11 | Z67: 345007.71 | AA67: 218331.18 | AB67: 126676.53 | AC67: 245510.39 | AD67: 186952.78 | AE67: 174163.67 | AF67: 12789.11 | AG67: 58557.61 | AH67: 38299.08 | AI67: 20258.53 | AJ67: 111648.3 | AK67: 92853.2 | AL67: 87183.2 | AM67: 5670 | AN67: 18795.1 | AO67: 15095.1 | AP67: 3700 | AQ67: 760742 | AR67: 603958 | AS67: 568849 | AT67: 35109 | AU67: 156784 | AV67: 105101 | AW67: 51683 | AX67: 522526 | AY67: 411655 | AZ67: 350369 | BA67: 61286 | BB67: 110871 | BC67: 59836 | BD67: 51035 | BE67: 0 | BF67: 0 | BG67: 0 | BH67: 0 | BI67: 0 | BJ67: 0 | BK67: 0 | BL67: 0 | BM67: 0 | BN67: 0 | BO67: 0 | BP67: 0 | BQ67: 0 | BR67: 0 | BS67: 0 | BT67: 0 | BU67: 0 | BV67: 0 | BW67: 0 | BX67: 0 | BY67: 0 | BZ67: 0 | CA67: 0 | CB67: 0 | CC67: 0 | CD67: 0 | CE67: 0 | CF67: 0 | CG67: 0 | CH67: 0 | CI67: 0 | CJ67: 0 | CK67: 0 | CL67: 0 | CM67: 0 | CN67: -1420 | CO67: 3380 | CP67: 113954.45 | CQ67: 774887.27 | CR67: 749624.97 | CS67: 0 | CT67: 0 | CU67: 0 | CV67: 7643 | CW67: 6181 | CX67: 5761 | CY67: 420 | CZ67: 1462 | DA67: 819 | DB67: 643 | DC67: 6251 | DD67: 62 | DE67: 5034 | DF67: 4752 | DG67: 282 | DH67: 1217 | DI67: 701 | DJ67: 516 | DK67: 487 | DL67: 439 | DM67: 436 | DN67: 3 | DO67: 48 | DP67: 36 | DQ67: 12 | DR67: 843 | DS67: 0 | DT67: 657 | DU67: 524 | DV67: 133 | DW67: 186 | DX67: 81 | DY67: 105 | DZ67: 0 | EA67: 0 | EB67: 0 | EC67: 0 | ED67: 0 | EE67: 0 | EF67: 0 | EG67: 0 | EH67: 0 | EI67: 0 | EJ67: 0 | EK67: 0 | EL67: 0 | EM67: 0 | EN67: 499 | EO67: 7 | EP67: 0 | EQ67: 492 | ER67: 0 | ES67: 0 | ET67: 2 | EU67: 0 | EV67: 0 | EW67: 0 | EX67: 0 | EY67: 0 | EZ67: 0 | FA67: 0 | FB67: 0
A68: 65 | B68: 其他 | C68: 临床药物试验办公室GCP | D68: 226429.5 | E68: 225622 | F68: 807.5 | G68: 848 | H68: 4 | I68: 46 | J68: 0 | K68: 0 | L68: 132 | M68: 0 | N68: 0 | O68: 241843.67 | P68: 91424.83 | Q68: 0 | R68: 91424.83 | S68: 150418.84 | T68: 0 | U68: 150418.84 | V68: 240762.9 | W68: 91424.83 | X68: 0 | Y68: 91424.83 | Z68: 149338.07 | AA68: 0 | AB68: 149338.07 | AC68: 14980.9 | AD68: 2768.83 | AE68: 0 | AF68: 2768.83 | AG68: 12212.07 | AH68: 0 | AI68: 12212.07 | AJ68: 160 | AK68: 128 | AL68: 0 | AM68: 128 | AN68: 32 | AO68: 0 | AP68: 32 | AQ68: 204376 | AR68: 76672 | AS68: 0 | AT68: 76672 | AU68: 127704 | AV68: 0 | AW68: 127704 | AX68: 21246 | AY68: 11856 | AZ68: 0 | BA68: 11856 | BB68: 9390 | BC68: 0 | BD68: 9390 | BE68: 1080.77 | BF68: 0 | BG68: 0 | BH68: 0 | BI68: 1080.77 | BJ68: 0 | BK68: 1080.77 | BL68: 110.17 | BM68: 0 | BN68: 0 | BO68: 0 | BP68: 110.17 | BQ68: 0 | BR68: 110.17 | BS68: 163.1 | BT68: 0 | BU68: 0 | BV68: 0 | BW68: 163.1 | BX68: 0 | BY68: 163.1 | BZ68: 140 | CA68: 0 | CB68: 0 | CC68: 0 | CD68: 140 | CE68: 0 | CF68: 140 | CG68: 667.5 | CH68: 0 | CI68: 0 | CJ68: 0 | CK68: 667.5 | CL68: 0 | CM68: 667.5 | CN68: 0 | CO68: 0 | CP68: 0 | CQ68: 240762.9 | CR68: 0 | CS68: 0 | CT68: 0 | CU68: 0 | CV68: 848 | CW68: 474 | CX68: 0 | CY68: 474 | CZ68: 374 | DA68: 0 | DB68: 374 | DC68: 848 | DD68: 0 | DE68: 474 | DF68: 0 | DG68: 474 | DH68: 374 | DI68: 0 | DJ68: 374 | DK68: 0 | DL68: 0 | DM68: 0 | DN68: 0 | DO68: 0 | DP68: 0 | DQ68: 0 | DR68: 0 | DS68: 0 | DT68: 0 | DU68: 0 | DV68: 0 | DW68: 0 | DX68: 0 | DY68: 0 | DZ68: 0 | EA68: 0 | EB68: 0 | EC68: 0 | ED68: 0 | EE68: 0 | EF68: 0 | EG68: 4 | EH68: 0 | EI68: 0 | EJ68: 0 | EK68: 4 | EL68: 0 | EM68: 4 | EN68: 0 | EO68: 0 | EP68: 0 | EQ68: 0 | ER68: 0 | ES68: 0 | ET68: 0 | EU68: 0 | EV68: 0 | EW68: 0 | EX68: 0 | EY68: 0 | EZ68: 0 | FA68: 0 | FB68: 0
A69: 66 | C69: 其它 | D69: 117.5 | E69: 50 | F69: 67.5 | G69: 646 | H69: 25 | I69: 0 | J69: 0 | K69: 0 | L69: 0 | M69: 0 | N69: 0 | O69: 461992.78 | P69: 375710.16 | Q69: 292361.4 | R69: 83348.76 | S69: 86282.62 | T69: 60390.12 | U69: 25892.5 | V69: 50 | W69: 25 | X69: 25 | Y69: 0 | Z69: 25 | AA69: 0 | AB69: 25 | AC69: 0 | AD69: 0 | AE69: 0 | AF69: 0 | AG69: 0 | AH69: 0 | AI69: 0 | AJ69: 0 | AK69: 0 | AL69: 0 | AM69: 0 | AN69: 0 | AO69: 0 | AP69: 0 | AQ69: 0 | AR69: 0 | AS69: 0 | AT69: 0 | AU69: 0 | AV69: 0 | AW69: 0 | AX69: 50 | AY69: 25 | AZ69: 25 | BA69: 0 | BB69: 25 | BC69: 0 | BD69: 25 | BE69: 461942.78 | BF69: 375685.16 | BG69: 292336.4 | BH69: 83348.76 | BI69: 86257.62 | BJ69: 60390.12 | BK69: 25867.5 | BL69: 0 | BM69: 0 | BN69: 0 | BO69: 0 | BP69: 0 | BQ69: 0 | BR69: 0 | BS69: 461875.28 | BT69: 375685.16 | BU69: 292336.4 | BV69: 83348.76 | BW69: 86190.12 | BX69: 60390.12 | BY69: 25800 | BZ69: 0 | CA69: 0 | CB69: 0 | CC69: 0 | CD69: 0 | CE69: 0 | CF69: 0 | CG69: 67.5 | CH69: 0 | CI69: 0 | CJ69: 0 | CK69: 67.5 | CL69: 0 | CM69: 67.5 | CN69: 0 | CO69: 0 | CP69: 0 | CQ69: 1475 | CR69: 0 | CS69: 0 | CT69: 103200 | CU69: 0 | CV69: 646 | CW69: 223 | CX69: 54 | CY69: 169 | CZ69: 423 | DA69: 1 | DB69: 422 | DC69: 646 | DD69: 0 | DE69: 223 | DF69: 54 | DG69: 169 | DH69: 423 | DI69: 1 | DJ69: 422 | DK69: 0 | DL69: 0 | DM69: 0 | DN69: 0 | DO69: 0 | DP69: 0 | DQ69: 0 | DR69: 0 | DS69: 0 | DT69: 0 | DU69: 0 | DV69: 0 | DW69: 0 | DX69: 0 | DY69: 0 | DZ69: 0 | EA69: 0 | EB69: 0 | EC69: 0 | ED69: 0 | EE69: 0 | EF69: 0 | EG69: 25 | EH69: 9 | EI69: 2 | EJ69: 7 | EK69: 16 | EL69: 14 | EM69: 2 | EN69: 1 | EO69: 1 | EP69: 0 | EQ69: 0 | ER69: 0 | ES69: 0 | ET69: 0 | EU69: 0 | EV69: 0 | EW69: 0 | EX69: 0 | EY69: 0 | EZ69: 0 | FA69: 0 | FB69: 0

Sheet 当月附表1
A1: 收入费用盈余表
C2: 附表-01
A3: 编制单位：上海交通大学医学院附属新华医院 | B3: 2026年05月 | C3: 单位：元
A4: 项 目 | B4: 本月数 | C4: 本年累计数
A5: 一、医疗业务盈余： | B5: 32594377 | C5: -1.7847916e+08
A6: （一）医疗服务盈余： | B6: 31904517 | C6: -2.0332504e+08
A7: 医疗收入 | B7: 6.361909e+08 | C7: 3.0576528e+09
A8: 加：财政基本拨款收入 | B8: 25021857 | C8: 1.2510928e+08
A9: 加：非同级财政基本拨款收入 | B9: 0 | C9: 0
A10: 减：医疗成本 | B10: 6.2930824e+08 | C10: 3386087139
A11: （二）其他盈余： | B11: 689860.17 | C11: 24845878
A12: 其他医疗活动收入 | B12: 4148289.1 | C12: 41687016
A13: 减：其他医疗活动费用 | B13: 3458428.9 | C13: 16841138
A14: （三）结转入结余分配： | B14: \
A15: 加：年初未弥补亏损 | B15: \
A16: 加：累计盈余弥补亏损 | B16: \
A17: 减：提取职工福利基金 | B17: \
A18: 转入累计盈余 | B18: \
A19: 年末未弥补亏损 | B19: \
A20: 二、医疗项目盈余： | B20: -3065473.1 | C20: -15707996
A21: 非同级财政项目拨款收入 | B21: 29800 | C21: 29800
A22: 减：非同级财政项目费用 | B22: 3095273.1 | C22: 15737796
A23: 三、财政项目盈余： | B23: 50315185 | C23: 39180998
A24: 财政项目拨款收入 | B24: 71780357 | C24: 1.470441e+08
A25: 减：财政项目费用 | B25: 21465172 | C25: 1.078631e+08
A26: 四、科教盈余： | B26: 380435.34 | C26: -8751563.6
A27: 科教收入 | B27: 8584327.8 | C27: 56615927
A28: 减：科教费用 | B28: 8203892.5 | C28: 65367491
A29: 本期盈余合计 | B29: 80224524 | C29: -1.6375773e+08
A30: 单位负责人： 总会计师： 财务负责人： 审核： 制表：
A31: 注：本表“医疗成本”根据“业务活动费用”“单位管理费用”科目及所属明细科目、经费性质为财政基本拨款经费、其他经费的本期发生额填列；“非同级财政项目费用”根据“业务活动费用”“单位管理费用”科目及所属明细科目、经费性质为非同级财政拨款经费的本期发生额填列。

Sheet 当月奉贤附表1
A1: 收入费用盈余表
C2: 附表-01
A3: 编制单位：上海交通大学医学院附属新华医院（奉贤） | B3: 2026年05月 | C3: 单位：元
A4: 项 目 | B4: 本月数 | C4: 本年累计数
A5: 一、医疗业务盈余： | B5: -14765630 | C5: -1.6877343e+08
A6: （一）医疗服务盈余： | B6: -14451707 | C6: -1.6736355e+08
A7: 医疗收入 | B7: 1.4262178e+08 | C7: 6.3976811e+08
A8: 加：财政基本拨款收入 | B8: 0 | C8: 0
A9: 加：非同级财政基本拨款收入 | B9: 0 | C9: 0
A10: 减：医疗成本 | B10: 1.5707349e+08 | C10: 8.0713167e+08
A11: （二）其他盈余： | B11: -313923.16 | C11: -1409874.6
A12: 其他医疗活动收入 | B12: 443597.32 | C12: 1924078.7
A13: 减：其他医疗活动费用 | B13: 757520.48 | C13: 3333953.3
A14: （三）结转入结余分配： | B14: \
A15: 加：年初未弥补亏损 | B15: \
A16: 加：累计盈余弥补亏损 | B16: \
A17: 减：提取职工福利基金 | B17: \
A18: 转入累计盈余 | B18: \
A19: 年末未弥补亏损 | B19: \
A20: 二、医疗项目盈余： | B20: -690765.35 | C20: -3452276.7
A21: 非同级财政项目拨款收入 | B21: 0 | C21: 0
A22: 减：非同级财政项目费用 | B22: 690765.35 | C22: 3452276.7
A23: 三、财政项目盈余： | B23: -9002540.4 | C23: -44962593
A24: 财政项目拨款收入 | B24: 0 | C24: 0
A25: 减：财政项目费用 | B25: 9002540.4 | C25: 44962593
A26: 四、科教盈余： | B26: 0 | C26: -485130
A27: 科教收入 | B27: 0 | C27: 0
A28: 减：科教费用 | B28: 0 | C28: 485130
A29: 本期盈余合计 | B29: -24458936 | C29: -2.1767343e+08
A30: 单位负责人： 总会计师： 财务负责人： 审核： 制表：
A31: 注：本表“医疗成本”根据“业务活动费用”“单位管理费用”科目及所属明细科目、经费性质为财政基本拨款经费、其他经费的本期发生额填列；“非同级财政项目费用”根据“业务活动费用”“单位管理费用”科目及所属明细科目、经费性质为非同级财政拨款经费的本期发生额填列。

Sheet 上年同期附表1
A1: 收入费用盈余表 | G1: 3
C2: 附表-01
A3: 编制单位：上海交通大学医学院附属新华医院 | B3: 2025年5月 | C3: 单位：元
A4: 项 目 | B4: 本月数 | C4: 本年累计数
A5: 一、医疗业务盈余： | B5: =B6+B11 | C5: =C6+C11 | H5: =SUM(H7:H28)
A6: （一）医疗服务盈余： | B6: =B7+B8+B9-B10 | C6: =C7+C8+C9-C10
A7: 医疗收入 | B7: 4.8206318e+08 | C7: 2.4095565e+09 | G7: 8.7776585e+08 | H7: =IF($G$1=1,C7-B7,C7-B7-G7)
A8: 加：财政基本拨款收入 | B8: 21873995 | C8: 109369975 | G8: 43747990 | H8: =IF($G$1=1,C8-B8,C8-B8-G8)
A9: 加：非同级财政基本拨款收入 | B9: 0 | C9: 0 | G9: 0 | H9: =IF($G$1=1,C9-B9,C9-B9-G9)
A10: 减：医疗成本 | B10: 5.1913758e+08 | C10: 2.7611034e+09 | G10: 1.1387105e+09 | H10: =IF($G$1=1,C10-B10,C10-B10-G10)
A11: （二）其他盈余： | B11: =B12-B13 | C11: =C12-C13
A12: 其他医疗活动收入 | B12: 7190499 | C12: 86260854 | G12: 29591859 | H12: =IF($G$1=1,C12-B12,C12-B12-G12)
A13: 减：其他医疗活动费用 | B13: 7039673 | C13: 30954978 | G13: 16004141 | H13: =IF($G$1=1,C13-B13,C13-B13-G13)
A14: （三）结转入结余分配： | B14: \ | C14: 0
A15: 加：年初未弥补亏损 | B15: \ | C15: 0
A16: 加：累计盈余弥补亏损 | B16: \ | C16: 0
A17: 减：提取职工福利基金 | B17: \ | C17: 0
A18: 转入累计盈余 | B18: \ | C18: 0
A19: 年末未弥补亏损 | B19: \ | C19: =C14+C15+C16-C17-C18
A20: 二、医疗项目盈余： | B20: =B21-B22 | C20: =C21-C22
A21: 非同级财政项目拨款收入 | B21: 0 | C21: 247100 | G21: 12500 | H21: =IF($G$1=1,C21-B21,C21-B21-G21)
A22: 减：非同级财政项目费用 | B22: 3903455.1 | C22: 20634890 | G22: 9775924.1 | H22: =IF($G$1=1,C22-B22,C22-B22-G22)
A23: 三、财政项目盈余： | B23: =B24-B25 | C23: =C24-C25
A24: 财政项目拨款收入 | B24: 19000000 | C24: 131122880 | G24: 98880000 | H24: =IF($G$1=1,C24-B24,C24-B24-G24)
A25: 减：财政项目费用 | B25: 15071943 | C25: 64695022 | G25: 22048496 | H25: =IF($G$1=1,C25-B25,C25-B25-G25)
A26: 四、科教盈余： | B26: =B27-B28 | C26: =C27-C28
A27: 科教收入 | B27: 7893591.8 | C27: 58697405 | G27: 6679393.2 | H27: =IF($G$1=1,C27-B27,C27-B27-G27)
A28: 减：科教费用 | B28: 8400965.5 | C28: 62185471 | G28: 14360921 | H28: =IF($G$1=1,C28-B28,C28-B28-G28)
A29: 本期盈余合计 | B29: =B26+B23+B20+B5 | C29: =C26+C23+C20+C5
A30: 单位负责人： 总会计师： 财务负责人： 审核： 制表：
A31: 注：本表“医疗成本”根据“业务活动费用”“单位管理费用”科目及所属明细科目、经费性质为财政基本拨款经费、其他经费的本期发生额填列；“非同级财政项目费用”根据“业务活动费用”“单位管理费用”科目及所属明细科目、经费性质为非同级财政拨款经费的本期发生额填列。

Sheet 当月附表2
A1: 医疗收入成本表
E2: 附表-02
A3: 编制单位：上海交通大学医学院附属新华医院 | C3: 2026年05月 | E3: 单位：元
A4: 项 目 | B4: 本月数 | C4: 本年累计数 | D4: 项 目 | E4: 本月数 | F4: 本年累计数
A5: 一、医疗收入 | B5: 6.361909e+08 | C5: 3.0576528e+09 | D5: 一、医疗成本 | E5: 6.2930824e+08 | F5: 3386087139
A6: 1.门急诊收入 | B6: 2.3290433e+08 | C6: 1.1329757e+09 | D6: （一）按性质分类
A7: 其中：挂号收入 | B7: 0 | C7: 0 | D7: 1.人员经费 | E7: 2.1460305e+08 | F7: 1.2610782e+09
A8: 诊察收入 | B8: 13503462 | C8: 62407701 | D8: 2.卫生材料费 | E8: 2.0636955e+08 | F8: 1.0448193e+09
A9: 检查收入 | B9: 37564434 | C9: 1.7918793e+08 | D9: 3.药品费 | E9: 1.5105081e+08 | F9: 7.6079614e+08
A10: 化验收入 | B10: 38024895 | C10: 179531179 | D10: 4.固定资产折旧费 | E10: 9796053.9 | F10: 47475824
A11: 治疗收入 | B11: 24185085 | C11: 1.1593086e+08 | D11: 5.无形资产摊销费 | E11: 1611789.9 | F11: 8158887.3
A12: 手术收入 | B12: 6494883.5 | C12: 27010752 | D12: 6.提取医疗风险基金 | E12: 954286.36 | F12: 4600481.8
A13: 卫生材料收入 | B13: 8378617.8 | C13: 40661902 | D13: 7.其他费用 | E13: 44922702 | F13: 2.5915832e+08
A14: 药品收入 | B14: 90258760 | C14: 4.5432965e+08 | D14: （二）按功能分类
A15: 其中：西药收入 | B15: 71958423 | C15: 3.6227034e+08 | D15: 1.业务活动费用 | E15: 6.0431976e+08 | F15: 3.222889e+09
A16: 中成药收入 | B16: 15717148 | C16: 79671055 | D16: 2.单位管理费用 | E16: 24988481 | F16: 1.6319814e+08
A17: 中药饮片收入 | B17: 2583189.6 | C17: 12388253
A18: 其他门诊收入 | B18: 14494190 | C18: 73915768
A19: 2.住院收入 | B19: 4.0328658e+08 | C19: 1.9246771e+09
A20: 其中：床位收入 | B20: 15464151 | C20: 76507614
A21: 诊察收入 | B21: 6460875 | C21: 31049690
A22: 检查收入 | B22: 30899872 | C22: 1.4166799e+08
A23: 化验收入 | B23: 39768300 | C23: 1.8764472e+08
A24: 治疗收入 | B24: 16856762 | C24: 74448057
A25: 手术收入 | B25: 49410230 | C25: 2.1157936e+08
A26: 护理收入 | B26: 6778243.9 | C26: 26908510
A27: 卫生材料收入 | B27: 1.6987025e+08 | C27: 8.2287385e+08
A28: 药品收入 | B28: 62564548 | C28: 3.0881139e+08
... A32: 其他住院收入 | B32: 5213340 | C32: 43185881
A33: 单位负责人： | B33: 总会计师： | C33: 财务负责人： | E33: 审核： | F33: 制表：
A34: 注：本表“医疗成本”及所属明细项目，根据“业务活动费用”“单位管理费用”科目及所属明细科目、经费性质为财政基本拨款经费、其他经费（不含非同级财政项目经费）的本期发生额填列。

Sheet 当月奉贤附表2
A1: 医疗收入成本表
E2: 附表-02
A3: 编制单位：上海交通大学医学院附属新华医院（奉贤） | C3: 2026年05月 | E3: 单位：元
A4: 项 目 | B4: 本月数 | C4: 本年累计数 | D4: 项 目 | E4: 本月数 | F4: 本年累计数
A5: 一、医疗收入 | B5: 1.4262178e+08 | C5: 6.3976811e+08 | D5: 一、医疗成本 | E5: 1.5707349e+08 | F5: 8.0713167e+08
A6: 1.门急诊收入 | B6: 41787089 | C6: 1.9893913e+08 | D6: （一）按性质分类
A7: 其中：挂号收入 | B7: 0 | C7: 0 | D7: 1.人员经费 | E7: 57635415 | F7: 3.3033002e+08
A8: 诊察收入 | B8: 2872733 | C8: 12991642 | D8: 2.卫生材料费 | E8: 58261689 | F8: 2.7618809e+08
A9: 检查收入 | B9: 9601311 | C9: 44517766 | D9: 3.药品费 | E9: 26091463 | F9: 123943940
A10: 化验收入 | B10: 6833067 | C10: 31843435 | D10: 4.固定资产折旧费 | E10: 1583779.1 | F10: 5377507.7
A11: 治疗收入 | B11: 3618404.7 | C11: 17779598 | D11: 5.无形资产摊销费 | E11: 449402.96 | F11: 2264347.9
A12: 手术收入 | B12: 1282917.8 | C12: 4489536.3 | D12: 6.提取医疗风险基金 | E12: 213932.67 | F12: 962253.68
A13: 卫生材料收入 | B13: 2024380.4 | C13: 9753526.8 | D13: 7.其他费用 | E13: 12837807 | F13: 68065506
A14: 药品收入 | B14: 14731720 | C14: 72393512 | D14: （二）按功能分类
A15: 其中：西药收入 | B15: 11392991 | C15: 56050660 | D15: 1.业务活动费用 | E15: 1.5124237e+08 | F15: 7.7248238e+08
A16: 中成药收入 | B16: 2890347.7 | C16: 14554446 | D16: 2.单位管理费用 | E16: 5831117.9 | F16: 34649282
A17: 中药饮片收入 | B17: 448381.37 | C17: 1788406.2
A18: 其他门诊收入 | B18: 822555.02 | C18: 5170115.6
A19: 2.住院收入 | B19: 1.0083469e+08 | C19: 4.4082898e+08
A20: 其中：床位收入 | B20: 4884763 | C20: 21126092
A21: 诊察收入 | B21: 806600 | C21: 3156775
A22: 检查收入 | B22: 7134245 | C22: 29564508
A23: 化验收入 | B23: 8036564 | C23: 34127699
A24: 治疗收入 | B24: 2722522.5 | C24: 10924731
A25: 手术收入 | B25: 12412492 | C25: 48728350
A26: 护理收入 | B26: 1200983.9 | C26: 4460814
A27: 卫生材料收入 | B27: 51745455 | C27: 2.3162823e+08
A28: 药品收入 | B28: 11464304 | C28: 51387425
... A32: 其他住院收入 | B32: 426762.43 | C32: 5724354
A33: 单位负责人： | B33: 总会计师： | C33: 财务负责人： | E33: 审核： | F33: 制表：
A34: 注：本表“医疗成本”及所属明细项目，根据“业务活动费用”“单位管理费用”科目及所属明细科目、经费性质为财政基本拨款经费、其他经费（不含非同级财政项目经费）的本期发生额填列。

Sheet 上年同期附表2
A1: 医疗收入成本表
E2: 附表-02
A3: 编制单位：上海交通大学医学院附属新华医院 | C3: 2025年5月 | E3: 单位：元
A4: 项 目 | B4: 本月数 | C4: 本年累计数 | D4: 项 目 | E4: 本月数 | F4: 本年累计数
A5: 一、医疗收入 | B5: 4.8206318e+08 | C5: 2.4095565e+09 | D5: 一、医疗成本 | E5: 5.1913758e+08 | F5: 2.7611034e+09
A6: 1.门急诊收入 | B6: 1.7229407e+08 | C6: 8.6485242e+08 | D6: （一）按性质分类
A7: 其中：挂号收入 | B7: 3907912 | C7: 17200080 | D7: 1.人员经费 | E7: 1.8247829e+08 | F7: 1.0890027e+09
A8: 诊察收入 | B8: 5994871 | C8: 30458812 | D8: 2.卫生材料费 | E8: 1.620134e+08 | F8: 7.6574251e+08
A9: 检查收入 | B9: 26708829 | C9: 135459365 | D9: 3.药品费 | E9: 1.2654685e+08 | F9: 6.3173917e+08
A10: 化验收入 | B10: 27446930 | C10: 138934789 | D10: 4.固定资产折旧费 | E10: 8885302 | F10: 45250566
A11: 治疗收入 | B11: 17020327 | C11: 83691329 | D11: 5.无形资产摊销费 | E11: 2003160.7 | F11: 10194571
A12: 手术收入 | B12: 3802190.1 | C12: 18161397 | D12: 6.提取医疗风险基金 | E12: 723094.77 | F12: 3614334.7
A13: 卫生材料收入 | B13: 6383414.7 | C13: 30826603 | D13: 7.其他费用 | E13: 36487483 | F13: 2.1555951e+08
A14: 药品收入 | B14: 67708333 | C14: 3.4024782e+08 | D14: （二）按功能分类
A15: 其中：西药收入 | B15: 52913546 | C15: 2.6687187e+08 | D15: 1.业务活动费用 | E15: 4.8550586e+08 | F15: 2.5383899e+09
A16: 中成药收入 | B16: 12306829 | C16: 61043822 | D16: 2.单位管理费用 | E16: 33631722 | F16: 2.2271347e+08
A17: 中药饮片收入 | B17: 2487958.3 | C17: 12332131
A18: 其他门诊收入 | B18: 13321262 | C18: 69872223
A19: 2.住院收入 | B19: 3.0976911e+08 | C19: 1.5447041e+09
A20: 其中：床位收入 | B20: 11614142 | C20: 57599028
A21: 诊察收入 | B21: 5929010 | C21: 28458850
A22: 检查收入 | B22: 22312675 | C22: 1.1073273e+08
A23: 化验收入 | B23: 30756950 | C23: 1.4918988e+08
A24: 治疗收入 | B24: 15728899 | C24: 83245853
A25: 手术收入 | B25: 30426376 | C25: 1.4332215e+08
A26: 护理收入 | B26: 4150093.2 | C26: 19313436
A27: 卫生材料收入 | B27: 1.1993995e+08 | C27: 6.0409356e+08
A28: 药品收入 | B28: 59171050 | C28: 3.0098118e+08
... A32: 其他住院收入 | B32: 9739965.4 | C32: 47767389
A33: 单位负责人： | B33: 总会计师： | C33: 财务负责人： | E33: 审核： | F33: 制表：
A34: 注：本表“医疗成本”及所属明细项目，根据“业务活动费用”“单位管理费用”科目及所属明细科目、经费性质为财政基本拨款经费、其他经费（不含非同级财政项目经费）的本期发生额填列。

Sheet 当月附表3
A1: 医疗成本费用明细表
F2: 附表-03
A3: 编制单位：上海交通大学医学院附属新华医院 | C3: 2026年05月 | F3: 单位：元
A4: 项 目 | B4: 合 计 | D4: 业务活动费用 | F4: 单位管理费用
B5: 本月数 | C5: 累计数 | D5: 本月数 | E5: 累计数 | F5: 本月数 | G5: 累计数
A6: 医疗成本合计 | B6: 6.2930824e+08 | C6: 3386087139 | D6: 6.0431976e+08 | E6: 3.222889e+09 | F6: 24988481 | G6: 1.6319814e+08
A7: （一）人员经费 | B7: 2.1460305e+08 | C7: 1.2610782e+09 | D7: 2.0329506e+08 | E7: 1.1866823e+09 | F7: 11307989 | G7: 74395889
A8: 工资福利费用 | B8: 2.1174238e+08 | C8: 1.2464169e+09 | D8: 2.0294219e+08 | E8: 1.1859319e+09 | F8: 8800185.9 | G8: 60484946
A9: 基本工资 | B9: 29638621 | C9: 1.4522753e+08 | D9: 28515058 | E9: 1.380491e+08 | F9: 1123563.1 | G9: 7178432.5
A10: 津贴补贴 | B10: 5052346.5 | C10: 24437362 | D10: 4854972 | E10: 23476090 | F10: 197374.5 | G10: 961271.5
A11: 奖金 | B11: 0 | C11: 0 | D11: 0 | E11: 0 | F11: 0 | G11: 0
A12: 伙食补助费 | B12: 2604484.5 | C12: 13017053 | D12: 2504484.5 | E12: 12511553 | F12: 100000 | G12: 505500
A13: 绩效工资 | B13: 1.2720355e+08 | C13: 8.2803007e+08 | D13: 1.2108714e+08 | E13: 7.828936e+08 | F13: 6116402.3 | G13: 45136472
A14: 基本养老保险缴费 | B14: 23346494 | C14: 1.1699831e+08 | D14: 22861641 | E14: 1.1423654e+08 | F14: 484853.17 | G14: 2761767.8
A15: 职业年金缴费 | B15: 6476603.4 | C15: 32634251 | D15: 6214772.3 | E15: 31306981 | F15: 261831.07 | G15: 1327269.8
A16: 基本医疗保险缴费 | B16: 6651221 | C16: 33445901 | D16: 6391319.2 | E16: 32131124 | F16: 259901.79 | G16: 1314777.2
A17: 其他社会保障缴费 | B17: 1033550.8 | C17: 5188737.1 | D17: 1013957.5 | E17: 5089103.5 | F17: 19593.32 | G17: 99633.6
... A33: （二）卫生材料费 | B33: 2.0636955e+08 | C33: 1.0448193e+09 | D33: 2.0612635e+08 | E33: 1.0426004e+09 | F33: 243197.88 | G33: 2218982.5
A34: 血费 | B34: 1792480 | C34: 4161245 | D34: 1792480 | E34: 4161245
A35: 氧气费 | B35: 548790.5 | C35: 2254050.5 | D35: 548790.5 | E35: 2254050.5
A36: 放射材料费 | B36: 152575 | C36: 481825 | D36: 152575 | E36: 481825
A37: 化验材料费 | B37: 31912675 | C37: 1.3288818e+08 | D37: 31912675 | E37: 1.3288818e+08
A38: 一次性医疗器械 | B38: 1.6216015e+08 | C38: 8.5660158e+08 | D38: 1.6216015e+08 | E38: 8.5660158e+08
A39: 手术器械类 | B39: 15262873 | C39: 74807843 | D39: 15262873 | E39: 74807843
A40: 植入材料和人工器官 | B40: 52809722 | C40: 2.8026628e+08 | D40: 52809722 | E40: 2.8026628e+08
A41: 各类介入器械 | B41: 57618111 | C41: 2.946586e+08 | D41: 57618111 | E41: 2.946586e+08
A42: 医用材料高分子生物材料 | B42: 17747771 | C42: 96083696 | D42: 17747771 | E42: 96083696
A43: 口腔材料 | B43: 195568 | C43: 1264308.7 | D43: 195568 | E43: 1264308.7
A44: 其他一次性医疗器械 | B44: 18526105 | C44: 1.0952085e+08 | D44: 18526105 | E44: 1.0952085e+08
A45: 不可单独收费医用消耗材料 | B45: 7762055.3 | C45: 34457989 | D45: 7762055.3 | E45: 34457989
A46: 其他卫生材料 | B46: 2040821.9 | C46: 13974476 | D46: 1797624 | E46: 11755493 | F46: 243197.88 | G46: 2218982.5
A47: （三）药品费 | B47: 1.5105081e+08 | C47: 7.6079614e+08 | D47: 1.5105081e+08 | E47: 7.6079614e+08 | F47: 0 | G47: 0
A48: 西药费 | B48: 1.4080417e+08 | C48: 7.0455525e+08 | D48: 1.4080417e+08 | E48: 7.0455525e+08 | F48: 0 | G48: 0
A49: 中成药费 | B49: 8144081.3 | C49: 46159564 | D49: 8144081.3 | E49: 46159564
A50: 中药饮片费 | B50: 2102562 | C50: 10081322 | D50: 2102562 | E50: 10081322
A51: （四）固定资产折旧费 | B51: 9796053.9 | C51: 47475824 | D51: 9384520.2 | E51: 45370459 | F51: 411533.69 | G51: 2105365.4
A52: （五）无形资产摊销费 | B52: 1611789.9 | C52: 8158887.3 | D52: 1533778.5 | E52: 7768830.2 | F52: 78011.43 | G52: 390057.15
A53: （六）提取医疗风险基金 | B53: 954286.36 | C53: 4600481.8 | D53: 954286.36 | E53: 4600481.8
A54: （七）商品和服务费用 | B54: 44922702 | C54: 2.5915832e+08 | D54: 31974953 | E54: 1.7507047e+08 | F54: 12947749 | G54: 84087846
A55: 办公费 | B55: 0 | C55: 0 | D55: 0 | E55: 0 | F55: 0 | G55: 0
A56: 印刷费 | B56: 255658.55 | C56: 1518763.7 | D56: 241550.23 | E56: 1494017.1 | F56: 14108.32 | G56: 24746.65
A57: 咨询费 | B57: 0 | C57: 0 | D57: 0 | E57: 0 | F57: 0 | G57: 0
A58: 手续费 | B58: 0 | C58: 0 | D58: 0 | E58: 0 | F58: 0 | G58: 0
A59: 水费 | B59: 709010.12 | C59: 3379757.4 | D59: 679969.04 | E59: 2629083.9 | F59: 29041.08 | G59: 750673.52
A60: 电费 | B60: 4810067.5 | C60: 19967910 | D60: 4620784.1 | E60: 19064428 | F60: 189283.37 | G60: 903482.5
A61: 邮电费 | B61: 368587.8 | C61: 1819454.6 | D61: 344595.96 | E61: 1355593 | F61: 23991.84 | G61: 463861.65
A62: 取暖费 | B62: 0 | C62: 0 | D62: 0 | E62: 0 | F62: 0 | G62: 0
A63: 物业管理费 | B63: 11820984 | C63: 53583209 | D63: 11353818 | E63: 50375310 | F63: 467165.44 | G63: 3207899.6
A64: 差旅费 | B64: 198815.33 | C64: 782642.36 | D64: 93297.14 | E64: 484703.28 | F64: 105518.19 | G64: 297939.08
A65: 因公出国（境）费 | B65: 174233.38 | C65: 548821.98 | D65: 147544.76 | E65: 452889.82 | F65: 26688.62 | G65: 95932.16
... A79: 其他商品和服务支出 | B79: 7945946.4 | C79: 45622009 | D79: 7438315.4 | E79: 34571997 | F79: 507631.04 | G79: 11050013
A80: 单位负责人： 总会计师： 财务负责人： 审核： 制表人：
A81: 注：本表“医疗成本”及所属明细项目，根据“业务活动费用”“单位管理费用”科目及所属明细科目、经费性质为财政基本拨款经费、其他经费的本期发生额填列。

Sheet 当月奉贤附表3
A1: 医疗成本费用明细表
F2: 附表-03
A3: 编制单位：上海交通大学医学院附属新华医院（奉贤） | C3: 2026年05月 | F3: 单位：元
A4: 项 目 | B4: 合 计 | D4: 业务活动费用 | F4: 单位管理费用
B5: 本月数 | C5: 累计数 | D5: 本月数 | E5: 累计数 | F5: 本月数 | G5: 累计数
A6: 医疗成本合计 | B6: 1.5707349e+08 | C6: 8.0713167e+08 | D6: 1.5124237e+08 | E6: 7.7248238e+08 | F6: 5831117.9 | G6: 34649282
A7: （一）人员经费 | B7: 57635415 | C7: 3.3033002e+08 | D7: 56085527 | E7: 3.2071819e+08 | F7: 1549887.9 | G7: 9611831.3
A8: 工资福利费用 | B8: 57607583 | C8: 3.3028107e+08 | D8: 56058124 | E8: 3.2067039e+08 | F8: 1549458.8 | G8: 9610681.7
A9: 基本工资 | B9: 4433945 | C9: 20351389 | D9: 4278422 | E9: 19625177 | F9: 155523 | G9: 726212
A10: 津贴补贴 | B10: 976854 | C10: 4460810 | D10: 946384 | E10: 4336750 | F10: 30470 | G10: 124060
A11: 奖金 | B11: 0 | C11: 0 | D11: 0 | E11: 0 | F11: 0 | G11: 0
A12: 伙食补助费 | B12: 0 | C12: 752004.6 | D12: 0 | E12: 752004.6 | F12: 0 | G12: 0
A13: 绩效工资 | B13: 45903085 | C13: 2.7346681e+08 | D13: 44714304 | E13: 2.6643901e+08 | F13: 1188780.9 | G13: 7027798.3
A14: 基本养老保险缴费 | B14: 2522307.5 | C14: 12317668 | D14: 2449160.6 | E14: 11618237 | F14: 73146.92 | G14: 699430.89
A15: 职业年金缴费 | B15: 1190206 | C15: 5828302.3 | D15: 1155690 | E15: 5488221.6 | F15: 34515.97 | G15: 340080.74
A16: 基本医疗保险缴费 | B16: 1182782.4 | C16: 5783332.8 | D16: 1148481.8 | E16: 5444563.7 | F16: 34300.68 | G16: 338769.14
A17: 其他社会保障缴费 | B17: 92658.96 | C17: 457189 | D17: 89971.84 | E17: 427779.06 | F17: 2687.12 | G17: 29409.94
... A33: （二）卫生材料费 | B33: 58261689 | C33: 2.7618809e+08 | D33: 58213846 | E33: 2.7564796e+08 | F33: 47843.44 | G33: 540126.4
A34: 血费 | B34: 87650 | C34: 142680 | D34: 87650 | E34: 142680
A35: 氧气费 | B35: 130435 | C35: 275300.5 | D35: 130435 | E35: 275300.5
A36: 放射材料费 | B36: 152575 | C36: 310825 | D36: 152575 | E36: 310825
A37: 化验材料费 | B37: 6740846.4 | C37: 27157287 | D37: 6740846.4 | E37: 27157287
A38: 一次性医疗器械 | B38: 49116782 | C38: 2.3634515e+08 | D38: 49116782 | E38: 2.3634515e+08
A39: 手术器械类 | B39: 4744865.9 | C39: 20551808 | D39: 4744865.9 | E39: 20551808
A40: 植入材料和人工器官 | B40: 14736971 | C40: 79011826 | D40: 14736971 | E40: 79011826
A41: 各类介入器械 | B41: 18794638 | C41: 84597850 | D41: 18794638 | E41: 84597850
A42: 医用材料高分子生物材料 | B42: 5285460.8 | C42: 23257499 | D42: 5285460.8 | E42: 23257499
A43: 口腔材料 | B43: 19376 | C43: 125351.3 | D43: 19376 | E43: 125351.3
A44: 其他一次性医疗器械 | B44: 5535470.4 | C44: 28800818 | D44: 5535470.4 | E44: 28800818
A45: 不可单独收费医用消耗材料 | B45: 1113426.7 | C45: 4657174.9 | D45: 1113426.7 | E45: 4657174.9
A46: 其他卫生材料 | B46: 919973.58 | C46: 7299666 | D46: 872130.14 | E46: 6759539.6 | F46: 47843.44 | G46: 540126.4
A47: （三）药品费 | B47: 26091463 | C47: 123943940 | D47: 26091463 | E47: 123943940 | F47: 0 | G47: 0
A48: 西药费 | B48: 25679928 | C48: 1.223785e+08 | D48: 25679928 | E48: 1.223785e+08 | F48: 0 | G48: 0
A49: 中成药费 | B49: 49354.88 | C49: 121231.29 | D49: 49354.88 | E49: 121231.29
A50: 中药饮片费 | B50: 362179.63 | C50: 1444204.4 | D50: 362179.63 | E50: 1444204.4
A51: （四）固定资产折旧费 | B51: 1583779.1 | C51: 5377507.7 | D51: 1546390.5 | E51: 5254802.9 | F51: 37388.63 | G51: 122704.71
A52: （五）无形资产摊销费 | B52: 449402.96 | C52: 2264347.9 | D52: 381041.54 | E52: 1922540.8 | F52: 68361.42 | G52: 341807.1
A53: （六）提取医疗风险基金 | B53: 213932.67 | C53: 962253.68 | D53: 213932.67 | E53: 962253.68
A54: （七）商品和服务费用 | B54: 12837807 | C54: 68065506 | D54: 8710170.5 | E54: 44032693 | F54: 4127636.5 | G54: 24032812
A55: 办公费 | B55: 0 | C55: 0 | D55: 0 | E55: 0 | F55: 0 | G55: 0
A56: 印刷费 | B56: 128628.9 | C56: 554568.06 | D56: 116276.79 | E56: 531335.93 | F56: 12352.11 | G56: 23232.13
A57: 咨询费 | B57: 0 | C57: 0 | D57: 0 | E57: 0 | F57: 0 | G57: 0
A58: 手续费 | B58: 0 | C58: 0 | D58: 0 | E58: 0 | F58: 0 | G58: 0
A59: 水费 | B59: 103311 | C59: 366612 | D59: 100314.98 | E59: 355919.87 | F59: 2996.02 | G59: 10692.13
A60: 电费 | B60: 1253537.4 | C60: 5223027.8 | D60: 1217184.8 | E60: 5104487.9 | F60: 36352.58 | G60: 118539.89
A61: 邮电费 | B61: 17797.88 | C61: 179002.76 | D61: 15580.45 | E61: 56355.48 | F61: 2217.43 | G61: 122647.28
A62: 取暖费 | B62: 0 | C62: 0 | D62: 0 | E62: 0 | F62: 0 | G62: 0
A63: 物业管理费 | B63: 3875539.1 | C63: 16894920 | D63: 2853136.1 | E63: 14580674 | F63: 1022403 | G63: 2314246.5
A64: 差旅费 | B64: 39763.04 | C64: 156528.42 | D64: 18659.41 | E64: 96940.62 | F64: 21103.63 | G64: 59587.8
A65: 因公出国（境）费 | B65: 34846.67 | C65: 109764.38 | D65: 29508.95 | E65: 90577.95 | F65: 5337.72 | G65: 19186.43
... A79: 其他商品和服务支出 | B79: 2753283.3 | C79: 12369218 | D79: 2541769.1 | E79: 9779225.7 | F79: 211514.2 | G79: 2589992.5
A80: 单位负责人： 总会计师： 财务负责人： 审核： 制表人：
A81: 注：本表“医疗成本”及所属明细项目，根据“业务活动费用”“单位管理费用”科目及所属明细科目、经费性质为财政基本拨款经费、其他经费的本期发生额填列。

Sheet 上年同期附表3
A1: 医疗成本费用明细表
F2: 附表-03
A3: 编制单位：上海交通大学医学院附属新华医院 | C3: 2025年5月 | F3: 单位：元
A4: 项 目 | B4: 合 计 | D4: 业务活动费用 | F4: 单位管理费用
B5: 本月数 | C5: 累计数 | D5: 本月数 | E5: 累计数 | F5: 本月数 | G5: 累计数
A6: 医疗成本合计 | B6: =D6+F6 | C6: =E6+G6 | D6: =D7+D33+D47+D51+D52+D53+D54 | E6: =E7+E33+E47+E51+E52+E53+E54 | F6: =F7+F33+F47+F51+F52+F54 | G6: =G7+G33+G47+G51+G52+G54
A7: （一）人员经费 | B7: =D7+F7 | C7: =E7+G7 | D7: =D8+D21 | E7: =E8+E21 | F7: =F8+F21 | G7: =G8+G21
A8: 工资福利费用 | B8: =D8+F8 | C8: =E8+G8 | D8: =SUM(D9:D20) | E8: =SUM(E9:E20) | F8: =SUM(F9:F20) | G8: =SUM(G9:G20)
A9: 基本工资 | B9: =D9+F9 | C9: =E9+G9 | D9: 23956698 | E9: 1.3176445e+08 | F9: 2604682 | G9: 13998383
A10: 津贴补贴 | B10: =D10+F10 | C10: =E10+G10 | D10: 3909533 | E10: 19660461 | F10: 298156.5 | G10: 1441494.5
A11: 奖金 | B11: =D11+F11 | C11: =E11+G11 | D11: 0 | E11: 0 | F11: 0 | G11: 0
A12: 伙食补助费 | B12: =D12+F12 | C12: =E12+G12 | D12: 2496940 | E12: 11559821 | F12: 500 | G12: 684500
A13: 绩效工资 | B13: =D13+F13 | C13: =E13+G13 | D13: 92938292 | E13: 6.1394882e+08 | F13: 9104201.6 | G13: 64008731
A14: 基本养老保险缴费 | B14: =D14+F14 | C14: =E14+G14 | D14: 20377980 | E14: 98222547 | F14: 1120116.9 | G14: 9630073.4
A15: 职业年金缴费 | B15: =D15+F15 | C15: =E15+G15 | D15: 5723381.4 | E15: 26718594 | F15: 529530.92 | G15: 4583700.2
A16: 基本医疗保险缴费 | B16: =D16+F16 | C16: =E16+G16 | D16: 5832483 | E16: 27216626 | F16: 518653.6 | G16: 4496986.6
A17: 其他社会保障缴费 | B17: =D17+F17 | C17: =E17+G17 | D17: 894547.83 | E17: 4264886.2 | F17: 41133.7 | G17: 341119.44
A18: 住房公积金 | B18: =D18+F18 | C18: =E18+G18 | D18: 7203769.7 | E18: 34169810 | F18: 453471.3 | G18: 3795975.2
A19: 医疗费 | B19: =D19+F19 | C19: =E19+G19 | D19: 0 | E19: 0 | F19: 0 | G19: 0
A20: 其他工资福利支出 | B20: =D20+F20 | C20: =E20+G20 | D20: 1660534.8 | E20: 4679096.4 | F20: 61995.99 | G20: 213351.68
A21: 对个人和家庭的补助费用 | B21: =D21+F21 | C21: =E21+G21 | D21: =SUM(D22:D32) | E21: =SUM(E22:E32) | F21: =SUM(F22:F32) | G21: =SUM(G22:G32)
A22: 离休费 | B22: =D22+F22 | C22: =E22+G22 | D22: 0 | E22: 0 | F22: 3552 | G22: 70384
A23: 退休费 | B23: =D23+F23 | C23: =E23+G23 | D23: 0 | E23: 0 | F23: 2321164 | G23: 11385179
A24: 退职费 | B24: =D24+F24 | C24: =E24+G24 | D24: 0 | E24: 0 | F24: 0 | G24: 0
A25: 抚恤金 | B25: =D25+F25 | C25: =E25+G25 | D25: 0 | E25: 0 | F25: 355484 | G25: 1140378
A26: 生活补助 | B26: =D26+F26 | C26: =E26+G26 | D26: 0 | E26: 3500 | F26: 300 | G26: 10200
A27: 救济费 | B27: =D27+F27 | C27: =E27+G27 | D27: 0 | E27: 0 | F27: 0 | G27: 0
A28: 医疗补助费 | B28: =D28+F28 | C28: =E28+G28 | D28: 16492.86 | E28: 570476.7 | F28: 44299.23 | G28: 375088.66
A29: 助学金 | B29: =D29+F29 | C29: =E29+G29 | D29: 0 | E29: 0 | F29: 0 | G29: 0
A30: 奖励金 | B30: =D30+F30 | C30: =E30+G30 | D30: 0 | E30: 0 | F30: 0 | G30: 0
A31: 生产补贴 | B31: =D31+F31 | C31: =E31+G31 | D31: 0 | E31: 0 | F31: 0 | G31: 0
A32: 其他对个人和家庭补助支出 | B32: =D32+F32 | C32: =E32+G32 | D32: 8750 | E32: 42846 | F32: 1650 | G32: 5250
A33: （二）卫生材料费 | B33: =D33+F33 | C33: =E33+G33 | D33: =D34+D35+D36+D37+D38+D45+D46 | E33: =E34+E35+E36+E37+E38+E45+E46 | F33: 1120215.5 | G33: 3916005.9
A34: 血费 | B34: =D34+F34 | C34: =E34+G34 | D34: 1132330 | E34: 4180545
A35: 氧气费 | B35: =D35+F35 | C35: =E35+G35 | D35: 761268.5 | E35: 2503872.6
A36: 放射材料费 | B36: =D36+F36 | C36: =E36+G36 | D36: 72000 | E36: 120000
A37: 化验材料费 | B37: =D37+F37 | C37: =E37+G37 | D37: 24505852 | E37: 91822954
A38: 一次性医疗器械 | B38: =D38+F38 | C38: =E38+G38 | D38: =SUM(D39:D44) | E38: =SUM(E39:E44)
A39: 手术器械类 | B39: =D39+F39 | C39: =E39+G39 | D39: 12063201 | E39: 66080951
A40: 植入材料和人工器官 | B40: =D40+F40 | C40: =E40+G40 | D40: 43715743 | E40: 2.0430033e+08
A41: 各类介入器械 | B41: =D41+F41 | C41: =E41+G41 | D41: 43917458 | E41: 2.0379146e+08
A42: 医用材料高分子生物材料 | B42: =D42+F42 | C42: =E42+G42 | D42: 9336745.8 | E42: 67176901
A43: 口腔材料 | B43: =D43+F43 | C43: =E43+G43 | D43: 190756 | E43: 2352036
A44: 其他一次性医疗器械 | B44: =D44+F44 | C44: =E44+G44 | D44: 16950818 | E44: 81397839
A45: 不可单独收费医用消耗材料 | B45: =D45+F45 | C45: =E45+G45 | D45: 7106980.6 | E45: 33425788
A46: 其他卫生材料 | B46: =D46+F46 | C46: =E46+G46 | D46: 1140028.5 | E46: 4673824.1 | F46: =F33 | G46: =G33
A47: （三）药品费 | B47: =D47+F47 | C47: =E47+G47 | D47: =D48+D49+D50 | E47: =E48+E49+E50 | F47: 0 | G47: 0
A48: 西药费 | B48: =D48+F48 | C48: =E48+G48 | D48: 1.1589433e+08 | E48: 5.8323479e+08
A49: 中成药费 | B49: =D49+F49 | C49: =E49+G49 | D49: 8590394.4 | E49: 38278449
A50: 中药饮片费 | B50: =D50+F50 | C50: =E50+G50 | D50: 2062130.9 | E50: 10225925
A51: （四）固定资产折旧费 | B51: =D51+F51 | C51: =E51+G51 | D51: 6810505.6 | E51: 34815749 | F51: 2074796.4 | G51: 10434817
A52: （五）无形资产摊销费 | B52: =D52+F52 | C52: =E52+G52 | D52: 34405.82 | E52: 172028.95 | F52: 1968754.9 | G52: 10022542
A53: （六）提取医疗风险基金 | B53: =D53+F53 | C53: =E53+G53 | D53: 723094.77 | E53: 3614334.7
A54: （七）商品和服务费用 | B54: =D54+F54 | C54: =E54+G54 | D54: =SUM(D55:D79) | E54: =SUM(E55:E79) | F54: =SUM(F55:F79) | G54: =SUM(G55:G79)
A55: 办公费 | B55: =D55+F55 | C55: =E55+G55 | D55: 0 | E55: 0 | F55: 0 | G55: 0
A56: 印刷费 | B56: =D56+F56 | C56: =E56+G56 | D56: 273976.09 | E56: 1963539.4 | F56: 47968.28 | G56: 142994.84
A57: 咨询费 | B57: =D57+F57 | C57: =E57+G57 | D57: 0 | E57: 0 | F57: 0 | G57: 0
A58: 手续费 | B58: =D58+F58 | C58: =E58+G58 | D58: 0 | E58: 0 | F58: 0 | G58: 0
A59: 水费 | B59: =D59+F59 | C59: =E59+G59 | D59: 497055.9 | E59: 2342816.3 | F59: 45987.93 | G59: 406385.4
A60: 电费 | B60: =D60+F60 | C60: =E60+G60 | D60: 2704307.3 | E60: 12497951 | F60: 250204.24 | G60: 2156472.9
A61: 邮电费 | B61: =D61+F61 | C61: =E61+G61 | D61: 276589.46 | E61: 1686918.2 | F61: 39684.09 | G61: 368027.72
A62: 取暖费 | B62: =D62+F62 | C62: =E62+G62 | D62: 0 | E62: 0 | F62: 0 | G62: 0
A63: 物业管理费 | B63: =D63+F63 | C63: =E63+G63 | D63: 6668521.3 | E63: 35612077 | F63: 616975.82 | G63: 6466254.9
A64: 差旅费 | B64: =D64+F64 | C64: =E64+G64 | D64: 53703.33 | E64: 393708.4 | F64: 78726.2 | G64: 232002.38
A65: 因公出国（境）费 | B65: =D65+F65 | C65: =E65+G65 | D65: 52846.75 | E65: 285497.53 | F65: 0 | G65: 0
A66: 维修(护）费 | B66: =D66+F66 | C66: =E66+G66 | D66: 3437371 | E66: 19098848 | F66: 3755471.7 | G66: 34443947
... A79: 其他商品和服务支出 | B79: =D79+F79 | C79: =E79+G79 | D79: 6811890.3 | E79: 23509755 | F79: 1247305.7 | G79: 8644920.9
A80: 单位负责人： 总会计师： 财务负责人： 审核： 制表人：
A81: 注：本表“医疗成本”及所属明细项目，根据“业务活动费用”“单位管理费用”科目及所属明细科目、经费性质为财政基本拨款经费、其他经费的本期发生额填列。
